Workbook
Name BDT_to_USD_2017: #REF!
Name BDT_to_USD_2014: #REF!
Name lesser_lean_season_duration: #REF!
Name nls_household_size: #REF!
Name primary_lean_season_duration: #REF!

Sheet Start Here
A1: Notes on how to engage with this cost-effectiveness analysis
A2: General:
A3: Published April 2022
A4: Make an editable copy of this spreadsheet by clicking "File" → "Make a copy..."
A5: Enter values in the "User inputs" and "Moral weights" tabs. View results on the "Results" tab.
A7: Standard color code on intervention tabs:
A8: Blue marks on-sheet calculations
A9: Yellow marks parameters pulled from the "Moral weights" tab
A11: Helpful GiveWell references:
A12: =HYPERLINK("https://docs.google.com/document/d/1ZKq-MNU-xtn_48uN33L6VvBEZRAduvjwWMeaEffL4K4/","Guide to GiveWell cost-effectiveness analyses") -> Guide to GiveWell cost-effectiveness analyses
A13: =HYPERLINK("http://www.givewell.org/charities/top-charities","Full reviews of our top charities") -> Full reviews of our top charities
A14: =HYPERLINK("http://www.givewell.org/international/technical/criteria/cost-effectiveness/cost-effectiveness-models","Past versions of our cost-effectiveness analyses") -> Past versions of our cost-effectiveness analyses
A15: =HYPERLINK("http://www.givewell.org/international/technical/criteria/cost-effectiveness","Discussion of cost-effectiveness as a criterion") -> Discussion of cost-effectiveness as a criterion
A16: =HYPERLINK("http://www.givewell.org/international/technical/criteria/cost-effectiveness#MoreonGiveWellsviewsoncosteffectivenessestimates","Blog posts discussing cost-effectiveness") -> Blog posts discussing cost-effectiveness

Sheet Results summary
A1: In-line chlorination
A3: Country | B3: Kenya
A4: Cost-effectiveness in multiples of cash | B4: ='ILC Kenya'!B78 -> 7.6024517
A7: Dispensers for Safe Water
A9: Country | B9: Kenya | C9: Uganda | D9: Malawi
A10: Cost-effectiveness in multiples of cash, long term | B10: =DSW!B145 -> 4.4216186 | C10: =DSW!C145 -> 7.015707 | D10: =DSW!D145 -> 8.6572971
A11: Cost-effectiveness in multiples of cash, short term | B11: ='DSW_short term'!B145 -> 3.5671652 | C11: ='DSW_short term'!C145 -> 6.26162 | D11: ='DSW_short term'!D145 -> 7.7374022
A13: Spending per country | B13: 0.12 | C13: 0.44 | D13: 0.43
A14: Cost-effectiveness in multiples of cash, weighted by spending per country | B14: =IFERROR(__xludf.DUMMYFUNCTION("AVERAGE.WEIGHTED(B10:D10,B13:D13)"),7.414285932455127) -> 7.4142859
A15: Cost-effectiveness in multiples of cash, weighted by spending per country, short term | B15: =IFERROR(__xludf.DUMMYFUNCTION("AVERAGE.WEIGHTED(B11:D11,B13:D13)"),6.576015717483511) -> 6.5760157

Sheet Moral weights
A1: Moral weights | B1: GiveWell 2020
A3: Value assigned to averting the death of an individual under 5 (Kenya) | B3: =B19 -> 107.98744
A4: Value assigned to averting the death of an individual under 5 (Uganda) | B4: =B27 -> 111.41844
A5: Value assigned to averting the death of an individual under 5 (Malawi) | B5: =B35 -> 112.92449
A6: Value assigned to averting the death of an individual 5 or older (malaria reference) | B6: 83.1
A7: Value assigned to averting the death of an individual 5 or older (Kenya) | B7: =B43 -> 68.400054
A8: Value assigned to averting the death of an individual 5 or older (Uganda) | B8: =B51 -> 70.672378
A9: Value assigned to averting the death of an individual 5 or older (Malawi) | B9: =B59 -> 66.077715
A10: Value assigned to averting the death of an individual 5 or older (Sub-Saharan Africa) | B10: =B67 -> 67.772002
A11: Value of averting one year of life lost to disease/disability (YLD) | B11: 2.3
A13: Kenya under 5
C14: -1 month | D14: Early Neonatal | E14: Late Neonatal | F14: Post Neonatal | G14: 1 to 4 | H14: 5 to 9 | I14: 10 to 14 | J14: 15 to 19 | K14: 20 to 24 | L14: 25 to 29 | M14: 30 to 34 | N14: 35 to 39 | O14: 40 to 44 | P14: 45 to 49 | Q14: 50 to 54 | R14: 55 to 59 | S14: 60 to 64 | T14: 65 to 69 | U14: 70 to 74 | V14: 75 to 79 | W14: 80 to 84 | X14: 85 plus
A15: Moral weights | C15: 33.4 | D15: 83.6 | E15: 84.5 | F15: 100.7 | G15: 127.3 | H15: 134.3 | I15: 133.1 | J15: 126.3 | K15: 118 | L15: 112.7 | M15: 106.3 | N15: 99.7 | O15: 86.4 | P15: 75.7 | Q15: 65.2 | R15: 54.8 | S15: 39.6 | T15: 31.4 | U15: 21.2 | V15: 16.5 | W15: 12.4 | X15: 12.4
A17: % in each age bracket | D17: =$H146/sum($H$146:$H$149) -> 0.06895421 | E17: =$H147/sum($H$146:$H$149) -> 0.095039491 | F17: =$H148/sum($H$146:$H$149) -> 0.45983349 | G17: =$H149/sum($H$146:$H$149) -> 0.37617281
A19: Value of preventing death | B19: =SUMPRODUCT(C15:X15,C17:X17) -> 107.98744 | C19: 33.4 | D19: 83.6 | E19: 84.5 | F19: 100.7 | G19: 127.3 | H19: 134.3 | I19: 133.1 | J19: 126.3 | K19: 118 | L19: 112.7 | M19: 106.3 | N19: 99.7 | O19: 86.4 | P19: 75.7 | Q19: 65.2 | R19: 54.8 | S19: 39.6 | T19: 31.4 | U19: 21.2 | V19: 16.5 | W19: 12.4 | X19: 12.4
A21: Uganda under 5
C22: -1 month | D22: Early Neonatal | E22: Late Neonatal | F22: Post Neonatal | G22: 1 to 4 | H22: 5 to 9 | I22: 10 to 14 | J22: 15 to 19 | K22: 20 to 24 | L22: 25 to 29 | M22: 30 to 34 | N22: 35 to 39 | O22: 40 to 44 | P22: 45 to 49 | Q22: 50 to 54 | R22: 55 to 59 | S22: 60 to 64 | T22: 65 to 69 | U22: 70 to 74 | V22: 75 to 79 | W22: 80 to 84 | X22: 85 plus
A23: Moral weights | C23: 33.4 | D23: 83.6 | E23: 84.5 | F23: 100.7 | G23: 127.3 | H23: 134.3 | I23: 133.1 | J23: 126.3 | K23: 118 | L23: 112.7 | M23: 106.3 | N23: 99.7 | O23: 86.4 | P23: 75.7 | Q23: 65.2 | R23: 54.8 | S23: 39.6 | T23: 31.4 | U23: 21.2 | V23: 16.5 | W23: 12.4 | X23: 12.4
A25: % in each age bracket | D25: =$H142/sum($H$142:$H$145) -> 0.031587633 | E25: =$H143/sum($H$142:$H$145) -> 0.054413718 | F25: =$H144/sum($H$142:$H$145) -> 0.45760417 | G25: =$H145/sum($H$142:$H$145) -> 0.45639448
A27: Value of preventing death | B27: =SUMPRODUCT(C23:X23,C25:X25) -> 111.41844 | C27: 33.4 | D27: 83.6 | E27: 84.5 | F27: 100.7 | G27: 127.3 | H27: 134.3 | I27: 133.1 | J27: 126.3 | K27: 118 | L27: 112.7 | M27: 106.3 | N27: 99.7 | O27: 86.4 | P27: 75.7 | Q27: 65.2 | R27: 54.8 | S27: 39.6 | T27: 31.4 | U27: 21.2 | V27: 16.5 | W27: 12.4 | X27: 12.4
A29: Malawi under 5
C30: -1 month | D30: Early Neonatal | E30: Late Neonatal | F30: Post Neonatal | G30: 1 to 4 | H30: 5 to 9 | I30: 10 to 14 | J30: 15 to 19 | K30: 20 to 24 | L30: 25 to 29 | M30: 30 to 34 | N30: 35 to 39 | O30: 40 to 44 | P30: 45 to 49 | Q30: 50 to 54 | R30: 55 to 59 | S30: 60 to 64 | T30: 65 to 69 | U30: 70 to 74 | V30: 75 to 79 | W30: 80 to 84 | X30: 85 plus
A31: Moral weights | C31: 33.4 | D31: 83.6 | E31: 84.5 | F31: 100.7 | G31: 127.3 | H31: 134.3 | I31: 133.1 | J31: 126.3 | K31: 118 | L31: 112.7 | M31: 106.3 | N31: 99.7 | O31: 86.4 | P31: 75.7 | Q31: 65.2 | R31: 54.8 | S31: 39.6 | T31: 31.4 | U31: 21.2 | V31: 16.5 | W31: 12.4 | X31: 12.4
A33: % in each age bracket | D33: =$H154/sum($H$154:$H$157) -> 0.021349484 | E33: =$H155/sum($H$154:$H$157) -> 0.041604288 | F33: =$H156/sum($H$154:$H$157) -> 0.43841647 | G33: =$H157/sum($H$154:$H$157) -> 0.49862976
A35: Value of preventing death | B35: =SUMPRODUCT(C31:X31,C33:X33) -> 112.92449 | C35: 33.4 | D35: 83.6 | E35: 84.5 | F35: 100.7 | G35: 127.3 | H35: 134.3 | I35: 133.1 | J35: 126.3 | K35: 118 | L35: 112.7 | M35: 106.3 | N35: 99.7 | O35: 86.4 | P35: 75.7 | Q35: 65.2 | R35: 54.8 | S35: 39.6 | T35: 31.4 | U35: 21.2 | V35: 16.5 | W35: 12.4 | X35: 12.4
A37: Kenya over 5
C38: -1 month | D38: Early Neonatal | E38: Late Neonatal | F38: Post Neonatal | G38: 1 to 4 | H38: 5 to 9 | I38: 10 to 14 | J38: 15 to 19 | K38: 20 to 24 | L38: 25 to 29 | M38: 30 to 34 | N38: 35 to 39 | O38: 40 to 44 | P38: 45 to 49 | Q38: 50 to 54 | R38: 55 to 59 | S38: 60 to 64 | T38: 65 to 69 | U38: 70 to 74 | V38: 75 to 79 | W38: 80 to 84 | X38: 85 plus
A39: Moral weights | C39: 33.4 | D39: 83.6 | E39: 84.5 | F39: 100.7 | G39: 127.3 | H39: 134.3 | I39: 133.1 | J39: 126.3 | K39: 118 | L39: 112.7 | M39: 106.3 | N39: 99.7 | O39: 86.4 | P39: 75.7 | Q39: 65.2 | R39: 54.8 | S39: 39.6 | T39: 31.4 | U39: 21.2 | V39: 16.5 | W39: 12.4 | X39: 12.4
A41: % in each age bracket | H41: =$H108/SUM($H$108:$H$124) -> 0.091451761 | I41: =$H109/SUM($H$108:$H$124) -> 0.057247478 | J41: =$H110/SUM($H$108:$H$124) -> 0.061691038 | K41: =$H111/SUM($H$108:$H$124) -> 0.051979421 | L41: =$H112/SUM($H$108:$H$124) -> 0.04019979 | M41: =$H113/SUM($H$108:$H$124) -> 0.037303912 | N41: =$H114/SUM($H$108:$H$124) -> 0.037488684 | O41: =$H115/SUM($H$108:$H$124) -> 0.038439488 | P41: =$H116/SUM($H$108:$H$124) -> 0.041924582 | Q41: =$H117/SUM($H$108:$H$124) -> 0.045366013 | R41: =$H118/SUM($H$108:$H$124) -> 0.05404625 | S41: =$H119/SUM($H$108:$H$124) -> 0.074415034 | T41: =$H120/SUM($H$108:$H$124) -> 0.074952472 | U41: =$H121/SUM($H$108:$H$124) -> 0.077134443 | V41: =$H122/SUM($H$108:$H$124) -> 0.074837919 | W41: =$H123/SUM($H$108:$H$124) -> 0.064386593 | X41: =$H124/SUM($H$108:$H$124) -> 0.077135123
A43: Value of preventing death | B43: =SUMPRODUCT(C39:X39,C41:X41) -> 68.400054 | C43: 33.4 | D43: 83.6 | E43: 84.5 | F43: 100.7 | G43: 127.3 | H43: 134.3 | I43: 133.1 | J43: 126.3 | K43: 118 | L43: 112.7 | M43: 106.3 | N43: 99.7 | O43: 86.4 | P43: 75.7 | Q43: 65.2 | R43: 54.8 | S43: 39.6 | T43: 31.4 | U43: 21.2 | V43: 16.5 | W43: 12.4 | X43: 12.4
A45: Uganda over 5
C46: -1 month | D46: Early Neonatal | E46: Late Neonatal | F46: Post Neonatal | G46: 1 to 4 | H46: 5 to 9 | I46: 10 to 14 | J46: 15 to 19 | K46: 20 to 24 | L46: 25 to 29 | M46: 30 to 34 | N46: 35 to 39 | O46: 40 to 44 | P46: 45 to 49 | Q46: 50 to 54 | R46: 55 to 59 | S46: 60 to 64 | T46: 65 to 69 | U46: 70 to 74 | V46: 75 to 79 | W46: 80 to 84 | X46: 85 plus
A47: Moral weights | C47: 33.4 | D47: 83.6 | E47: 84.5 | F47: 100.7 | G47: 127.3 | H47: 134.3 | I47: 133.1 | J47: 126.3 | K47: 118 | L47: 112.7 | M47: 106.3 | N47: 99.7 | O47: 86.4 | P47: 75.7 | Q47: 65.2 | R47: 54.8 | S47: 39.6 | T47: 31.4 | U47: 21.2 | V47: 16.5 | W47: 12.4 | X47: 12.4
A49: % in each age bracket | H49: =$H91/SUM($H$91:$H$107) -> 0.11179462 | I49: =$H92/SUM($H$91:$H$107) -> 0.060160856 | J49: =$H93/SUM($H$91:$H$107) -> 0.062138423 | K49: =$H94/SUM($H$91:$H$107) -> 0.054187929 | L49: =$H95/SUM($H$91:$H$107) -> 0.042595094 | M49: =$H96/SUM($H$91:$H$107) -> 0.038092333 | N49: =$H97/SUM($H$91:$H$107) -> 0.035206246 | O49: =$H98/SUM($H$91:$H$107) -> 0.037108576 | P49: =$H99/SUM($H$91:$H$107) -> 0.040685862 | Q49: =$H100/SUM($H$91:$H$107) -> 0.04371492 | R49: =$H101/SUM($H$91:$H$107) -> 0.050157185 | S49: =$H102/SUM($H$91:$H$107) -> 0.064284479 | T49: =$H103/SUM($H$91:$H$107) -> 0.064856393 | U49: =$H104/SUM($H$91:$H$107) -> 0.069652872 | V49: =$H105/SUM($H$91:$H$107) -> 0.075782201 | W49: =$H106/SUM($H$91:$H$107) -> 0.069426458 | X49: =$H107/SUM($H$91:$H$107) -> 0.080155552
A51: Value of preventing death | B51: =SUMPRODUCT(C47:X47,C49:X49) -> 70.672378 | C51: 33.4 | D51: 83.6 | E51: 84.5 | F51: 100.7 | G51: 127.3 | H51: 134.3 | I51: 133.1 | J51: 126.3 | K51: 118 | L51: 112.7 | M51: 106.3 | N51: 99.7 | O51: 86.4 | P51: 75.7 | Q51: 65.2 | R51: 54.8 | S51: 39.6 | T51: 31.4 | U51: 21.2 | V51: 16.5 | W51: 12.4 | X51: 12.4
A53: Malawi over 5
C54: -1 month | D54: Early Neonatal | E54: Late Neonatal | F54: Post Neonatal | G54: 1 to 4 | H54: 5 to 9 | I54: 10 to 14 | J54: 15 to 19 | K54: 20 to 24 | L54: 25 to 29 | M54: 30 to 34 | N54: 35 to 39 | O54: 40 to 44 | P54: 45 to 49 | Q54: 50 to 54 | R54: 55 to 59 | S54: 60 to 64 | T54: 65 to 69 | U54: 70 to 74 | V54: 75 to 79 | W54: 80 to 84 | X54: 85 plus
A55: Moral weights | C55: 33.4 | D55: 83.6 | E55: 84.5 | F55: 100.7 | G55: 127.3 | H55: 134.3 | I55: 133.1 | J55: 126.3 | K55: 118 | L55: 112.7 | M55: 106.3 | N55: 99.7 | O55: 86.4 | P55: 75.7 | Q55: 65.2 | R55: 54.8 | S55: 39.6 | T55: 31.4 | U55: 21.2 | V55: 16.5 | W55: 12.4 | X55: 12.4
A57: % in each age bracket | H57: =$H125/SUM($H$125:$H$141) -> 0.090936105 | I57: =$H126/SUM($H$125:$H$141) -> 0.044442645 | J57: =$H127/SUM($H$125:$H$141) -> 0.053983558 | K57: =$H128/SUM($H$125:$H$141) -> 0.050029524 | L57: =$H129/SUM($H$125:$H$141) -> 0.040708978 | M57: =$H130/SUM($H$125:$H$141) -> 0.040101521 | N57: =$H131/SUM($H$125:$H$141) -> 0.039078476 | O57: =$H132/SUM($H$125:$H$141) -> 0.040416318 | P57: =$H133/SUM($H$125:$H$141) -> 0.042797779 | Q57: =$H134/SUM($H$125:$H$141) -> 0.042005673 | R57: =$H135/SUM($H$125:$H$141) -> 0.048312193 | S57: =$H136/SUM($H$125:$H$141) -> 0.072360983 | T57: =$H137/SUM($H$125:$H$141) -> 0.081825849 | U57: =$H138/SUM($H$125:$H$141) -> 0.082401855 | V57: =$H139/SUM($H$125:$H$141) -> 0.078548213 | W57: =$H140/SUM($H$125:$H$141) -> 0.067078213 | X57: =$H141/SUM($H$125:$H$141) -> 0.084972118
A59: Value of preventing death | B59: =SUMPRODUCT(C55:X55,C57:X57) -> 66.077715 | C59: 33.4 | D59: 83.6 | E59: 84.5 | F59: 100.7 | G59: 127.3 | H59: 134.3 | I59: 133.1 | J59: 126.3 | K59: 118 | L59: 112.7 | M59: 106.3 | N59: 99.7 | O59: 86.4 | P59: 75.7 | Q59: 65.2 | R59: 54.8 | S59: 39.6 | T59: 31.4 | U59: 21.2 | V59: 16.5 | W59: 12.4 | X59: 12.4
A61: Sub-Saharan Africa over 5
C62: -1 month | D62: Early Neonatal | E62: Late Neonatal | F62: Post Neonatal | G62: 1 to 4 | H62: 5 to 9 | I62: 10 to 14 | J62: 15 to 19 | K62: 20 to 24 | L62: 25 to 29 | M62: 30 to 34 | N62: 35 to 39 | O62: 40 to 44 | P62: 45 to 49 | Q62: 50 to 54 | R62: 55 to 59 | S62: 60 to 64 | T62: 65 to 69 | U62: 70 to 74 | V62: 75 to 79 | W62: 80 to 84 | X62: 85 plus
A63: Moral weights | C63: 33.4 | D63: 83.6 | E63: 84.5 | F63: 100.7 | G63: 127.3 | H63: 134.3 | I63: 133.1 | J63: 126.3 | K63: 118 | L63: 112.7 | M63: 106.3 | N63: 99.7 | O63: 86.4 | P63: 75.7 | Q63: 65.2 | R63: 54.8 | S63: 39.6 | T63: 31.4 | U63: 21.2 | V63: 16.5 | W63: 12.4 | X63: 12.4
A65: % in each age bracket | H65: =$H74/SUM($H$74:$H$90) -> 0.11625393 | I65: =$H75/SUM($H$74:$H$90) -> 0.052016034 | J65: =$H76/SUM($H$74:$H$90) -> 0.043813561 | K65: =$H77/SUM($H$74:$H$90) -> 0.040901103 | L65: =$H78/SUM($H$74:$H$90) -> 0.036937175 | M65: =$H79/SUM($H$74:$H$90) -> 0.0366142 | N65: =$H80/SUM($H$74:$H$90) -> 0.037545981 | O65: =$H81/SUM($H$74:$H$90) -> 0.040649398 | P65: =$H82/SUM($H$74:$H$90) -> 0.044788413 | Q65: =$H83/SUM($H$74:$H$90) -> 0.049934392 | R65: =$H84/SUM($H$74:$H$90) -> 0.058424203 | S65: =$H85/SUM($H$74:$H$90) -> 0.07126602 | T65: =$H86/SUM($H$74:$H$90) -> 0.070801507 | U65: =$H87/SUM($H$74:$H$90) -> 0.071993347 | V65: =$H88/SUM($H$74:$H$90) -> 0.077576675 | W65: =$H89/SUM($H$74:$H$90) -> 0.070217849 | X65: =$H90/SUM($H$74:$H$90) -> 0.080266206
A67: Value of preventing death | B67: =SUMPRODUCT(C63:X63,C65:X65) -> 67.772002 | C67: 33.4 | D67: 83.6 | E67: 84.5 | F67: 100.7 | G67: 127.3 | H67: 134.3 | I67: 133.1 | J67: 126.3 | K67: 118 | L67: 112.7 | M67: 106.3 | N67: 99.7 | O67: 86.4 | P67: 75.7 | Q67: 65.2 | R67: 54.8 | S67: 39.6 | T67: 31.4 | U67: 21.2 | V67: 16.5 | W67: 12.4 | X67: 12.4
A71: GBD data
A73: measure | B73: location | C73: sex | D73: age | E73: cause | F73: metric | G73: year | H73: val | I73: upper | J73: lower
A74: Deaths | B74: Sub-Saharan Africa | C74: Both | D74: 5 to 9 | E74: Enteric infections | F74: Number | G74: 2019 | H74: 31711.74 | I74: 44172.62 | J74: 22845.46
A75: Deaths | B75: Sub-Saharan Africa | C75: Both | D75: 10 to 14 | E75: Enteric infections | F75: Number | G75: 2019 | H75: 14188.93 | I75: 19769.38 | J75: 10036.62
A76: Deaths | B76: Sub-Saharan Africa | C76: Both | D76: 15 to 19 | E76: Enteric infections | F76: Number | G76: 2019 | H76: 11951.46 | I76: 17858.92 | J76: 8026.263
A77: Deaths | B77: Sub-Saharan Africa | C77: Both | D77: 20 to 24 | E77: Enteric infections | F77: Number | G77: 2019 | H77: 11157 | I77: 16946.38 | J77: 7211.808
A78: Deaths | B78: Sub-Saharan Africa | C78: Both | D78: 25 to 29 | E78: Enteric infections | F78: Number | G78: 2019 | H78: 10075.72 | I78: 15604.45 | J78: 6465.784
A79: Deaths | B79: Sub-Saharan Africa | C79: Both | D79: 30 to 34 | E79: Enteric infections | F79: Number | G79: 2019 | H79: 9987.619 | I79: 15836.47 | J79: 6419.897
A80: Deaths | B80: Sub-Saharan Africa | C80: Both | D80: 35 to 39 | E80: Enteric infections | F80: Number | G80: 2019 | H80: 10241.79 | I80: 16103.97 | J80: 6587.959
A81: Deaths | B81: Sub-Saharan Africa | C81: Both | D81: 40 to 44 | E81: Enteric infections | F81: Number | G81: 2019 | H81: 11088.34 | I81: 17905.91 | J81: 7032.376
A82: Deaths | B82: Sub-Saharan Africa | C82: Both | D82: 45 to 49 | E82: Enteric infections | F82: Number | G82: 2019 | H82: 12217.38 | I82: 19575.53 | J82: 7793.059
A83: Deaths | B83: Sub-Saharan Africa | C83: Both | D83: 50 to 54 | E83: Enteric infections | F83: Number | G83: 2019 | H83: 13621.1 | I83: 22430.69 | J83: 8409.627
A84: Deaths | B84: Sub-Saharan Africa | C84: Both | D84: 55 to 59 | E84: Enteric infections | F84: Number | G84: 2019 | H84: 15936.95 | I84: 25911.77 | J84: 9942.258
A85: Deaths | B85: Sub-Saharan Africa | C85: Both | D85: 60 to 64 | E85: Enteric infections | F85: Number | G85: 2019 | H85: 19439.94 | I85: 30982.75 | J85: 11913.31
... A157: Deaths | B157: Malawi | C157: Both | D157: 1 to 4 | E157: Enteric infections | F157: Number | G157: 2019 | H157: 1631.9914 | I157: 2670.5035 | J157: 935.97628

Sheet ILC Kenya
A1: In-line chlorination | B1: Kenya
A2: Under-5 deaths averted
A3: Percent of population that is under 5, Kenya 2019 | B3: 0.128
A4: Annual all-cause mortality in under-5s, Kenya 2019 | B4: 0.00831
A5: Relative risk of all-cause mortality | B5: ='Mortality effect size'!B11 -> 0.86389322
A6: Internal validity adjustment, under-5 mortality | B6: ='Internal validity adjustment'!B6 -> 0.79575782
A7: External validity adjustment | B7: ='External validity adjustment'!B6 -> 1.213858
A8: Percent reduction in under-5 all-cause mortality, initial estimate | B8: =(1-B5)*B6*B7 -> 0.13147058
A9: Maximum plausible percent reduction in under-5 all-cause mortality | B9: ='Internal validity adjustment'!B11 -> 0.109
A10: Percent reduction in under-5 all-cause mortality, final estimate | B10: =MIN(B8,B9) -> 0.109
A11: Annual under-5 deaths averted per 100,000 people covered, adjusted | B11: =B3*B4*B10*100000 -> 11.594112
A12: Moral value per under-5 death averted | B12: ='Moral weights'!B3 -> 107.98744
A13: Units of value per 100,000 people covered | B13: =B11*B12 -> 1252.0185
A15: Over-5 deaths averted
A16: Percent of population that is over 5, Kenya 2019 | B16: =1-B3 -> 0.872
A17: Annual all-cause mortality in over-5s, Kenya 2019 | B17: ='Baseline mortality'!E57 -> 0.0054903649
A18: Relative risk of all-cause mortality | B18: =B5 -> 0.86389322
A19: Over-5 mortality scaling factor | B19: ='Adult mortality scaling factor'!B17 -> 0.31739734
A20: Internal validity adjustment, over-5 mortality | B20: ='Internal validity adjustment'!B7 -> 0.50414983
A21: External validity adjustment | B21: ='External validity adjustment'!B6 -> 1.213858
A22: Plausibility cap adjustment | B22: =B10/B8 -> 0.82908285
A23: Annual over-5 deaths averted per 100,000 people covered, adjusted | B23: =B16*B17*(1-B18)*B19*B20*B21*B22*100000 -> 10.493641
A24: Implied reduction in over-5 all-cause mortality, for illustration only | B24: =(1-B18)*B19*B20*B21*B22 -> 0.021918382
A25: Moral value per over-5 death averted | B25: ='Moral weights'!B7 -> 68.400054
A26: Units of value per 100,000 covered | B26: =B23*B25 -> 717.76559
A28: Morbidity
A29: Annual YLDs attributed to enteric infections per 100,000, Kenya 2019 | B29: 179.59
A30: Relative risk of diarrhea incidence/prevalence from in-line chlorination | B30: ='Morbidity effect size'!B7 -> 0.805
A31: Internal validity adjustment | B31: ='Internal validity adjustment'!E3 -> 0.9
A32: External validity adjustment | B32: ='External validity adjustment'!B29 -> 0.95612229
A33: Implied reduction in morbidity | B33: =(1-B30)*B31*B32 -> 0.16779946
A34: Annual YLDs averted per 100,000 people covered, adjusted | B34: =B29*(1-B30)*B31*B32 -> 30.135105
A35: Moral value per YLD averted | B35: ='Moral weights'!B11 -> 2.3
A36: Units of value per 100,000 covered | B36: =B34*B35 -> 69.310742
A38: Development effects
A39: Units of value for development effects per treatment-year from seasonal malaria chemoprevention | B39: 0.126
A40: Development effects of in-line chlorination as a percentage of seasonal malaria chemoprevention | B40: 0.44
A41: Percent of population that is under 5, Kenya 2019 | B41: =B3 -> 0.128
A42: Percent of population that is 5-14, Kenya 2019 | B42: 0.254
A43: YLD rate attributed to enteric infections in under-5s, Kenya 2019 | B43: 317.43
A44: YLD rate attributed to enteric infections in 5-14s, Kenya 2019 | B44: 124.83
A45: Per capita burden of enteric infection morbidity in 5-14s as a percentage of under-5 morbidity | B45: =B44/B43 -> 0.39325206
A46: Annual units of value per 100,000 covered | B46: =((B39*B40*B41)+(B39*B40*B42*B45))*100000 -> 1263.4001
A47: Internal validity adjustment | B47: ='Internal validity adjustment'!B6 -> 0.79575782
A48: External validity adjustment | B48: ='External validity adjustment'!B6 -> 1.213858
A49: Adjusted annual units of value per 100,000 covered | B49: =B46*B47*B48 -> 1220.3649
A51: Medical costs averted
A52: Baseline annual diarrhea incidence per under-5 child | B52: ='Costs averted supp calculations'!G13 -> 4.0173377
A53: Morbidity reduction | B53: =B33 -> 0.16779946
A54: Averted diarrhea cases per under-five child per year | B54: =B52*B53 -> 0.6741071
A55: Annual cost of diarrhea illness averted, per under-5 | B55: ='Costs averted supp calculations'!B76 -> 15.949146
A56: Percentage of the population that is under 5, 2019 | B56: =B3 -> 0.128
A57: Annual cost of diarrhea illness averted, per person served | B57: =B55*B56 -> 2.0414907
A58: Non-diarrheal illness averted multiplier | B58: ='Internal validity adjustment'!B23 -> 3.7440053
A59: Total annual cost of illness averted, per person served | B59: =B57*B58 -> 7.6433522
A60: Internal validity adjustment for medical costs averted | B60: 1
A61: External validity adjustment for medical costs averted | B61: 1.1
A62: Adjusted total annual cost of illness averted, per person served | B62: =B59*B60*B61 -> 8.4076874
A63: Average consumption per capita, national average | B63: =99.82*12 -> 1197.84
A64: Per capita increase in ln(consumption) resulting from intervention | B64: =ln(B63+B62)-LN(B63) -> 0.0069945216
A65: Value assigned to doubling consumption for one person for one year | B65: 1
A66: Value assigned to increasing ln(consumption) by one unit for one person for one year | B66: =B65/ln(2) -> 1.442695
A67: Units of value from medical costs averted per person, per year | B67: =B64*B66 -> 0.010090962
A68: Units of value per 100,000 covered | B68: =B67*100000 -> 1009.0962
A70: Costs
A72: Annual cost per person served | B72: =DSW!B74 -> 1.6760327
A74: Results
A75: Units of value per dollar donated | B75: =((B13+B26+B36+B49+B68)/100000)/B72 -> 0.025468213
A76: Total units of value per $10,000 donated | B76: =B75*10000 -> 254.68213
A77: Units of value per $10,000 donated, GiveDirectly | B77: 33.5
A78: ILC vs. cash | B78: =B76/B77 -> 7.6024517
A80: Contribution of each outcome to overall cost-effectiveness
A81: Percent of cost-effectiveness coming from under-5 mortality reduction | B81: =B13/(B$13+B$26+B$36+B$49+B$68) -> 0.29331196
A82: Percent of cost-effectiveness coming from over-5 mortality reduction | B82: =B26/(B$13+B$26+B$36+B$49+B$68) -> 0.16815186
A83: Percent of cost-effectiveness coming from morbidity reduction | B83: =B36/(B$13+B$26+B$36+B$49+B$68) -> 0.016237515
A84: Percent of cost-effectiveness coming from development effects | B84: =B49/(B$13+B$26+B$36+B$49+B$68) -> 0.28589644
A85: Percent of cost-effectiveness coming from medical costs averted | B85: =B68/(B$13+B$26+B$36+B$49+B$68) -> 0.23640224
A87: Note: This does not include leverage and funging adjustments.

Sheet DSW_short term
A1: Dispensers for Safe Water | B1: Kenya | C1: Uganda | D1: Malawi
A2: Under-5 deaths averted
A3: Percent of population that is under 5, 2019 | B3: 0.1255 | C3: 0.1362 | D3: 0.137
A4: Annual all-cause mortality in under-5s, DSW counties | B4: ='Baseline mortality'!$F17 -> 0.011882306 | C4: ='Baseline mortality'!$F33 -> 0.010936118 | D4: ='Baseline mortality'!$F38 -> 0.01342
A5: Relative risk of all-cause mortality | B5: ='Mortality effect size'!B11 -> 0.86389322 | C5: ='Mortality effect size'!B11 -> 0.86389322 | D5: ='Mortality effect size'!B11 -> 0.86389322
A6: Internal validity adjustment, under-5 mortality | B6: ='Internal validity adjustment'!B6 -> 0.79575782 | C6: ='Internal validity adjustment'!B6 -> 0.79575782 | D6: ='Internal validity adjustment'!B6 -> 0.79575782
A7: External validity adjustment | B7: ='External validity adjustment'!B11 -> 0.55825117 | C7: ='External validity adjustment'!B16 -> 0.56602231 | D7: ='External validity adjustment'!B21 -> 1.1082514
A8: Percent reduction in under-5 all-cause mortality, initial estimate | B8: =(1-B5)*B6*B7 -> 0.060463087 | C8: =(1-C5)*C6*C7 -> 0.061304764 | D8: =(1-D5)*D6*D7 -> 0.12003253
A9: Maximum plausible percent reduction in under-5 all-cause mortality | B9: ='Internal validity adjustment'!B12 -> 0.056 | C9: ='Internal validity adjustment'!B13 -> 0.084 | D9: ='Internal validity adjustment'!B14 -> 0.109
A10: Percent reduction in under-5 all-cause mortality, final estimate | B10: =MIN(B8,B9) -> 0.056 | C10: =MIN(C8,C9) -> 0.061304764 | D10: =MIN(D8,D9) -> 0.109
A11: Annual under-5 deaths averted per 100,000 people covered, adjusted | B11: =B3*B4*B10*100000 -> 8.3508846 | C11: =C3*C4*C10*100000 -> 9.1313405 | D11: =D3*D4*D10*100000 -> 20.040086
A12: Moral value per under-5 death averted | B12: ='Moral weights'!B3 -> 107.98744 | C12: ='Moral weights'!B4 -> 111.41844 | D12: ='Moral weights'!B5 -> 112.92449
A13: Units of value per 100,000 covered | B13: =B11*B12 -> 901.79065 | C13: =C11*C12 -> 1017.3997 | D13: =D11*D12 -> 2263.0164
A15: Over-5 deaths averted
A16: Percent of population that is over 5, 2019 | B16: =1-B3 -> 0.8745 | C16: =1-C3 -> 0.8638 | D16: =1-D3 -> 0.863
A17: Annual all-cause mortality in over-5s, 2019 | B17: ='Baseline mortality'!$E57 -> 0.0054903649 | C17: ='Baseline mortality'!$F57 -> 0.0044403378 | D17: ='Baseline mortality'!$G57 -> 0.0053512929
A18: Relative risk of all-cause mortality | B18: =B5 -> 0.86389322 | C18: =C5 -> 0.86389322 | D18: =D5 -> 0.86389322
A19: Over-5 mortality scaling factor | B19: ='Adult mortality scaling factor'!$B17 -> 0.31739734 | C19: ='Adult mortality scaling factor'!$C17 -> 0.89173438 | D19: ='Adult mortality scaling factor'!$D17 -> 0.6011233
A20: Internal validity adjustment, over-5 mortality | B20: ='Internal validity adjustment'!B7 -> 0.50414983 | C20: ='Internal validity adjustment'!B7 -> 0.50414983 | D20: ='Internal validity adjustment'!B7 -> 0.50414983
A21: External validity adjustment | B21: ='External validity adjustment'!B11 -> 0.55825117 | C21: ='External validity adjustment'!B16 -> 0.56602231 | D21: ='External validity adjustment'!B21 -> 1.1082514
A22: Plausibility cap adjustment | B22: =B10/B8 -> 0.92618493 | C22: =C10/C8 -> 1 | D22: =D10/D8 -> 0.9080872
A23: Annual over-5 deaths averted per 100,000 people covered, adjusted | B23: =B16*B17*(1-B18)*B19*B20*B21*B22*100000 -> 5.4066848 | C23: =C16*C17*(1-C18)*C19*C20*C21*C22*100000 -> 13.284269 | D23: =D16*D17*(1-D18)*D19*D20*D21*D22*100000 -> 19.170714
A24: Implied reduction in over-5 all-cause mortality, for illustration only | B24: =(1-B18)*B19*B20*B21*B22 -> 0.01126082 | C24: =(1-C18)*C19*C20*C21*C22 -> 0.034634462 | D24: =(1-D18)*D19*D20*D21*D22 -> 0.041511533
A25: Moral value per over-5 death averted | B25: ='Moral weights'!B7 -> 68.400054 | C25: ='Moral weights'!B8 -> 70.672378 | D25: ='Moral weights'!B9 -> 66.077715
A26: Units of value per 100,000 covered | B26: =B23*B25 -> 369.81753 | C26: =C23*C25 -> 938.8309 | D26: =D23*D25 -> 1266.757
A28: Morbidity
A29: Annual YLDs attributed to enteric infections per 100,000, 2019 | B29: 179.59 | C29: 190.23 | D29: 218.97
A30: Relative risk reduction for diarrhea episodes | B30: ='Morbidity effect size'!B7 -> 0.805 | C30: ='Morbidity effect size'!B7 -> 0.805 | D30: ='Morbidity effect size'!B7 -> 0.805
A31: Internal validity adjustment | B31: ='Internal validity adjustment'!E3 -> 0.9 | C31: ='Internal validity adjustment'!E3 -> 0.9 | D31: ='Internal validity adjustment'!E3 -> 0.9
A32: External validity adjustment | B32: ='External validity adjustment'!B33 -> 0.48857663 | C32: ='External validity adjustment'!B37 -> 0.78522404 | D32: ='External validity adjustment'!B41 -> 1.0170933
A33: Implied reduction in morbidity | B33: =(1-B30)*B31*B32 -> 0.085745198 | C33: =(1-C30)*C31*C32 -> 0.13780682 | D33: =(1-D30)*D31*D32 -> 0.17849988
A34: Annual YLDs averted per 100,000 people covered, adjusted | B34: =B29*(1-B30)*B31*B32 -> 15.39898 | C34: =C29*(1-C30)*C31*C32 -> 26.214991 | D34: =D29*(1-D30)*D31*D32 -> 39.086118
A35: Moral value per YLD averted | B35: ='Moral weights'!$B11 -> 2.3 | C35: ='Moral weights'!$B11 -> 2.3 | D35: ='Moral weights'!$B11 -> 2.3
A36: Units of value per 100,000 covered | B36: =B34*B35 -> 35.417654 | C36: =C34*C35 -> 60.29448 | D36: =D34*D35 -> 89.898072
A38: Development effects
A39: Units of value for development effects per treatment-year from seasonal malaria chemoprevention | B39: 0.126 | C39: 0.126 | D39: 0.126
A40: Development effects of in-line chlorination as a percentage of seasonal malaria chemoprevention | B40: 0.44 | C40: 0.44 | D40: 0.44
A41: Percent of population that is under 5, 2019 | B41: =B3 -> 0.1255 | C41: =C3 -> 0.1362 | D41: =D3 -> 0.137
A42: Percent of population that is 5-14, 2019 | B42: 0.254 | C42: 0.292 | D42: 0.287
A43: YLD rate attributed to enteric infections in under-5s, 2019 | B43: 317.43 | C43: 398.01 | D43: 460.79
A44: YLD rate attributed to enteric infections in 5-14s, 2019 | B44: 124.83 | C44: 116.35 | D44: 140.43
A45: Per capita burden of enteric infection morbidity in 5-14s as a percentage of under-5 morbidity | B45: =B44/B43 -> 0.39325206 | C45: =C44/C43 -> 0.29232934 | D45: =D44/D43 -> 0.30475922
A46: Annual units of value per 100,000 covered | B46: =((B39*B40*B41)+(B39*B40*B42*B45))*100000 -> 1249.5401 | C46: =((C39*C40*C41)+(C39*C40*C42*C45))*100000 -> 1228.3296 | D46: =((D39*D40*D41)+(D39*D40*D42*D45))*100000 -> 1244.4389
A47: Internal validity adjustment | B47: ='Internal validity adjustment'!$B6 -> 0.79575782 | C47: ='Internal validity adjustment'!B6 -> 0.79575782 | D47: ='Internal validity adjustment'!B6 -> 0.79575782
A48: External validity adjustment | B48: ='External validity adjustment'!B11 -> 0.55825117 | C48: ='External validity adjustment'!B16 -> 0.56602231 | D48: ='External validity adjustment'!B21 -> 1.1082514
A49: Adjusted annual units of value per 100,000 covered | B49: =B46*B47*B48 -> 555.08662 | C49: =C46*C47*C48 -> 553.26013 | D49: =D46*D47*D48 -> 1097.4703
A51: Medical costs averted
A52: Baseline annual diarrhea incidence per under-5 child | B52: ='Costs averted supp calculations'!G13 -> 4.0173377 | C52: ='Costs averted supp calculations'!H31 -> 3.5683236 | D52: ='Costs averted supp calculations'!H45 -> 4.1253906
A53: Morbidity reduction | B53: =B33 -> 0.085745198 | C53: =C33 -> 0.13780682 | D53: =D33 -> 0.17849988
A54: Averted diarrhea cases per under-five child per year | B54: =B52*B53 -> 0.34446741 | C54: =C52*C53 -> 0.49173933 | D54: =D52*D53 -> 0.73638172
A55: Annual cost of diarrhea illness averted, per under-5 | B55: ='Costs averted supp calculations'!C76 -> 8.1499828 | C55: ='Costs averted supp calculations'!D76 -> 5.7002878 | D55: ='Costs averted supp calculations'!E76 -> 8.0537424
A56: Percentage of the population that is under 5, 2019 | B56: =B3 -> 0.1255 | C56: =C3 -> 0.1362 | D56: =D3 -> 0.137
A57: Annual cost of diarrhea illness averted, per person served | B57: =B55*B56 -> 1.0228228 | C57: =C55*C56 -> 0.7763792 | D57: =D55*D56 -> 1.1033627
A58: Non-diarrheal illness averted multiplier | B58: ='Internal validity adjustment'!B23 -> 3.7440053 | C58: ='Internal validity adjustment'!B23 -> 3.7440053 | D58: ='Internal validity adjustment'!B23 -> 3.7440053
A59: Total annual cost of illness averted, per person served | B59: =B57*B58 -> 3.8294541 | C59: =C57*C58 -> 2.9067678 | D59: =D57*D58 -> 4.1309959
A60: Internal validity adjustment for medical costs averted | B60: 1 | C60: 1 | D60: 1
A61: External validity adjustment for medical costs averted | B61: 1.1 | C61: 1.1 | D61: 1.1
A62: Adjusted total annual cost of illness averted, per person served | B62: =B59*B60*B61 -> 4.2123995 | C62: =C59*C60*C61 -> 3.1974446 | D62: =D59*D60*D61 -> 4.5440954
A63: Average consumption per capita, national average | B63: =99.82*12 -> 1197.84 | C63: =97.43*12 -> 1169.16 | D63: =62.79*12 -> 753.48
A64: Adjustment for lower than average consumption in DSW beneficiaries | B64: 0.558 | C64: 0.534 | D64: 0.53
A65: DSW beneficiary annual consumption per capita, rough estimate | B65: =B63*B64 -> 668.39472 | C65: =C63*C64 -> 624.33144 | D65: =D63*D64 -> 399.3444
A66: Per capita increase in ln(consumption) resulting from intervention | B66: =ln(B65+B62)-LN(B65) -> 0.0062824871 | C66: =ln(C65+C62)-LN(C65) -> 0.00510832 | D66: =ln(D65+D62)-LN(D65) -> 0.011314636
A67: Value assigned to doubling consumption for one person for one year | B67: 1 | C67: 1 | D67: 1
A68: Value assigned to increasing ln(consumption) by one unit for one person for one year | B68: =B67/ln(2) -> 1.442695 | C68: =C67/ln(2) -> 1.442695 | D68: =D67/ln(2) -> 1.442695
A69: Units of value from medical costs averted per person, per year | B69: =B66*B68 -> 0.009063713 | C69: =C66*C68 -> 0.007369748 | D69: =D66*D68 -> 0.016323569
A70: Units of value per 100,000 covered | B70: =B69*100000 -> 906.3713 | C70: =C69*100000 -> 736.9748 | D70: =D69*100000 -> 1632.3569
A72: Costs
A73: Annual cost per under-5 child served | B73: 17.68 | C73: 8.1 | D73: 15.56
A74: Annual cost per person served | B74: =IFERROR(__xludf.DUMMYFUNCTION("IMPORTRANGE(""https://docs.google.com/spreadsheets/d/1cCwtsgnz-Va6YXiq3YfCBS0tXhPCGwXft9-I3VIi2_I/edit#gid=1489192849"",""Costs!d33"")"),2.4905135258789595) -> 2.4905135 | C74: =IFERROR(__xludf.DUMMYFUNCTION("IMPORTRANGE(""https://docs.google.com/spreadsheets/d/1cCwtsgnz-Va6YXiq3YfCBS0tXhPCGwXft9-I3VIi2_I/edit#gid=1489192849"",""Costs!c33"")"),1.3777443795781372) -> 1.3777444 | D74: =IFERROR(__xludf.DUMMYFUNCTION("IMPORTRANGE(""https://docs.google.com/spreadsheets/d/1cCwtsgnz-Va6YXiq3YfCBS0tXhPCGwXft9-I3VIi2_I/edit#gid=1489192849"",""Costs!b33"")"),2.0960773568600675) -> 2.0960774
A76: Results
A77: Units of value per dollar donated | B77: =((B13+B26+B36+B49+B70)/100000)/B74 -> 0.011116116 | C77: =((C13+C26+C36+C49+C70)/100000)/C74 -> 0.024001259 | D77: =((D13+D26+D36+D49+D70)/100000)/D74 -> 0.030292292
A78: Total units of value per $10,000 donated | B78: =B77*10000 -> 111.16116 | C78: =C77*10000 -> 240.01259 | D78: =D77*10000 -> 302.92292
A79: Units of value per $10,000 donated, GiveDirectly | B79: 33.5 | C79: 33.5 | D79: 33.5
A80: DSW vs. cash before adjustments | B80: =B78/B79 -> 3.3182436 | C80: =C78/C79 -> 7.1645551 | D80: =D78/D79 -> 9.0424751
A82: Downside adjustments
A84: Risk of wastage
A85: Double treatment | B85: 0 | C85: 0 | D85: 0
A86: Ineffective goods | B86: 0 | C86: 0 | D86: 0
A87: Goods purchased and left in storage until they expire / Cash doesn't reach recipients or is taken back from them inappropriately | B87: 0 | C87: 0 | D87: 0
A88: Total adjustment for risk of wastage | B88: =sum(B85:B87) -> 0 | C88: =sum(C85:C87) -> 0 | D88: =sum(D85:D87) -> 0
A90: Quality of monitoring and evaluation
A91: Unrepresentative monitoring results | B91: 0.1 | C91: 0.1 | D91: 0.1
A92: False monitoring results | B92: 0 | C92: 0 | D92: 0
A93: Total adjustment for quality of monitoring and evaluation | B93: =sum(B91:B92) -> 0.1 | C93: =sum(C91:C92) -> 0.1 | D93: =sum(D91:D92) -> 0.1
A95: Confidence in funds being used for intended purpose
A96: Change of priorities | B96: 0 | C96: 0 | D96: 0
A97: Non-funding bottlenecks | B97: 0 | C97: 0 | D97: 0
A98: Within-org fungibility | B98: 0 | C98: 0 | D98: 0
A99: Total adjustment for confidence in funds being used for intended purpose | B99: =sum(B96:B98) -> 0 | C99: =sum(C96:C98) -> 0 | D99: =sum(D96:D98) -> 0
A101: Total downside adjustment factor | B101: =1-sum(B88,B93,B99) -> 0.9 | C101: =1-sum(C88,C93,C99) -> 0.9 | D101: =1-sum(D88,D93,D99) -> 0.9
A103: Inclusion/exclusion
A104: Adjustments for excluded effects
A105: Treatment costs averted | B105: 0 | C105: 0 | D105: 0
A106: Spillover effects on neighbouring communities | B106: 0.05 | C106: 0.05 | D106: 0.05
A108: Total adjustment factor for excluded effects | B108: =sum(1,B105:B106) -> 1.05 | C108: =sum(1,C105:C106) -> 1.05 | D108: =sum(1,D105:D106) -> 1.05
A109: Total units of value after adjustments for downside adjustments and excluded effects | B109: =B78*B101*B108 -> 105.0473 | C109: =C78*C101*C108 -> 226.8119 | D109: =D78*D101*D108 -> 286.26216
A111: Leverage / Funging
A112: Government costs | B112: =IFERROR(__xludf.DUMMYFUNCTION("IMPORTRANGE(""https://docs.google.com/spreadsheets/d/1cCwtsgnz-Va6YXiq3YfCBS0tXhPCGwXft9-I3VIi2_I/edit#gid=1489192849"",""Costs!d65:d65"")"),0.0) -> 0 | C112: =IFERROR(__xludf.DUMMYFUNCTION("IMPORTRANGE(""https://docs.google.com/spreadsheets/d/1cCwtsgnz-Va6YXiq3YfCBS0tXhPCGwXft9-I3VIi2_I/edit#gid=1489192849"",""Costs!C65:C65"")"),0.03289856102039222) -> 0.032898561 | D112: =IFERROR(__xludf.DUMMYFUNCTION("IMPORTRANGE(""https://docs.google.com/spreadsheets/d/1cCwtsgnz-Va6YXiq3YfCBS0tXhPCGwXft9-I3VIi2_I/edit#gid=1489192849"",""Costs!B65"")"),0.22188710821689012) -> 0.22188711
A114: Upstream / downstream expenditure
A115: How much of government spending is upstream of IRC | B115: 0 | C115: 0 | D115: 0
...

Sheet DSW
A1: Dispensers for Safe Water | B1: Kenya | C1: Uganda | D1: Malawi
A2: Under-5 deaths averted
A3: Percent of population that is under 5, 2019 | B3: 0.1255 | C3: 0.1362 | D3: 0.137
A4: Annual all-cause mortality in under-5s, DSW counties | B4: ='Baseline mortality'!$F17 -> 0.011882306 | C4: ='Baseline mortality'!$F33 -> 0.010936118 | D4: ='Baseline mortality'!$F38 -> 0.01342
A5: Relative risk of all-cause mortality | B5: ='Mortality effect size'!B11 -> 0.86389322 | C5: ='Mortality effect size'!B11 -> 0.86389322 | D5: ='Mortality effect size'!B11 -> 0.86389322
A6: Internal validity adjustment, under-5 mortality | B6: ='Internal validity adjustment'!B6 -> 0.79575782 | C6: ='Internal validity adjustment'!B6 -> 0.79575782 | D6: ='Internal validity adjustment'!B6 -> 0.79575782
A7: External validity adjustment | B7: ='External validity adjustment'!B11 -> 0.55825117 | C7: ='External validity adjustment'!B16 -> 0.56602231 | D7: ='External validity adjustment'!B21 -> 1.1082514
A8: Percent reduction in under-5 all-cause mortality, initial estimate | B8: =(1-B5)*B6*B7 -> 0.060463087 | C8: =(1-C5)*C6*C7 -> 0.061304764 | D8: =(1-D5)*D6*D7 -> 0.12003253
A9: Maximum plausible percent reduction in under-5 all-cause mortality | B9: ='Internal validity adjustment'!B12 -> 0.056 | C9: ='Internal validity adjustment'!B13 -> 0.084 | D9: ='Internal validity adjustment'!B14 -> 0.109
A10: Percent reduction in under-5 all-cause mortality, final estimate | B10: =MIN(B8,B9) -> 0.056 | C10: =MIN(C8,C9) -> 0.061304764 | D10: =MIN(D8,D9) -> 0.109
A11: Annual under-5 deaths averted per 100,000 people covered, adjusted | B11: =B3*B4*B10*100000 -> 8.3508846 | C11: =C3*C4*C10*100000 -> 9.1313405 | D11: =D3*D4*D10*100000 -> 20.040086
A12: Moral value per under-5 death averted | B12: ='Moral weights'!B3 -> 107.98744 | C12: ='Moral weights'!B4 -> 111.41844 | D12: ='Moral weights'!B5 -> 112.92449
A13: Units of value per 100,000 covered | B13: =B11*B12 -> 901.79065 | C13: =C11*C12 -> 1017.3997 | D13: =D11*D12 -> 2263.0164
A15: Over-5 deaths averted
A16: Percent of population that is over 5, 2019 | B16: =1-B3 -> 0.8745 | C16: =1-C3 -> 0.8638 | D16: =1-D3 -> 0.863
A17: Annual all-cause mortality in over-5s, 2019 | B17: ='Baseline mortality'!$E57 -> 0.0054903649 | C17: ='Baseline mortality'!$F57 -> 0.0044403378 | D17: ='Baseline mortality'!$G57 -> 0.0053512929
A18: Relative risk of all-cause mortality | B18: =B5 -> 0.86389322 | C18: =C5 -> 0.86389322 | D18: =D5 -> 0.86389322
A19: Over-5 mortality scaling factor | B19: ='Adult mortality scaling factor'!$B17 -> 0.31739734 | C19: ='Adult mortality scaling factor'!$C17 -> 0.89173438 | D19: ='Adult mortality scaling factor'!$D17 -> 0.6011233
A20: Internal validity adjustment, over-5 mortality | B20: ='Internal validity adjustment'!B7 -> 0.50414983 | C20: ='Internal validity adjustment'!B7 -> 0.50414983 | D20: ='Internal validity adjustment'!B7 -> 0.50414983
A21: External validity adjustment | B21: ='External validity adjustment'!B11 -> 0.55825117 | C21: ='External validity adjustment'!B16 -> 0.56602231 | D21: ='External validity adjustment'!B21 -> 1.1082514
A22: Plausibility cap adjustment | B22: =B10/B8 -> 0.92618493 | C22: =C10/C8 -> 1 | D22: =D10/D8 -> 0.9080872
A23: Annual over-5 deaths averted per 100,000 people covered, adjusted | B23: =B16*B17*(1-B18)*B19*B20*B21*B22*100000 -> 5.4066848 | C23: =C16*C17*(1-C18)*C19*C20*C21*C22*100000 -> 13.284269 | D23: =D16*D17*(1-D18)*D19*D20*D21*D22*100000 -> 19.170714
A24: Implied reduction in over-5 all-cause mortality, for illustration only | B24: =(1-B18)*B19*B20*B21*B22 -> 0.01126082 | C24: =(1-C18)*C19*C20*C21*C22 -> 0.034634462 | D24: =(1-D18)*D19*D20*D21*D22 -> 0.041511533
A25: Moral value per over-5 death averted | B25: ='Moral weights'!B7 -> 68.400054 | C25: ='Moral weights'!B8 -> 70.672378 | D25: ='Moral weights'!B9 -> 66.077715
A26: Units of value per 100,000 covered | B26: =B23*B25 -> 369.81753 | C26: =C23*C25 -> 938.8309 | D26: =D23*D25 -> 1266.757
A28: Morbidity
A29: Annual YLDs attributed to enteric infections per 100,000, 2019 | B29: 179.59 | C29: 190.23 | D29: 218.97
A30: Relative risk reduction for diarrhea episodes | B30: ='Morbidity effect size'!B7 -> 0.805 | C30: ='Morbidity effect size'!B7 -> 0.805 | D30: ='Morbidity effect size'!B7 -> 0.805
A31: Internal validity adjustment | B31: ='Internal validity adjustment'!E3 -> 0.9 | C31: ='Internal validity adjustment'!E3 -> 0.9 | D31: ='Internal validity adjustment'!E3 -> 0.9
A32: External validity adjustment | B32: ='External validity adjustment'!B33 -> 0.48857663 | C32: ='External validity adjustment'!B37 -> 0.78522404 | D32: ='External validity adjustment'!B41 -> 1.0170933
A33: Implied reduction in morbidity | B33: =(1-B30)*B31*B32 -> 0.085745198 | C33: =(1-C30)*C31*C32 -> 0.13780682 | D33: =(1-D30)*D31*D32 -> 0.17849988
A34: Annual YLDs averted per 100,000 people covered, adjusted | B34: =B29*(1-B30)*B31*B32 -> 15.39898 | C34: =C29*(1-C30)*C31*C32 -> 26.214991 | D34: =D29*(1-D30)*D31*D32 -> 39.086118
A35: Moral value per YLD averted | B35: ='Moral weights'!$B11 -> 2.3 | C35: ='Moral weights'!$B11 -> 2.3 | D35: ='Moral weights'!$B11 -> 2.3
A36: Units of value per 100,000 covered | B36: =B34*B35 -> 35.417654 | C36: =C34*C35 -> 60.29448 | D36: =D34*D35 -> 89.898072
A38: Development effects
A39: Units of value for development effects per treatment-year from seasonal malaria chemoprevention | B39: 0.126 | C39: 0.126 | D39: 0.126
A40: Development effects of in-line chlorination as a percentage of seasonal malaria chemoprevention | B40: 0.44 | C40: 0.44 | D40: 0.44
A41: Percent of population that is under 5, 2019 | B41: =B3 -> 0.1255 | C41: =C3 -> 0.1362 | D41: =D3 -> 0.137
A42: Percent of population that is 5-14, 2019 | B42: 0.254 | C42: 0.292 | D42: 0.287
A43: YLD rate attributed to enteric infections in under-5s, 2019 | B43: 317.43 | C43: 398.01 | D43: 460.79
A44: YLD rate attributed to enteric infections in 5-14s, 2019 | B44: 124.83 | C44: 116.35 | D44: 140.43
A45: Per capita burden of enteric infection morbidity in 5-14s as a percentage of under-5 morbidity | B45: =B44/B43 -> 0.39325206 | C45: =C44/C43 -> 0.29232934 | D45: =D44/D43 -> 0.30475922
A46: Annual units of value per 100,000 covered | B46: =((B39*B40*B41)+(B39*B40*B42*B45))*100000 -> 1249.5401 | C46: =((C39*C40*C41)+(C39*C40*C42*C45))*100000 -> 1228.3296 | D46: =((D39*D40*D41)+(D39*D40*D42*D45))*100000 -> 1244.4389
A47: Internal validity adjustment | B47: ='Internal validity adjustment'!$B6 -> 0.79575782 | C47: ='Internal validity adjustment'!B6 -> 0.79575782 | D47: ='Internal validity adjustment'!B6 -> 0.79575782
A48: External validity adjustment | B48: ='External validity adjustment'!B11 -> 0.55825117 | C48: ='External validity adjustment'!B16 -> 0.56602231 | D48: ='External validity adjustment'!B21 -> 1.1082514
A49: Adjusted annual units of value per 100,000 covered | B49: =B46*B47*B48 -> 555.08662 | C49: =C46*C47*C48 -> 553.26013 | D49: =D46*D47*D48 -> 1097.4703
A51: Medical costs averted
A52: Baseline annual diarrhea incidence per under-5 child | B52: ='Costs averted supp calculations'!G13 -> 4.0173377 | C52: ='Costs averted supp calculations'!H31 -> 3.5683236 | D52: ='Costs averted supp calculations'!H45 -> 4.1253906
A53: Morbidity reduction | B53: =B33 -> 0.085745198 | C53: =C33 -> 0.13780682 | D53: =D33 -> 0.17849988
A54: Averted diarrhea cases per under-five child per year | B54: =B52*B53 -> 0.34446741 | C54: =C52*C53 -> 0.49173933 | D54: =D52*D53 -> 0.73638172
A55: Annual cost of diarrhea illness averted, per under-5 | B55: ='Costs averted supp calculations'!C76 -> 8.1499828 | C55: ='Costs averted supp calculations'!D76 -> 5.7002878 | D55: ='Costs averted supp calculations'!E76 -> 8.0537424
A56: Percentage of the population that is under 5, 2019 | B56: =B3 -> 0.1255 | C56: =C3 -> 0.1362 | D56: =D3 -> 0.137
A57: Annual cost of diarrhea illness averted, per person served | B57: =B55*B56 -> 1.0228228 | C57: =C55*C56 -> 0.7763792 | D57: =D55*D56 -> 1.1033627
A58: Non-diarrheal illness averted multiplier | B58: ='Internal validity adjustment'!B23 -> 3.7440053 | C58: ='Internal validity adjustment'!B23 -> 3.7440053 | D58: ='Internal validity adjustment'!B23 -> 3.7440053
A59: Total annual cost of illness averted, per person served | B59: =B57*B58 -> 3.8294541 | C59: =C57*C58 -> 2.9067678 | D59: =D57*D58 -> 4.1309959
A60: Internal validity adjustment for medical costs averted | B60: 1 | C60: 1 | D60: 1
A61: External validity adjustment for medical costs averted | B61: 1.1 | C61: 1.1 | D61: 1.1
A62: Adjusted total annual cost of illness averted, per person served | B62: =B59*B60*B61 -> 4.2123995 | C62: =C59*C60*C61 -> 3.1974446 | D62: =D59*D60*D61 -> 4.5440954
A63: Average consumption per capita, national average | B63: =99.82*12 -> 1197.84 | C63: =97.43*12 -> 1169.16 | D63: =62.79*12 -> 753.48
A64: Adjustment for lower than average consumption in DSW beneficiaries | B64: 0.558 | C64: 0.534 | D64: 0.53
A65: DSW beneficiary annual consumption per capita, rough estimate | B65: =B63*B64 -> 668.39472 | C65: =C63*C64 -> 624.33144 | D65: =D63*D64 -> 399.3444
A66: Per capita increase in ln(consumption) resulting from intervention | B66: =ln(B65+B62)-LN(B65) -> 0.0062824871 | C66: =ln(C65+C62)-LN(C65) -> 0.00510832 | D66: =ln(D65+D62)-LN(D65) -> 0.011314636
A67: Value assigned to doubling consumption for one person for one year | B67: 1 | C67: 1 | D67: 1
A68: Value assigned to increasing ln(consumption) by one unit for one person for one year | B68: =B67/ln(2) -> 1.442695 | C68: =C67/ln(2) -> 1.442695 | D68: =D67/ln(2) -> 1.442695
A69: Units of value from medical costs averted per person, per year | B69: =B66*B68 -> 0.009063713 | C69: =C66*C68 -> 0.007369748 | D69: =D66*D68 -> 0.016323569
A70: Units of value per 100,000 covered | B70: =B69*100000 -> 906.3713 | C70: =C69*100000 -> 736.9748 | D70: =D69*100000 -> 1632.3569
A72: Costs
A74: Annual cost per person served | B74: =IFERROR(__xludf.DUMMYFUNCTION("IMPORTRANGE(""https://docs.google.com/spreadsheets/d/1cCwtsgnz-Va6YXiq3YfCBS0tXhPCGwXft9-I3VIi2_I/edit#gid=1489192849"",""Costs!d61"")"),1.6760327345434698) -> 1.6760327 | C74: =IFERROR(__xludf.DUMMYFUNCTION("IMPORTRANGE(""https://docs.google.com/spreadsheets/d/1cCwtsgnz-Va6YXiq3YfCBS0tXhPCGwXft9-I3VIi2_I/edit#gid=1489192849"",""Costs!c61"")"),1.2160493032038628) -> 1.2160493 | D74: =IFERROR(__xludf.DUMMYFUNCTION("IMPORTRANGE(""https://docs.google.com/spreadsheets/d/1cCwtsgnz-Va6YXiq3YfCBS0tXhPCGwXft9-I3VIi2_I/edit#gid=1489192849"",""Costs!b61"")"),1.857356006279095) -> 1.857356
A76: Results
A77: Units of value per dollar donated | B77: =((B13+B26+B36+B49+B70)/100000)/B74 -> 0.016518077 | C77: =((C13+C26+C36+C49+C70)/100000)/C74 -> 0.027192648 | D77: =((D13+D26+D36+D49+D70)/100000)/D74 -> 0.034185685
A78: Total units of value per $10,000 donated | B78: =B77*10000 -> 165.18077 | C78: =C77*10000 -> 271.92648 | D78: =D77*10000 -> 341.85685
A79: Units of value per $10,000 donated, GiveDirectly | B79: 33.5 | C79: 33.5 | D79: 33.5
A80: DSW vs. cash before adjustments | B80: =B78/B79 -> 4.9307692 | C80: =C78/C79 -> 8.1172083 | D80: =D78/D79 -> 10.204682
A82: Downside adjustments
A84: Risk of wastage
A85: Double treatment | B85: 0 | C85: 0 | D85: 0
A86: Ineffective goods | B86: 0 | C86: 0 | D86: 0
A87: Goods purchased and left in storage until they expire / Cash doesn't reach recipients or is taken back from them inappropriately | B87: 0 | C87: 0 | D87: 0
A88: Total adjustment for risk of wastage | B88: =sum(B85:B87) -> 0 | C88: =sum(C85:C87) -> 0 | D88: =sum(D85:D87) -> 0
A90: Quality of monitoring and evaluation
A91: Unrepresentative monitoring results | B91: 0.1 | C91: 0.1 | D91: 0.1
A92: False monitoring results | B92: 0 | C92: 0 | D92: 0
A93: Total adjustment for quality of monitoring and evaluation | B93: =sum(B91:B92) -> 0.1 | C93: =sum(C91:C92) -> 0.1 | D93: =sum(D91:D92) -> 0.1
A95: Confidence in funds being used for intended purpose
A96: Change of priorities | B96: 0 | C96: 0 | D96: 0
A97: Non-funding bottlenecks | B97: 0 | C97: 0 | D97: 0
A98: Within-org fungibility | B98: 0 | C98: 0 | D98: 0
A99: Total adjustment for confidence in funds being used for intended purpose | B99: =sum(B96:B98) -> 0 | C99: =sum(C96:C98) -> 0 | D99: =sum(D96:D98) -> 0
A101: Total downside adjustment factor | B101: =1-sum(B88,B93,B99) -> 0.9 | C101: =1-sum(C88,C93,C99) -> 0.9 | D101: =1-sum(D88,D93,D99) -> 0.9
A103: Inclusion/exclusion
A104: Adjustments for excluded effects
A105: Treatment costs averted | B105: 0 | C105: 0 | D105: 0
A106: Spillover effects on neighbouring communities | B106: 0.05 | C106: 0.05 | D106: 0.05
A108: Total adjustment factor for excluded effects | B108: =sum(1,B105:B106) -> 1.05 | C108: =sum(1,C105:C106) -> 1.05 | D108: =sum(1,D105:D106) -> 1.05
A109: Total units of value after adjustments for downside adjustments and excluded effects | B109: =B78*B101*B108 -> 156.09583 | C109: =C78*C101*C108 -> 256.97052 | D109: =D78*D101*D108 -> 323.05472
A111: Leverage / Funging
A112: Government costs | B112: =IFERROR(__xludf.DUMMYFUNCTION("IMPORTRANGE(""https://docs.google.com/spreadsheets/d/1cCwtsgnz-Va6YXiq3YfCBS0tXhPCGwXft9-I3VIi2_I/edit#gid=1489192849"",""Costs!d65"")"),0.0) -> 0 | C112: =IFERROR(__xludf.DUMMYFUNCTION("IMPORTRANGE(""https://docs.google.com/spreadsheets/d/1cCwtsgnz-Va6YXiq3YfCBS0tXhPCGwXft9-I3VIi2_I/edit#gid=1489192849"",""Costs!C65"")"),0.03289856102039222) -> 0.032898561 | D112: =IFERROR(__xludf.DUMMYFUNCTION("IMPORTRANGE(""https://docs.google.com/spreadsheets/d/1cCwtsgnz-Va6YXiq3YfCBS0tXhPCGwXft9-I3VIi2_I/edit#gid=1489192849"",""Costs!B65"")"),0.22188710821689012) -> 0.22188711
A114: Upstream / downstream expenditure
A115: How much of government spending is upstream of DSW | B115: 0 | C115: 0 | D115: 0
A116: Expenditure causally upstream of our donation - GW | B116: =B74 -> 1.6760327 | C116: =C74 -> 1.2160493 | D116: =D74 -> 1.857356
...

Sheet Baseline mortality
A1: Under-5 mortality
A3: See this document for an explanation of how we selected data for these estimates. https://docs.google.com/document/d/1Y72rwA9ClqXF0e47xGY4xeilAT_1645wK7PXq9V6Vf4/edit?usp=sharing
A6: Kenya DSW Counties | B6: Children <5 per household | C6: Households per dispenser | D6: # of dispensers | E6: Children <5 served | F6: Under-5 mortality rate (GBD)
A7: Busia | B7: 0.7 | C7: 29.09 | D7: 1351 | E7: =B7*C7*D7 -> 27510.413 | F7: 1126
A8: Siaya | B8: 0.73 | C8: 22.73 | D8: 3021 | E8: =B8*C8*D8 -> 50127.151 | F8: 1282
A9: Homa Bay | B9: 0.58 | C9: 21.83 | D9: 1511 | E9: =B9*C9*D9 -> 19131.375 | F9: 1477
A10: Migori | B10: 0.6 | C10: 24.99 | D10: 4058 | E10: =B10*C10*D10 -> 60845.652 | F10: 1593
A11: Vihiga | B11: 0.64 | C11: 21.74 | D11: 2359 | E11: =B11*C11*D11 -> 32822.182 | F11: 987
A12: Kakamega | B12: 0.61 | C12: 22.87 | D12: 2876 | E12: =B12*C12*D12 -> 40122.213 | F12: 1025
A13: Bungoma | B13: 0.79 | C13: 15.5 | D13: 1079 | E13: =B13*C13*D13 -> 13212.355 | F13: 753
A14: Uasin Gishu | B14: 0.81 | C14: 17.21 | D14: 374 | E14: =B14*C14*D14 -> 5213.5974 | F14: 502
A15: Trans Nzoia | B15: 0.56 | C15: 23.59 | D15: 1125 | E15: =B15*C15*D15 -> 14861.7 | F15: 471
A16: Population-weighted average | F16: =IFERROR(__xludf.DUMMYFUNCTION("AVERAGE.WEIGHTED(F7:F15,E7:E15)"),1188.2305982519292) -> 1188.2306
A17: Annualized rate | F17: =F16/100000 -> 0.011882306
A20: Uganda DSW Districts | B20: Children <5 per household | C20: Households per dispenser | D20: # of dispensers | E20: Children <5 served | F20: Under-5 mortality rate (GBD)
A21: Budaka | B21: 0.95 | C21: 41.42 | D21: 414 | E21: =B21*C21*D21 -> 16290.486 | F21: 51.8
A22: Butaleja | B22: 0.98 | C22: 58.84 | D22: 379 | E22: =B22*C22*D22 -> 21854.353 | F22: 55
A23: Butebo | B23: 0.59 | C23: 56.06 | D23: 310 | E23: =B23*C23*D23 -> 10253.374 | F23: 52
A24: Kibuku | B24: 1.03 | C24: 42.92 | D24: 357 | E24: =B24*C24*D24 -> 15782.113 | F24: 54.3
A25: Mbale | B25: 0.69 | C25: 46.3 | D25: 384 | E25: =B25*C25*D25 -> 12267.648 | F25: 47.9
A26: Manafwa | B26: 0.75 | C26: 35.92 | D26: 862 | E26: =B26*C26*D26 -> 23222.28 | F26: 55.3
A27: Namisindwa | B27: 0.65 | C27: 47.84 | D27: 555 | E27: =B27*C27*D27 -> 17258.28 | F27: 55.3
A28: Namutumba | B28: 0.93 | C28: 54.57 | D28: 407 | E28: =B28*C28*D28 -> 20655.291 | F28: 59.2
A29: Pallisa | B29: 0.58 | C29: 61.69 | D29: 422 | E29: =B29*C29*D29 -> 15099.244 | F29: 54
A30: Sironko | B30: 0.82 | C30: 24.16 | D30: 734 | E30: =B30*C30*D30 -> 14541.421 | F30: 47.9
A31: Tororo | B31: 0.82 | C31: 46.55 | D31: 565 | E31: =B31*C31*D31 -> 21566.615 | F31: 61.5
A32: Population-weighted average | F32: =IFERROR(__xludf.DUMMYFUNCTION("AVERAGE.WEIGHTED(F21:F31,E21:E31)"),54.68059192771852) -> 54.680592
A33: Annualized rate | F33: =(F32/1000)/5 -> 0.010936118
A36: Malawi DSW Districts | F36: Under-5 mortality rate
A37: Zomba | F37: 67.1
A38: Annualized rate | F38: =(F37/1000)/5 -> 0.01342
A41: Over-5 mortality
E43: Kenya | F43: Uganda | G43: Malawi
A45: Annual mortality rate, 2019, age 5-14 | E45: 63.09 | F45: 77.49 | G45: 92.23
A46: Annual mortality rate, 2019, age 15-49 | E46: 336.64 | F46: 271.83 | G46: 324.93
A47: Annual mortality rate, 2019, age 50-69 | E47: 1844.62 | F47: 1706.55 | G47: 2017.29
A48: Annual mortality rate, 2019, age 70+ | E48: 7744.32 | F48: 7839.23 | G48: 7988.33
A50: Total population 5-14 in 2019 | E50: 12744043 | F50: 11987722 | G50: 5291885.6
A51: Total population 15-49 in 2019 | E51: 26047768 | F51: 18880758 | G51: 8999476.4
A52: Total population 50-69 in 2019 | E52: 4134770 | F52: 2563429.1 | G52: 1243971.3
A53: Total population 70+ in 2019 | E53: 885085.04 | F53: 596196.79 | G53: 320894.42
A54: Total population over 5 | E54: =sum(E50:E53) -> 43811667 | F54: =sum(F50:F53) -> 34028106 | G54: =sum(G50:G53) -> 15856228
A56: Annual mortality rate, 2019, over 5 (per 100k) | E56: =IFERROR(__xludf.DUMMYFUNCTION("average.weighted(E45:E48,E50:E53)"),549.0364913399334) -> 549.03649 | F56: =IFERROR(__xludf.DUMMYFUNCTION("average.weighted(F45:F48,F50:F53)"),444.0337845521016) -> 444.03378 | G56: =IFERROR(__xludf.DUMMYFUNCTION("average.weighted(G45:G48,G50:G53)"),535.1292873801242) -> 535.12929
A57: Percent | E57: =E56/100000 -> 0.0054903649 | F57: =F56/100000 -> 0.0044403378 | G57: =G56/100000 -> 0.0053512929
A60: Source for annual mortality | E60: http://ghdx.healthdata.org/gbd-results-tool?params=gbd-api-2019-permalink/8fc83ccd3f9357ffa4925efe478e5e60
A61: Source for population | E61: https://docs.google.com/spreadsheets/d/1MsFXeSfBx1tA2_hLikyeNRvy2YKEtM53XyOfxw_XtVg/edit#gid=0

Sheet Mortality effect size
A1: We began with all 13 trials of water quality interventions reporting under-5 all-cause mortality included in the Kremer et al. meta-analysis. We excluded trials in which the intervention did not involve chlorination. We excluded trials with follow-up of less than one year, which excludes shorter trials that tend to be less robust and may have greater publication bias. This also limits excess uncertainty that is intruduced by pooling trials with large variation in follow-up length. We excluded Haushofer et al. for two reasons. First, it is a follow-up of the Null 2018 RCT, so it does not meet the independence assumption underlying this meta-analysis method. Second, we find the effect size implausibly large (including the bottom of the 95% confidence interval) given the modest intervention effect on chlorination rates (see our accompanying water quality report for more information). We then generated weights based on inverse variance (a common meta-analysis method that minimizes variance of the mean), and similarity to simple chlorination interventions such as Dispensers for Safe Water and in-line chlorination, and took the weighted mean of the effect size of each trial on mortality. The pooling method was designed with help from statistics consultant Megan Higgs. Unpublished mortality data for Reller 2003 and Boisson 2013 are included with permission from the authors.
A3: Trial | B3: Intervention type | C3: Addl interventions? | D3: Type | E3: Control n | F3: Control deaths | G3: Control nondeaths | H3: Treatment n | I3: Treatment deaths | J3: Treatment nondeaths | K3: Mortality RR | L3: ln(Mortality RR) | M3: SE of ln(RR) | N3: 1/variance weight | O3: Similarity weight | P3: Total weight | Q3: % weight
A4: Reller 2003 | B4: Chlorination | C4: yes | D4: Safe storage vessel | E4: 187 | F4: 2 | G4: =E4-F4 -> 185 | H4: 739 | I4: 3 | J4: =H4-I4 -> 736 | K4: =(I4/H4)/(F4/E4) -> 0.37956698 | L4: =LN(K4) -> -0.9687242 | M4: =SQRT((1/F4)+(1/I4)-(1/E4)-(1/H4)) -> 0.90919336 | N4: =1/(M4^2) -> 1.2097273 | O4: 0.875 | P4: =N4*O4 -> 1.0585114 | Q4: =P4/SUM(P$4:P$8) -> 0.019559271
A5: Boisson 2013 | B5: Chlorination | C5: no | E5: 1484 | F5: 1 | G5: =E5-F5 -> 1483 | H5: 1507 | I5: 2 | J5: =H5-I5 -> 1505 | K5: =(I5/H5)/(F5/E5) -> 1.9694758 | L5: =LN(K5) -> 0.67776741 | M5: =SQRT((1/F5)+(1/I5)-(1/E5)-(1/H5)) -> 1.2241987 | N5: =1/(M5^2) -> 0.66726161 | O5: 1 | P5: =N5*O5 -> 0.66726161 | Q5: =P5/SUM(P$4:P$8) -> 0.012329721
A6: Luby 2018 | B6: Chlorination | C6: yes | D6: Safe storage vessel | E6: 1306 | F6: 62 | G6: =E6-F6 -> 1244 | H6: 656 | I6: 27 | J6: =H6-I6 -> 629 | K6: =(I6/H6)/(F6/E6) -> 0.86698466 | L6: =LN(K6) -> -0.142734 | M6: =SQRT((1/F6)+(1/I6)-(1/E6)-(1/H6)) -> 0.22555705 | N6: =1/(M6^2) -> 19.65564 | O6: 0.75 | P6: =N6*O6 -> 14.74173 | Q6: =P6/SUM(P$4:P$8) -> 0.27239904
A7: Null 2018 | B7: Chlorination | C7: no | E7: 2811 | F7: 114 | G7: =E7-F7 -> 2697 | H7: 888 | I7: 30 | J7: =H7-I7 -> 858 | K7: =(I7/H7)/(F7/E7) -> 0.83303698 | L7: =LN(K7) -> -0.18267724 | M7: =SQRT((1/F7)+(1/I7)-(1/E7)-(1/H7)) -> 0.20155245 | N7: =1/(M7^2) -> 24.616359 | O7: 1 | P7: =N7*O7 -> 24.616359 | Q7: =P7/SUM(P$4:P$8) -> 0.45486334
A8: Humphrey 2019 | B8: Chlorination | C8: yes | D8: Handwashing, infant play space and education to prevent geophagia, education on hygienic prep of complementary food, education on safe disposal of feces | E8: 959 | F8: 50 | G8: =E8-F8 -> 909 | H8: 995 | I8: 49 | J8: =H8-I8 -> 946 | K8: =(I8/H8)/(F8/E8) -> 0.94454271 | L8: =LN(K8) -> -0.05705437 | M8: =SQRT((1/F8)+(1/I8)-(1/E8)-(1/H8)) -> 0.19585807 | N8: =1/(M8^2) -> 26.06856 | O8: 0.5 | P8: =N8*O8 -> 13.03428 | Q8: =P8/SUM(P$4:P$8) -> 0.24084862
A10: Pooled ln(RR) | B10: =IFERROR(__xludf.DUMMYFUNCTION("AVERAGE.WEIGHTED(L4:L8,Q4:Q8)"),-0.14630610636010422) -> -0.14630611
A11: Pooled relative risk | B11: =EXP(B10) -> 0.86389322
A12: SE of ln(RR) | B12: =SQRT((M4*$Q4)^2+(M5*$Q5)^2+(M6*$Q6)^2+(M7*$Q7)^2+(M8*$Q8)^2) -> 0.12226753
A13: 95% CI lower bound | B13: =exp(B10-1.96*B12) -> 0.6798042
A14: 95% CI upper bound | B14: =exp(B10+1.96*B12) -> 1.097833

Sheet Adult mortality scaling factor
B1: Kenya | C1: Uganda | D1: Malawi
A3: Percent of total age 5-14 mortality attributed to enteric infections in 2019 | B3: 24.5 | C3: 12.92 | D3: 14.54
A4: Percent of total age 15-49 mortality attributed to enteric infections in 2019 | B4: 4.67 | C4: 4.21 | D4: 5.5
A5: Percent of total age 50-69 mortality attributed to enteric infections in 2019 | B5: 4.32 | C5: 3.56 | D5: 5.11
A6: Percent of total age 70+ mortality attributed to enteric infections in 2019 | B6: 5.67 | C6: 4.41 | D6: 6.41
A8: Total mortality 5-14 in 2019 | B8: 8040.7385 | C8: 9289.7455 | D8: 4880.5436
A9: Total mortality 15-49 in 2019 | B9: 87687.698 | C9: 51322.952 | D9: 29241.819
A10: Total mortality 50-69 in 2019 | B10: 76270.712 | C10: 43746.174 | D10: 25094.529
A11: Total mortality 70+ in 2019 | B11: 68543.787 | C11: 46737.212 | D11: 25634.097
A12: Total mortality over 5 | B12: =sum(B8:B11) -> 240542.93 | C12: =sum(C8:C11) -> 151096.08 | D12: =sum(D8:D11) -> 84850.99
A14: Percent of total under-5 mortality attributed to enteric infections in 2019 | B14: 17.35 | C14: 5.18 | D14: 10.28
A15: Percent of total over-5 mortality attributed to enteric infections in 2019 | B15: =IFERROR(__xludf.DUMMYFUNCTION("AVERAGE.WEIGHTED(B3:B6,B8:B11)"),5.506843878214529) -> 5.5068439 | C15: =IFERROR(__xludf.DUMMYFUNCTION("AVERAGE.WEIGHTED(C3:C6,C8:C11)"),4.619184083657283) -> 4.6191841 | D15: =IFERROR(__xludf.DUMMYFUNCTION("AVERAGE.WEIGHTED(D3:D6,D8:D11)"),6.1795474803426975) -> 6.1795475
A17: Scaling factor | B17: =B15/B14 -> 0.31739734 | C17: =C15/C14 -> 0.89173438 | D17: =D15/D14 -> 0.6011233
A19: Source for mortality attributed to enteric infections | B19: http://ghdx.healthdata.org/gbd-results-tool?params=gbd-api-2019-permalink/523dbc2310120ceac6bb14926f3e0802
A20: Source for total under-5 mortality attributed to enteric infections | B20: http://ghdx.healthdata.org/gbd-results-tool?params=gbd-api-2019-permalink/523dbc2310120ceac6bb14926f3e0802

Sheet Morbidity effect size
A2: Relative risk of diarrhea with chlorination in randomized controlled trials
A3: Diarrhea relative risk with chlorination | B3: 0.77
A4: Effect size in blinded vs. unblinded trials with objective outcome (mortality) | B4: 0.92
A5: Effect size in blinded vs. unblinded trials with subjective outcome | B5: 0.78
A6: Adjustment for self-report bias | B6: =B5/B4 -> 0.84782609
A7: Diarrhea RR adjusted for self-report bias | B7: =1-((1-B3)*B6) -> 0.805

Sheet Internal validity adjustment
A2: Mortality internal validity adjustment | D2: Morbidity internal validity adjustment
A3: Adjustment for bundled interventions | B3: =B41 -> 0.79575782 | D3: Internal validity adjustment for morbidity | E3: 0.9
A4: Adjustment for smaller Mills-Reincke effect in over-5s | B4: =B26 -> 0.63354682
A6: Internal validity adjustment for under-5 mortality | B6: =B3 -> 0.79575782
A7: Internal validity adjustment for over-5 mortality | B7: =B3*B4 -> 0.50414983
A10: Plausibility limit
A11: Maximum plausible under-5 mortality effect size, ILC Kenya | B11: 0.109
A12: Maximum plausible under-5 mortality effect size, DSW Kenya | B12: 0.056
A13: Maximum plausible under-5 mortality effect size, DSW Uganda | B13: 0.084
A14: Maximum plausible under-5 mortality effect size, DSW Malawi | B14: 0.109
A17: Mills-Reincke adjustment
A18: Percent of all-cause mortality caused by enteric infections, Kenya 2019 | B18: 0.1735
A19: Reduction in diarrhea morbidity caused by in-line chlorination in Kenya | B19: ='ILC Kenya'!B33 -> 0.16779946
A20: Reduction in all-cause mortality implied by enteric infection mortality data, ILC Kenya | B20: =B18*B19 -> 0.029113207
A21: Reduction in all-cause mortality implied by our CEA, ILC Kenya | B21: ='ILC Kenya'!B10 -> 0.109
A22: Percent of all-cause mortality reduction not directly attributable to enteric mortality reduction | B22: =1-B20/B21 -> 0.73290636
A23: All-cause mortality reduction is X fold greater than expected | B23: =B21/B20 -> 3.7440053
A24: Estimated non-enteric deaths averted per enteric death averted, for illustration only | B24: =B23-1 -> 2.7440053
A25: Impact of Mills-Reincke effect in over-5s relative to under-5s | B25: 0.5
A26: Adjustment for smaller Mills-Reincke effect in over-5s | B26: =1-B22*B25 -> 0.63354682
A30: Bundled intervention adjustment
A32: Trial | B32: Water treatment | C32: Additional interventions? | D32: Type | E32: Proportion of intervention groups with relevant bundled treatments | F32: Contribution of additional intervention to effect size in groups that include it | G32: Overall contribution of additional mechanism to effect size | H32: Original mortality RR | I32: Adjusted mortality RR | J32: Study weight
A33: Reller 2003 | B33: Chlorination | C33: yes | D33: Safe storage vessel | E33: 0.5 | F33: 0.2 | G33: =E33*F33 -> 0.1 | H33: ='Mortality effect size'!K4 -> 0.37956698 | I33: =1-((1-H33)*(1-G33)) -> 0.44161028 | J33: ='Mortality effect size'!Q4 -> 0.019559271
A34: Boisson 2013 | B34: Chlorination | C34: no | G34: =E34*F34 -> 0 | H34: ='Mortality effect size'!K5 -> 1.9694758 | I34: =1-((1-H34)*(1-G34)) -> 1.9694758 | J34: ='Mortality effect size'!Q5 -> 0.012329721
A35: Luby 2018 | B35: Chlorination | C35: yes | D35: Safe storage vessel | E35: 1 | F35: 0.2 | G35: =E35*F35 -> 0.2 | H35: ='Mortality effect size'!K6 -> 0.86698466 | I35: =1-((1-H35)*(1-G35)) -> 0.89358773 | J35: ='Mortality effect size'!Q6 -> 0.27239904
A36: Null 2018 | B36: Chlorination | C36: no | G36: =E36*F36 -> 0 | H36: ='Mortality effect size'!K7 -> 0.83303698 | I36: =1-((1-H36)*(1-G36)) -> 0.83303698 | J36: ='Mortality effect size'!Q7 -> 0.45486334
A37: Humphrey 2019 | B37: Chlorination | C37: yes | D37: Handwashing, infant play space and education to prevent geophagia, education on hygienic prep of complementary food, education on safe disposal of feces | E37: 1 | F37: 0.67 | G37: =E37*F37 -> 0.67 | H37: ='Mortality effect size'!K8 -> 0.94454271 | I37: =1-((1-H37)*(1-G37)) -> 0.9816991 | J37: ='Mortality effect size'!Q8 -> 0.24084862
A39: Pooled effect size estimate, adjusted for bundled treatments | B39: =IFERROR(__xludf.DUMMYFUNCTION("AVERAGE.WEIGHTED(I33:I37,J33:J37)"),0.8916919655799829) -> 0.89169197
A40: Pooled effect size, original | B40: ='Mortality effect size'!B11 -> 0.86389322
A41: Adjustment for bundled treatments | B41: =(1-B39)/(1-B40) -> 0.79575782

Sheet External validity adjustment
A1: Mortality
A3: ILC Kenya
A4: Adjustment for proportion of deaths linked to water quality in Kremer et al. vs Kenya | B4: ='Deaths linked to water quality'!B$6 -> 1.1426072
A5: Adherence adjustment | B5: ='Adherence adjustments'!B$27 -> 1.0623581
A6: External validity adjustment | B6: =B4*B5 -> 1.213858
A8: DSW Kenya
A9: Adjustment for proportion of deaths linked to water quality in Kremer et al. vs Kenya | B9: ='Deaths linked to water quality'!B6 -> 1.1426072
A10: Adherence adjustment | B10: ='Adherence adjustments'!B19 -> 0.48857663
A11: External validity adjustment | B11: =B9*B10 -> 0.55825117
A13: DSW Uganda
A14: Adjustment for proportion of deaths linked to water quality in Kremer et al. vs Uganda | B14: ='Deaths linked to water quality'!C6 -> 0.7208418
A15: Adherence adjustment | B15: ='Adherence adjustments'!C19 -> 0.78522404
A16: External validity adjustment | B16: =B14*B15 -> 0.56602231
A18: DSW Malawi
A19: Adjustment for proportion of deaths linked to water quality in Kremer et al. vs Malawi | B19: ='Deaths linked to water quality'!D6 -> 1.089626
A20: Adherence adjustment | B20: ='Adherence adjustments'!D19 -> 1.0170933
A21: External validity adjustment | B21: =B19*B20 -> 1.1082514
A24: Morbidity
A26: ILC Kenya | E26: ='Deaths linked to water quality'!G6
A27: Adherence adjustment | B27: ='Adherence adjustments'!B27 -> 1.0623581
A28: Adjustment for less intensive implementation in charity context vs. RCT | B28: 0.9
A29: External validity adjustment | B29: =B27*B28 -> 0.95612229
A31: DSW Kenya
A32: Adherence adjustment | B32: ='Adherence adjustments'!B19 -> 0.48857663
A33: External validity adjustment | B33: =B32 -> 0.48857663
A35: DSW Uganda
A36: Adherence adjustment | B36: ='Adherence adjustments'!C19 -> 0.78522404
A37: External validity adjustment | B37: =B36 -> 0.78522404
A39: DSW Malawi
A40: Adherence adjustment | B40: ='Adherence adjustments'!D19 -> 1.0170933
A41: External validity adjustment | B41: =B40 -> 1.0170933

Sheet Deaths linked to water quality
A1: Adjustment for proportion of deaths linked to water quality
B3: Kenya | C3: Uganda | D3: Malawi
A5: Percent of total mortality attributed to enteric infections in 2019 | B5: =SUMIFS($H$25:$H$552, $B$25:$B$552, "Kenya", $G$25:$G$552, 2019, $A$25:$A$552, "deaths", $D$25:$D$552, "All Ages", $E$25:$E$552, "Enteric infections") -> 0.076547203 | C5: =SUMIFS($H$25:$H$552, $B$25:$B$552, "Uganda", $G$25:$G$552, 2019, $A$25:$A$552, "deaths", $D$25:$D$552, "All Ages", $E$25:$E$552, "Enteric infections") -> 0.048291682 | D5: =SUMIFS($H$25:$H$552, $B$25:$B$552, "Malawi", $G$25:$G$552, 2019, $A$25:$A$552, "deaths", $D$25:$D$552, "All Ages", $E$25:$E$552, "Enteric infections") -> 0.072997811
A6: Adjustment for proportion of deaths linked to water quality in Kremer et al. vs beneficiaries | B6: =B5/$D18 -> 1.1426072 | C6: =C5/$D18 -> 0.7208418 | D6: =D5/$D18 -> 1.089626
A10: Calculations for adjustment by total deaths attributed to enteric infections
A12: Trial | B12: Location | C12: Year conducted | D12: % deaths attributed to enteric infections (GBD) | E12: Weight in meta-analysis
A13: Reller 2003 | B13: Guatemala | C13: 2001-2002 | D13: =(SUMIFS(H$25:H$552, B$25:B$552, "Guatemala", G$25:G$552, 2001, A$25:A$552, "deaths", D$25:D$552, "All Ages", E$25:E$552, "Enteric infections")+SUMIFS(H$25:H$552, B$25:B$552, "Guatemala", G$25:G$552, 2002, A$25:A$552, "deaths", D$25:D$552, "All Ages", E$25:E$552, "Enteric infections"))/2 -> 0.072590216 | E13: ='Mortality effect size'!Q4 -> 0.019559271
A14: Boisson 2013 | B14: India | C14: 2010-2011 | D14: =(SUMIFS(H$25:H$552, B$25:B$552, "India", G$25:G$552, 2010, A$25:A$552, "deaths", D$25:D$552, "All Ages", E$25:E$552, "Enteric infections")+SUMIFS(H$25:H$552, B$25:B$552, "India", G$25:G$552, 2011, A$25:A$552, "deaths", D$25:D$552, "All Ages", E$25:E$552, "Enteric infections"))/2 -> 0.10151913 | E14: ='Mortality effect size'!Q5 -> 0.012329721
A15: Luby 2018 | B15: Bangladesh | C15: 2013-2014 | D15: =(SUMIFS(H$25:H$552, B$25:B$552, "Bangladesh", G$25:G$552, 2013, A$25:A$552, "deaths", D$25:D$552, "All Ages", E$25:E$552, "Enteric infections")+SUMIFS(H$25:H$552, B$25:B$552, "Bangladesh", G$25:G$552, 2014, A$25:A$552, "deaths", D$25:D$552, "All Ages", E$25:E$552, "Enteric infections"))/2 -> 0.055074491 | E15: ='Mortality effect size'!Q6 -> 0.27239904
A16: Null 2018 | B16: Kenya | C16: 2014-2016 | D16: =SUMIFS(H$25:H$552, B$25:B$552, "Kenya", G$25:G$552, 2015, A$25:A$552, "deaths", D$25:D$552, "All Ages", E$25:E$552, "Enteric infections") -> 0.086877618 | E16: ='Mortality effect size'!Q7 -> 0.45486334
A17: Humphrey 2019 | B17: Zimbabwe | C17: 2013-2016 | D17: =(SUMIFS(H$25:H$552, B$25:B$552, "Zimbabwe", G$25:G$552, 2013, A$25:A$552, "deaths", D$25:D$552, "All Ages", E$25:E$552, "Enteric infections")+SUMIFS(H$25:H$552, B$25:B$552, "Zimbabwe", G$25:G$552, 2016, A$25:A$552, "deaths", D$25:D$552, "All Ages", E$25:E$552, "Enteric infections"))/2 -> 0.04069883 | E17: ='Mortality effect size'!Q8 -> 0.24084862
A18: Weighted average | D18: =SUMPRODUCT(D13:D17,E13:E17) -> 0.066993454
A22: GBD raw data
A24: measure | B24: location | C24: sex | D24: age | E24: cause | F24: metric | G24: year | H24: val | I24: upper | J24: lower
A25: Deaths | B25: Bangladesh | C25: Both | D25: Under 5 | E25: Enteric infections | F25: Percent | G25: 1996 | H25: 0.11768271 | I25: 0.1470037 | J25: 0.091416931
A26: Deaths | B26: Bangladesh | C26: Both | D26: All Ages | E26: Enteric infections | F26: Percent | G26: 1996 | H26: 0.1005422 | I26: 0.12991174 | J26: 0.079671727
A27: YLDs (Years Lived with Disability) | B27: Bangladesh | C27: Both | D27: Under 5 | E27: Enteric infections | F27: Percent | G27: 1996 | H27: 0.051674175 | I27: 0.064419699 | J27: 0.040822959
A28: YLDs (Years Lived with Disability) | B28: Bangladesh | C28: Both | D28: All Ages | E28: Enteric infections | F28: Percent | G28: 1996 | H28: 0.025549862 | I28: 0.029879862 | J28: 0.02191678
A29: Deaths | B29: Guatemala | C29: Both | D29: Under 5 | E29: Enteric infections | F29: Percent | G29: 1996 | H29: 0.18250405 | I29: 0.2012627 | J29: 0.16349261
A30: Deaths | B30: Guatemala | C30: Both | D30: All Ages | E30: Enteric infections | F30: Percent | G30: 1996 | H30: 0.096265637 | I30: 0.10366543 | J30: 0.089011577
A31: YLDs (Years Lived with Disability) | B31: Guatemala | C31: Both | D31: Under 5 | E31: Enteric infections | F31: Percent | G31: 1996 | H31: 0.12101842 | I31: 0.14313701 | J31: 0.098830805
A32: YLDs (Years Lived with Disability) | B32: Guatemala | C32: Both | D32: All Ages | E32: Enteric infections | F32: Percent | G32: 1996 | H32: 0.034842165 | I32: 0.039632463 | J32: 0.030389339
A33: Deaths | B33: India | C33: Both | D33: Under 5 | E33: Enteric infections | F33: Percent | G33: 1996 | H33: 0.13958879 | I33: 0.16827256 | J33: 0.11222027
A34: Deaths | B34: India | C34: Both | D34: All Ages | E34: Enteric infections | F34: Percent | G34: 1996 | H34: 0.13567109 | I34: 0.17950293 | J34: 0.099788584
A35: YLDs (Years Lived with Disability) | B35: India | C35: Both | D35: Under 5 | E35: Enteric infections | F35: Percent | G35: 1996 | H35: 0.034721126 | I35: 0.043053417 | J35: 0.027785461
A36: YLDs (Years Lived with Disability) | B36: India | C36: Both | D36: All Ages | E36: Enteric infections | F36: Percent | G36: 1996 | H36: 0.025576731 | I36: 0.029557152 | J36: 0.022181372
... A552: YLDs (Years Lived with Disability) | B552: Zimbabwe | C552: Both | D552: All Ages | E552: Enteric infections | F552: Percent | G552: 2019 | H552: 0.024508313 | I552: 0.028457904 | J552: 0.021200463

Sheet Adherence adjustments
A1: Adherence in trials underlying Kremer et al. meta-analysis vs. DSW and ILC
A3: Weighted average adherence in Kremer et al. meta-analysis trials | B3: =B53 -> 0.51559734
A6: DSW adherence adjustment | B6: Kenya | C6: Uganda | D6: Malawi
A7: % of households whose water tests positive for free chlorine | B7: 0.45 | C7: 0.56 | D7: 0.6
A8: % of households that self-report using dispensers | B8: 0.6086 | C8: 0.6137 | D8: 0.6853
A9: % of households that self-report using chlorination methods other than dispensers | B9: 0.0092 | C9: 0.0093 | D9: 0.0043
A10: % of households that self-report chlorinating water | B10: =B8+B9 -> 0.6178 | C10: =C8+C9 -> 0.623 | D10: =D8+D9 -> 0.6896
A11: % of households whose water tests positive for total chlorine | B11: 0.49 | C11: 0.6 | D11: 0.65
A12: Adjustment for self-report bias | B12: =B11/B10 -> 0.79313694 | C12: =C11/C10 -> 0.96308186 | D12: =D11/D10 -> 0.94257541
A13: % of chlorinated water that was chlorinated via dispensers use | B13: =B8/(B8+B9) -> 0.98510845 | C13: =C8/(C8+C9) -> 0.98507223 | D13: =D8/(D8+D9) -> 0.9937645
A14: % of households using a water point with a dispenser that use dispensers | B14: =B7*B13 -> 0.4432988 | C14: =C7*C13 -> 0.55164045 | D14: =D7*D13 -> 0.5962587
A15: % of households that would treat water in the absence of dispensers | B15: =B41 -> 0.22359135 | C15: =C41 -> 0.17191746 | D15: =D41 -> 0.07854038
A16: % of households that self-report non-dispenser water treatment | B16: 0.0406 | C16: 0.0261 | D16: 0.0071
A17: % of households that use non-dispenser water treatment, adjusted for self-report bias | B17: =B16*B12 -> 0.03220136 | C17: =C16*C12 -> 0.025136437 | D17: =D16*D12 -> 0.0066922854
A18: Increase in water treatment as a result of dispensers, percentage points | B18: =B14-B15+B17 -> 0.25190881 | C18: =C14-C15+C17 -> 0.40485942 | D18: =D14-D15+D17 -> 0.52441061
A19: Adherence adjustment for DSW | B19: =B18/B$3 -> 0.48857663 | C19: =C18/B$3 -> 0.78522404 | D19: =D18/B$3 -> 1.0170933
A21: ILC adherence adjustment | B21: Kenya
A22: Adherence in Pickering et al. 2019 (free chlorine rate of samples) | B22: 0.8
A23: % of households that would treat water in the absence of dispensers | B23: =B41 -> 0.22359135
A24: % of households that use non-dispenser water treatment, adjusted for self-report bias | B24: =B17 -> 0.03220136
A25: Increase in water treatment as a result of ILC | B25: =B22-B23+B24 -> 0.60861
A26: Adjustment for lower ILC adherence with higher Cl level | B26: 0.9
A27: Adherence adjustment for ILC | B27: =(B25/B3)*B26 -> 1.0623581
A30: Calculations for counterfactual water treatment in DSW and ILC | B30: Kenya | C30: Uganda | D30: Malawi
A31: Self-reported water treatment rate, all methods, DSW baseline | B31: 0.294 | C31: 0.0872 | D31: 0
A32: Adjustment for self-report bias | B32: =B12 -> 0.79313694 | C32: =C12 -> 0.96308186 | D32: =D12 -> 0.94257541
A33: Adjusted counterfactual water treatment rate, all methods, DSW | B33: =B31*B32 -> 0.23318226 | C33: =C31*C32 -> 0.083980738 | D33: =D31*D32 -> 0
A34: Self-reported water treatment rate, rural, all "appropriate" methods, DHS | B34: 0.442 | C34: 0.442 | D34: 0.273
A35: % of people treating water, Uganda mean | B35: 0.498 | C35: 0.498 | D35: 0.498
A36: % of people treating water, Uganda region tentatively prioritized by DSW | B36: 0.304 | C36: 0.304 | D36: 0.304
A37: Adjustment for national DHS data overestimating water treatment rates in DSW regions | B37: =B36/B35 -> 0.61044177 | C37: =C36/C35 -> 0.61044177 | D37: =D36/D35 -> 0.61044177
A38: Adjusted counterfactual water treatment rate, all "appropriate" methods, DHS | B38: =B34*B32*B37 -> 0.21400045 | C38: =C34*C32*C37 -> 0.25985418 | D38: =D34*D32*D37 -> 0.15708076
A39: Weight assigned to DSW estimate | B39: 1 | C39: 1 | D39: 1
A40: Weight assigned to DHS estimate | B40: 1 | C40: 1 | D40: 1
A41: Adjusted counterfactual water treatment rate, weighted average of DSW and DHS | B41: =(B33*B39+B38*B40)/(B39+B40) -> 0.22359135 | C41: =(C33*C39+C38*C40)/(C39+C40) -> 0.17191746 | D41: =(D33*D39+D38*D40)/(D39+D40) -> 0.07854038
A44: Water treatment coverage in Kremer et al. trials | B44: Intervention coverage (minus counterfactual water treatment coverage) | C44: Adjusted study weight
A45: Reller 2003 | B45: 0.38 | C45: ='Mortality effect size'!Q4 -> 0.019559271
A46: Boisson 2013 | B46: 0.3 | C46: ='Mortality effect size'!Q5 -> 0.012329721
A47: Luby 2018 | B47: 0.805 | C47: ='Mortality effect size'!Q6 -> 0.27239904
A48: Null 2018 | B48: 0.2775 | C48: ='Mortality effect size'!Q7 -> 0.45486334
A49: Humphrey 2019 | B49: 0.66 | C49: ='Mortality effect size'!Q8 -> 0.24084862
A50: Total weight | C50: =SUM(C45:C49) -> 1
A53: Weighted average adherence | B53: =SUMPRODUCT(B45:B49,C45:C49) -> 0.51559734

Sheet Costs averted supp calculations
A1: Kenya under-5 annual diarrhea incidence
A3: Kenya DSW Counties | B3: Children <5 per household | C3: Households per dispenser | D3: # of dispensers | E3: Children <5 served | F3: U5 diarrhea prevalence | G3: U5 diarrhea annual incidence
A4: Bungoma | B4: 0.7 | C4: 29.09 | D4: 1351 | E4: =B4*C4*D4 -> 27510.413 | F4: 0.195 | G4: =(F4*365)/(14+D$52-1) -> 3.9433881
A5: Busia | B5: 0.73 | C5: 22.73 | D5: 3021 | E5: =B5*C5*D5 -> 50127.151 | F5: 0.182 | G5: =(F5*365)/(14+D$52-1) -> 3.6804955
A6: Homa Bay | B6: 0.58 | C6: 21.83 | D6: 1511 | E6: =B6*C6*D6 -> 19131.375 | F6: 0.235 | G6: =(F6*365)/(14+D$52-1) -> 4.7522882
A7: Kakamega | B7: 0.6 | C7: 24.99 | D7: 4058 | E7: =B7*C7*D7 -> 60845.652 | F7: 0.208 | G7: =(F7*365)/(14+D$52-1) -> 4.2062806
A8: Migori | B8: 0.64 | C8: 21.74 | D8: 2359 | E8: =B8*C8*D8 -> 32822.182 | F8: 0.279 | G8: =(F8*365)/(14+D$52-1) -> 5.6420783
A9: Siaya | B9: 0.61 | C9: 22.87 | D9: 2876 | E9: =B9*C9*D9 -> 40122.213 | F9: 0.141 | G9: =(F9*365)/(14+D$52-1) -> 2.8513729
A10: Trans Nzoia | B10: 0.79 | C10: 15.5 | D10: 1079 | E10: =B10*C10*D10 -> 13212.355 | F10: 0.149 | G10: =(F10*365)/(14+D$52-1) -> 3.0131529
A11: Uasin Gishu | B11: 0.81 | C11: 17.21 | D11: 374 | E11: =B11*C11*D11 -> 5213.5974 | F11: 0.093 | G11: =(F11*365)/(14+D$52-1) -> 1.8806928
A12: Vihiga | B12: 0.56 | C12: 23.59 | D12: 1125 | E12: =B12*C12*D12 -> 14861.7 | F12: 0.236 | G12: =(F12*365)/(14+D$52-1) -> 4.7725107
A13: Population-weighted average | F13: =IFERROR(__xludf.DUMMYFUNCTION("AVERAGE.WEIGHTED(F4:F12,E4:E12)"),0.1986567976642028) -> 0.1986568 | G13: =IFERROR(__xludf.DUMMYFUNCTION("AVERAGE.WEIGHTED(G4:G12,E4:E12)"),4.017337674103784) -> 4.0173377
A14: Adjusted for time trend | G14: =G13*B62 -> 3.8187739
A17: Uganda under-5 annual diarrhea incidence
A19: Uganda DSW Districts | B19: Children <5 per household | C19: Households per dispenser | D19: # of dispensers | E19: Children <5 served | F19: U5 diarrhea prevalence | G19: Corresponding region | H19: U5 diarrhea annual incidence
A20: Budaka | B20: 0.95 | C20: 41.42 | D20: 414 | E20: =B20*C20*D20 -> 16290.486 | F20: 0.179 | G20: Bukedi | H20: =(F20*365)/(14+D$52-1) -> 3.619828
A21: Butaleja | B21: 0.98 | C21: 58.84 | D21: 379 | E21: =B21*C21*D21 -> 21854.353 | F21: 0.179 | G21: Bukedi | H21: =(F21*365)/(14+D$52-1) -> 3.619828
A22: Butebo | B22: 0.59 | C22: 56.06 | D22: 310 | E22: =B22*C22*D22 -> 10253.374 | F22: 0.179 | G22: Bukedi | H22: =(F22*365)/(14+D$52-1) -> 3.619828
A23: Kibuku | B23: 1.03 | C23: 42.92 | D23: 357 | E23: =B23*C23*D23 -> 15782.113 | F23: 0.179 | G23: Bukedi | H23: =(F23*365)/(14+D$52-1) -> 3.619828
A24: Manafwa | B24: 0.69 | C24: 46.3 | D24: 384 | E24: =B24*C24*D24 -> 12267.648 | F24: 0.143 | G24: Bugisu | H24: =(F24*365)/(14+D$52-1) -> 2.8918179
A25: Mbale | B25: 0.75 | C25: 35.92 | D25: 862 | E25: =B25*C25*D25 -> 23222.28 | F25: 0.143 | G25: Bugisu | H25: =(F25*365)/(14+D$52-1) -> 2.8918179
A26: Namisindwa | B26: 0.65 | C26: 47.84 | D26: 555 | E26: =B26*C26*D26 -> 17258.28 | F26: 0.143 | G26: Bugisu | H26: =(F26*365)/(14+D$52-1) -> 2.8918179
A27: Namutumba | B27: 0.93 | C27: 54.57 | D27: 407 | E27: =B27*C27*D27 -> 20655.291 | F27: 0.273 | G27: Busoga | H27: =(F27*365)/(14+D$52-1) -> 5.5207433
A28: Pallisa | B28: 0.58 | C28: 61.69 | D28: 422 | E28: =B28*C28*D28 -> 15099.244 | F28: 0.179 | G28: Bukedi | H28: =(F28*365)/(14+D$52-1) -> 3.619828
A29: Sironko | B29: 0.82 | C29: 24.16 | D29: 734 | E29: =B29*C29*D29 -> 14541.421 | F29: 0.143 | G29: Bugisu | H29: =(F29*365)/(14+D$52-1) -> 2.8918179
A30: Tororo | B30: 0.82 | C30: 46.55 | D30: 565 | E30: =B30*C30*D30 -> 21566.615 | F30: 0.179 | G30: Bukedi | H30: =(F30*365)/(14+D$52-1) -> 3.619828
A31: Population-weighted average | F31: =sumproduct(E20:E30,F20:F30)/SUM(E20:E30) -> 0.17645311 | H31: =IFERROR(__xludf.DUMMYFUNCTION("AVERAGE.WEIGHTED(H20:H30,E20:E30)"),3.568323627894385) -> 3.5683236
A32: Adjusted for time trend | H32: =H31*B63 -> 3.460367
A35: Malawi under-5 annual diarrhea incidence
A37: Malawi DSW health clusters | B37: Children <5 per household | C37: Households per dispenser | D37: # of dispensers | E37: Children <5 served | F37: U5 diarrhea prevalence | G37: Corresponding region | H37: U5 diarrhea annual incidence
A38: Chingale | B38: 0.57 | C38: 48.72 | D38: 509 | E38: =B38*C38*D38 -> 14135.134 | F38: 0.204 | G38: Southern | H38: =(F38*365)/(14+D$52-1) -> 4.1253906
A39: Zomba City | B39: 0.56 | C39: 34.04 | D39: 229 | E39: =B39*C39*D39 -> 4365.2896 | F39: 0.204 | G39: Southern | H39: =(F39*365)/(14+D$52-1) -> 4.1253906
A40: Domasi | B40: 0.7 | C40: 23.03 | D40: 717 | E40: =B40*C40*D40 -> 11558.757 | F40: 0.204 | G40: Southern | H40: =(F40*365)/(14+D$52-1) -> 4.1253906
A41: Likangala | B41: 0.67 | C41: 49.09 | D41: 668 | E41: =B41*C41*D41 -> 21970.72 | F41: 0.204 | G41: Southern | H41: =(F41*365)/(14+D$52-1) -> 4.1253906
A42: Matawale | B42: 0.65 | C42: 26.32 | D42: 223 | E42: =B42*C42*D42 -> 3815.084 | F42: 0.204 | G42: Southern | H42: =(F42*365)/(14+D$52-1) -> 4.1253906
A43: Mayaka | B43: 0.64 | C43: 47.2 | D43: 738 | E43: =B43*C43*D43 -> 22293.504 | F43: 0.204 | G43: Southern | H43: =(F43*365)/(14+D$52-1) -> 4.1253906
A44: Thondwe | B44: 0.56 | C44: 37.85 | D44: 659 | E44: =B44*C44*D44 -> 13968.164 | F44: 0.204 | G44: Southern | H44: =(F44*365)/(14+D$52-1) -> 4.1253906
A45: Population-weighted average | F45: =sumproduct(E38:E44,F38:F44)/SUM(E38:E44) -> 0.204 | H45: =IFERROR(__xludf.DUMMYFUNCTION("AVERAGE.WEIGHTED(H38:H44,E38:E44)"),4.12539059902932) -> 4.1253906
A46: Adjusted for time trend | H46: =H45*B64 -> 3.9805092
A49: Diarrhea case duration
A51: Diarrhea case duration data from Lamberti et al. 2012 | B51: % of cases | C51: Duration (days) | D51: Mean duration (days)
A52: Severity | D52: =IFERROR(__xludf.DUMMYFUNCTION("AVERAGE.WEIGHTED(C53:C55,B53:B55)"),5.0492) -> 5.0492
A53: Mild | B53: 0.648 | C53: 4.3
A54: Moderate | B54: 0.347 | C54: 6.4
A55: Severe | B55: 0.005 | C55: 8.4
A58: Adjustment for time trend in diarrhea incidence
A60: Slope of change in diarrhea incidence in sub-Saharan Africa, 1999-2019 | B60: =SLOPE(H91:H111,G91:G111) -> -2082.0169
A61: Intercept of change in diarrhea incidence in sub-Saharan Africa, 1999-2019 | B61: =INTERCEPT(H91:H111,G91:G111) -> 4403798.6
A62: Adjustment for diarrhea incidence change, 2014-2019 | B62: =(B$60*2019+B$61)/(B$60*2014+B$61) -> 0.95057329
A63: Adjustment for diarrhea incidence change, 2016-2019 | B63: =(B$60*2019+B$61)/(B$60*2016+B$61) -> 0.96974583
A64: Adjustment for diarrhea incidence change, 2015.5-2019 | B64: =(B$60*2019+B$61)/(B$60*2015.5+B$61) -> 0.96488055
A69: Cost of diarrhea illness averted | B69: Kenya ILC | C69: Kenya DSW | D69: Uganda DSW | E69: Malawi DSW
A70: % of children under 5 with diarrhea who seek care | B70: 0.576 | C70: 0.576 | D70: 0.705 | E70: 0.658
A71: % of total diarrhea cases that receive inpatient care | B71: =$C85 -> 0.05825 | C71: =$C85 -> 0.05825 | D71: =$C85 -> 0.05825 | E71: =$C85 -> 0.05825
A72: % of total diarrhea cases that receive outpatient care | B72: =B70-B71 -> 0.51775 | C72: =C70-C71 -> 0.51775 | D72: =D70-D71 -> 0.64675 | E72: =E70-E71 -> 0.59975
A73: Cost per inpatient episode (direct + indirect) | B73: 116.59 | C73: 116.59 | D73: 44.23 | E73: 44.23
A74: Cost per outpatient episode (direct + indirect) | B74: 32.58 | C74: 32.58 | D74: 13.94 | E74: 13.94
A75: Annual cost of diarrhea illness, per under 5 | B75: =($B$71*$B$73+$B$72*$B$74)*$G$13 -> 95.048854 | C75: =(B$71*B$73+B$72*B$74)*G$13 -> 95.048854 | D75: =(D71*D73+D72*D74)*H31 -> 41.364338 | E75: =(E71*E73+E72*E74)*H45 -> 45.119036
A76: Annual cost of diarrhea illness averted, per under-5 | B76: =B75*'ILC Kenya'!B33 -> 15.949146 | C76: =C75*DSW!B33 -> 8.1499828 | D76: =D75*DSW!C33 -> 5.7002878 | E76: =E75*DSW!D33 -> 8.0537424
A80: Publication | B80: Location | C80: Percent of under-5 diarrhea cases that are hospitalized
A81: Burton et al. 2011 | B81: Rural Kenya | C81: 0.016
A82: Page et al. 2011 | B82: Rural Niger | C82: 0.082
A83: Breiman et al. 2011 | B83: Urban Kenya | C83: 0.068
A84: Omore et al. 2013 | B84: Western Kenya | C84: 0.067
A85: Mean | C85: =AVERAGE(C81:C84) -> 0.05825
A88: GBD diarrhea incidence data for time trend
A90: measure | B90: location | C90: sex | D90: age | E90: cause | F90: metric | G90: year | H90: val | I90: upper | J90: lower
A91: Incidence | B91: Sub-Saharan Africa | C91: Both | D91: Under 5 | E91: Diarrheal diseases | F91: Rate | G91: 1999 | H91: 241550.5 | I91: 269280.33 | J91: 209228.02
A92: Incidence | B92: Sub-Saharan Africa | C92: Both | D92: Under 5 | E92: Diarrheal diseases | F92: Rate | G92: 2000 | H92: 241321.75 | I92: 268834.89 | J92: 208998.27
A93: Incidence | B93: Sub-Saharan Africa | C93: Both | D93: Under 5 | E93: Diarrheal diseases | F93: Rate | G93: 2001 | H93: 240100.84 | I93: 267282.9 | J93: 208623.74
A94: Incidence | B94: Sub-Saharan Africa | C94: Both | D94: Under 5 | E94: Diarrheal diseases | F94: Rate | G94: 2002 | H94: 237543.68 | I94: 264589.72 | J94: 207125.4
A95: Incidence | B95: Sub-Saharan Africa | C95: Both | D95: Under 5 | E95: Diarrheal diseases | F95: Rate | G95: 2003 | H95: 234355.1 | I95: 261206.06 | J95: 205233.84
A96: Incidence | B96: Sub-Saharan Africa | C96: Both | D96: Under 5 | E96: Diarrheal diseases | F96: Rate | G96: 2004 | H96: 231257.89 | I96: 257276.25 | J96: 202825.04
A97: Incidence | B97: Sub-Saharan Africa | C97: Both | D97: Under 5 | E97: Diarrheal diseases | F97: Rate | G97: 2005 | H97: 228996.67 | I97: 254446.78 | J97: 200741.52
A98: Incidence | B98: Sub-Saharan Africa | C98: Both | D98: Under 5 | E98: Diarrheal diseases | F98: Rate | G98: 2006 | H98: 226951.61 | I98: 252480.56 | J98: 198647.11
A99: Incidence | B99: Sub-Saharan Africa | C99: Both | D99: Under 5 | E99: Diarrheal diseases | F99: Rate | G99: 2007 | H99: 224289.56 | I99: 250130.04 | J99: 195958.44
A100: Incidence | B100: Sub-Saharan Africa | C100: Both | D100: Under 5 | E100: Diarrheal diseases | F100: Rate | G100: 2008 | H100: 221433.35 | I100: 247354.95 | J100: 193145.06
A101: Incidence | B101: Sub-Saharan Africa | C101: Both | D101: Under 5 | E101: Diarrheal diseases | F101: Rate | G101: 2009 | H101: 218784.05 | I101: 245089.44 | J101: 190715.04
A102: Incidence | B102: Sub-Saharan Africa | C102: Both | D102: Under 5 | E102: Diarrheal diseases | F102: Rate | G102: 2010 | H102: 216744.37 | I102: 243704.07 | J102: 188515.48
... A111: Incidence | B111: Sub-Saharan Africa | C111: Both | D111: Under 5 | E111: Diarrheal diseases | F111: Rate | G111: 2019 | H111: 205309.85 | I111: 241138.05 | J111: 169144.53

Sheet InclusionExclusion
A1: Items considered for inclusion | B1: Included? | C1: Rough best guess of effect size | D1: Can it be objectively justified? | E1: Ease of modelling | F1: Consistency | G1: Notes
B2: Color code | C2: <15% = very low | D2: 0 = Not really | E2: 0 = It is impossible to model the effect with any reasonable degree of accuracy
C3: 15-25% = medium | D3: 1 = Quantifying the effect is a guess - but some answers are more likely than others; the evidence relies on non-experimental studies; or the evidence is very contradictory. | E3: 1 = It's unclear how we would model this effect, and it would add a lot of complexity to the model | F3: 1 = The effect would be equally relevant to other CEAs, and has not been included
C4: 25-50% = high | D4: 2 = Quantifying the effect requires an extrapolation from direct evidence, the evidence is mixed, or the evidence relies on quasi-experimental studies. | E4: 2 = The methodology is clear, but adds substantial complexity to the model | F4: 2 = The effect is included in other CEAs, but is less (half as) relevant here OR the effect is not included in other CEAs, but is more (twice as) relevant here
C5: >50% = very high | D5: 3 = There is strong direct evidence of this effect (e.g. an RCT in a similar setting); or the effect is obvious | E5: 3 = The methodology is clear and simple | F5: 3 = The effect is included in other CEAs
A7: [Intervention name]
A8: [Item — e.g. "Child Mortaliy"] | B8: ["Included" or "Excluded"] | C8: 0.5 | D8: 3 | E8: 3 | F8: 3 | G8: [E.g. "Main effect of intervention; Drawing on a meta-analysis of RCTs"]

Sheet Main parameters
B2: =DSW!$B$1 -> Kenya | C2: =DSW!$C$1 -> Uganda | D2: =DSW!$D$1 -> Malawi
A3: Percent reduction in under-5 all-cause mortality | B3: =DSW!B10 -> 0.056 | C3: =DSW!C10 -> 0.061304764 | D3: =DSW!D10 -> 0.109
A4: Percent reduction in over-5 all-cause mortality | B4: =DSW!B24 -> 0.01126082 | C4: =DSW!C24 -> 0.034634462 | D4: =DSW!D24 -> 0.041511533
B6: =DSW!$B$1 -> Kenya | C6: =DSW!$C$1 -> Uganda | D6: =DSW!$D$1 -> Malawi
A7: Percent reduction in morbidity | B7: =DSW!B33 -> 0.085745198 | C7: =DSW!C33 -> 0.13780682 | D7: =DSW!D33 -> 0.17849988
B9: =DSW!$B$1 -> Kenya | C9: =DSW!$C$1 -> Uganda | D9: =DSW!$D$1 -> Malawi
A10: Development effects - annual units of value per 100,000 covered | B10: =DSW!B49 -> 555.08662 | C10: =DSW!C49 -> 553.26013 | D10: =DSW!D49 -> 1097.4703
B12: =DSW!$B$1 -> Kenya | C12: =DSW!$C$1 -> Uganda | D12: =DSW!$D$1 -> Malawi
A13: Total annual cost of illness averted, per person served | B13: =DSW!B62 -> 4.2123995 | C13: =DSW!C62 -> 3.1974446 | D13: =DSW!D62 -> 4.5440954
A14: =DSW!A70 -> Units of value per 100,000 covered | B14: =DSW!B70 -> 906.3713 | C14: =DSW!C70 -> 736.9748 | D14: =DSW!D70 -> 1632.3569
B16: =DSW!$B$1 -> Kenya | C16: =DSW!$C$1 -> Uganda | D16: =DSW!$D$1 -> Malawi
A17: =DSW!A74 -> Annual cost per person served | B17: =DSW!B74 -> 1.6760327 | C17: =DSW!C74 -> 1.2160493 | D17: =DSW!D74 -> 1.857356
