Workbook

Sheet Main CEA
A1: Inputs | B1: Expected | C1: Description | G1: Source
A2: Costs
A3: Fixed Costs - Year 1 | B3: 125000 | C3: Best guess (Held constant in all CEAs) | G3: -
A4: Fixed Costs - Scale | B4: 225000 | C4: Best guess (Held constant in all CEAs) | G4: -
A5: Start up costs - FACILITY SET UP | B5: ='Cost Estimates'!B62 -> 10683.333 | C5: See Cost Estimates, for ~11,000 capacity | G5: -
A6: Start up costs - TRAINING P/TREATMENT adj. for turnover | B6: ='Cost Estimates'!B65 -> 3.381 | C6: See Cost Estimates | G6: -
A7: Cost estimate p/treatment - In Hospital | B7: ='Cost Estimates'!B44 -> 264.46365 | C7: See Cost Estimates | G7: -
A8: Population Data & Other Baselines
A9: Karachi, Sindh, Pakistan
A10: Approximation of number of births in a large facility x year | B10: 7700 | C10: A large hospital has registered 7,700 births and I think there are larger ones | G10: Frequency of Stillbirths in a Tertiary Care Hospital, Karachi - PMC
A11: Lahore, Punjab, Pakistan
A12: Approximation of number of births in a large facility x year | B12: 15606 | C12: Live births reported in 2018 in Sir Ganga Ram Hospital Lahore | G12: https://www.pc.gov.pk/uploads/crvs_reports/Vital_Statistics_Punja_3-11-20.pdf
A13: Peshawar, Khyber Pakhtunkhwa, Pakistan
A14: Approximation of number of births in a large facility x year | B14: =ROUND(36460/9,0) -> 4051 | C14: 36,460 deliveries were conducted over the 9 year period in the largest tertiary care hospital in Pakistan | G14: TRENDS IN MATERNAL MORTALITY IN TERTIARY CARE HOSPITAL IN PESHAWAR - PAKISTAN
A15: Quetta, Balochistan, Pakistan
A16: Approximation of number of births in a large facility x year | B16: =round(33396/5,0) -> 6679 | C16: 33,396 at Department of Obstetrics and Gynecology unit-4 Bolan Medical Complex Hospital, Quetta, from 1st January 2012 to 31st December, 2016, | G16: Trial of Labour after one Caesarean Section-Five year Experience in a Tertiary Care Hospital, Quetta | Journal of The Society of Obstetricians and Gynaecologists of Pakistan
A17: KC Treatment, Effects & Low Birth Weight Risks
A18: Risk of Death for Low Birth Weight (neonatal) | B18: =Calculations!B13 -> 0.1344366 | C18: Average of estimates, see calculations | G18: -
A19: Mortality Reduction effect due to KC (by discharge) | B19: 0.32 | G19: Kangaroo mother care for preterm or low birth weight infants: A systematic review and meta-analysis
A20: Disability weight of being LBW | B20: 0.106 | C20: Disability weight for "Low birth weight - All sequelae" | G20: GLOBAL BURDEN OF DISEASE 2004 UPDATE: DISABILITY WEIGHTS FOR DISEASES AND CONDITIONS
A21: Life expectancy in Pakistan | B21: 66.1 | G21: Our World in Data, 2021
A22: Morbidity and developmental impact of LBW (DALYs) | B22: =B20*B21 -> 7.0066 | C22: There is substantial evidence that KC has an effect on morbidity, see report | G22: 2022 LSGH - 275 KMC Report DRAFT MF
A23: Morbidity effects | B23: 0.15 | C23: As a best guess, we take the reduction in the risk of sepsis - "There was a 15% reduction in severe infection/sepsis at the latest follow-up (RR 0.85, 95% CI 0.79 to 0.92; 9 trials, 9847 infants; moderate certainty evidence)" | G23: https://www.medrxiv.org/content/10.1101/2022.09.14.22279053v1.full.pdf
A24: Expected KMC | B24: 0.7 | C24: "70% of preterm and low-birthweight babies are estimated to be suitable for KMC" | G24: https://apps.who.int/iris/rest/bitstreams/1148441/retrieve
A25: Low Birth Weight Prevalence | B25: =Calculations!B$6 -> 0.22397846 | C25: Constructed with Demographic and Health Survey Data, see Calculations | G25: Pakistan Demographic and Health Survey 2017-18 [FR354]
A26: Timing
A27: Time spent preparing intervention (year) | B27: 1 | G27: -
A28: Timing to scale in treatment (year) | B28: 4
A29: Number of years charity runs for if unsuccessful | B29: 3 | C29: If after 3 years it looks unlikely the charity will be successful, we assume they will end the operation. Costs after this point will therefore be incurred probabilistically.
A30: % of population reached at scale | B30: 1 | C30: Assumes ward can intake all potential patients
A31: Other Assumptions
A32: Discount rate | B32: 0.04 | G32: -
A33: DALY per neonate death averted | B33: 33.07 | G33: Copy of 2017 GiveWell Cost-Effectiveness Analysis — "standard" moral weights version
A34: Probability of success - Chance charity is able to align stakeholders and set up wards | B34: 0.65 | C34: This is a fairly complex intervention, so I expect it to be at the lower end | G34: -
A35: Baseline Coverage of KC | B35: 0.11 | C35: This is an extremely rough proxy, based on the report % of newborns who were put immediately after birth on the skin of the mother's chest | G35: Pakistan Demographic and Health Survey 2017-18 [FR354]
A36: Chance change would have happened anyways | B36: 0.1 | C36: This is a subjective best guess | G36: -
A37: Calculations - Karachi, Sindh, Pakistan
A38: Year | B38: 1 | C38: 2 | D38: 3 | E38: 4 | F38: 5 | G38: 6 | H38: 7 | I38: 8 | J38: 9 | K38: 10 | L38: 11 | M38: 12 | N38: 13 | O38: 14 | P38: 15 | Q38: 16 | R38: 17 | S38: 18 | T38: 19 | U38: 20 | V38: 21 | W38: 22 | X38: 23 | Y38: 24 | Z38: 25
A39: Scale | B39: =MIN((B38-$B$27)/$B$28,1) -> 0 | C39: =MIN((C38-$B$27)/$B$28,1) -> 0.25 | D39: =MIN((D38-$B$27)/$B$28,1) -> 0.5 | E39: =MIN((E38-$B$27)/$B$28,1) -> 0.75 | F39: =MIN((F38-$B$27)/$B$28,1) -> 1 | G39: =MIN((G38-$B$27)/$B$28,1) -> 1 | H39: =MIN((H38-$B$27)/$B$28,1) -> 1 | I39: =MIN((I38-$B$27)/$B$28,1) -> 1 | ... Z39: =MIN((Z38-$B$27)/$B$28,1) -> 1
A40: Fixed Costs | B40: =B3 -> 125000 | C40: =$B4 -> 225000 | D40: =$B4 -> 225000 | E40: =$B4*$B$34 -> 146250 | F40: =$B4*$B$34 -> 146250 | G40: =$B4*$B$34 -> 146250 | H40: =$B4*$B$34 -> 146250 | I40: =$B4*$B$34 -> 146250 | J40: =$B4*$B$34 -> 146250 | K40: =$B4*$B$34 -> 146250 | L40: =$B4*$B$34 -> 146250 | ... Z40: =$B4*$B$34 -> 146250
A41: Start Up costs | B41: =$B$34*(($B5*B10)/11000+($B10*$B25*$B30*1*$B$24)*$B$6) -> 7514.0163 | C41: 0 | D41: 0 | E41: 0 | F41: 0 | G41: 0 | H41: 0 | I41: 0 | J41: 0 | K41: 0 | L41: 0 | M41: 0 | N41: 0 | O41: 0 | P41: 0 | Q41: 0 | R41: 0 | S41: 0 | T41: 0 | U41: 0 | V41: 0 | W41: 0 | X41: 0 | Y41: 0 | Z41: 0
A42: Variable Costs | B42: =$B7*B44 -> 0 | C42: =$B7*C44 -> 51881.723 | D42: =$B7*D44 -> 103763.45 | E42: =$B7*E44*$B$34 -> 101169.36 | F42: =$B7*F44*$B$34 -> 134892.48 | G42: =$B7*G44*$B$34 -> 134892.48 | H42: =$B7*H44*$B$34 -> 134892.48 | I42: =$B7*I44*$B$34 -> 134892.48 | J42: =$B7*J44*$B$34 -> 134892.48 | K42: =$B7*K44*$B$34 -> 134892.48 | L42: =$B7*L44*$B$34 -> 134892.48 | ... Z42: =$B7*Z44*$B$34 -> 134892.48
A43: Total Costs | B43: =SUM(B40:B42) -> 132514.02 | C43: =SUM(C40:C42) -> 276881.72 | D43: =SUM(D40:D42) -> 328763.45 | E43: =SUM(E40:E42) -> 247419.36 | F43: =SUM(F40:F42) -> 281142.48 | G43: =SUM(G40:G42) -> 281142.48 | H43: =SUM(H40:H42) -> 281142.48 | I43: =SUM(I40:I42) -> 281142.48 | ... Z43: =SUM(Z40:Z42) -> 281142.48
A44: Number of treatments | B44: =$B10*$B25*$B30*B39*$B$34*$B$24 -> 0 | C44: =$B10*$B25*$B30*C39*$B$34*$B$24 -> 196.17714 | D44: =$B10*$B25*$B30*D39*$B$34*$B$24 -> 392.35427 | E44: =$B10*$B25*$B30*E39*$B$34*$B$24 -> 588.53141 | F44: =$B10*$B25*$B30*F39*$B$34*$B$24 -> 784.70855 | G44: =$B10*$B25*$B30*G39*$B$34*$B$24 -> 784.70855 | H44: =$B10*$B25*$B30*H39*$B$34*$B$24 -> 784.70855 | I44: =$B10*$B25*$B30*I39*$B$34*$B$24 -> 784.70855 | ... Z44: =$B10*$B25*$B30*Z39*$B$34*$B$24 -> 784.70855
A45: Deaths Averted | B45: =B44*(1-$B36)*$B18*$B19 -> 0 | C45: =C44*(1-$B36)*$B18*$B19 -> 7.5955356 | D45: =D44*(1-$B36)*$B18*$B19 -> 15.191071 | E45: =E44*(1-$B36)*$B18*$B19 -> 22.786607 | F45: =F44*(1-$B36)*$B18*$B19 -> 30.382142 | G45: =G44*(1-$B36)*$B18*$B19 -> 30.382142 | H45: =H44*(1-$B36)*$B18*$B19 -> 30.382142 | I45: =I44*(1-$B36)*$B18*$B19 -> 30.382142 | ... Z45: =Z44*(1-$B36)*$B18*$B19 -> 30.382142
A46: DALYs Averted | B46: =(B45*$B33)+(B44*$B22*$B$23) -> 0 | C46: =(C45*$B33)+(C44*$B22*$B$23) -> 457.36457 | D46: =(D45*$B33)+(D44*$B22*$B$23) -> 914.72914 | E46: =(E45*$B33)+(E44*$B22*$B$23) -> 1372.0937 | F46: =(F45*$B33)+(F44*$B22*$B$23) -> 1829.4583 | G46: =(G45*$B33)+(G44*$B22*$B$23) -> 1829.4583 | H46: =(H45*$B33)+(H44*$B22*$B$23) -> 1829.4583 | I46: =(I45*$B33)+(I44*$B22*$B$23) -> 1829.4583 | ... Z46: =(Z45*$B33)+(Z44*$B22*$B$23) -> 1829.4583
A47: Calculations - Lahore, Punjab, Pakistan
A48: Year | B48: 1 | C48: 2 | D48: 3 | E48: 4 | F48: 5 | G48: 6 | H48: 7 | I48: 8 | J48: 9 | K48: 10 | L48: 11 | M48: 12 | N48: 13 | O48: 14 | P48: 15 | Q48: 16 | R48: 17 | S48: 18 | T48: 19 | U48: 20 | V48: 21 | W48: 22 | X48: 23 | Y48: 24 | Z48: 25
A49: Scale | B49: =MIN((B48-$B$27)/$B$28,1) -> 0 | C49: =MIN((C48-$B$27)/$B$28,1) -> 0.25 | D49: =MIN((D48-$B$27)/$B$28,1) -> 0.5 | E49: =MIN((E48-$B$27)/$B$28,1) -> 0.75 | F49: =MIN((F48-$B$27)/$B$28,1) -> 1 | G49: =MIN((G48-$B$27)/$B$28,1) -> 1 | H49: =MIN((H48-$B$27)/$B$28,1) -> 1 | I49: =MIN((I48-$B$27)/$B$28,1) -> 1 | ... Z49: =MIN((Z48-$B$27)/$B$28,1) -> 1
A50: Fixed Costs | B50: =$B3 -> 125000 | C50: =$B4 -> 225000 | D50: =$B4 -> 225000 | E50: =$B4*$B$34 -> 146250 | F50: =$B4*$B$34 -> 146250 | G50: =$B4*$B$34 -> 146250 | H50: =$B4*$B$34 -> 146250 | I50: =$B4*$B$34 -> 146250 | J50: =$B4*$B$34 -> 146250 | K50: =$B4*$B$34 -> 146250 | L50: =$B4*$B$34 -> 146250 | ... Z50: =$B4*$B$34 -> 146250
A51: Start Up costs | B51: =$B$34*(($B5*B12)/11000+($B12*$B25*$B30*1*$B$24)*$B$6) -> 15229.057 | C51: 0 | D51: 0 | E51: 0 | F51: 0 | G51: 0 | H51: 0 | I51: 0 | J51: 0 | K51: 0 | L51: 0 | M51: 0 | N51: 0 | O51: 0 | P51: 0 | Q51: 0 | R51: 0 | S51: 0 | T51: 0 | U51: 0 | V51: 0 | W51: 0 | X51: 0 | Y51: 0 | Z51: 0
A52: Variable Costs | B52: =$B7*B54 -> 0 | C52: =$B7*C54 -> 105151.45 | D52: =$B7*D54 -> 210302.9 | E52: =$B7*E54*$B$34 -> 205045.33 | F52: =$B7*F54*$B$34 -> 273393.77 | G52: =$B7*G54*$B$34 -> 273393.77 | H52: =$B7*H54*$B$34 -> 273393.77 | I52: =$B7*I54*$B$34 -> 273393.77 | J52: =$B7*J54*$B$34 -> 273393.77 | K52: =$B7*K54*$B$34 -> 273393.77 | L52: =$B7*L54*$B$34 -> 273393.77 | ... Z52: =$B7*Z54*$B$34 -> 273393.77
A53: Total Costs | B53: =SUM(B50:B52) -> 140229.06 | C53: =SUM(C50:C52) -> 330151.45 | D53: =SUM(D50:D52) -> 435302.9 | E53: =SUM(E50:E52) -> 351295.33 | F53: =SUM(F50:F52) -> 419643.77 | G53: =SUM(G50:G52) -> 419643.77 | H53: =SUM(H50:H52) -> 419643.77 | I53: =SUM(I50:I52) -> 419643.77 | ... Z53: =SUM(Z50:Z52) -> 419643.77
A54: Number of treatments | B54: =$B12*$B25*$B30*B49*$B$34*$B$24 -> 0 | C54: =$B12*$B25*$B30*C49*$B$34*$B$24 -> 397.60265 | D54: =$B12*$B25*$B30*D49*$B$34*$B$24 -> 795.2053 | E54: =$B12*$B25*$B30*E49*$B$34*$B$24 -> 1192.8079 | F54: =$B12*$B25*$B30*F49*$B$34*$B$24 -> 1590.4106 | G54: =$B12*$B25*$B30*G49*$B$34*$B$24 -> 1590.4106 | H54: =$B12*$B25*$B30*H49*$B$34*$B$24 -> 1590.4106 | I54: =$B12*$B25*$B30*I49*$B$34*$B$24 -> 1590.4106 | ... Z54: =$B12*$B25*$B30*Z49*$B$34*$B$24 -> 1590.4106
A55: Deaths Averted | B55: =B54*(1-$B36)*$B18*$B19 -> 0 | C55: =C54*(1-$B36)*$B18*$B19 -> 15.394276 | D55: =D54*(1-$B36)*$B18*$B19 -> 30.788553 | E55: =E54*(1-$B36)*$B18*$B19 -> 46.182829 | F55: =F54*(1-$B36)*$B18*$B19 -> 61.577106 | G55: =G54*(1-$B36)*$B18*$B19 -> 61.577106 | H55: =H54*(1-$B36)*$B18*$B19 -> 61.577106 | I55: =I54*(1-$B36)*$B18*$B19 -> 61.577106 | ... Z55: =Z54*(1-$B36)*$B18*$B19 -> 61.577106
A56: DALYs Averted | B56: =(B55*$B33)+(B54*$B22*$B$23) -> 0 | C56: =(C55*$B33)+(C54*$B22*$B$23) -> 926.96513 | D56: =(D55*$B33)+(D54*$B22*$B$23) -> 1853.9303 | E56: =(E55*$B33)+(E54*$B22*$B$23) -> 2780.8954 | F56: =(F55*$B33)+(F54*$B22*$B$23) -> 3707.8605 | G56: =(G55*$B33)+(G54*$B22*$B$23) -> 3707.8605 | H56: =(H55*$B33)+(H54*$B22*$B$23) -> 3707.8605 | I56: =(I55*$B33)+(I54*$B22*$B$23) -> 3707.8605 | ... Z56: =(Z55*$B33)+(Z54*$B22*$B$23) -> 3707.8605
A57: Calculations - Peshawar, Khyber Pakhtunkhwa, Pakistan
A58: Year | B58: 1 | C58: 2 | D58: 3 | E58: 4 | F58: 5 | G58: 6 | H58: 7 | I58: 8 | J58: 9 | K58: 10 | L58: 11 | M58: 12 | N58: 13 | O58: 14 | P58: 15 | Q58: 16 | R58: 17 | S58: 18 | T58: 19 | U58: 20 | V58: 21 | W58: 22 | X58: 23 | Y58: 24 | Z58: 25
A59: Scale | B59: =MIN((B58-$B$27)/$B$28,1) -> 0 | C59: =MIN((C58-$B$27)/$B$28,1) -> 0.25 | D59: =MIN((D58-$B$27)/$B$28,1) -> 0.5 | E59: =MIN((E58-$B$27)/$B$28,1) -> 0.75 | F59: =MIN((F58-$B$27)/$B$28,1) -> 1 | G59: =MIN((G58-$B$27)/$B$28,1) -> 1 | H59: =MIN((H58-$B$27)/$B$28,1) -> 1 | I59: =MIN((I58-$B$27)/$B$28,1) -> 1 | ... Z59: =MIN((Z58-$B$27)/$B$28,1) -> 1
A60: Fixed Costs | B60: =$B3 -> 125000 | C60: =$B4 -> 225000 | D60: =$B4 -> 225000 | E60: =$B4*$B$34 -> 146250 | F60: =$B4*$B$34 -> 146250 | G60: =$B4*$B$34 -> 146250 | H60: =$B4*$B$34 -> 146250 | I60: =$B4*$B$34 -> 146250 | J60: =$B4*$B$34 -> 146250 | K60: =$B4*$B$34 -> 146250 | L60: =$B4*$B$34 -> 146250 | ... Z60: =$B4*$B$34 -> 146250
A61: Start Up costs | B61: =$B$34*(($B5*B14)/11000+($B14*$B25*$B30*1*$B$24)*$B$6) -> 3953.1532 | C61: 0 | D61: 0 | E61: 0 | F61: 0 | G61: 0 | H61: 0 | I61: 0 | J61: 0 | K61: 0 | L61: 0 | M61: 0 | N61: 0 | O61: 0 | P61: 0 | Q61: 0 | R61: 0 | S61: 0 | T61: 0 | U61: 0 | V61: 0 | W61: 0 | X61: 0 | Y61: 0 | Z61: 0
A62: Variable Costs | B62: =$B7*B64 -> 0 | C62: =$B7*C64 -> 27295.176 | D62: =$B7*D64 -> 54590.353 | E62: =$B7*E64*$B$34 -> 53225.594 | F62: =$B7*F64*$B$34 -> 70967.459 | G62: =$B7*G64*$B$34 -> 70967.459 | H62: =$B7*H64*$B$34 -> 70967.459 | I62: =$B7*I64*$B$34 -> 70967.459 | J62: =$B7*J64*$B$34 -> 70967.459 | K62: =$B7*K64*$B$34 -> 70967.459 | L62: =$B7*L64*$B$34 -> 70967.459 | ... Z62: =$B7*Z64*$B$34 -> 70967.459
A63: Total Costs | B63: =SUM(B60:B62) -> 128953.15 | C63: =SUM(C60:C62) -> 252295.18 | D63: =SUM(D60:D62) -> 279590.35 | E63: =SUM(E60:E62) -> 199475.59 | F63: =SUM(F60:F62) -> 217217.46 | G63: =SUM(G60:G62) -> 217217.46 | H63: =SUM(H60:H62) -> 217217.46 | I63: =SUM(I60:I62) -> 217217.46 | ... Z63: =SUM(Z60:Z62) -> 217217.46
A64: Number of treatments | B64: =$B14*$B25*$B30*B59*$B$34*$B$24 -> 0 | C64: =$B14*$B25*$B30*C59*$B$34*$B$24 -> 103.20956 | D64: =$B14*$B25*$B30*D59*$B$34*$B$24 -> 206.41911 | E64: =$B14*$B25*$B30*E59*$B$34*$B$24 -> 309.62867 | F64: =$B14*$B25*$B30*F59*$B$34*$B$24 -> 412.83822 | G64: =$B14*$B25*$B30*G59*$B$34*$B$24 -> 412.83822 | H64: =$B14*$B25*$B30*H59*$B$34*$B$24 -> 412.83822 | I64: =$B14*$B25*$B30*I59*$B$34*$B$24 -> 412.83822 | ... Z64: =$B14*$B25*$B30*Z59*$B$34*$B$24 -> 412.83822
A65: Deaths Averted | B65: =B64*(1-$B36)*$B18*$B19 -> 0 | C65: =C64*(1-$B36)*$B18*$B19 -> 3.9960409 | D65: =D64*(1-$B36)*$B18*$B19 -> 7.9920817 | E65: =E64*(1-$B36)*$B18*$B19 -> 11.988123 | F65: =F64*(1-$B36)*$B18*$B19 -> 15.984163 | G65: =G64*(1-$B36)*$B18*$B19 -> 15.984163 | H65: =H64*(1-$B36)*$B18*$B19 -> 15.984163 | I65: =I64*(1-$B36)*$B18*$B19 -> 15.984163 | ... Z65: =Z64*(1-$B36)*$B18*$B19 -> 15.984163
A66: DALYs Averted | B66: =(B65*$B33)+(B64*$B22*$B$23) -> 0 | C66: =(C65*$B33)+(C64*$B22*$B$23) -> 240.62128 | D66: =(D65*$B33)+(D64*$B22*$B$23) -> 481.24257 | E66: =(E65*$B33)+(E64*$B22*$B$23) -> 721.86385 | F66: =(F65*$B33)+(F64*$B22*$B$23) -> 962.48513 | G66: =(G65*$B33)+(G64*$B22*$B$23) -> 962.48513 | H66: =(H65*$B33)+(H64*$B22*$B$23) -> 962.48513 | I66: =(I65*$B33)+(I64*$B22*$B$23) -> 962.48513 | ... Z66: =(Z65*$B33)+(Z64*$B22*$B$23) -> 962.48513
A67: Calculations - Quetta, Balochistan, Pakistan
A68: Year | B68: 1 | C68: 2 | D68: 3 | E68: 4 | F68: 5 | G68: 6 | H68: 7 | I68: 8 | J68: 9 | K68: 10 | L68: 11 | M68: 12 | N68: 13 | O68: 14 | P68: 15 | Q68: 16 | R68: 17 | S68: 18 | T68: 19 | U68: 20 | V68: 21 | W68: 22 | X68: 23 | Y68: 24 | Z68: 25
A69: Scale | B69: =MIN((B68-$B$27)/$B$28,1) -> 0 | C69: =MIN((C68-$B$27)/$B$28,1) -> 0.25 | D69: =MIN((D68-$B$27)/$B$28,1) -> 0.5 | E69: =MIN((E68-$B$27)/$B$28,1) -> 0.75 | F69: =MIN((F68-$B$27)/$B$28,1) -> 1 | G69: =MIN((G68-$B$27)/$B$28,1) -> 1 | H69: =MIN((H68-$B$27)/$B$28,1) -> 1 | I69: =MIN((I68-$B$27)/$B$28,1) -> 1 | ... Z69: =MIN((Z68-$B$27)/$B$28,1) -> 1
A70: Fixed Costs | B70: =$B3 -> 125000 | C70: =$B4 -> 225000 | D70: =$B4 -> 225000 | E70: =$B4*$B$34 -> 146250 | F70: =$B4*$B$34 -> 146250 | G70: =$B4*$B$34 -> 146250 | H70: =$B4*$B$34 -> 146250 | I70: =$B4*$B$34 -> 146250 | J70: =$B4*$B$34 -> 146250 | K70: =$B4*$B$34 -> 146250 | L70: =$B4*$B$34 -> 146250 | ... Z70: =$B4*$B$34 -> 146250
A71: Start Up costs | B71: =$B$34*(($B5*B16)/11000+($B16*$B25*$B30*1*$B$24)*$B$6) -> 6517.6772 | C71: 0 | D71: 0 | E71: 0 | F71: 0 | G71: 0 | H71: 0 | I71: 0 | J71: 0 | K71: 0 | L71: 0 | M71: 0 | N71: 0 | O71: 0 | P71: 0 | Q71: 0 | R71: 0 | S71: 0 | T71: 0 | U71: 0 | V71: 0 | W71: 0 | X71: 0 | Y71: 0 | Z71: 0
A72: Variable Costs | B72: =$B7*B74 -> 0 | C72: =$B7*C74 -> 45002.341 | D72: =$B7*D74 -> 90004.682 | E72: =$B7*E74*$B$34 -> 87754.565 | F72: =$B7*F74*$B$34 -> 117006.09 | G72: =$B7*G74*$B$34 -> 117006.09 | H72: =$B7*H74*$B$34 -> 117006.09 | I72: =$B7*I74*$B$34 -> 117006.09 | J72: =$B7*J74*$B$34 -> 117006.09 | K72: =$B7*K74*$B$34 -> 117006.09 | L72: =$B7*L74*$B$34 -> 117006.09 | ... Z72: =$B7*Z74*$B$34 -> 117006.09
A73: Total Costs | B73: =SUM(B70:B72) -> 131517.68 | C73: =SUM(C70:C72) -> 270002.34 | D73: =SUM(D70:D72) -> 315004.68 | E73: =SUM(E70:E72) -> 234004.56 | F73: =SUM(F70:F72) -> 263256.09 | G73: =SUM(G70:G72) -> 263256.09 | H73: =SUM(H70:H72) -> 263256.09 | I73: =SUM(I70:I72) -> 263256.09 | ... Z73: =SUM(Z70:Z72) -> 263256.09
A74: Number of treatments | B74: =$B16*$B25*$B30*B69*$B$34*$B$24 -> 0 | C74: =$B16*$B25*$B30*C69*$B$34*$B$24 -> 170.16456 | D74: =$B16*$B25*$B30*D69*$B$34*$B$24 -> 340.32912 | E74: =$B16*$B25*$B30*E69*$B$34*$B$24 -> 510.49367 | F74: =$B16*$B25*$B30*F69*$B$34*$B$24 -> 680.65823 | G74: =$B16*$B25*$B30*G69*$B$34*$B$24 -> 680.65823 | H74: =$B16*$B25*$B30*H69*$B$34*$B$24 -> 680.65823 | I74: =$B16*$B25*$B30*I69*$B$34*$B$24 -> 680.65823 | ... Z74: =$B16*$B25*$B30*Z69*$B$34*$B$24 -> 680.65823
A75: Deaths Averted | B75: =B74*(1-$B36)*$B18*$B19 -> 0 | C75: =C74*(1-$B36)*$B18*$B19 -> 6.5883873 | D75: =D74*(1-$B36)*$B18*$B19 -> 13.176775 | E75: =E74*(1-$B36)*$B18*$B19 -> 19.765162 | F75: =F74*(1-$B36)*$B18*$B19 -> 26.353549 | G75: =G74*(1-$B36)*$B18*$B19 -> 26.353549 | H75: =H74*(1-$B36)*$B18*$B19 -> 26.353549 | I75: =I74*(1-$B36)*$B18*$B19 -> 26.353549 | ... Z75: =Z74*(1-$B36)*$B18*$B19 -> 26.353549
A76: DALYs Averted | B76: =(B75*$B33)+(B74*$B22*$B$23) -> 0 | C76: =(C75*$B33)+(C74*$B22*$B$23) -> 396.71922 | D76: =(D75*$B33)+(D74*$B22*$B$23) -> 793.43843 | E76: =(E75*$B33)+(E74*$B22*$B$23) -> 1190.1577 | F76: =(F75*$B33)+(F74*$B22*$B$23) -> 1586.8769 | G76: =(G75*$B33)+(G74*$B22*$B$23) -> 1586.8769 | H76: =(H75*$B33)+(H74*$B22*$B$23) -> 1586.8769 | I76: =(I75*$B33)+(I74*$B22*$B$23) -> 1586.8769 | ... Z76: =(Z75*$B33)+(Z74*$B22*$B$23) -> 1586.8769
A77: Results
A78: Karachi, Sindh, Pakistan
A79: Deaths averted | B79: {=NPV(B32,45:45)} -> 404.35366
A80: DALYs averted | B80: {=NPV(B32,46:46)} -> 24348.123
A81: Cost | B81: {=NPV(B32,43:43)} -> 4258687.2
A82: USD / DALY | B82: =B81/B80 -> 174.90823
A83: Lahore, Punjab, Pakistan
A84: Deaths averted | B84: {=NPV(B32,55:55)} -> 819.52509
A85: DALYs averted | B85: {=NPV(B32,56:56)} -> 49347.638
A86: Cost | B86: {=NPV(B32,53:53)} -> 6159796.2
A87: USD / DALY | B87: =B86/B85 -> 124.82454
A88: Peshawar, Khyber Pakhtunkhwa, Pakistan
A89: Deaths averted | B89: {=NPV(B32,65:65)} -> 212.73203
A90: DALYs averted | B90: {=NPV(B32,66:66)} -> 12809.643
A91: Cost | B91: {=NPV(B32,63:63)} -> 3381233.8
A92: USD / DALY | B92: =B91/B90 -> 263.96004
A93: Quetta, Balochistan, Pakistan
A94: Deaths averted | B94: {=NPV(B32,75:75)} -> 350.73741
A95: DALYs averted | B95: {=NPV(B32,76:76)} -> 21119.625
A96: Cost | B96: {=NPV(B32,73:73)} -> 4013173.4
A97: USD / DALY | B97: =B96/B95 -> 190.02105
A98: Average
A99: Deaths averted | B99: =AVERAGE(B79,B84,B89,B94) -> 446.83705
A100: DALYs averted | B100: =AVERAGE(B80,B85,B90,B95) -> 26906.257
...

Sheet Calculations
A1: Weighted Low Birth Weight Prevalence based on Demographic and Health Se
A2: Age of Mother | B2: Percentage less than 2.5 kg among weighed | C2: Number of births in sample
A3: <20 | B3: 0.335 | C3: 972
A4: 20-34 | B4: 0.205 | C4: 8482
A5: 35-49 | B5: 0.275 | C5: 1040
A6: Estimate | B6: =((B3*C3)+(B4*C4)+(B5*C5))/SUM(C3:C5) -> 0.22397846
A7: Weighted Low Birth Weight Counterfactual Mortality
A8: Item | B8: Figure | C8: n | D8: Notes | E8: Source
A9: Estimate 1 | B9: =133/1000 -> 0.133 | C9: 776 | D9: Periurban setting - Bangladesh / Retrospective Cohort Study (n=776) | E9: Neonatal mortality of low-birth-weight infants in Bangladesh. - PMC
A10: Estimate 2 | B10: 0.111 | C10: 885 | D10: Community-based - South Ethiopia / Mixed-method (n=885) | E10: Magnitude and Risk of Dying among Low Birth Weight Neonates in Rural Ethiopia: A Community-Based Cross-Sectional Study - PMC
A11: Estimate 3 | B11: 0.083 | C11: 216 | D11: Public Hospitals - Ethiopia / Prospective Cohort Study (n=216) | E11: The Kaplan Meier estimates of mortality and its predictors among newborns admitted with low birth weight at public hospitals in Ethiopia | PLOS ONE
A12: Estimate 4 | B12: 0.152 | C12: n/a | D12: Meta-analysis | E12: https://academic.oup.com/trstmh/article-abstract/95/6/569/1905057?redirectedFrom=fulltext&login=false#no-access-message
A13: Estimate | B13: =AVERAGE((B9*C9+B10*C10+B11*C11)/SUM(C9:C11),B12) -> 0.1344366 | D13: (Weighted (by n) average of estimates 1-3 + Estimate 4) / 2

Sheet Cost Estimates
A1: Estimates
A2: 1. r.i.c.e model // VARIABLE TREATMENT COSTS
A3: Item | B3: Estimate | C3: Notes | D3: Source
A4: P/Treatment | B4: 455 | C4: Uttar Pradesh, India | D4: Internal
A5: 2. Incremental costs per treatment reported in India // VARIABLE TREATMENT COSTS
A6: Item | B6: Estimate | C6: Notes | D6: Source
A7: P/Treatment | B7: 72 | C7: Average 3 Indian States | D7: Incremental costs of scaling up kangaroo mother care: Results from implementation research in Ethiopia and India - - Acta Paediatrica - Wiley Online Library
A8: 3. Costs per treatment calculated from study // VARIABLE TREATMENT COSTS
A9: Item | B9: Estimate | C9: Notes | D9: Source
A10: Salaries | B10: 11788
A11: Other variable | B11: 7501
A12: Number in treatment arm | B12: 149
A13: P/Treatment | B13: =SUM(B10:B11)/B12 -> 129.45638 | C13: Average 3 Indian States | D13: Incremental costs of scaling up kangaroo mother care: Results from implementation research in Ethiopia and India - - Acta Paediatrica - Wiley Online Library
A14: 4. My estimate // VARIABLE TREATMENT COSTS
A15: Nurse Salary Estimates
A16: Item | B16: Figure | C16: Notes | D16: Source
A17: Estimate 1 PKR | B17: =37500*12 -> 450000 | C17: Average Annual Salary for Nurse 2-5 years experience | D17: Staff Nurse Average Salary in Pakistan 2023 - The Complete Guide
A18: Estimate 2 PKR | B18: 267998.72 | C18: Annual Salary for Assistant Nurse or Midwive | D18: LiST Costing Tool
A19: Average USD | B19: =IFERROR(__xludf.DUMMYFUNCTION("GOOGLEFINANCE(""currency:pkrusd"")*AVERAGE(B17:B18)"),1289.8488012805449) -> 1289.8488
A20: Manager Salary Estimates
A21: Item | B21: Figure | C21: Notes | D21: Source
A22: Estimate 1 PKR | B22: =47100*12 -> 565200 | C22: Average | D22: Nurse Average Salary in Pakistan 2023 - The Complete Guide
A23: Estimate 2 PKR | B23: 353817.84 | C23: Annual Salary for Nurse | D23: LiST Costing Tool
A24: Average USD | B24: =IFERROR(__xludf.DUMMYFUNCTION("GOOGLEFINANCE(""currency:pkrusd"")*AVERAGE(B22:B23)"),1650.9695996919768) -> 1650.9696
A25: Estimate of nurse need and manager need per treatment
A26: Nurse ratio p/treatment | B26: =15/540 -> 0.027777778 | C26: r.i.c.e ratio is ~15 x ~540 treatments
A27: Manager ratio p/treatment | B27: =4/540 -> 0.0074074074 | C27: r.i.c.e ratio is ~4 x ~540 treatments
A28: Assistant ratio/ptreatment | B28: =11/540 -> 0.02037037 | C28: r.i.c.e ratio is ~11 ~540 treatments.
A29: Variable costs p/treatment
A30: Additional consumables | B30: 3.63 | C30: KMC garments (e.g.,cloth wraps) 2 USD + Other consumables 1 USD + Parent education literature 0.63 USD | D30: The cost-savings of implementing kangaroo mother care in Nicaragua
A31: Treatment | B31: =(B19*B26+B24*B27+(B19/2)*B28)+B30 -> 64.825887 | C31: I assume 50% cost of nurse for assistant
A32: 5. WHO Guideline breakdown - followed guidelines for assumed 100 treated // VARIABLE TREATMENT COSTS
A33: Item | B33: Figure | C33: Notes | D33: Source
A34: Beds needed p/100 treated (rounded) | B34: =ROUND(100*(6.61/365)*1.5,0) -> 3 | C34: Expected KMC x (Average length of stay / 365) x 1.5 // 1.5 to account for fluctuations, according to document // Average length of stay is 6.61 days - average of three sources cited | D34: https://apps.who.int/iris/rest/bitstreams/1148441/retrieve | E34: Safety, Effectiveness and Barriers to Follow-up Using an ‘Early Discharge’ Kangaroo Care Policy in a Resource Poor Setting | F34: Kangaroo care in pre-term or low birth weight babies in a postnatal ward | G34: Maternal experience of intermittent kangaroo mother care for late preterm infants: a mixed-methods study in four postnatal wards in China - PMC
A35: Number staff needed p/100 treated (rounded) | B35: =ROUND((B34/8)*3*(7/5),0) -> 2 | C35: Total beds needed / 8 x (# shifts/day) x (7/#days worked/week) // For a basic KMC ward assume 1 nurse or equivalent staff for 8–10 beds | D35: https://apps.who.int/iris/rest/bitstreams/1148441/retrieve
A36: Staff cost per treated + Additional Consumables | B36: =(B35/100)*B19+B30 -> 29.426976 | C36: Costs of Nurse and Additional consumables from 4. My Estimate
A37: Final estimate // VARIABLE TREATMENT COSTS
A38: Total | B38: Number | C38: Weight
A39: Estimate 1 | B39: =B4 -> 455 | C39: 12 | D39: We think that this is likely to be the most accurate depiction of a programme like this.
A40: Estimate 2 | B40: =B7 -> 72 | C40: 3
A41: Estimate 3 | B41: =B13 -> 129.45638 | C41: 3
A42: Estimate 4 | B42: =B31 -> 64.825887 | C42: 3
A43: Estimate 5 | B43: =B36 -> 29.426976 | C43: 3
A44: Final | B44: =(B39*C39+B40*C40+B41*C41+B42*C42+B43*C43)/SUM(C39:C43) -> 264.46365
A46: 1. Kangaroo Mothercare DIB - Cameroon // START UP COSTS
A47: Median Infrastructure Investment | B47: 20000 | C47: We believe that this median estimate may represent costs for a 400 bed hospital, but its a very rudimentary guess | D47: CAMEROON
A48: Average cost p/ clinician trained | B48: 911 | D48: CAMEROON
A49: 2. KC Scale up - NICARAGUA // START UP COSTS
A50: 15-day training session at the regional KMC training center in Bogota, Colombia, for three health workers | B50: 17088
A51: Furniture for counseling room | B51: 1556
A52: Belts, clothing, and equipment for breastfeeding | B52: 1515
A53: Durable medical equipment | B53: 841
A54: Workshop and other sessions to review/adapt tools | B54: 650
A55: Counseling literature | B55: 768
A56: Promotional materials | B56: 695
A57: Total | B57: =SUM(B50:B56) -> 23113 | C57: 11,000 birth hospital | D57: https://scielosp.org/pdf/rpsp/2013.v34n3/176-182/en
A58: Total w/out training | B58: =B57-B50 -> 6025 | C58: We believe these training costs are inflated due to the lack of training materials, and need to travel to Colombia, we are quite certain these would not be that large | D58: https://scielosp.org/pdf/rpsp/2013.v34n3/176-182/en
A59: 3. KC Scale up - GENERAL // START UP COSTS
A60: Training cost p/practitioner | B60: 115 | C60: From expert interview w/ Lafiya Nigeria | F60: ← Filip has $30 per person trained to deliver syphalis RDTs and Penecilin treatment. This is a bit simpler but a lot lower maybe you two should talk and make sure that estimates are comparable
A61: Final estimate // START UP COSTS
A62: Facility Set Up ~ 10.000 live birth capacity | B62: =IFERROR(__xludf.DUMMYFUNCTION("AVERAGE.WEIGHTED(B47,1,B58,2)"),10683.333333333334) -> 10683.333 | C62: Weighted average of 1. Kangaroo Mothercare DIB - Cameroon // START UP COSTS & 2. KC Scale up - NICARAGUA // START UP COSTS - We put double the weight on the Nicaragua estimates because they are reported in a more credible manner (w/breakdowns) and we are more certain about the size of the hospital.
A63: Training costs p/expected treatment at scale | B63: =(B35*B60)/100 -> 2.3 | C63: Using 5. WHO Guideline breakdown - followed guidelines for assumed 100 treated // VARIABLE TREATMENT COSTS & 3. KC Scale up - GENERAL // START UP COSTS
A64: Adjustment for turnover | B64: =21/(100/7) -> 1.47 | C64: Cameroon study suggests a 7% turnover rate p/year for nurses - We assume 21 years at scale. | D64: CAMEROON
A65: Training cost p/treatement at scale adjusted p/turnover | B65: =B63*B64 -> 3.381
