Workbook
Name MigrantsAtScale: #REF!
Name DiscountRate: #REF!
Name ConsumptionDoublingsMigrant: #REF!
Name CostScale: #REF!
Name AudienceSize: #REF!
Name CostOfMigrating: #REF!
Name MigrantsAtScale: #REF!
Name TimePrep: #REF!
Name TotalDoublings: #REF!
Name TimeToScale: #REF!
Name TotalAirtimeCost: #REF!
Name CostOfMigrating: #REF!
Name TimeToFail: #REF!
Name ProbSuccess: 'Main model'!$B$116
Name AnnualRiseInIncome: #REF!
Name CostY1: #REF!
Name TotalProductionCost: #REF!
Name CostY1: #REF!
Name TimeToScale: #REF!
Name TotalProductionCost: #REF!
Name ConsumptionIncreaseMigrant: #REF!
Name TimeToScale: #REF!
Name ConsumptionDoublingsMigrant: #REF!
Name Scale: #REF!
Name DiscountRate: #REF!
Name Year: #REF!
Name CampaignMonths: #REF!
Name CostScale: #REF!
Name NumberOfStations: #REF!
Name AudienceSize: #REF!
Name CostScale: #REF!
Name Scale: #REF!
Name ConsumptionIncreaseMigrant: #REF!
Name TimeToFail: 'OLD 2023 CEA'!$B$12
Name TotalDALYs: #REF!
Name TotalAirtimeCost: #REF!
Name AudienceSize: #REF!
Name Year: #REF!
Name ConsumptionDoublingsMigrant: #REF!
Name TotalDALYs: #REF!
Name Year: #REF!
Name NumberOfStations: #REF!
Name ProbSuccess: 'OLD 2023 CEA'!$B$11
Name ProbCounterfactual: #REF!
Name TimeToFail: 'Main model'!$B$117
Name TotalProductionCost: #REF!
Name CampaignMonths: #REF!
Name AnnualRiseInIncome: #REF!
Name TotalDoublings: #REF!
Name ProbSuccess: #REF!
Name TotalAirtimeCost: #REF!
Name MigrantsAtScale: #REF!
Name NumberOfStations: #REF!
Name Scale: #REF!
Name TotalDoublings: #REF!
Name ConsumptionIncreaseMigrant: #REF!
Name CostOfMigrating: #REF!
Name TotalDALYs: #REF!
Name ProbCounterfactual: #REF!
Name AnnualRiseInIncome: #REF!

Sheet Key
B1: Welcome to our CEA...
A3: Introduction – what this is and what this is not
B4: Our CEAs are primarily designed to support the AIM team to make decisions between ideas. This means we prioritise our CEAs being comparable to each other. This is not always the same as prioritising accuracy. For example if one CEA goes into much more depth than others, that would be a bad thing for our overall decision making. Also we use similar figures across CEAs justified on grounds of being the default figure to use across CEAs. You might even spot some strange uses of units like "DALY equivalents" where monetary benefits are converted to health benefits or visa versa. That said, there should not be errors or mistakes in our CEAs. These do occasionally crop up. If you do find an error or just want to challenge our modelling assumptions we are open to feedback. Feel free to reach out to the us via the form at: https://www.charityentrepreneurship.com/contact
A7: Key to colours used in the CEA
C8: Input
C9: Subjective judgement
C10: Variable imported input from another tab/sheet (mostly used when data input varies based on country chosen)
C11: Calculation
A14: Guide to the tabs
B15: Tab name | C15: Description
B16: Main CEA | C16: The main tab of this CEA where most inputs live and calculations happen
B17: Country data | C17: Occasionally we want to model multiple countries at once. This tab contains the data that varies based on the country being modelled.
B18: Uncertainty | C18: Sometimes we want to model the uncertainty. This tab runs a simple Monte Carlo uncertainty moddelling script.
B19: Data: _____ | C19: These tabs contain various data sets that may be used in modelling. They may or may not have been used in this CEA.
B20: Calc: _____ | C20: Sometimes a CEA author will want to do some background data calculations in another tab so might add a tab like this
A23: Reading the CEA
C25: Researcher's best guess expected value estimate for the input at hand ↓ | D25: The unit of measurement for the estimate ↓ | E25: An explanation of our thinking in relation to the input ↓ | F25: Link or links to the key sources data is taken from ↓ | I25: ◄ | J25: Hidden columns may be used for uncertainty ▶ modelling ↓
C26: Value | D26: Units | E26: Description | F26: Source | G26: Reviewer notes | H26: Replies | I26: → | J26: ← Hidden optional uncertinaty modelling
B28: Description of intervention
B29: [Fill out description here] | E29: ← We normally begin with a description of the intervention
B30: Geographic focus: | C30: [country / region] | E30: ← If this cell is highlighted orange you can use it as a dropdown to decide what country you want to see the results for
B31: Beneficiary – this CEA models the costs effect and reach per: | C31: [person]
B32: Impact – this CEA models the impact in terms of: | C32: [DALY] | E32: ← The CEA will normally measure impact in the amount of this per $, in this example it would be [DALY]/$
B34: Costs of intervention | E34: ← The CEA is modular and broken down into sections for easy reading and to allow comparison between different CEAs
B36: 1. FIXED COSTS | E36: ← Each section is comprised of various sub-sections like this
B37: [Subheading]
B38: Fixed costs in [first] year [Suggest: $130,000] | C38: 130000 | D38: $ | E38: ← Some cells have notes like this ◥. They were to help the CEA authors, mostly you can ignore them
B39: Ongoing annual fixed costs when at scale [Suggest: $280,000] | C39: 280000 | D39: $
B40: Additional upfront fixed costs before reaching scale [Normally: $0] | C40: 0 | D40: $
B42: TOTAL CHARITY COSTS WHEN AT SCALE | E42: ← Sections end with a subsection in bold that calculates the results of that section
B43: Total fixed costs when at scale | C43: =C39 -> 280000 | D43: $
B45: Effects per [beneficiary]
B47: Reach of intervention
B49: Tractability & counterfactuals
B51: Timing to scale and discounting | E51: ← In this section the CEA author defines the discount rates, the changing effects over time, And the time taken to scale up the costs and the impact.
E52: The actual calculations are hard to follow so are often hidden, but they should all be replicated in a more transparent easy to follow way in the timeline check below
B54: Results
B56: Timeline check | E56: ← The timeline shows the cost and the impact each year. It does the same calculations as the "Timing to scale and discounting" section
B58: ** Result 4 – cost effectiveness FINAL RESULT ** | E58: ← We have a range of different results. This helps support decision making (we can manage multiple numbers) and allow us to understand and compare our models
B59: R4: Cost effectiveness per year ($/Impact) | C59: 100 | D59: $/[DALY]
B60: R4: Cost effectiveness per year (Impact/$1000) | C60: =1000*(1/C59) -> 10 | D60: [DALY]/$1000 | E60: ← These R4 cost effectiveness figures are the key results to look at. Look out for numbers less than 100 $/DALY or more than 10 DALY/$1000 or equivalent.
A65: Advice to researchers on filling out this CEA
B67: • Please check out the various notes and tips as you work through the CEA they look like little black arrows like on this box.
A74: Example CEA

Sheet Main model
B1: Value | C1: Units | D1: Description | E1: Source
A2: Description of intervention
A3: This is a policy/advocacy intervention that targets ULAB recycling in Thailand and scaling to two other similar countries. The goal would be the push some of the informal recycling market share into the formal recycling sector. We are moddeling some general policy improvements here, based on an estimate of the effect of BLL.
A4: Geographic focus: | B4: Thailand
A5: Beneficiary – this CEA models the costs effect and reach per: | B5: country
A6: Impact – this CEA models the impact in terms of: | B6: DALY equivelents
A9: Costs of intervention
A11: 1. FIXED COSTS
A12: Fixed costs in first year | B12: 130000 | C12: $ | D12: Estimate (from Joey) for 90% confidence interval for CE seed grant is $100k to $190k
A13: Ongoing annual fixed costs when at scale - base | B13: 280000 | C13: $ | D13: Based on estimate from Joey
A14: Total ongoing annual fixed costs when at scale | B14: =B13 -> 280000 | C14: $
A16: 2. VARIABLE CHARITY COSTS
A17: ="Median salary in "&B4 -> Median salary in Thailand | B17: {=INDEX('Median salaries'!G:G,MATCH(B4,'Median salaries'!A:A,0))} -> 14366.019 | C17: $
A18: Policy costs | B18: =50000 + 5*B17 -> 121830.1 | C18: $ | D18: Policy costs: We use $50,000 + 5 * median local salary
A19: Cost per additional country | B19: =B18 -> 121830.1 | C19: $/country | D19: ="Unsure what those other countries are; assuming the same costs as "&B4 -> Unsure what those other countries are; assuming the same costs as Thailand
A21: TOTAL CHARITY COSTS WHEN AT SCALE
A22: Total costs when at scale | B22: =B14 + B19*B103 -> 645490.29 | D22: For display; not actually used in any formula
A24: ="Effects per "&$B$5 -> Effects per country
A25: Key assumptions / data
A26: One year of doubled consumption to DALYs [fixed] | B26: =1/2.5 -> 0.4 | C26: ratio
A27: Discount rate for health impacts | B27: 0.014 | C27: % discounted
A28: Discount rate for consumption impacts | B28: 0.04 | C28: % discounted
A29: Population per country | B29: 71700000 | C29: people | E29: https://ourworldindata.org/grapher/population?time=latest&country=~THA&focus=~THA
A30: Births per country per year | B30: =8.24/1000*B29 -> 590808 | C30: births | E30: https://ourworldindata.org/grapher/crude-birth-rate
A32: Reduction in BLLs due to the intervention
A33: Percentage of burden attributable to informal ULAB recycling
A34: Directly due to ULAB recycling | B34: 0.15 | C34: % | D34: Best guess based on tab on 'overall GBD ULAB recycling' and upcoming paper from Forsyth which states that ULABs are responsible for 30% of lead poisoning in Dhaka, Bangladesh. Bret Ericson thought it is somewhere around 10%, Hugo thought 20%.
A35: Total burden attributable to cookware | B35: 0.25 | C35: % | D35: Best guess
A36: % of cookware contamination resulting from ULAB recycling. | B36: 0.1 | C36: % | D36: Intuition. Some experts told us that in Mexico, both formal and informal recyclers sell lead (dust) to artisinal cookware makers.
A37: Additional contamination via grown crops near ULAB recycling plants/informal recyclers | B37: 0.02 | C37: % | D37: One route is contamination via vegetables, see paper: https://www.sciencedirect.com/science/article/abs/pii/S0013935123012215
A38: Percentage attributable to formal and informal ULAB recycling | B38: =B34 + B35*B36 + B37 -> 0.195 | C38: %
A40: Decrease in burden when substantial regulations are implemented
A41: Estimating the effect of the policies in Brazil | D41: We base our calculation on the effect estimated for Brazil
A42: Burden due to informal recycling in Brazil before improved regulation | B42: 0.8 | C42: % | D42: Estimate, based on assuming that the formal sector emits 5x less lead (per battery) than the informal sector, which seems plausible (see Table 1 in the report)
A43: Size of informal sector in Brazil before improved regulation | B43: 0.45 | C43: % | D43: Carlos Zaim mentioned 40-45% , other sources claim 'the majority', so i went for 45%. Also, the blogpost mention some rough numbers, but that must have come from Carlos as well- https://leadbatteries.substack.com/p/how-brazil-solved-its-lead-acid-battery
A44: Size of informal sector in Brazil after regulation | B44: 0.1 | C44: % | D44: IBER has 75% of market in 2022, could expect this to have increased
A45: Decrease of size of informal recycling due to regulations | B45: =1-B44/B43 -> 0.77777778 | C45: % | D45: Mark stevenson made a judgementcall, that a decrease of 50% would happen if taxes are cut in India Hugo: This number should be at least 50%. Best info he got on this was a quote: "most was informal before", Now 75% of the battery recycling is going via IBER. Also, Pure Earth states about 80%, see here: https://www.google.com/url?q=https://e360.yale.edu/features/getting-the-lead-out-why-battery-recycling-is-a-global-health-hazard%23:~:text%3DFuller%2520at%2520Pure%2520Earth%2520says,%252C%25E2%2580%259D%2520mainly%2520through%2520economic%2520incentives&sa=D&source=editors&ust=1733491202096199&usg=AOvVaw0aomdHgPlN28-Xc1QU9qWz
A46: Decrease of total ULAB burden due to regulations | B46: =B42*B45 -> 0.62222222 | C46: %
A48: Discounts for moving to a new context
A49: Improved policies not as effective as in Brazil, e.g. different response as there are different incentives, unknown | B49: 0.35 | C49: % reduction | D49: Intuition, there might be many reasons to think that the policy is not as effective. We err on the side that things worked out quite well for Brazil, e.g. because only some of the policies may be implemented
A50: Enforcement is not as good as in Brazil | B50: 0.2 | C50: % reduction | D50: It seems like with IBER, things worked out very well in Brazil. This might not work out up to such an extent in Thailand
A51: When informal recyclers are gone, site may still be contaminated (until cleaned) | B51: 0.4 | C51: % reduction | D51: Impact comes from informal recyclers not relocating and no new informal recyclers starting. Carlos explained that as part of the Brazil legislation, one needs to clean up the plot before it can be used. Therefore, this is much a smaller problem. Updated the discount from 70% to 40%, as i expect this legislation not to be watertight, and potentially now viable to introduce in other countries.
A52: Decrease of total ULAB burden of a country when policies are improved substantially | B52: =B46*(1-B49)*(1-B50)*(1-B51) -> 0.19413333 | C52: %
A54: Overall effect
A55: Reduction in burden if substantial regulations are implemented | B55: =B38*B52 -> 0.037856 | C55: % reduction
A57: Health effect (CVD and kidney disease)
A58: DALY burden (GBD)
A59: Total health burden in DALYs due to lead exposure (in 2021) in the country | B59: 121536 | C59: DALY/year | D59: Health burden of lead exposure in Thailand. Note that this only considers cardiovascular diseases and kidney diseases. | E59: https://vizhub.healthdata.org/gbd-results?params=gbd-api-2021-permalink/f35471a2acd6ed1a409c70b34c920728
A60: Total DALY burden lead exposure due to ULAB recycling | B60: =B59*B38 -> 23699.52 | C60: DALY/year | D60: Not used
A61: Percentage of health burden that is locked in, in the year the intervention is rolled out | B61: 0.5 | C61: % | D61: Lead accumulates in the body and causes damage to organs over time. Therefore, even when a source of exposure is removed, some of its health effects will persist (or be "locked in"). We expect that some percentage of the health benefits will materialize relatively quickly but some only be seen in a future generation. We have not been able to research this point in depth but, based on a conversation with ChatGPT, we roughly expect the locked-in portion of the health effects to be around 50%.
A62: Total DALY reduction due to the intervention, per country per year | B62: =B59*B55*B61 -> 2300.4334 | C62: DALY/year | D62: Effect in year 1
A64: Growth of effect over time | D64: We expect the health effect to grow over time, as sketched out in this section. However, for simplicity, this assumption is not integrated into the model.
A65: Effect size in the year the intervention is rolled out | B65: =B55*(1-B61) -> 0.018928 | C65: %
A66: Effect size once lock-in burden disappears | B66: =B55 -> 0.037856 | C66: % reduction
A67: Number of years until locked-in effects disappear | B67: 20 | C67: years | D67: We estimate that the effect size will linearly increase over the scope of 20 years.
A68: ="Increase in effect size during the first "&B67&" years, per year" -> Increase in effect size during the first 20 years, per year | B68: =(B66-B65)/B67 -> 0.0009464 | C68: %
A70: Cognitive and economic effects
A71: BLL in Country | B71: 5.12 | C71: µg/dL | D71: This is 2019, assuming nothing has changed. Note that Brazil was only 2.19 at the time. | E71: https://ourworldindata.org/grapher/lead-concentrations-blood-children?tab=table
A72: Reduction in BLL thanks to policies introduced | B72: =B55 -> 0.037856 | C72: % change | D72: Assumed to be the same as the burden reduction
A73: Intermediate effect size - reduction in BLL | B73: =B71*B72 -> 0.19382272 | C73: μg/dL
A74: Internal validity effect | B74: 0 | C74: % change | D74: Not used (this is relevant when effect size is taken from a study)
A75: External validity effect | B75: 0 | C75: % change | D75: Not used
A76: Discounted effect size - reduction in BLL | B76: =B73*(1+B74)*(1+B75) -> 0.19382272 | C76: μg/dL
A77: Estimated IQ point loss per 1 μg/dl increase in blood levels throughout childhood | B77: =0.5*0.75 -> 0.375 | C77: IQ points per μg/dL | D77: There is substantial uncertainty about this relationship. A seminal study by Lanphear et al. (2005) estimates 0.5 IQ points per 1 μg/dL at BLLs below 10 μg/dL. This is also what the LEEP model uses (see link). However, modelers such as GiveWell have used a more conservative value of 0.20 with a 25% downward validity discount (resulting in 0.15). We have chosen to use the original 0.5 with the same discount as GiveWell, giving use 0.38. | E77: https://www.givewell.org/research/incubation-grants/Pure-Earth-lead-exposure-July-2021 https://docs.google.com/document/d/1NH99fuXpXcCcz-vjaP1x3ZOVDNYd4gflWWb2B5y3TcQ/edit#heading=h.cqwbetxdrmad https://my.causal.app/models/212624?token=97c447ae91e74281b8032591b190e316 | F77: (note that this is higher than our previous model for lead research)
A78: IQ points gained per person | B78: =B76*B77 -> 0.07268352 | C78: IQ points
A79: % increase in income (/consumption) for every 1 point increase in IQ | B79: 0.0067 | C79: % change | D79: From GiveWell | E79: https://docs.google.com/spreadsheets/d/15h60n8jDSQMFpmA_y4ilYOUE0mP-C9SRosEMHuWDnug/edit#gid=154585324
A80: % increase in income per person (in each year of working life) | B80: =B78*B79 -> 0.00048697958 | C80: % change
A81: Future fertility rate in a typical target country (a guess) | B81: 1.5 | D81: A big guess. But most of the short-listed countries are richer LMCs or UMCs, which have quite low fertility rates
A82: Multiplier for resource sharing | B82: =(2+B81)/2 -> 1.75 | C82: coefficient | D82: Each working adult's income benefits not only the worker but also dependents (e.g. children)
A83: Conversion to consumption doublings | B83: =log(1+B80,2)*B82 -> 0.001229186 | C83: ratio | D83: Assuming all extra income is consumed
A84: DALY equivalents per person per year of their working life | B84: =B83*B26 -> 0.00049167441 | C84: DEs/person/year | D84: DE = DALY equivalent
A85: Number of years of working life | B85: =65-20 -> 45 | C85: years | D85: Length of working life
A86: Total DALY-equivalent benefit over working life | B86: =-PV(B28,B85,B84) -> 0.010187513 | C86: DEs/person
A87: Delay in benefits | B87: 15 | C87: years | D87: Age when people start working. (Note that this could probably be a bit less, as the damage doesn't just happen around birth but also in childhood)
A88: Present value of consumption benefit | B88: =B86*(1-B28)^B87 -> 0.0055225122 | C88: DEs/person
A89: Total net impact per country per year | B89: =B88*B30 -> 3262.7444 | C89: DEs/country | D89: Impact is primarily associated with births
A91: Change of the effect over time | D91: We expect the cognitive effects will affect additional birth cohorts, as sketched out in this section. However, for simplicity, this assumption is not integrated into the model.
A92: Additional birth cohorts affected after | B92: 2 | D92: Lead exposure affects brain development throughout childhood, not only at birth, which means that children already been born by the time of the intervention's roll-out will also partly benefit. We didn't have time to research this question in depth, but, based on an answer from ChatGPT, we estimate that ~50% of the brain damage happens by age 2 and ~80% by age 5. Summing over ages 1-10, we roughly estimate than an equivalent of two extra birth cohorts will benefit from the intervention.
A93: Effect in the first year after roll-out | B93: =B89*(1+B92) -> 9788.2332 | C93: DEs/person
A95: Total impact per year
A96: Total net impact, per country per year, at scale | B96: =B62+B89 -> 5563.1778 | C96: DEs/person
A98: % of effect that is due to health effects | B98: =B62/B96 -> 0.41351067 | C98: % | D98: This is significantly higher than LEEP's estimate of <20%. We are not fully sure what's driving this difference. One reason is that GBD's estimates of the health burden of lead exposure have increased (by ~50%); however, this alone is not enough to explain the difference.
A100: Reach of intervention
A102: ="Number of "&$B$5&"s can reach a year when at scale" -> Number of countrys can reach a year when at scale
A103: Number of countries worked in at scale | B103: 3 | C103: count | D103: We estimate that the charity can work in three countries in parallel, though we are very uncertain about this
A105: Result 1 – cost effectiveness, at scale, assume success, ignoring counterfactuals
A106: R1: Number reached per year, at scale, assume success, ignore counterfactuals | B106: =B103 -> 3 | C106: countries/year
A107: R1: Cost per year, at scale, assume success, ignore counterfactuals (charity costs only) | B107: =B$22 -> 645490.29 | C107: $/year
A108: R1: Impact per year, at scale, assume success, ignore counterfactuals | B108: =B96*B106 -> 16689.533 | C108: DEs/year
A109: R1: Cost effectiveness per year, at scale, assume success, ignore counterfactuals ($/Impact) | B109: =B107/B108 -> 38.676353 | C109: $/DE
A110: R1: Cost effectiveness per year, at scale, assume success, ignore counterfactuals (Impact/$1000) | B110: =1000*(1/B109) -> 25.855592 | C110: DEs/$1000
A112: % of costs that are fixed | B112: =B13/B107 -> 0.43377879
A114: Tractability & counterfactuals
A115: Probability of success etc
A116: Probability of success [suggest: 90% for direct, 25% for policy] | B116: 0.2 | C116: % | D116: Best guess. For comparison, LEEP currently assumes very high chance of success per country (~80%+, from memory) but we think that this work is much less tractable. For lead research, we assumed 10%, since less of that overall ToC is under the charity's control.
A117: Last year charity runs if unsuccessful [suggest: 4] | B117: 4 | C117: years | D117: Seems reasonable, as timelines for progress might be quite long
A118: If charity fails, what % of variable costs are spent [Suggest: 40%] | B118: 0.4 | C118: %
A120: Counterfactuals
A121: Probability change happens anyway, per year [suggest: 0% for direct, suggest 1%-7% for policy] | B121: 0.04 | C121: % discounted | D121: One would expect, now that there is the LEAF funding, that change might happen anyway. Via their awareness raising or via UN/UNEP/OP there would be a policy level change.
A122: In case useful: Number yrs until 50%+ change happens anyway | B122: =IFERROR(LOG(0.5,(1-B121)),"never") -> 16.979748 | C122: years
...

Sheet  Top Down - GBD
A1: I think this approach is the best/most correct, and could do with improvements. Results are surprisingly simliar as the LeRA type top down approach
C2: Bangladesh | D2: Argentina | E2: Thailand | F2: Units | G2: Description | H2: Source | I2: Review
A3: Total DALY burden Lead exposure in 2021 in country | C3: 927511 | D3: 78594 | E3: 131213 | F3: DALY | H3: https://ourworldindata.org/grapher/disease-burden-lead?tab=table
A4: Average increase/decrease, last 10 years ( 2011 - 2021) | C4: 0.21 | D4: =-6% -> -0.06 | E4: 0.14 | F4: % | G4: Based on trajectory since 1990 | H4: https://ourworldindata.org/grapher/disease-burden-lead?tab=table
A5: Increase of total DALY burden per year | C5: =(1+C4)^(1/41)-1 -> 0.0046601017 | D5: =(1+D4)^(1/41)-1 -> -0.001508018 | E5: =(1+E4)^(1/41)-1 -> 0.0032009233 | F5: %
A6: Total DALY burden Lead exposure GBD in 2024 | C6: =C3*(1+C5)^3 -> 940538.41 | D6: =D3*(1+D5)^3 -> 78238.972 | E6: =E3*(1+E5)^3 -> 132477.05 | F6: DALY
A7: Percentage attributable to informal ULAB recycling
B8: Directly due to informal ULAB recycling | C8: 0.35 | D8: 0.15 | E8: 0.15 | G8: Judgement, based on tab on 'overall GBD ULAB recycling' and upcoming paper from Forsyth I heard about which states that ULAB is 50% of lead poisoning in Dhaka, Bangladesh. Bret Ericson thinks it is somewhere around 10%, Hugo said that he stated 20% in the past. Note that it differs from place to place, but is hard to get over 50% with just paint, cookware and cosmetics. Potentially, ULAB recycling is cause more than 20%
B9: Due to Cookware | C9: 0.15 | D9: 0.15 | E9: 0.15 | G9: Intuition --> LeRA: help us out here!
B10: Counterfactual effect of fewer informal ULAB recycling on the burden due to Cookware | C10: 0.2 | D10: 0.2 | E10: 0.2 | G10: Intuition, Bret Ericson told me that in Mexico, both formal and informal recyclers sell lead (dust) to artisinal cookware makers.
B11: Additional contamination via grown crops near ULAB recycling plants/informal recyclers
A12: Percentage attributable to informal ULAB recycling | C12: =C8+C9*C10 -> 0.38 | D12: =D8+D9*D10 -> 0.18 | E12: =E8+E9*E10 -> 0.18
A13: Total DALY burden Lead exposure due to ULAB recycling in 2024 | C13: =C6*C12 -> 357404.59 | D13: =D6*D12 -> 14083.015 | E13: =E6*E12 -> 23845.868 | F13: DALY
A15: Decrease of total ULAB burden of a country when policies are improved substantially
A16: Model after Brazil
B17: Burden due to informal recycling in Brazil before improved regulation | C17: 0.8 | H17: Intutition
B18: Size of informal sector in Brazil before improved regulation | C18: 0.5 | H18: Carlos mentioned 45% , other sources claim 'the majority', so i went for 50%. Also, the blogpost mention some rough numbers, but that must have come from Carlos as well- https://leadbatteries.substack.com/p/how-brazil-solved-its-lead-acid-battery
B19: Size of informal sector in Brazil before after regulation | C19: 0.1 | H19: IBER has 75% of market in 2022, could expect this to have increased
B20: Decrease of size of informal recycling due to regulations | C20: =1-C19/C18 -> 0.8 | H20: Should check what happened in Brazil, I think it was about this size. Additionally: Mark stevenson made a judgementcall, that this would happen if taxes are cut in India on this.. Hugo: This number should be at least 50%. Best info he got on this was a quote: "most was informal before", Now 75% of the battery recycling is going via IBER. Also, Pure Earth states about 80% https://www.google.com/url?q=https://e360.yale.edu/features/getting-the-lead-out-why-battery-recycling-is-a-global-health-hazard%23:~:text%3DFuller%2520at%2520Pure%2520Earth%2520says,%252C%25E2%2580%259D%2520mainly%2520through%2520economic%2520incentives&sa=D&source=editors&ust=1733491202096199&usg=AOvVaw0aomdHgPlN28-Xc1QU9qWz
B21: Undiscounted decrease of total ULAB burden due to regulations | C21: =C17*C20 -> 0.64
A22: Discounts
B23: Improvement not being as large/effective in other countries (potentially as the problem at the start wasnt as big, i.e. the informal sector was smaller to start with) | C23: 0.15 | G23: Just intution, I consider this quite a big discount (thus being conservative)
B24: Decrease of informal leads to an increase in formal (which is better, but still not great) | C24: 0.05 | G24: Because informal is in populated area's and in so many more places
B25: When informal recyclers are gone: site is still contaminated indefenitely (untill cleaned) | C25: 0.4 | G25: Impact comes from Informal recyclers not relocating and no new informal recyclers starting. Carlos explained that as part of the Brazil legislation, one needs to clean up the plot before it can be used. Therefore, this is much a smaller problem. Updated the discount from 70% to 40%, as i expect this legislation not to be watertight, and potentially now viable to introduce in other countries.
B26: Growth of the ULAB market in the upcoming years | C26: =-average(1.04^7,1)+1 -> -0.15796589 | G26: Take 4% growth. This is quick and dirty, should put this in a proper model
A27: Decrease of total ULAB burden of a country when policies are improved substantially | C27: =C21*(1-C23)*(1-C24)*(1-C25)*(1-C26) -> 0.35906206
A29: Decrease of DALY burden when policies are implemented | C29: =C13*$C$27 -> 128330.43 | D29: =D13*$C$27 -> 5056.6764 | E29: =E13*$C$27 -> 8562.1466 | F29: DALY
A31: Probability of succes (improved policies are adopted) | C31: 0.05 | D31: 0.4 | E31: 0.35 | G31: Intuition
A32: Discount for enforcement not being as good as in Brazil | C32: 0.99 | D32: 0.1 | E32: 0.2 | G32: Intuition
A33: Expected decrease of DALY burden with advocacy initiative | C33: =C29*C31*(1-C32) -> 64.165216 | D33: =D29*D31*(1-D32) -> 1820.4035 | E33: =E29*E31*(1-E32) -> 2397.4011 | F33: DALY
A35: Years of counterfactual impact | C35: 7 | D35: =C35 -> 7 | E35: =D35 -> 7 | F35: Years | G35: Intuition, also given LEAF things might move a bit quicker
A36: Discount for time discounting | C36: 0.85 | D36: 0.85 | E36: 0.85 | F36: % | G36: Quick number to finish the calculation
A37: Total NPV Daly averted | C37: =C33*C35*C36 -> 381.78303 | D37: =D33*D35*D36 -> 10831.401 | E37: =E33*E35*E36 -> 14264.536 | F37: DALY
A39: Cost for the charity at scale | C39: ='Main CEA - Top down GBD'!B14 -> #REF! | D39: =C39 -> #REF! | E39: =D39 -> #REF! | F39: $
A40: Years needed for advocacy work | C40: 3 | D40: =C40 -> 3 | E40: =D40 -> 3 | F40: Amount | G40: Intuition, this might be optimistic?
A41: Total costs | C41: =C39*C40 -> #REF! | D41: =D39*D40 -> #REF! | E41: =E39*E40 -> #REF! | F41: $
A43: Cost-effectiveness (Dollar per daly) | C43: =C41/C37 -> #REF! | D43: =D41/D37 -> #REF! | E43: =E41/E37 -> #REF! | F43: $/Daly
A46: Remarks
B47: Consider looking at the CEA of Pure Earth by Givewell: https://docs.google.com/spreadsheets/d/1x0BchpoMphvAqSe71hJqM2gBByeRIf2oaz3WGVrVdow/edit?gid=109713399#gid=109713399

Sheet Top Down - BLL
A1: This CEA is moddeled after LeRA, which is a Blood lead level top down approach. Especially sensitive to the estimate of line 8
C2: Bangladesh | D2: Argentina | E2: Thailand | F2: Units | G2: Description | H2: Source
A3: BLL in Country | C3: 7.87 | D3: =AVERAGE(D4:D6) -> 2.96 | E3: 5.12 | F3: µg/dL | G3: This is 2019, just assume nothing changed, which is conservative probably. Note that Brazil was only 2.19 at the time | H3: https://ourworldindata.org/grapher/lead-concentrations-blood-children?tab=table
B4: Colombia | D4: 3.06
B5: Brazil | D5: 2.65
B6: Equador | D6: 3.17
A8: Reduction in BLL thanks to policies introduced | C8: 0.05 | F8: % change | G8: A guess. LeRA CEA had a higher number, (12.5%) but I consider that optimistic. Moddeled this loosely after the brazil model ( 20% due to ULAB, able to make that 25% better; which is a bit more optimistic than the brazil model sheet actually...)
A9: Intermediate effect size - reduction in BLL | C9: =C3*$C$8 -> 0.3935 | D9: =D3*$C$8 -> 0.148 | E9: =E3*$C$8 -> 0.256 | F9: μg/dL
A10: Internal validity effect [Suggest range 0% to -80%, e.g. -40%] | C10: 0 | F10: % change | G10: Not used (this is relevant when effect size is taken from a study)
A11: External validity effect [Suggest range +40% to -80%, e.g. -10%] | C11: 0 | F11: % change | G11: Not used
A12: Discounted effect size - reduction in BLL | C12: =C9*(1+$C$10)*(1+$C$11) -> 0.3935 | D12: =D9*(1+$C$10)*(1+$C$11) -> 0.148 | E12: =E9*(1+$C$10)*(1+$C$11) -> 0.256 | F12: μg/dL
A13: Estimated IQ point loss per 1 μg/dl increase in blood levels throughout childhood | C13: 0.15 | F13: IQ points per μg/dL | G13: Following GiveWell | H13: https://docs.google.com/document/d/1NH99fuXpXcCcz-vjaP1x3ZOVDNYd4gflWWb2B5y3TcQ/edit#heading=h.cqwbetxdrmad | I13: Thijs: LEEP uses a higher number, and also I don't see the used number straight away in the Give well linked doc
A14: IQ points gained per person | C14: =C12*$C$13 -> 0.059025 | D14: =D12*$C$13 -> 0.0222 | E14: =E12*$C$13 -> 0.0384 | F14: IQ points
A15: % increase in income (/consumption) for every 1 point increase in IQ | C15: 0.0067 | F15: % change | G15: From GiveWell | H15: https://docs.google.com/spreadsheets/d/15h60n8jDSQMFpmA_y4ilYOUE0mP-C9SRosEMHuWDnug/edit#gid=154585324
A16: % increase in income per person (in each year of working life) | C16: =C14*$C$15 -> 0.0003954675 | D16: =D14*$C$15 -> 0.00014874 | E16: =E14*$C$15 -> 0.00025728 | F16: % change
A17: Multiplier for resource sharing | C17: 2 | F17: coefficient | G17: Following GiveWell's reasoning: Each working adult's income benefits multiple people; on average ~2
A18: Conversion to consumption doublings | C18: =log(1+C16,2)*$C$17 -> 0.0011408524 | D18: =log(1+D16,2)*$C$17 -> 0.00042914101 | E18: =log(1+E16,2)*$C$17 -> 0.00074225768 | F18: ratio | G18: Assuming all extra income is consumed
A19: One year of doubled consumption to DALYs [fixed] | C19: =1/2.3 -> 0.43478261 | F19: ratio | G19: From GiveWell
A20: DALY equivlents per person per year of their working life | C20: =$C$19*C18 -> 0.0004960228 | D20: =$C$19*D18 -> 0.00018658305 | E20: =$C$19*E18 -> 0.00032272073 | F20: DEs/person/year
A21: Number of years of working life | C21: =65-20 -> 45 | F21: years | G21: Length of working life
A22: Discount rate for consumption impacts | C22: 0.04
A23: Total DALY-equivalent benefit over working life | C23: =-PV($C$22,$C$21,C20) -> 0.010277612 | D23: =-PV($C$22,$C$21,D20) -> 0.0038660081 | E23: =-PV($C$22,$C$21,E20) -> 0.0066867864 | F23: DEs/person
A24: Delay in benefits | C24: 15 | F24: years | G24: Age when people start working
A25: Present value of consumption benefit | C25: =C23*(1-$C$22)^$C$24 -> 0.0055713535 | D25: =D23*(1-$C$22)^$C$24 -> 0.0020957104 | E25: =E23*(1-$C$22)^$C$24 -> 0.0036248158 | F25: DEs/person
A26: Health benefit as a % of consumption benefit | C26: =16/84 -> 0.19047619 | F26: % | G26: For simplicity, I'm following LEEP, who estimate that health benefits make up 16% of the total. | H26: https://leadelimination.org/how-cost-effective-are-leeps-paint-programs/
A27: Present value of health benefit | C27: =$C$26*C25 -> 0.0010612102 | D27: =$C$26*D25 -> 0.00039918292 | E27: =$C$26*E25 -> 0.00069044111 | F27: DALYs/person
A28: Total net impact per person per year | C28: =C27+C25 -> 0.0066325637 | D28: =D27+D25 -> 0.0024948933 | E28: =E27+E25 -> 0.0043152569 | F28: DEs/person
A29: Births per country per year | C29: 3489953 | D29: 503823 | E29: 591200 | F29: Births, in 2023
A30: Total net impact per country per year | C30: =C28*C29 -> 23147.336 | D30: =D28*D29 -> 1256.9846 | E30: =E28*E29 -> 2551.1799 | F30: DEs/country
A32: Probability of succes (improved policies are adopted) | C32: 0.05 | D32: 0.4 | E32: 0.35 | G32: Intuition
A33: Expected net impact per country per year | C33: =C30*C32 -> 1157.3668 | D33: =D30*D32 -> 502.79385 | E33: =E30*E32 -> 892.91296 | F33: DEs/country
A35: Years of counterfactual impact | C35: 7 | D35: =C35 -> 7 | E35: =D35 -> 7 | F35: Years | G35: Intuition, also given LEAF things might move a bit quicker
A36: Discount for time discounting | C36: 0.85 | D36: 0.85 | E36: 0.85 | F36: % | G36: Quick number to finish the calculation
A37: Total NPV Daly averted | C37: =C33*C35*C36 -> 6886.3323 | D37: =D33*D35*D36 -> 2991.6234 | E37: =E33*E35*E36 -> 5312.8321 | F37: DEs
A39: Cost for the charity at scale | C39: ='Main CEA - Top down GBD'!B14 -> #REF! | D39: =C39 -> #REF! | E39: =D39 -> #REF! | F39: $
A40: Years needed for advocacy work | C40: 3 | D40: =C40 -> 3 | E40: =D40 -> 3 | F40: Amount | G40: Intuition, this might be optimistic?
A41: Total costs | C41: =C39*C40 -> #REF! | D41: =D39*D40 -> #REF! | E41: =E39*E40 -> #REF! | F41: $
A43: Cost-effectiveness (Dollar per daly) | C43: =C41/C37 -> #REF! | D43: =D41/D37 -> #REF! | E43: =E41/E37 -> #REF! | F43: $/Daly-equivalent

Sheet Overall GBD ULAB recycling
D2: Lower estimate (10%) | E2: Best-guess (50%) | F2: High estimate(90%) | G2: Units | H2: Description | I2: Source
A3: Informal recycling | B3: Estimate DALY burden in 2013 by researchers of *Informal recycling* (90 countries) | D3: 0.127248 | E3: =AVERAGE(D3,F3) -> 0.869862 | F3: 1.612476 | G3: Million DALY | H3: Based on paper, best guess is average | I3: https://annalsofglobalhealth.org/articles/231/files/submission/proof/231-1-536-1-10-20180511.pdf
B4: Correct for being conservative
C5: Correction for predictions of increase in BLL are lower than actual BLL found in studies | D5: 0.05 | E5: 0.15 | F5: 0.25 | G5: % | H5: "We further stated that these predictions are much lower than actual the BLLs found by researchers at sites in the field53-57 and that our predictions are very likely underestimates."
C6: Correction detailed vs. limited assesment page 6 | D6: 0.1 | E6: 0.25 | F6: 0.5 | G6: % | H6: Unclear how much a increase in soil translate to the overall increase in a burden
B7: Improved estimate DALY burden 2013 | D7: =D3*(1+D5)*(1+D6) -> 0.14697144 | E7: =E3*(1+E5)*(1+E6) -> 1.2504266 | F7: =F3*(1+F5)*(1+F6) -> 3.0233925 | G7: Million DALY
B8: Growth of market per year | D8: 0.03 | E8: 0.04 | F8: 0.05 | G8: % | H8: Quick numbers, based on what I think I have read in places. Should be easy to source from the internet
B9: Number of years since 2013 | D9: =2024-2013 -> 11 | E9: =D9 -> 11 | F9: =E9 -> 11 | G9: Years
B10: Undiscounted estimate of Daly Burden 2024 | D10: =D7*(1+D8)^D9 -> 0.20344285 | E10: =E7*(1+E8)^E9 -> 1.9249743 | F10: =F7*(1+F8)^F9 -> 5.1710272 | G10: Million DALY
B11: Discount for less recycling being done by informal recyclers | D11: 0.4 | E11: 0.2 | F11: 0.1 | G11: % | H11: Andreas mentioned it is limited in Africa but still seems rampant in Asia. So expect share to be similar in Asia, and less so in Africa. I expect the market in Asia to be bigger
B12: Updated estimate of DALY burden 2024 | D12: =D10*(1-D11) -> 0.12206571 | E12: =E10*(1-E11) -> 1.5399795 | F12: =F10*(1-F11) -> 4.6539245 | G12: Million DALY
B14: Total DALY burden lead exposure GBD in 2021 | D14: 33.89055 | E14: 33.89055 | F14: 33.89055 | G14: Million DALY | I14: https://ourworldindata.org/grapher/disease-burden-lead?tab=table
B15: Increase of total DALY burden per year | D15: =(1+0.55)^(1/41)-1 -> 0.010746478 | E15: =D15 -> 0.010746478 | F15: =E15 -> 0.010746478 | G15: % | H15: Based on trajectory since 1990 | I15: https://ourworldindata.org/grapher/disease-burden-lead?tab=table
B16: Total DALY burden lead exposure GBD in 2024 | D16: =D14*(1+D15)^3 -> 34.994946 | E16: =E14*(1+E15)^3 -> 34.994946 | F16: =F14*(1+F15)^3 -> 34.994946 | G16: Million DALY
B17: Discount for the fact that the paper only looks at 90 contries, rather than all 238 countries | D17: 0.2 | E17: 0.2 | F17: 0.2 | H17: This is a guess. The paper looked at 90 LMIC countries. So DALY burden outside of that should be limited, but does leave out HICS, which might altogether have some part of the burden. They did leave out the balkans and countries in conflict (e.g. Syria)
B18: Total DALY burden Lead exposure GBD in 2024 for the 90 countries | D18: =D16*(1-D17) -> 27.995957 | E18: =E16*(1-E17) -> 27.995957 | F18: =F16*(1-F17) -> 27.995957
B19: Percentage attributable to informal ULAB recycling | D19: =D12/D18 -> 0.0043601192 | E19: =E12/E18 -> 0.05500721 | F19: =F12/F18 -> 0.16623559
A21: Formal recycling | B21: Amount of informal recycler for every formal recycler
C22: Total number of informal recyclers in all 90 countries in 2013 | D22: 30000 | E22: =AVERAGE(D22,F22) -> 20000 | F22: 10000 | G22: Amount | H22: Based on paper, best guess is average | I22: https://annalsofglobalhealth.org/articles/231/files/submission/proof/231-1-536-1-10-20180511.pdf
C23: Total number of informal recyclers in all 90 countries in 2024 | D23: =D22*(1+D8)^D9 -> 41527.016 | E23: =E22*(1+E8)^E9 -> 30789.081 | F23: =F22*(1+F8)^F9 -> 17103.394 | G23: Amount
C24: Estimate of average amount of formal recyclers per country | D24: 2 | E24: 5 | F24: 10 | G24: Amount | H24: Intuition, might be much higher if you also incorporate the informal but large recyclers (unclear if paper includes these)
C25: Total amount of formal recyclers | D25: =D24*90 -> 180 | E25: =E24*90 -> 450 | F25: =F24*90 -> 900 | G25: Amount
C26: Amount of informal recycler for every formal recycler | D26: =D23/D25 -> 230.70565 | E26: =E23/E25 -> 68.42018 | F26: =F23/F25 -> 19.003771 | G26: Amount
B27: Undiscounted additional DALY due to formal recycling | D27: =D12/D26 -> 0.00052909718 | E27: =E12/E26 -> 0.022507679 | F27: =F12/F26 -> 0.24489479 | G27: Million DALY
B28: More contamination per formal site, because troughput is higher | D28: 1.5 | E28: 3 | F28: 5 | G28: Factor | H28: Intution
B29: Discount for formal sites being less so in populated areas | D29: 0.8 | E29: 0.6 | F29: 0.3 | G29: %
B30: Discounted additional DALY due to formal recycling | D30: =D27*D28*(1-D29) -> 0.00015872916 | E30: =E27*E28*(1-E29) -> 0.027009215 | F30: =F27*F28*(1-F29) -> 0.85713177 | G30: Million DALY
B31: Sanity check - formal recyclers account for x% of total burden of ULAB recycling | D31: =D30/D33 -> 0.0012986696 | E31: =E30/E33 -> 0.017236382 | F31: =F30/F33 -> 0.15552949 | G31: %
A33: Total burden of ULAB recycling in 2024 in the 90 countries | D33: =D30+D12 -> 0.12222444 | E33: =E30+E12 -> 1.5669887 | F33: =F30+F12 -> 5.5110562 | G33: Million DALY
A34: Total burden of lead exposure in 2024 in the 90 countries | D34: =D18 -> 27.995957 | E34: =E18 -> 27.995957 | F34: =F18 -> 27.995957 | G34: Million DALY | H34: IHME
A35: Percentage of Lead exposure burden attributable to ULAB recycling | D35: =D33/D34 -> 0.0043657889 | E35: =E33/E34 -> 0.055971964 | F35: =F33/F34 -> 0.19685186 | G35: %

Sheet Bottom Up
C1: Bangladesh | D1: Argentina | E1: Thailand | F1: Units | G1: Description | H1: Source
A2: Total DALY burden in 90 countries | C2: ='Overall GBD ULAB recycling'!E3*10^6 -> 869862 | F2: DALY | H2: Paper by Bret Ericson: https://annalsofglobalhealth.org/articles/231/files/submission/proof/231-1-536-1-10-20180511.pdf
A3: Amount of Informal recyclers | C3: =Average(10599,29241) -> 19920 | F3: Amount of sites | H3: Paper by Bret Ericson: https://annalsofglobalhealth.org/articles/231/files/submission/proof/231-1-536-1-10-20180511.pdf
A4: Naive average DALY burden per informal site | C4: =C2/C3 -> 43.667771 | F4: DALY / site
A5: Discount for being densely populated compared to average | C5: -0.3 | D5: 0.1 | E5: 0 | F5: % | H5: Intution
A6: Daly burden per informal site | C6: =$C$4*(1-C5) -> 56.768102 | D6: =$C$4*(1-D5) -> 39.300994 | E6: =$C$4*(1-E5) -> 43.667771 | F6: DALY / site
A8: Overall population | C8: 171466986 | D8: 45538402 | E8: 71702438 | H8: https://ourworldindata.org/grapher/population?tab=table
A9: Size of ULAB market compared to Bangladesh [Very naive] | C9: =C8/$C$8 -> 1 | D9: =D8/$C$8 -> 0.26558117 | E9: =E8/$C$8 -> 0.41817052 | G9: This is naive, I think ULAB is comperatively big in Bangladesh, so wouldn't scale with population directly
A10: Amount of informal sites per country | C10: 1300 | D10: =C10*D9 -> 345.25552 | E10: =C10*E9 -> 543.62167 | F10: Informal recycling sites per country | H10: https://www.unep.org/topics/chemicals-and-pollution-action/pollution-and-health/heavy-metals/used-lead-acid-batteries claims there are over 1.100 sites in Bangladesh.
A11: Total DALY burden per country due to informal ULAB recycling | C11: =C10*C6 -> 73798.533 | D11: =D10*D6 -> 13568.885 | E11: =E10*E6 -> 23738.747
A14: From here onwards: Similar to the Top down approach!
A15: Decrease of total ULAB burden of a country when policies are improved substantially | C15: =' Top Down - GBD'!C27 -> 0.35906206
A17: Decrease of DALY burden when policies are implemented | C17: =$C$15*C11 -> 26498.254 | D17: =$C$15*D11 -> 4872.0718 | E17: =$C$15*E11 -> 8523.6834 | F17: DALY
A19: Probability of succes (improved policies are adopted) | C19: 0.05 | D19: 0.2 | E19: 0.1 | G19: Intuition
A20: Discount for enforcement not being as good as in Brazil | C20: 0.4 | D20: 0.2 | E20: 0.3 | G20: Intuition
A21: Expected decrease of DALY burden with advocacy initiative | C21: =C17*C19*(1-C20) -> 794.94761 | D21: =D17*D19*(1-D20) -> 779.53149 | E21: =E17*E19*(1-E20) -> 596.65783 | F21: DALY
A23: Years of counterfactual impact | C23: 7 | D23: =C23 -> 7 | E23: =D23 -> 7 | F23: Years | G23: Intuition, also given LEAF things might move a bit quicker
A24: Discount for time discounting | C24: 0.85 | D24: 0.85 | E24: 0.85 | F24: % | G24: Quick number to finish the calculation
A25: Total NPV Daly averted | C25: =C21*C23*C24 -> 4729.9383 | D25: =D21*D23*D24 -> 4638.2124 | E25: =E21*E23*E24 -> 3550.1141 | F25: DALY
A27: Cost for the charity at scale | C27: ='Main CEA - Top down GBD'!B14 -> #REF! | D27: =C27 -> #REF! | E27: =D27 -> #REF! | F27: $
A28: Years needed for advocacy work | C28: 3 | D28: =C28 -> 3 | E28: =D28 -> 3 | F28: Amount | G28: Intuition, this might be optimistic?
A29: Total costs | C29: =C27*C28 -> #REF! | D29: =D27*D28 -> #REF! | E29: =E27*E28 -> #REF! | F29: $
A31: Cost-effectiveness (Dollar per daly) | C31: =C29/C25 -> #REF! | D31: =D29/D25 -> #REF! | E31: =E29/E25 -> #REF! | F31: $/Daly

Sheet OLD 2023 CEA
A1: =IFERROR(IF(K4*L4*SUM(I3:I251)+COUNTA(I3:I251)=0,"Inputs",1/0),"YOU HAVE EDITED ROWS J K or L – PLEASE DO NOT DO THIS") -> Inputs | B1: Expected | C1: UseCarlo | D1: p05 | E1: p95 | F1: Param1 | G1: Param2 | H1: Param3 | I1: NO EDIT | J1: Units | K1: Distr. mean | L1: Distr. median | N1: Description | O1: Source | P1: Comments | Q1: Replies
A2: Description of intervention | I2: DO NOT EDIT COLUMN | K2: FORMULA DO NOT EDIT THIS COLUMN
A3: [Fill out description here]
A4: Geographic focus of this CEA | B4: [country / region] | K4: {=SWITCH(C4:C223, "Normal", (D4:D223+E4:E223)/2, "Lognormal", EXP((LN(D4:D223)+LN(E4:E223))/2 + ((LN(E4:E223)-(LN(D4:D223)+LN(E4:E223))/2)/1.645)^2/2), "Beta", F4:F223/(F4:F223+G4:G223), "", "", "output", "")} | L4: {=SWITCH(C4:C223, "Normal", (D4:D223+E4:E223)/2, "Lognormal", EXP((LN(D4:D223)+LN(E4:E223))/2), "Beta", "Not Implemented", "", "", "output", "")}
A7: Tractability & counterfactuals
A8: Probability of success etc
A9: Probability per year that change would happen anyway (even if no charity) | J9: %
A10: In case useful: Number yrs until 50%+ change happens anyway | B10: =IFERROR(LOG(0.5,(1-B9)),"never") -> never
A11: Probability of success (that the expected impact happens) [suggest: 90% for direct, 30% for policy] | B11: 0.9 | C11: Beta | D11: 0.85 | E11: 0.95 | J11: % | K11: #DIV/0! | L11: Not Implemented
A12: Last year charity runs if unsuccessful [suggest: 4] | B12: 4 | C12: Normal | D12: 1 | E12: 6 | J12: years | K12: 3.5 | L12: 3.5
A13: =" In case useful: Total prob. change happens in timeframe ("&B12&"yrs)" -> In case useful: Total prob. change happens in timeframe (4yrs) | B13: =1-(1-B11)*(1-B9)^B12 -> 0.9
A16: Costs
A17: Key assumptions
A18: Discount rate, for costs [keep fixed in all CEAs] | B18: 0.04 | J18: %
A20: 1. FIXED CHARITY COSTS
A21: Period 1 – initial scaling | N21: This section assumes a linear increase in fixed costs during the scaling period
A22: Cost period 1 begins in year __ [fixed] | B22: 1 | J22: Year
A23: Cost period 1 ends in year __ [suggest: 2-5; min: 2] | B23: 3 | C23: Normal | D23: 2 | E23: 4 | J23: Year | K23: 3 | L23: 3 | N23: Period inclusive of this year
A24: Costs at period 1 start [fixed, based on CE grant sizes] | B24: 130000 | C24: LogNormal | D24: 100000 | E24: 170000 | J24: $ | K24: 132090.96 | L24: 130384.05 | N24: Estimate (from Joey) for 90% confidence interval for CE seed grant is $100k to $190k | O24: -
A25: Costs at period 1 end [default: $250,000] | B25: 250000 | C25: LogNormal | D25: 150000 | E25: 400000 | J25: $ | K25: 256079.77 | L25: 244948.97
A26: Total fixed costs over period 1, NPV | B26: =B30*(1-B$18)^(B22-1) -> 542800 | J26: $
A27: Increase per year | B27: =(B25-B24)/(B23-B22) -> 60000 | J27: $
A28: Total length of period | B28: =B23-B22+1 -> 3 | J28: years
A29: Cumulative discount multiplier over period | B29: =(1-B$18)^B28 -> 0.884736 | J29: %
A30: Total fixed costs of period at starting year of period | B30: =((B24*((1-B29)) + B27*((1-B29)/(B$18)-1-(B28-1)*B29)) /(B$18)) -> 542800 | J30: $ | N30: Formula based on SUM (a+kb)r^k, where k is variable 0→year (C10) and a is base cost (C19) and b is annual addition (C14) and r is the discount rate (C5)
A31: Total fixed costs over period, NPV (single line formula version) | B31: =((B24*((1-(1-B$18)^(B23-B22+1))) + ((B25-B24)/(B23-B22))*((1-(1-B$18)^(B23-B22+1))/(B$18)-1-((B23-B22+1)-1)*(1-B$18)^(B23-B22+1))) /(B$18)) *(1-B$64)^(B22-1) -> 542800 | J31: $
A32: Total fixed costs over period 1, NPV, if not successful | B32: =IF(B$12<B22,0, IF(B$12>B23,B26, ((B24*((1-(1-B$18)^(B$12-B22+1))) + B27*((1-(1-B$18)^(B$12-B22+1))/(B$18)-1-((B$12-B22+1)-1)*(1-B$18)^(B$12-B22+1))) /(B$18)) *(1-B$18)^(B22-1) )) -> 542800 | J32: $
A33: Period 2 – ongoing costs | B33: ← Can copy and paste these rows (or section above) to add additional costing periods below
A34: Cost period 2 begins in year ___ [previous period end +1] | B34: =B23+1 -> 4 | J34: Year
A35: Cost period 2 ends on year ___ OR "ongoing" [suggest: 16] | B35: 16 | C35: LogNormal | D35: 5 | E35: 35 | J35: Year | K35: 15.757346 | L35: 13.228757
A36: Annual fixed costs in this period | B36: =B25 -> 250000 | J36: $ | O36: -
A37: Total fixed costs over period 2, NPV | B37: =(IF(B35="ongoing", B36/B$18, B36*((1-(1-B$18)^B35))/(B$18)) - B36*((1-(1-B$18)^(B34-1)))/(B$18)) *(1-B$18)^(B34-1) -> 2014616.2 | J37: $
A38: Total fixed costs over period 2, NPV, if not successful | B38: =IF(B$12<B34,0,IF(B$12>B35,B37, B36*((1-(1-B$18)^B$12))/(B$18) - B36*((1-(1-B$18)^(B34-1)))/(B$18) )) *(1-B$18)^(B34-1) -> 195689.45 | J38: $
A41: 2. VARIABLE CHARITY COSTS
A42: [Subheading]
A43: Cost of intervention per person | J43: $/person
A44: Variable costs per [group] (for staff/training/set-up/etc) | J44: $
A45: Number of people reached [by/in] in each [group/etc] | J45: person
A46: Total cost per person | B46: =B43+IF(B45="",0,B44/B45) -> 0 | J46: $/person
A47: Number of people reached, NPV | B47: =B126 -> #DIV/0! | J47: people
A48: Total variable costs, NPV | B48: =B47*B46 -> #DIV/0! | J48: $
A49: Total variable costs, NPV, if not successful [Suggest: $0] | B49: 0 | J49: $
A51: 2. TOTAL CHARITY COSTS
A52: Total costs if successful | B52: =B48+B37+B26 -> #DIV/0! | J52: $
A53: Total costs if not successful | B53: =B49+B38+B32 -> 738489.45 | J53: $
A54: Total expected cost per successful charity | B54: =B52+((1-B11)/B11)*B53 -> #DIV/0! | J54: $
A56: 3. NON-CHARITY COSTS
A57: Costs to government | B57: 0 | J57: $/year
A58: Costs to other charities | B58: 0 | J58: $/year
A61: Effects per [person]
A62: Key assumptions / data
A63: One year of doubled consumption to DALYs [fixed] | B63: =1/2.3 -> 0.43478261 | J63: ratio
A64: Discount rate, for impacts per person [fixed] | B64: 0.04 | J64: %
A66: [Effect 1]
A67: [Subheading]
A68: [informed input] | J68: count
A69: [guess input] | J69: % reduction
A70: [Effect size] | J70: e.g. DALYs
A71: Internal validity effect [Suggest range 0% to -80%, e.g. -40%] | J71: % change
A72: External validity effect [Suggest range +40% to -80%, e.g. -10%] | J72: % change
A73: [Discounted effect size] | B73: =B70*(1+B71)*(1+B72) -> 0 | J73: e.g. DALYs
A74: [calculation] | J74: count/year
A75: [Subheading]
A76: [informed input] | J76: count
A77: [guess input] | J77: % reduction
A78: [calculation] | J78: count/year
A79: Timing of effect
A80: Impact per person per year
A81: Number of years that impact spread over [Suggest: 1-40; Min: 1] | B81: 1
A82: Delay on impact starting from intervention date [Suggest: 0] | B82: 0
A83: Value of impact in year of intervention (discounted), per person | B83: =IF(B81="ongoing", B80/B$64, B80*((1-(1-B$64)^B81))/(B$64)) *(1-B$64)^(B82) -> 0
A85: [Effect 2]
A86: Value of impact in year of intervention (discounted), per person
A88: Costs/Disbenefits to beneficiaries | B88: ← If no or only negligible put as "0" and justify reasoning. Suggest for most CEAs do one or other. (Note if costs/disbenefits delayed can use "timing of effect" calculations above)
A89: Health disbenefits per beneficiary per year | J89: [DALY]/person/year
A90: Cost per beneficiary per year [Optional, delete if a DALY/$ CEA] | J90: $/person/year
A92: Total impact per person per year, in year of intervention (discounted) | B92: ← suggest for most CEAs do one or the other
A93: Total net [health/consumption] impact per person per year | B93: =B89+B86+B83 -> 0 | J93: [DALY]/person/year
A96: Effects, reach of intervention
A97: Key assumptions / data
A98: Population growth rate [if relevant, e.g. +5% if intervention drives national policy change that affects the whole country and the country has a 5% population growth] | J98: %
A99: DALY rate change over time [if relevant, e.g. -2.5% if infant mortality is decreasing by 2.5% per year] | J99: %
A100: Effective discount rate, for reach of costs over time | B100: =B18-(B98+B99) -> 0.04
A101: Effective discount rate, for reach of impacts over time | B101: =B64+B9-(B98+B99) -> 0.04
A103: Number of people can reach a year
A104: [Subheading]
A105: [informed input] | J105: count
A106: [guess input] | J106: % reduction
A107: [calculation] | J107: count/year
A109: Impact timing and calculations
A110: Period 1 – initial scaling
A111: Impact period 1 begins in year __ [suggest: 0, suggest range 0-2] | B111: 0 | J111: Year
A112: Impact period 1 ends (reaches end costs) in year __ [suggest: 2-8] | J112: Year
A113: Number of people reached in first year of period 1 [suggest: 0] | B113: 0 | J113: People
A114: Number of people reached per year when at scale | J114: People
A115: Increase per year | B115: =(B114-B113)/(B112-B111) -> #DIV/0!
A116: Total people reached over period 1, NPV, for costs | B116: =((B113*((1-(1-B$100)^(B112-B111+1))) + B115*((1-(1-B$100)^(B112-B111+1))/(B$100)-1-((B112-B111+1)-1)*(1-B$100)^(B112-B111+1))) /(B$100)) *(1-B$100)^(B111-1) -> #DIV/0!
A117: Total people reached over period 1, NPV, for impacts | B117: =((B113*((1-(1-B$101)^(B112-B111+1))) + B115*((1-(1-B$101)^(B112-B111+1))/(B$101)-1-((B112-B111+1)-1)*(1-B$101)^(B112-B111+1))) /(B$101)) *(1-B$101)^(B111-1) -> #DIV/0!
A118: Period 2 – running at scale
A119: Impact period 2 begins on year ___ [previous period end +1] | B119: =B112+1 -> 1 | J119: Year
...

Sheet Median salaries
A1: 0. DUPLICATE TEMPLATE BEFORE USE | B1: CALCAULTIONS | F1: ↓ NOTE: If you want more columns, you have to: add a column to the right of column F and copy column F equations to the new column. Do the same for column I. Repeat to as many columns as you want | G1: ↓ 3. ADD DATA HEADINGS | I1: ↓ NOTE: If you want more columns, you have to: add a column to the right of column F and copy column F equations to the new column. Do the same for column I. Repeat to as many columns as you want | K1: 2. FILL OUT THESE | L1: =IF(COUNTIF(L3:L1001,"ERROR – NOT LISTED. Add alt spelling to ''Countries'' tab")>1,"CHECK SPELLINGS","") | M1: 1. COPY DATA HERE ↓ make sure data headings are in the top row and country names in the first column | W1: ↓ Can do calcaultions on data here if you need to ↓
A2: CE Country list | B2: Region | C2: Country MATCH position | D2: =G2 -> Median salary of working people | E2: =H2 | F2: =I2 | G2: Median salary of working people | L2: Headings: | M2: Country | N2: Median income or consumption (2017 $) | O2: Annual income (2024 $) | P2: % working age | Q2: Unemployment | R2: Median salary of working people
A3: =Countries!B2 -> Afghanistan | B3: =Countries!I2 -> South Asia | C3: =IFERROR(IFERROR(IFERROR(IFERROR(IFERROR(IFERROR(IFERROR(MATCH(Countries!$B2,$M$3:$M$1003,0),MATCH(Countries!$C2,$M$3:$M$1003,0)),MATCH(Countries!$D2,$M$3:$M$1003,0)),MATCH(Countries!$E2,$M$3:$M$1003,0)),MATCH(Countries!$F2,$M$3:$M$1003,0)),MATCH(Countries!$G2,$M$3:$M$1003,0)),MATCH(Countries!$H2,$M$3:$M$1003,0)),"X") -> 1 | D3: =IF(G$2="","",IF($C3="X","",INDEX($N$3:$CC$1003,$C3,MATCH(G$2,$N$2:$CC$2,0)))) -> 7827.0018 | E3: =IF(H$2="","",IF($C3="X","",INDEX($N$3:$CC$1003,$C3,MATCH(H$2,$N$2:$CC$2,0)))) | F3: =IF(I$2="","",IF($C3="X","",INDEX($N$3:$CC$1003,$C3,MATCH(I$2,$N$2:$CC$2,0)))) | G3: =IF(A3="","",IF(G$2="","", IF(D3="",IF($K$16="Use global average",D$276,IF($K$16="Use regional average",INDEX(D$280:D$296,MATCH($B3,$B$280:$B$296,0)),IF($K$16="Leave blank","",IF($K$16="Fill with zeros", 0,IF($K$16="Use global median",D$277,"Fill out I16"))))), D3))) -> 7827.0018 | H3: =IF(H$2="","", IF(E3="",IF($K$16="Use global average",E$276,IF($K$16="Use regional average",INDEX(E$280:E$296,MATCH($B3,$B$280:$B$296,0)),IF($K$16="Leave blank","",IF($K$16="Fill with zeros", 0,IF($K$16="Use global median",E$277,"Fill out I16"))))), E3)) | I3: =IF(I$2="","", IF(F3="",IF($K$16="Use global average",F$276,IF($K$16="Use regional average",INDEX(F$280:F$296,MATCH($B3,$B$280:$B$296,0)),IF($K$16="Leave blank","",IF($K$16="Fill with zeros", 0,IF($K$16="Use global median",F$277,"Fill out I16"))))), F3)) | J3: ← 4. COPY – Use a forumula to inport data OR copy and paste data into: "Data summary" tab | L3: =IF(M3="","",IF(COUNTIF(Countries!$B$1:$H$271,M3)>0,"",IF(COUNTIF(Countries!$M$1:$S$271,M3)>0,"Not a country","ERROR – NOT LISTED. Add alt spelling to ''Countries'' tab"))) | M3: Afghanistan | N3: NA | O3: =N4*365*1.28 -> 5636.6311 | P3: 0.8383609 | Q3: 0.141 | R3: =IFERROR(O3/(P3*(1-Q3)),"") -> 7827.0018
A4: =Countries!B3 -> Albania | B4: =Countries!I3 -> Europe | C4: =IFERROR(IFERROR(IFERROR(IFERROR(IFERROR(IFERROR(IFERROR(MATCH(Countries!$B3,$M$3:$M$1003,0),MATCH(Countries!$C3,$M$3:$M$1003,0)),MATCH(Countries!$D3,$M$3:$M$1003,0)),MATCH(Countries!$E3,$M$3:$M$1003,0)),MATCH(Countries!$F3,$M$3:$M$1003,0)),MATCH(Countries!$G3,$M$3:$M$1003,0)),MATCH(Countries!$H3,$M$3:$M$1003,0)),"X") -> 2 | D4: =IF(G$2="","",IF($C4="X","",INDEX($N$3:$CC$1003,$C4,MATCH(G$2,$N$2:$CC$2,0)))) -> 0 | E4: =IF(H$2="","",IF($C4="X","",INDEX($N$3:$CC$1003,$C4,MATCH(H$2,$N$2:$CC$2,0)))) | F4: =IF(I$2="","",IF($C4="X","",INDEX($N$3:$CC$1003,$C4,MATCH(I$2,$N$2:$CC$2,0)))) | G4: =IF(A4="","",IF(G$2="","", IF(D4="",IF($K$16="Use global average",D$276,IF($K$16="Use regional average",INDEX(D$280:D$296,MATCH($B4,$B$280:$B$296,0)),IF($K$16="Leave blank","",IF($K$16="Fill with zeros", 0,IF($K$16="Use global median",D$277,"Fill out I16"))))), D4))) -> 0 | H4: =IF(H$2="","", IF(E4="",IF($K$16="Use global average",E$276,IF($K$16="Use regional average",INDEX(E$280:E$296,MATCH($B4,$B$280:$B$296,0)),IF($K$16="Leave blank","",IF($K$16="Fill with zeros", 0,IF($K$16="Use global median",E$277,"Fill out I16"))))), E4)) | I4: =IF(I$2="","", IF(F4="",IF($K$16="Use global average",F$276,IF($K$16="Use regional average",INDEX(F$280:F$296,MATCH($B4,$B$280:$B$296,0)),IF($K$16="Leave blank","",IF($K$16="Fill with zeros", 0,IF($K$16="Use global median",F$277,"Fill out I16"))))), F4)) | K4: DATA DESCRIPTION | L4: =IF(M4="","",IF(COUNTIF(Countries!$B$1:$H$271,M4)>0,"",IF(COUNTIF(Countries!$M$1:$S$271,M4)>0,"Not a country","ERROR – NOT LISTED. Add alt spelling to ''Countries'' tab"))) | M4: Albania | N4: 12.064707 | P4: 0.50014008 | Q4: 0.11629 | R4: =IFERROR(O4/(P4*(1-Q4)),"") -> 0
A5: =Countries!B4 -> Algeria | B5: =Countries!I4 -> North Africa | C5: =IFERROR(IFERROR(IFERROR(IFERROR(IFERROR(IFERROR(IFERROR(MATCH(Countries!$B4,$M$3:$M$1003,0),MATCH(Countries!$C4,$M$3:$M$1003,0)),MATCH(Countries!$D4,$M$3:$M$1003,0)),MATCH(Countries!$E4,$M$3:$M$1003,0)),MATCH(Countries!$F4,$M$3:$M$1003,0)),MATCH(Countries!$G4,$M$3:$M$1003,0)),MATCH(Countries!$H4,$M$3:$M$1003,0)),"X") -> 3 | D5: =IF(G$2="","",IF($C5="X","",INDEX($N$3:$CC$1003,$C5,MATCH(G$2,$N$2:$CC$2,0)))) -> 7307.1808 | E5: =IF(H$2="","",IF($C5="X","",INDEX($N$3:$CC$1003,$C5,MATCH(H$2,$N$2:$CC$2,0)))) | F5: =IF(I$2="","",IF($C5="X","",INDEX($N$3:$CC$1003,$C5,MATCH(I$2,$N$2:$CC$2,0)))) | G5: =IF(A5="","",IF(G$2="","", IF(D5="",IF($K$16="Use global average",D$276,IF($K$16="Use regional average",INDEX(D$280:D$296,MATCH($B5,$B$280:$B$296,0)),IF($K$16="Leave blank","",IF($K$16="Fill with zeros", 0,IF($K$16="Use global median",D$277,"Fill out I16"))))), D5))) -> 7307.1808 | H5: =IF(H$2="","", IF(E5="",IF($K$16="Use global average",E$276,IF($K$16="Use regional average",INDEX(E$280:E$296,MATCH($B5,$B$280:$B$296,0)),IF($K$16="Leave blank","",IF($K$16="Fill with zeros", 0,IF($K$16="Use global median",E$277,"Fill out I16"))))), E5)) | I5: =IF(I$2="","", IF(F5="",IF($K$16="Use global average",F$276,IF($K$16="Use regional average",INDEX(F$280:F$296,MATCH($B5,$B$280:$B$296,0)),IF($K$16="Leave blank","",IF($K$16="Fill with zeros", 0,IF($K$16="Use global median",F$277,"Fill out I16"))))), F5)) | L5: =IF(M5="","",IF(COUNTIF(Countries!$B$1:$H$271,M5)>0,"",IF(COUNTIF(Countries!$M$1:$S$271,M5)>0,"Not a country","ERROR – NOT LISTED. Add alt spelling to ''Countries'' tab"))) | M5: Algeria | N5: 8.04364 | O5: =N5*365*1.28 -> 3757.9886 | P5: 0.5876962 | Q5: 0.12491 | R5: =IFERROR(O5/(P5*(1-Q5)),"") -> 7307.1808
A6: =Countries!B5 -> Andorra | B6: =Countries!I5 -> Europe | C6: =IFERROR(IFERROR(IFERROR(IFERROR(IFERROR(IFERROR(IFERROR(MATCH(Countries!$B5,$M$3:$M$1003,0),MATCH(Countries!$C5,$M$3:$M$1003,0)),MATCH(Countries!$D5,$M$3:$M$1003,0)),MATCH(Countries!$E5,$M$3:$M$1003,0)),MATCH(Countries!$F5,$M$3:$M$1003,0)),MATCH(Countries!$G5,$M$3:$M$1003,0)),MATCH(Countries!$H5,$M$3:$M$1003,0)),"X") -> 4 | D6: =IF(G$2="","",IF($C6="X","",INDEX($N$3:$CC$1003,$C6,MATCH(G$2,$N$2:$CC$2,0)))) | E6: =IF(H$2="","",IF($C6="X","",INDEX($N$3:$CC$1003,$C6,MATCH(H$2,$N$2:$CC$2,0)))) | F6: =IF(I$2="","",IF($C6="X","",INDEX($N$3:$CC$1003,$C6,MATCH(I$2,$N$2:$CC$2,0)))) | G6: =IF(A6="","",IF(G$2="","", IF(D6="",IF($K$16="Use global average",D$276,IF($K$16="Use regional average",INDEX(D$280:D$296,MATCH($B6,$B$280:$B$296,0)),IF($K$16="Leave blank","",IF($K$16="Fill with zeros", 0,IF($K$16="Use global median",D$277,"Fill out I16"))))), D6))) -> 33026.356 | H6: =IF(H$2="","", IF(E6="",IF($K$16="Use global average",E$276,IF($K$16="Use regional average",INDEX(E$280:E$296,MATCH($B6,$B$280:$B$296,0)),IF($K$16="Leave blank","",IF($K$16="Fill with zeros", 0,IF($K$16="Use global median",E$277,"Fill out I16"))))), E6)) | I6: =IF(I$2="","", IF(F6="",IF($K$16="Use global average",F$276,IF($K$16="Use regional average",INDEX(F$280:F$296,MATCH($B6,$B$280:$B$296,0)),IF($K$16="Leave blank","",IF($K$16="Fill with zeros", 0,IF($K$16="Use global median",F$277,"Fill out I16"))))), F6)) | K6: Calculating median salary based on data on median per-capita income. | L6: =IF(M6="","",IF(COUNTIF(Countries!$B$1:$H$271,M6)>0,"",IF(COUNTIF(Countries!$M$1:$S$271,M6)>0,"Not a country","ERROR – NOT LISTED. Add alt spelling to ''Countries'' tab"))) | M6: Andorra | N6: NA | O6: =N6*365*1.28 -> #VALUE! | P6: 0.3824098 | Q6: #VALUE! | R6: =IFERROR(O6/(P6*(1-Q6)),"") | S6: =IFERROR(R6,"")
A7: =Countries!B6 -> Angola | B7: =Countries!I6 -> Sub-Saharan Africa | C7: =IFERROR(IFERROR(IFERROR(IFERROR(IFERROR(IFERROR(IFERROR(MATCH(Countries!$B6,$M$3:$M$1003,0),MATCH(Countries!$C6,$M$3:$M$1003,0)),MATCH(Countries!$D6,$M$3:$M$1003,0)),MATCH(Countries!$E6,$M$3:$M$1003,0)),MATCH(Countries!$F6,$M$3:$M$1003,0)),MATCH(Countries!$G6,$M$3:$M$1003,0)),MATCH(Countries!$H6,$M$3:$M$1003,0)),"X") -> 5 | D7: =IF(G$2="","",IF($C7="X","",INDEX($N$3:$CC$1003,$C7,MATCH(G$2,$N$2:$CC$2,0)))) -> 2074.9561 | E7: =IF(H$2="","",IF($C7="X","",INDEX($N$3:$CC$1003,$C7,MATCH(H$2,$N$2:$CC$2,0)))) | F7: =IF(I$2="","",IF($C7="X","",INDEX($N$3:$CC$1003,$C7,MATCH(I$2,$N$2:$CC$2,0)))) | G7: =IF(A7="","",IF(G$2="","", IF(D7="",IF($K$16="Use global average",D$276,IF($K$16="Use regional average",INDEX(D$280:D$296,MATCH($B7,$B$280:$B$296,0)),IF($K$16="Leave blank","",IF($K$16="Fill with zeros", 0,IF($K$16="Use global median",D$277,"Fill out I16"))))), D7))) -> 2074.9561 | H7: =IF(H$2="","", IF(E7="",IF($K$16="Use global average",E$276,IF($K$16="Use regional average",INDEX(E$280:E$296,MATCH($B7,$B$280:$B$296,0)),IF($K$16="Leave blank","",IF($K$16="Fill with zeros", 0,IF($K$16="Use global median",E$277,"Fill out I16"))))), E7)) | I7: =IF(I$2="","", IF(F7="",IF($K$16="Use global average",F$276,IF($K$16="Use regional average",INDEX(F$280:F$296,MATCH($B7,$B$280:$B$296,0)),IF($K$16="Leave blank","",IF($K$16="Fill with zeros", 0,IF($K$16="Use global median",F$277,"Fill out I16"))))), F7)) | L7: =IF(M7="","",IF(COUNTIF(Countries!$B$1:$H$271,M7)>0,"",IF(COUNTIF(Countries!$M$1:$S$271,M7)>0,"Not a country","ERROR – NOT LISTED. Add alt spelling to ''Countries'' tab"))) | M7: Angola | N7: 3.4205022 | O7: =N7*365*1.28 -> 1598.0586 | P7: 0.9005461 | Q7: 0.14478 | R7: =IFERROR(O7/(P7*(1-Q7)),"") -> 2074.9561
A8: =Countries!B7 -> Antigua and Barbuda | B8: =Countries!I7 -> Caribbean | C8: =IFERROR(IFERROR(IFERROR(IFERROR(IFERROR(IFERROR(IFERROR(MATCH(Countries!$B7,$M$3:$M$1003,0),MATCH(Countries!$C7,$M$3:$M$1003,0)),MATCH(Countries!$D7,$M$3:$M$1003,0)),MATCH(Countries!$E7,$M$3:$M$1003,0)),MATCH(Countries!$F7,$M$3:$M$1003,0)),MATCH(Countries!$G7,$M$3:$M$1003,0)),MATCH(Countries!$H7,$M$3:$M$1003,0)),"X") -> 6 | D8: =IF(G$2="","",IF($C8="X","",INDEX($N$3:$CC$1003,$C8,MATCH(G$2,$N$2:$CC$2,0)))) | E8: =IF(H$2="","",IF($C8="X","",INDEX($N$3:$CC$1003,$C8,MATCH(H$2,$N$2:$CC$2,0)))) | F8: =IF(I$2="","",IF($C8="X","",INDEX($N$3:$CC$1003,$C8,MATCH(I$2,$N$2:$CC$2,0)))) | G8: =IF(A8="","",IF(G$2="","", IF(D8="",IF($K$16="Use global average",D$276,IF($K$16="Use regional average",INDEX(D$280:D$296,MATCH($B8,$B$280:$B$296,0)),IF($K$16="Leave blank","",IF($K$16="Fill with zeros", 0,IF($K$16="Use global median",D$277,"Fill out I16"))))), D8))) -> 12713.18 | H8: =IF(H$2="","", IF(E8="",IF($K$16="Use global average",E$276,IF($K$16="Use regional average",INDEX(E$280:E$296,MATCH($B8,$B$280:$B$296,0)),IF($K$16="Leave blank","",IF($K$16="Fill with zeros", 0,IF($K$16="Use global median",E$277,"Fill out I16"))))), E8)) | I8: =IF(I$2="","", IF(F8="",IF($K$16="Use global average",F$276,IF($K$16="Use regional average",INDEX(F$280:F$296,MATCH($B8,$B$280:$B$296,0)),IF($K$16="Leave blank","",IF($K$16="Fill with zeros", 0,IF($K$16="Use global median",F$277,"Fill out I16"))))), F8)) | L8: =IF(M8="","",IF(COUNTIF(Countries!$B$1:$H$271,M8)>0,"",IF(COUNTIF(Countries!$M$1:$S$271,M8)>0,"Not a country","ERROR – NOT LISTED. Add alt spelling to ''Countries'' tab"))) | M8: Antigua and Barbuda | N8: NA | O8: =N8*365*1.28 -> #VALUE! | P8: 0.41747425 | Q8: #VALUE! | R8: =IFERROR(O8/(P8*(1-Q8)),"")
A9: =Countries!B8 -> Argentina | B9: =Countries!I8 -> Latin America | C9: =IFERROR(IFERROR(IFERROR(IFERROR(IFERROR(IFERROR(IFERROR(MATCH(Countries!$B8,$M$3:$M$1003,0),MATCH(Countries!$C8,$M$3:$M$1003,0)),MATCH(Countries!$D8,$M$3:$M$1003,0)),MATCH(Countries!$E8,$M$3:$M$1003,0)),MATCH(Countries!$F8,$M$3:$M$1003,0)),MATCH(Countries!$G8,$M$3:$M$1003,0)),MATCH(Countries!$H8,$M$3:$M$1003,0)),"X") -> 7 | D9: =IF(G$2="","",IF($C9="X","",INDEX($N$3:$CC$1003,$C9,MATCH(G$2,$N$2:$CC$2,0)))) | E9: =IF(H$2="","",IF($C9="X","",INDEX($N$3:$CC$1003,$C9,MATCH(H$2,$N$2:$CC$2,0)))) | F9: =IF(I$2="","",IF($C9="X","",INDEX($N$3:$CC$1003,$C9,MATCH(I$2,$N$2:$CC$2,0)))) | G9: =IF(A9="","",IF(G$2="","", IF(D9="",IF($K$16="Use global average",D$276,IF($K$16="Use regional average",INDEX(D$280:D$296,MATCH($B9,$B$280:$B$296,0)),IF($K$16="Leave blank","",IF($K$16="Fill with zeros", 0,IF($K$16="Use global median",D$277,"Fill out I16"))))), D9))) -> 11787.248 | H9: =IF(H$2="","", IF(E9="",IF($K$16="Use global average",E$276,IF($K$16="Use regional average",INDEX(E$280:E$296,MATCH($B9,$B$280:$B$296,0)),IF($K$16="Leave blank","",IF($K$16="Fill with zeros", 0,IF($K$16="Use global median",E$277,"Fill out I16"))))), E9)) | I9: =IF(I$2="","", IF(F9="",IF($K$16="Use global average",F$276,IF($K$16="Use regional average",INDEX(F$280:F$296,MATCH($B9,$B$280:$B$296,0)),IF($K$16="Leave blank","",IF($K$16="Fill with zeros", 0,IF($K$16="Use global median",F$277,"Fill out I16"))))), F9)) | L9: =IF(M9="","",IF(COUNTIF(Countries!$B$1:$H$271,M9)>0,"",IF(COUNTIF(Countries!$M$1:$S$271,M9)>0,"Not a country","ERROR – NOT LISTED. Add alt spelling to ''Countries'' tab"))) | M9: Argentina | N9: NA | O9: =N9*365*1.28 -> #VALUE! | P9: 0.5239751 | Q9: 0.06805 | R9: =IFERROR(O9/(P9*(1-Q9)),"")
A10: =Countries!B9 -> Armenia | B10: =Countries!I9 -> Europe | C10: =IFERROR(IFERROR(IFERROR(IFERROR(IFERROR(IFERROR(IFERROR(MATCH(Countries!$B9,$M$3:$M$1003,0),MATCH(Countries!$C9,$M$3:$M$1003,0)),MATCH(Countries!$D9,$M$3:$M$1003,0)),MATCH(Countries!$E9,$M$3:$M$1003,0)),MATCH(Countries!$F9,$M$3:$M$1003,0)),MATCH(Countries!$G9,$M$3:$M$1003,0)),MATCH(Countries!$H9,$M$3:$M$1003,0)),"X") -> 8 | D10: =IF(G$2="","",IF($C10="X","",INDEX($N$3:$CC$1003,$C10,MATCH(G$2,$N$2:$CC$2,0)))) -> 7046.4437 | E10: =IF(H$2="","",IF($C10="X","",INDEX($N$3:$CC$1003,$C10,MATCH(H$2,$N$2:$CC$2,0)))) | F10: =IF(I$2="","",IF($C10="X","",INDEX($N$3:$CC$1003,$C10,MATCH(I$2,$N$2:$CC$2,0)))) | G10: =IF(A10="","",IF(G$2="","", IF(D10="",IF($K$16="Use global average",D$276,IF($K$16="Use regional average",INDEX(D$280:D$296,MATCH($B10,$B$280:$B$296,0)),IF($K$16="Leave blank","",IF($K$16="Fill with zeros", 0,IF($K$16="Use global median",D$277,"Fill out I16"))))), D10))) -> 7046.4437 | H10: =IF(H$2="","", IF(E10="",IF($K$16="Use global average",E$276,IF($K$16="Use regional average",INDEX(E$280:E$296,MATCH($B10,$B$280:$B$296,0)),IF($K$16="Leave blank","",IF($K$16="Fill with zeros", 0,IF($K$16="Use global median",E$277,"Fill out I16"))))), E10)) | I10: =IF(I$2="","", IF(F10="",IF($K$16="Use global average",F$276,IF($K$16="Use regional average",INDEX(F$280:F$296,MATCH($B10,$B$280:$B$296,0)),IF($K$16="Leave blank","",IF($K$16="Fill with zeros", 0,IF($K$16="Use global median",F$277,"Fill out I16"))))), F10)) | K10: DATA SOURCE | L10: =IF(M10="","",IF(COUNTIF(Countries!$B$1:$H$271,M10)>0,"",IF(COUNTIF(Countries!$M$1:$S$271,M10)>0,"Not a country","ERROR – NOT LISTED. Add alt spelling to ''Countries'' tab"))) | M10: Armenia | N10: 6.7156725 | O10: =N10*365*1.28 -> 3137.5622 | P10: 0.48710114 | Q10: 0.08588 | R10: =IFERROR(O10/(P10*(1-Q10)),"") -> 7046.4437
A11: =Countries!B10 -> Australia | B11: =Countries!I10 -> Australia | C11: =IFERROR(IFERROR(IFERROR(IFERROR(IFERROR(IFERROR(IFERROR(MATCH(Countries!$B10,$M$3:$M$1003,0),MATCH(Countries!$C10,$M$3:$M$1003,0)),MATCH(Countries!$D10,$M$3:$M$1003,0)),MATCH(Countries!$E10,$M$3:$M$1003,0)),MATCH(Countries!$F10,$M$3:$M$1003,0)),MATCH(Countries!$G10,$M$3:$M$1003,0)),MATCH(Countries!$H10,$M$3:$M$1003,0)),"X") -> 10 | D11: =IF(G$2="","",IF($C11="X","",INDEX($N$3:$CC$1003,$C11,MATCH(G$2,$N$2:$CC$2,0)))) -> 46966.263 | E11: =IF(H$2="","",IF($C11="X","",INDEX($N$3:$CC$1003,$C11,MATCH(H$2,$N$2:$CC$2,0)))) | F11: =IF(I$2="","",IF($C11="X","",INDEX($N$3:$CC$1003,$C11,MATCH(I$2,$N$2:$CC$2,0)))) | G11: =IF(A11="","",IF(G$2="","", IF(D11="",IF($K$16="Use global average",D$276,IF($K$16="Use regional average",INDEX(D$280:D$296,MATCH($B11,$B$280:$B$296,0)),IF($K$16="Leave blank","",IF($K$16="Fill with zeros", 0,IF($K$16="Use global median",D$277,"Fill out I16"))))), D11))) -> 46966.263 | H11: =IF(H$2="","", IF(E11="",IF($K$16="Use global average",E$276,IF($K$16="Use regional average",INDEX(E$280:E$296,MATCH($B11,$B$280:$B$296,0)),IF($K$16="Leave blank","",IF($K$16="Fill with zeros", 0,IF($K$16="Use global median",E$277,"Fill out I16"))))), E11)) | I11: =IF(I$2="","", IF(F11="",IF($K$16="Use global average",F$276,IF($K$16="Use regional average",INDEX(F$280:F$296,MATCH($B11,$B$280:$B$296,0)),IF($K$16="Leave blank","",IF($K$16="Fill with zeros", 0,IF($K$16="Use global median",F$277,"Fill out I16"))))), F11)) | L11: =IF(M11="","",IF(COUNTIF(Countries!$B$1:$H$271,M11)>0,"",IF(COUNTIF(Countries!$M$1:$S$271,M11)>0,"Not a country","ERROR – NOT LISTED. Add alt spelling to ''Countries'' tab"))) -> Not a country | M11: Aruba | N11: NA | O11: =N11*365*1.28 -> #VALUE! | P11: 0.5050402 | Q11: #VALUE! | R11: =IFERROR(O11/(P11*(1-Q11)),"")
A12: =Countries!B11 -> Austria | B12: =Countries!I11 -> Europe | C12: =IFERROR(IFERROR(IFERROR(IFERROR(IFERROR(IFERROR(IFERROR(MATCH(Countries!$B11,$M$3:$M$1003,0),MATCH(Countries!$C11,$M$3:$M$1003,0)),MATCH(Countries!$D11,$M$3:$M$1003,0)),MATCH(Countries!$E11,$M$3:$M$1003,0)),MATCH(Countries!$F11,$M$3:$M$1003,0)),MATCH(Countries!$G11,$M$3:$M$1003,0)),MATCH(Countries!$H11,$M$3:$M$1003,0)),"X") -> 11 | D12: =IF(G$2="","",IF($C12="X","",INDEX($N$3:$CC$1003,$C12,MATCH(G$2,$N$2:$CC$2,0)))) -> 54507.986 | E12: =IF(H$2="","",IF($C12="X","",INDEX($N$3:$CC$1003,$C12,MATCH(H$2,$N$2:$CC$2,0)))) | F12: =IF(I$2="","",IF($C12="X","",INDEX($N$3:$CC$1003,$C12,MATCH(I$2,$N$2:$CC$2,0)))) | G12: =IF(A12="","",IF(G$2="","", IF(D12="",IF($K$16="Use global average",D$276,IF($K$16="Use regional average",INDEX(D$280:D$296,MATCH($B12,$B$280:$B$296,0)),IF($K$16="Leave blank","",IF($K$16="Fill with zeros", 0,IF($K$16="Use global median",D$277,"Fill out I16"))))), D12))) -> 54507.986 | H12: =IF(H$2="","", IF(E12="",IF($K$16="Use global average",E$276,IF($K$16="Use regional average",INDEX(E$280:E$296,MATCH($B12,$B$280:$B$296,0)),IF($K$16="Leave blank","",IF($K$16="Fill with zeros", 0,IF($K$16="Use global median",E$277,"Fill out I16"))))), E12)) | I12: =IF(I$2="","", IF(F12="",IF($K$16="Use global average",F$276,IF($K$16="Use regional average",INDEX(F$280:F$296,MATCH($B12,$B$280:$B$296,0)),IF($K$16="Leave blank","",IF($K$16="Fill with zeros", 0,IF($K$16="Use global median",F$277,"Fill out I16"))))), F12)) | K12: OWiD | L12: =IF(M12="","",IF(COUNTIF(Countries!$B$1:$H$271,M12)>0,"",IF(COUNTIF(Countries!$M$1:$S$271,M12)>0,"Not a country","ERROR – NOT LISTED. Add alt spelling to ''Countries'' tab"))) | M12: Australia | N12: 53.050495 | O12: =N12*365*1.28 -> 24785.191 | P12: 0.54799927 | Q12: 0.037 | R12: =IFERROR(O12/(P12*(1-Q12)),"") -> 46966.263
A13: =Countries!B12 -> Azerbaijan | B13: =Countries!I12 -> West Asia | C13: =IFERROR(IFERROR(IFERROR(IFERROR(IFERROR(IFERROR(IFERROR(MATCH(Countries!$B12,$M$3:$M$1003,0),MATCH(Countries!$C12,$M$3:$M$1003,0)),MATCH(Countries!$D12,$M$3:$M$1003,0)),MATCH(Countries!$E12,$M$3:$M$1003,0)),MATCH(Countries!$F12,$M$3:$M$1003,0)),MATCH(Countries!$G12,$M$3:$M$1003,0)),MATCH(Countries!$H12,$M$3:$M$1003,0)),"X") -> 12 | D13: =IF(G$2="","",IF($C13="X","",INDEX($N$3:$CC$1003,$C13,MATCH(G$2,$N$2:$CC$2,0)))) -> 9156.4912 | E13: =IF(H$2="","",IF($C13="X","",INDEX($N$3:$CC$1003,$C13,MATCH(H$2,$N$2:$CC$2,0)))) | F13: =IF(I$2="","",IF($C13="X","",INDEX($N$3:$CC$1003,$C13,MATCH(I$2,$N$2:$CC$2,0)))) | G13: =IF(A13="","",IF(G$2="","", IF(D13="",IF($K$16="Use global average",D$276,IF($K$16="Use regional average",INDEX(D$280:D$296,MATCH($B13,$B$280:$B$296,0)),IF($K$16="Leave blank","",IF($K$16="Fill with zeros", 0,IF($K$16="Use global median",D$277,"Fill out I16"))))), D13))) -> 9156.4912 | H13: =IF(H$2="","", IF(E13="",IF($K$16="Use global average",E$276,IF($K$16="Use regional average",INDEX(E$280:E$296,MATCH($B13,$B$280:$B$296,0)),IF($K$16="Leave blank","",IF($K$16="Fill with zeros", 0,IF($K$16="Use global median",E$277,"Fill out I16"))))), E13)) | I13: =IF(I$2="","", IF(F13="",IF($K$16="Use global average",F$276,IF($K$16="Use regional average",INDEX(F$280:F$296,MATCH($B13,$B$280:$B$296,0)),IF($K$16="Leave blank","",IF($K$16="Fill with zeros", 0,IF($K$16="Use global median",F$277,"Fill out I16"))))), F13)) | L13: =IF(M13="","",IF(COUNTIF(Countries!$B$1:$H$271,M13)>0,"",IF(COUNTIF(Countries!$M$1:$S$271,M13)>0,"Not a country","ERROR – NOT LISTED. Add alt spelling to ''Countries'' tab"))) | M13: Austria | N13: 58.25852 | O13: =N13*365*1.28 -> 27218.381 | P13: 0.52557274 | Q13: 0.0499 | R13: =IFERROR(O13/(P13*(1-Q13)),"") -> 54507.986
A14: =Countries!B13 -> Bahamas | B14: =Countries!I13 -> Caribbean | C14: =IFERROR(IFERROR(IFERROR(IFERROR(IFERROR(IFERROR(IFERROR(MATCH(Countries!$B13,$M$3:$M$1003,0),MATCH(Countries!$C13,$M$3:$M$1003,0)),MATCH(Countries!$D13,$M$3:$M$1003,0)),MATCH(Countries!$E13,$M$3:$M$1003,0)),MATCH(Countries!$F13,$M$3:$M$1003,0)),MATCH(Countries!$G13,$M$3:$M$1003,0)),MATCH(Countries!$H13,$M$3:$M$1003,0)),"X") -> 13 | D14: =IF(G$2="","",IF($C14="X","",INDEX($N$3:$CC$1003,$C14,MATCH(G$2,$N$2:$CC$2,0)))) | E14: =IF(H$2="","",IF($C14="X","",INDEX($N$3:$CC$1003,$C14,MATCH(H$2,$N$2:$CC$2,0)))) | F14: =IF(I$2="","",IF($C14="X","",INDEX($N$3:$CC$1003,$C14,MATCH(I$2,$N$2:$CC$2,0)))) | G14: =IF(A14="","",IF(G$2="","", IF(D14="",IF($K$16="Use global average",D$276,IF($K$16="Use regional average",INDEX(D$280:D$296,MATCH($B14,$B$280:$B$296,0)),IF($K$16="Leave blank","",IF($K$16="Fill with zeros", 0,IF($K$16="Use global median",D$277,"Fill out I16"))))), D14))) -> 12713.18 | H14: =IF(H$2="","", IF(E14="",IF($K$16="Use global average",E$276,IF($K$16="Use regional average",INDEX(E$280:E$296,MATCH($B14,$B$280:$B$296,0)),IF($K$16="Leave blank","",IF($K$16="Fill with zeros", 0,IF($K$16="Use global median",E$277,"Fill out I16"))))), E14)) | I14: =IF(I$2="","", IF(F14="",IF($K$16="Use global average",F$276,IF($K$16="Use regional average",INDEX(F$280:F$296,MATCH($B14,$B$280:$B$296,0)),IF($K$16="Leave blank","",IF($K$16="Fill with zeros", 0,IF($K$16="Use global median",F$277,"Fill out I16"))))), F14)) | K14: IF DATA MISSING: | L14: =IF(M14="","",IF(COUNTIF(Countries!$B$1:$H$271,M14)>0,"",IF(COUNTIF(Countries!$M$1:$S$271,M14)>0,"Not a country","ERROR – NOT LISTED. Add alt spelling to ''Countries'' tab"))) | M14: Azerbaijan | N14: 8.059334 | O14: =N14*365*1.28 -> 3765.3208 | P14: 0.43584393 | Q14: 0.0565 | R14: =IFERROR(O14/(P14*(1-Q14)),"") -> 9156.4912
A15: =Countries!B14 -> Bahrain | B15: =Countries!I14 -> West Asia | C15: =IFERROR(IFERROR(IFERROR(IFERROR(IFERROR(IFERROR(IFERROR(MATCH(Countries!$B14,$M$3:$M$1003,0),MATCH(Countries!$C14,$M$3:$M$1003,0)),MATCH(Countries!$D14,$M$3:$M$1003,0)),MATCH(Countries!$E14,$M$3:$M$1003,0)),MATCH(Countries!$F14,$M$3:$M$1003,0)),MATCH(Countries!$G14,$M$3:$M$1003,0)),MATCH(Countries!$H14,$M$3:$M$1003,0)),"X") -> 14 | D15: =IF(G$2="","",IF($C15="X","",INDEX($N$3:$CC$1003,$C15,MATCH(G$2,$N$2:$CC$2,0)))) | E15: =IF(H$2="","",IF($C15="X","",INDEX($N$3:$CC$1003,$C15,MATCH(H$2,$N$2:$CC$2,0)))) | F15: =IF(I$2="","",IF($C15="X","",INDEX($N$3:$CC$1003,$C15,MATCH(I$2,$N$2:$CC$2,0)))) | G15: =IF(A15="","",IF(G$2="","", IF(D15="",IF($K$16="Use global average",D$276,IF($K$16="Use regional average",INDEX(D$280:D$296,MATCH($B15,$B$280:$B$296,0)),IF($K$16="Leave blank","",IF($K$16="Fill with zeros", 0,IF($K$16="Use global median",D$277,"Fill out I16"))))), D15))) -> 24646.405 | H15: =IF(H$2="","", IF(E15="",IF($K$16="Use global average",E$276,IF($K$16="Use regional average",INDEX(E$280:E$296,MATCH($B15,$B$280:$B$296,0)),IF($K$16="Leave blank","",IF($K$16="Fill with zeros", 0,IF($K$16="Use global median",E$277,"Fill out I16"))))), E15)) | I15: =IF(I$2="","", IF(F15="",IF($K$16="Use global average",F$276,IF($K$16="Use regional average",INDEX(F$280:F$296,MATCH($B15,$B$280:$B$296,0)),IF($K$16="Leave blank","",IF($K$16="Fill with zeros", 0,IF($K$16="Use global median",F$277,"Fill out I16"))))), F15)) | L15: =IF(M15="","",IF(COUNTIF(Countries!$B$1:$H$271,M15)>0,"",IF(COUNTIF(Countries!$M$1:$S$271,M15)>0,"Not a country","ERROR – NOT LISTED. Add alt spelling to ''Countries'' tab"))) | M15: Bahamas | N15: NA | O15: =N15*365*1.28 -> #VALUE! | P15: 0.4247221 | Q15: 0.10089 | R15: =IFERROR(O15/(P15*(1-Q15)),"")
A16: =Countries!B15 -> Bangladesh | B16: =Countries!I15 -> South Asia | C16: =IFERROR(IFERROR(IFERROR(IFERROR(IFERROR(IFERROR(IFERROR(MATCH(Countries!$B15,$M$3:$M$1003,0),MATCH(Countries!$C15,$M$3:$M$1003,0)),MATCH(Countries!$D15,$M$3:$M$1003,0)),MATCH(Countries!$E15,$M$3:$M$1003,0)),MATCH(Countries!$F15,$M$3:$M$1003,0)),MATCH(Countries!$G15,$M$3:$M$1003,0)),MATCH(Countries!$H15,$M$3:$M$1003,0)),"X") -> 15 | D16: =IF(G$2="","",IF($C16="X","",INDEX($N$3:$CC$1003,$C16,MATCH(G$2,$N$2:$CC$2,0)))) -> 4395.3047 | E16: =IF(H$2="","",IF($C16="X","",INDEX($N$3:$CC$1003,$C16,MATCH(H$2,$N$2:$CC$2,0)))) | F16: =IF(I$2="","",IF($C16="X","",INDEX($N$3:$CC$1003,$C16,MATCH(I$2,$N$2:$CC$2,0)))) | G16: =IF(A16="","",IF(G$2="","", IF(D16="",IF($K$16="Use global average",D$276,IF($K$16="Use regional average",INDEX(D$280:D$296,MATCH($B16,$B$280:$B$296,0)),IF($K$16="Leave blank","",IF($K$16="Fill with zeros", 0,IF($K$16="Use global median",D$277,"Fill out I16"))))), D16))) -> 4395.3047 | H16: =IF(H$2="","", IF(E16="",IF($K$16="Use global average",E$276,IF($K$16="Use regional average",INDEX(E$280:E$296,MATCH($B16,$B$280:$B$296,0)),IF($K$16="Leave blank","",IF($K$16="Fill with zeros", 0,IF($K$16="Use global median",E$277,"Fill out I16"))))), E16)) | I16: =IF(I$2="","", IF(F16="",IF($K$16="Use global average",F$276,IF($K$16="Use regional average",INDEX(F$280:F$296,MATCH($B16,$B$280:$B$296,0)),IF($K$16="Leave blank","",IF($K$16="Fill with zeros", 0,IF($K$16="Use global median",F$277,"Fill out I16"))))), F16)) | K16: Use regional average | L16: =IF(M16="","",IF(COUNTIF(Countries!$B$1:$H$271,M16)>0,"",IF(COUNTIF(Countries!$M$1:$S$271,M16)>0,"Not a country","ERROR – NOT LISTED. Add alt spelling to ''Countries'' tab"))) | M16: Bahrain | N16: NA | O16: =N16*365*1.28 -> #VALUE! | P16: 0.29246946 | Q16: 0.01339 | R16: =IFERROR(O16/(P16*(1-Q16)),"")
A17: =Countries!B16 -> Barbados | B17: =Countries!I16 -> Caribbean | C17: =IFERROR(IFERROR(IFERROR(IFERROR(IFERROR(IFERROR(IFERROR(MATCH(Countries!$B16,$M$3:$M$1003,0),MATCH(Countries!$C16,$M$3:$M$1003,0)),MATCH(Countries!$D16,$M$3:$M$1003,0)),MATCH(Countries!$E16,$M$3:$M$1003,0)),MATCH(Countries!$F16,$M$3:$M$1003,0)),MATCH(Countries!$G16,$M$3:$M$1003,0)),MATCH(Countries!$H16,$M$3:$M$1003,0)),"X") -> 16 | D17: =IF(G$2="","",IF($C17="X","",INDEX($N$3:$CC$1003,$C17,MATCH(G$2,$N$2:$CC$2,0)))) | E17: =IF(H$2="","",IF($C17="X","",INDEX($N$3:$CC$1003,$C17,MATCH(H$2,$N$2:$CC$2,0)))) | F17: =IF(I$2="","",IF($C17="X","",INDEX($N$3:$CC$1003,$C17,MATCH(I$2,$N$2:$CC$2,0)))) | G17: =IF(A17="","",IF(G$2="","", IF(D17="",IF($K$16="Use global average",D$276,IF($K$16="Use regional average",INDEX(D$280:D$296,MATCH($B17,$B$280:$B$296,0)),IF($K$16="Leave blank","",IF($K$16="Fill with zeros", 0,IF($K$16="Use global median",D$277,"Fill out I16"))))), D17))) -> 12713.18 | H17: =IF(H$2="","", IF(E17="",IF($K$16="Use global average",E$276,IF($K$16="Use regional average",INDEX(E$280:E$296,MATCH($B17,$B$280:$B$296,0)),IF($K$16="Leave blank","",IF($K$16="Fill with zeros", 0,IF($K$16="Use global median",E$277,"Fill out I16"))))), E17)) | I17: =IF(I$2="","", IF(F17="",IF($K$16="Use global average",F$276,IF($K$16="Use regional average",INDEX(F$280:F$296,MATCH($B17,$B$280:$B$296,0)),IF($K$16="Leave blank","",IF($K$16="Fill with zeros", 0,IF($K$16="Use global median",F$277,"Fill out I16"))))), F17)) | K17: • Regional average – If only a few data points missing, it's okay to use regional average (especially true for per capita or "rates" data). But be careful with using regional averages for absolute numbers. • Global average / blanks – In general if there are lots of data missing, it's better to leave missing data blank, or use the global average (these are the same when z-scored). • Fill with zeros – Only used when missing data strongly implies the results are zero for all unlisted countries (e.g. number of hurricanes hitting each country). • Global median scores – Might very occasionally be appropriate where there are a few clear anomalously high countries. | L17: =IF(M17="","",IF(COUNTIF(Countries!$B$1:$H$271,M17)>0,"",IF(COUNTIF(Countries!$M$1:$S$271,M17)>0,"Not a country","ERROR – NOT LISTED. Add alt spelling to ''Countries'' tab"))) | M17: Bangladesh | N17: 4.7816916 | O17: =N17*365*1.28 -> 2234.0063 | P17: 0.53094788 | Q17: 0.04271 | R17: =IFERROR(O17/(P17*(1-Q17)),"") -> 4395.3047
A18: =Countries!B17 -> Belarus | B18: =Countries!I17 -> Europe | C18: =IFERROR(IFERROR(IFERROR(IFERROR(IFERROR(IFERROR(IFERROR(MATCH(Countries!$B17,$M$3:$M$1003,0),MATCH(Countries!$C17,$M$3:$M$1003,0)),MATCH(Countries!$D17,$M$3:$M$1003,0)),MATCH(Countries!$E17,$M$3:$M$1003,0)),MATCH(Countries!$F17,$M$3:$M$1003,0)),MATCH(Countries!$G17,$M$3:$M$1003,0)),MATCH(Countries!$H17,$M$3:$M$1003,0)),"X") -> 17 | D18: =IF(G$2="","",IF($C18="X","",INDEX($N$3:$CC$1003,$C18,MATCH(G$2,$N$2:$CC$2,0)))) -> 16404.618 | E18: =IF(H$2="","",IF($C18="X","",INDEX($N$3:$CC$1003,$C18,MATCH(H$2,$N$2:$CC$2,0)))) | F18: =IF(I$2="","",IF($C18="X","",INDEX($N$3:$CC$1003,$C18,MATCH(I$2,$N$2:$CC$2,0)))) | G18: =IF(A18="","",IF(G$2="","", IF(D18="",IF($K$16="Use global average",D$276,IF($K$16="Use regional average",INDEX(D$280:D$296,MATCH($B18,$B$280:$B$296,0)),IF($K$16="Leave blank","",IF($K$16="Fill with zeros", 0,IF($K$16="Use global median",D$277,"Fill out I16"))))), D18))) -> 16404.618 | H18: =IF(H$2="","", IF(E18="",IF($K$16="Use global average",E$276,IF($K$16="Use regional average",INDEX(E$280:E$296,MATCH($B18,$B$280:$B$296,0)),IF($K$16="Leave blank","",IF($K$16="Fill with zeros", 0,IF($K$16="Use global median",E$277,"Fill out I16"))))), E18)) | I18: =IF(I$2="","", IF(F18="",IF($K$16="Use global average",F$276,IF($K$16="Use regional average",INDEX(F$280:F$296,MATCH($B18,$B$280:$B$296,0)),IF($K$16="Leave blank","",IF($K$16="Fill with zeros", 0,IF($K$16="Use global median",F$277,"Fill out I16"))))), F18)) | L18: =IF(M18="","",IF(COUNTIF(Countries!$B$1:$H$271,M18)>0,"",IF(COUNTIF(Countries!$M$1:$S$271,M18)>0,"Not a country","ERROR – NOT LISTED. Add alt spelling to ''Countries'' tab"))) | M18: Barbados | N18: NA | O18: =N18*365*1.28 -> #VALUE! | P18: 0.5055671 | Q18: 0.08501 | R18: =IFERROR(O18/(P18*(1-Q18)),"")
A19: =Countries!B18 -> Belgium | B19: =Countries!I18 -> Europe | C19: =IFERROR(IFERROR(IFERROR(IFERROR(IFERROR(IFERROR(IFERROR(MATCH(Countries!$B18,$M$3:$M$1003,0),MATCH(Countries!$C18,$M$3:$M$1003,0)),MATCH(Countries!$D18,$M$3:$M$1003,0)),MATCH(Countries!$E18,$M$3:$M$1003,0)),MATCH(Countries!$F18,$M$3:$M$1003,0)),MATCH(Countries!$G18,$M$3:$M$1003,0)),MATCH(Countries!$H18,$M$3:$M$1003,0)),"X") -> 18 | D19: =IF(G$2="","",IF($C19="X","",INDEX($N$3:$CC$1003,$C19,MATCH(G$2,$N$2:$CC$2,0)))) -> 47062.972 | E19: =IF(H$2="","",IF($C19="X","",INDEX($N$3:$CC$1003,$C19,MATCH(H$2,$N$2:$CC$2,0)))) | F19: =IF(I$2="","",IF($C19="X","",INDEX($N$3:$CC$1003,$C19,MATCH(I$2,$N$2:$CC$2,0)))) | G19: =IF(A19="","",IF(G$2="","", IF(D19="",IF($K$16="Use global average",D$276,IF($K$16="Use regional average",INDEX(D$280:D$296,MATCH($B19,$B$280:$B$296,0)),IF($K$16="Leave blank","",IF($K$16="Fill with zeros", 0,IF($K$16="Use global median",D$277,"Fill out I16"))))), D19))) -> 47062.972 | H19: =IF(H$2="","", IF(E19="",IF($K$16="Use global average",E$276,IF($K$16="Use regional average",INDEX(E$280:E$296,MATCH($B19,$B$280:$B$296,0)),IF($K$16="Leave blank","",IF($K$16="Fill with zeros", 0,IF($K$16="Use global median",E$277,"Fill out I16"))))), E19)) | I19: =IF(I$2="","", IF(F19="",IF($K$16="Use global average",F$276,IF($K$16="Use regional average",INDEX(F$280:F$296,MATCH($B19,$B$280:$B$296,0)),IF($K$16="Leave blank","",IF($K$16="Fill with zeros", 0,IF($K$16="Use global median",F$277,"Fill out I16"))))), F19)) | L19: =IF(M19="","",IF(COUNTIF(Countries!$B$1:$H$271,M19)>0,"",IF(COUNTIF(Countries!$M$1:$S$271,M19)>0,"Not a country","ERROR – NOT LISTED. Add alt spelling to ''Countries'' tab"))) | M19: Belarus | N19: 17.238052 | O19: =N19*365*1.28 -> 8053.6179 | P19: 0.5091113 | Q19: 0.0357 | R19: =IFERROR(O19/(P19*(1-Q19)),"") -> 16404.618
A20: =Countries!B19 -> Belize | B20: =Countries!I19 -> Latin America | C20: =IFERROR(IFERROR(IFERROR(IFERROR(IFERROR(IFERROR(IFERROR(MATCH(Countries!$B19,$M$3:$M$1003,0),MATCH(Countries!$C19,$M$3:$M$1003,0)),MATCH(Countries!$D19,$M$3:$M$1003,0)),MATCH(Countries!$E19,$M$3:$M$1003,0)),MATCH(Countries!$F19,$M$3:$M$1003,0)),MATCH(Countries!$G19,$M$3:$M$1003,0)),MATCH(Countries!$H19,$M$3:$M$1003,0)),"X") -> 19 | D20: =IF(G$2="","",IF($C20="X","",INDEX($N$3:$CC$1003,$C20,MATCH(G$2,$N$2:$CC$2,0)))) -> 5051.3412 | E20: =IF(H$2="","",IF($C20="X","",INDEX($N$3:$CC$1003,$C20,MATCH(H$2,$N$2:$CC$2,0)))) | F20: =IF(I$2="","",IF($C20="X","",INDEX($N$3:$CC$1003,$C20,MATCH(I$2,$N$2:$CC$2,0)))) | G20: =IF(A20="","",IF(G$2="","", IF(D20="",IF($K$16="Use global average",D$276,IF($K$16="Use regional average",INDEX(D$280:D$296,MATCH($B20,$B$280:$B$296,0)),IF($K$16="Leave blank","",IF($K$16="Fill with zeros", 0,IF($K$16="Use global median",D$277,"Fill out I16"))))), D20))) -> 5051.3412 | H20: =IF(H$2="","", IF(E20="",IF($K$16="Use global average",E$276,IF($K$16="Use regional average",INDEX(E$280:E$296,MATCH($B20,$B$280:$B$296,0)),IF($K$16="Leave blank","",IF($K$16="Fill with zeros", 0,IF($K$16="Use global median",E$277,"Fill out I16"))))), E20)) | I20: =IF(I$2="","", IF(F20="",IF($K$16="Use global average",F$276,IF($K$16="Use regional average",INDEX(F$280:F$296,MATCH($B20,$B$280:$B$296,0)),IF($K$16="Leave blank","",IF($K$16="Fill with zeros", 0,IF($K$16="Use global median",F$277,"Fill out I16"))))), F20)) | L20: =IF(M20="","",IF(COUNTIF(Countries!$B$1:$H$271,M20)>0,"",IF(COUNTIF(Countries!$M$1:$S$271,M20)>0,"Not a country","ERROR – NOT LISTED. Add alt spelling to ''Countries'' tab"))) | M20: Belgium | N20: 54.49564 | O20: =N20*365*1.28 -> 25460.363 | P20: 0.57283463 | Q20: 0.0556 | R20: =IFERROR(O20/(P20*(1-Q20)),"") -> 47062.972
A21: =Countries!B20 -> Benin | B21: =Countries!I20 -> Sub-Saharan Africa | C21: =IFERROR(IFERROR(IFERROR(IFERROR(IFERROR(IFERROR(IFERROR(MATCH(Countries!$B20,$M$3:$M$1003,0),MATCH(Countries!$C20,$M$3:$M$1003,0)),MATCH(Countries!$D20,$M$3:$M$1003,0)),MATCH(Countries!$E20,$M$3:$M$1003,0)),MATCH(Countries!$F20,$M$3:$M$1003,0)),MATCH(Countries!$G20,$M$3:$M$1003,0)),MATCH(Countries!$H20,$M$3:$M$1003,0)),"X") -> 20 | D21: =IF(G$2="","",IF($C21="X","",INDEX($N$3:$CC$1003,$C21,MATCH(G$2,$N$2:$CC$2,0)))) -> 2326.286 | E21: =IF(H$2="","",IF($C21="X","",INDEX($N$3:$CC$1003,$C21,MATCH(H$2,$N$2:$CC$2,0)))) | F21: =IF(I$2="","",IF($C21="X","",INDEX($N$3:$CC$1003,$C21,MATCH(I$2,$N$2:$CC$2,0)))) | G21: =IF(A21="","",IF(G$2="","", IF(D21="",IF($K$16="Use global average",D$276,IF($K$16="Use regional average",INDEX(D$280:D$296,MATCH($B21,$B$280:$B$296,0)),IF($K$16="Leave blank","",IF($K$16="Fill with zeros", 0,IF($K$16="Use global median",D$277,"Fill out I16"))))), D21))) -> 2326.286 | H21: =IF(H$2="","", IF(E21="",IF($K$16="Use global average",E$276,IF($K$16="Use regional average",INDEX(E$280:E$296,MATCH($B21,$B$280:$B$296,0)),IF($K$16="Leave blank","",IF($K$16="Fill with zeros", 0,IF($K$16="Use global median",E$277,"Fill out I16"))))), E21)) | I21: =IF(I$2="","", IF(F21="",IF($K$16="Use global average",F$276,IF($K$16="Use regional average",INDEX(F$280:F$296,MATCH($B21,$B$280:$B$296,0)),IF($K$16="Leave blank","",IF($K$16="Fill with zeros", 0,IF($K$16="Use global median",F$277,"Fill out I16"))))), F21)) | L21: =IF(M21="","",IF(COUNTIF(Countries!$B$1:$H$271,M21)>0,"",IF(COUNTIF(Countries!$M$1:$S$271,M21)>0,"Not a country","ERROR – NOT LISTED. Add alt spelling to ''Countries'' tab"))) | M21: Belize | N21: 4.6116567 | O21: =N21*365*1.28 -> 2154.566 | P21: 0.4670347 | Q21: 0.08672 | R21: =IFERROR(O21/(P21*(1-Q21)),"") -> 5051.3412
A22: =Countries!B21 -> Bhutan | B22: =Countries!I21 -> South Asia | C22: =IFERROR(IFERROR(IFERROR(IFERROR(IFERROR(IFERROR(IFERROR(MATCH(Countries!$B21,$M$3:$M$1003,0),MATCH(Countries!$C21,$M$3:$M$1003,0)),MATCH(Countries!$D21,$M$3:$M$1003,0)),MATCH(Countries!$E21,$M$3:$M$1003,0)),MATCH(Countries!$F21,$M$3:$M$1003,0)),MATCH(Countries!$G21,$M$3:$M$1003,0)),MATCH(Countries!$H21,$M$3:$M$1003,0)),"X") -> 22 | D22: =IF(G$2="","",IF($C22="X","",INDEX($N$3:$CC$1003,$C22,MATCH(G$2,$N$2:$CC$2,0)))) -> 17858.164 | E22: =IF(H$2="","",IF($C22="X","",INDEX($N$3:$CC$1003,$C22,MATCH(H$2,$N$2:$CC$2,0)))) | F22: =IF(I$2="","",IF($C22="X","",INDEX($N$3:$CC$1003,$C22,MATCH(I$2,$N$2:$CC$2,0)))) | G22: =IF(A22="","",IF(G$2="","", IF(D22="",IF($K$16="Use global average",D$276,IF($K$16="Use regional average",INDEX(D$280:D$296,MATCH($B22,$B$280:$B$296,0)),IF($K$16="Leave blank","",IF($K$16="Fill with zeros", 0,IF($K$16="Use global median",D$277,"Fill out I16"))))), D22))) -> 17858.164 | H22: =IF(H$2="","", IF(E22="",IF($K$16="Use global average",E$276,IF($K$16="Use regional average",INDEX(E$280:E$296,MATCH($B22,$B$280:$B$296,0)),IF($K$16="Leave blank","",IF($K$16="Fill with zeros", 0,IF($K$16="Use global median",E$277,"Fill out I16"))))), E22)) | I22: =IF(I$2="","", IF(F22="",IF($K$16="Use global average",F$276,IF($K$16="Use regional average",INDEX(F$280:F$296,MATCH($B22,$B$280:$B$296,0)),IF($K$16="Leave blank","",IF($K$16="Fill with zeros", 0,IF($K$16="Use global median",F$277,"Fill out I16"))))), F22)) | L22: =IF(M22="","",IF(COUNTIF(Countries!$B$1:$H$271,M22)>0,"",IF(COUNTIF(Countries!$M$1:$S$271,M22)>0,"Not a country","ERROR – NOT LISTED. Add alt spelling to ''Countries'' tab"))) | M22: Benin | N22: 4.0014644 | O22: =N22*365*1.28 -> 1869.4842 | P22: 0.81567406 | Q22: 0.01476 | R22: =IFERROR(O22/(P22*(1-Q22)),"") -> 2326.286
A23: =Countries!B22 -> Bolivia | B23: =Countries!I22 -> Latin America | C23: =IFERROR(IFERROR(IFERROR(IFERROR(IFERROR(IFERROR(IFERROR(MATCH(Countries!$B22,$M$3:$M$1003,0),MATCH(Countries!$C22,$M$3:$M$1003,0)),MATCH(Countries!$D22,$M$3:$M$1003,0)),MATCH(Countries!$E22,$M$3:$M$1003,0)),MATCH(Countries!$F22,$M$3:$M$1003,0)),MATCH(Countries!$G22,$M$3:$M$1003,0)),MATCH(Countries!$H22,$M$3:$M$1003,0)),"X") -> 23 | D23: =IF(G$2="","",IF($C23="X","",INDEX($N$3:$CC$1003,$C23,MATCH(G$2,$N$2:$CC$2,0)))) -> 13015.232 | E23: =IF(H$2="","",IF($C23="X","",INDEX($N$3:$CC$1003,$C23,MATCH(H$2,$N$2:$CC$2,0)))) | F23: =IF(I$2="","",IF($C23="X","",INDEX($N$3:$CC$1003,$C23,MATCH(I$2,$N$2:$CC$2,0)))) | G23: =IF(A23="","",IF(G$2="","", IF(D23="",IF($K$16="Use global average",D$276,IF($K$16="Use regional average",INDEX(D$280:D$296,MATCH($B23,$B$280:$B$296,0)),IF($K$16="Leave blank","",IF($K$16="Fill with zeros", 0,IF($K$16="Use global median",D$277,"Fill out I16"))))), D23))) -> 13015.232 | H23: =IF(H$2="","", IF(E23="",IF($K$16="Use global average",E$276,IF($K$16="Use regional average",INDEX(E$280:E$296,MATCH($B23,$B$280:$B$296,0)),IF($K$16="Leave blank","",IF($K$16="Fill with zeros", 0,IF($K$16="Use global median",E$277,"Fill out I16"))))), E23)) | I23: =IF(I$2="","", IF(F23="",IF($K$16="Use global average",F$276,IF($K$16="Use regional average",INDEX(F$280:F$296,MATCH($B23,$B$280:$B$296,0)),IF($K$16="Leave blank","",IF($K$16="Fill with zeros", 0,IF($K$16="Use global median",F$277,"Fill out I16"))))), F23)) | L23: =IF(M23="","",IF(COUNTIF(Countries!$B$1:$H$271,M23)>0,"",IF(COUNTIF(Countries!$M$1:$S$271,M23)>0,"Not a country","ERROR – NOT LISTED. Add alt spelling to ''Countries'' tab"))) -> Not a country | M23: Bermuda | N23: NA | O23: =N23*365*1.28 -> #VALUE! | P23: 0.5333539 | Q23: #VALUE! | R23: =IFERROR(O23/(P23*(1-Q23)),"")
A24: =Countries!B23 -> Bosnia | B24: =Countries!I23 -> Europe | C24: =IFERROR(IFERROR(IFERROR(IFERROR(IFERROR(IFERROR(IFERROR(MATCH(Countries!$B23,$M$3:$M$1003,0),MATCH(Countries!$C23,$M$3:$M$1003,0)),MATCH(Countries!$D23,$M$3:$M$1003,0)),MATCH(Countries!$E23,$M$3:$M$1003,0)),MATCH(Countries!$F23,$M$3:$M$1003,0)),MATCH(Countries!$G23,$M$3:$M$1003,0)),MATCH(Countries!$H23,$M$3:$M$1003,0)),"X") -> 24 | D24: =IF(G$2="","",IF($C24="X","",INDEX($N$3:$CC$1003,$C24,MATCH(G$2,$N$2:$CC$2,0)))) -> 17603.566 | E24: =IF(H$2="","",IF($C24="X","",INDEX($N$3:$CC$1003,$C24,MATCH(H$2,$N$2:$CC$2,0)))) | F24: =IF(I$2="","",IF($C24="X","",INDEX($N$3:$CC$1003,$C24,MATCH(I$2,$N$2:$CC$2,0)))) | G24: =IF(A24="","",IF(G$2="","", IF(D24="",IF($K$16="Use global average",D$276,IF($K$16="Use regional average",INDEX(D$280:D$296,MATCH($B24,$B$280:$B$296,0)),IF($K$16="Leave blank","",IF($K$16="Fill with zeros", 0,IF($K$16="Use global median",D$277,"Fill out I16"))))), D24))) -> 17603.566 | H24: =IF(H$2="","", IF(E24="",IF($K$16="Use global average",E$276,IF($K$16="Use regional average",INDEX(E$280:E$296,MATCH($B24,$B$280:$B$296,0)),IF($K$16="Leave blank","",IF($K$16="Fill with zeros", 0,IF($K$16="Use global median",E$277,"Fill out I16"))))), E24)) | I24: =IF(I$2="","", IF(F24="",IF($K$16="Use global average",F$276,IF($K$16="Use regional average",INDEX(F$280:F$296,MATCH($B24,$B$280:$B$296,0)),IF($K$16="Leave blank","",IF($K$16="Fill with zeros", 0,IF($K$16="Use global median",F$277,"Fill out I16"))))), F24)) | L24: =IF(M24="","",IF(COUNTIF(Countries!$B$1:$H$271,M24)>0,"",IF(COUNTIF(Countries!$M$1:$S$271,M24)>0,"Not a country","ERROR – NOT LISTED. Add alt spelling to ''Countries'' tab"))) | M24: Bhutan | N24: 13.86247 | O24: =N24*365*1.28 -> 6476.546 | P24: 0.3856096 | Q24: 0.0595 | R24: =IFERROR(O24/(P24*(1-Q24)),"") -> 17858.164
A25: =Countries!B24 -> Botswana | B25: =Countries!I24 -> Sub-Saharan Africa | C25: =IFERROR(IFERROR(IFERROR(IFERROR(IFERROR(IFERROR(IFERROR(MATCH(Countries!$B24,$M$3:$M$1003,0),MATCH(Countries!$C24,$M$3:$M$1003,0)),MATCH(Countries!$D24,$M$3:$M$1003,0)),MATCH(Countries!$E24,$M$3:$M$1003,0)),MATCH(Countries!$F24,$M$3:$M$1003,0)),MATCH(Countries!$G24,$M$3:$M$1003,0)),MATCH(Countries!$H24,$M$3:$M$1003,0)),"X") -> 25 | D25: =IF(G$2="","",IF($C25="X","",INDEX($N$3:$CC$1003,$C25,MATCH(G$2,$N$2:$CC$2,0)))) -> 5209.6018 | E25: =IF(H$2="","",IF($C25="X","",INDEX($N$3:$CC$1003,$C25,MATCH(H$2,$N$2:$CC$2,0)))) | F25: =IF(I$2="","",IF($C25="X","",INDEX($N$3:$CC$1003,$C25,MATCH(I$2,$N$2:$CC$2,0)))) | G25: =IF(A25="","",IF(G$2="","", IF(D25="",IF($K$16="Use global average",D$276,IF($K$16="Use regional average",INDEX(D$280:D$296,MATCH($B25,$B$280:$B$296,0)),IF($K$16="Leave blank","",IF($K$16="Fill with zeros", 0,IF($K$16="Use global median",D$277,"Fill out I16"))))), D25))) -> 5209.6018 | H25: =IF(H$2="","", IF(E25="",IF($K$16="Use global average",E$276,IF($K$16="Use regional average",INDEX(E$280:E$296,MATCH($B25,$B$280:$B$296,0)),IF($K$16="Leave blank","",IF($K$16="Fill with zeros", 0,IF($K$16="Use global median",E$277,"Fill out I16"))))), E25)) | I25: =IF(I$2="","", IF(F25="",IF($K$16="Use global average",F$276,IF($K$16="Use regional average",INDEX(F$280:F$296,MATCH($B25,$B$280:$B$296,0)),IF($K$16="Leave blank","",IF($K$16="Fill with zeros", 0,IF($K$16="Use global median",F$277,"Fill out I16"))))), F25)) | L25: =IF(M25="","",IF(COUNTIF(Countries!$B$1:$H$271,M25)>0,"",IF(COUNTIF(Countries!$M$1:$S$271,M25)>0,"Not a country","ERROR – NOT LISTED. Add alt spelling to ''Countries'' tab"))) | M25: Bolivia | N25: 14.911999 | O25: =N25*365*1.28 -> 6966.8859 | P25: 0.55500072 | Q25: 0.03552 | R25: =IFERROR(O25/(P25*(1-Q25)),"") -> 13015.232
A26: =Countries!B25 -> Brazil | B26: =Countries!I25 -> Latin America | C26: =IFERROR(IFERROR(IFERROR(IFERROR(IFERROR(IFERROR(IFERROR(MATCH(Countries!$B25,$M$3:$M$1003,0),MATCH(Countries!$C25,$M$3:$M$1003,0)),MATCH(Countries!$D25,$M$3:$M$1003,0)),MATCH(Countries!$E25,$M$3:$M$1003,0)),MATCH(Countries!$F25,$M$3:$M$1003,0)),MATCH(Countries!$G25,$M$3:$M$1003,0)),MATCH(Countries!$H25,$M$3:$M$1003,0)),"X") -> 26 | D26: =IF(G$2="","",IF($C26="X","",INDEX($N$3:$CC$1003,$C26,MATCH(G$2,$N$2:$CC$2,0)))) -> 15188.621 | E26: =IF(H$2="","",IF($C26="X","",INDEX($N$3:$CC$1003,$C26,MATCH(H$2,$N$2:$CC$2,0)))) | F26: =IF(I$2="","",IF($C26="X","",INDEX($N$3:$CC$1003,$C26,MATCH(I$2,$N$2:$CC$2,0)))) | G26: =IF(A26="","",IF(G$2="","", IF(D26="",IF($K$16="Use global average",D$276,IF($K$16="Use regional average",INDEX(D$280:D$296,MATCH($B26,$B$280:$B$296,0)),IF($K$16="Leave blank","",IF($K$16="Fill with zeros", 0,IF($K$16="Use global median",D$277,"Fill out I16"))))), D26))) -> 15188.621 | H26: =IF(H$2="","", IF(E26="",IF($K$16="Use global average",E$276,IF($K$16="Use regional average",INDEX(E$280:E$296,MATCH($B26,$B$280:$B$296,0)),IF($K$16="Leave blank","",IF($K$16="Fill with zeros", 0,IF($K$16="Use global median",E$277,"Fill out I16"))))), E26)) | I26: =IF(I$2="","", IF(F26="",IF($K$16="Use global average",F$276,IF($K$16="Use regional average",INDEX(F$280:F$296,MATCH($B26,$B$280:$B$296,0)),IF($K$16="Leave blank","",IF($K$16="Fill with zeros", 0,IF($K$16="Use global median",F$277,"Fill out I16"))))), F26)) | L26: =IF(M26="","",IF(COUNTIF(Countries!$B$1:$H$271,M26)>0,"",IF(COUNTIF(Countries!$M$1:$S$271,M26)>0,"Not a country","ERROR – NOT LISTED. Add alt spelling to ''Countries'' tab"))) | M26: Bosnia and Herzegovina | N26: 17.60119 | O26: =N26*365*1.28 -> 8223.276 | P26: 0.5348488 | Q26: 0.1266 | R26: =IFERROR(O26/(P26*(1-Q26)),"") -> 17603.566
A27: =Countries!B26 -> Brunei Darussalam | B27: =Countries!I26 -> Southeast Asia | C27: =IFERROR(IFERROR(IFERROR(IFERROR(IFERROR(IFERROR(IFERROR(MATCH(Countries!$B26,$M$3:$M$1003,0),MATCH(Countries!$C26,$M$3:$M$1003,0)),MATCH(Countries!$D26,$M$3:$M$1003,0)),MATCH(Countries!$E26,$M$3:$M$1003,0)),MATCH(Countries!$F26,$M$3:$M$1003,0)),MATCH(Countries!$G26,$M$3:$M$1003,0)),MATCH(Countries!$H26,$M$3:$M$1003,0)),"X") -> 27 | D27: =IF(G$2="","",IF($C27="X","",INDEX($N$3:$CC$1003,$C27,MATCH(G$2,$N$2:$CC$2,0)))) | E27: =IF(H$2="","",IF($C27="X","",INDEX($N$3:$CC$1003,$C27,MATCH(H$2,$N$2:$CC$2,0)))) | F27: =IF(I$2="","",IF($C27="X","",INDEX($N$3:$CC$1003,$C27,MATCH(I$2,$N$2:$CC$2,0)))) | G27: =IF(A27="","",IF(G$2="","", IF(D27="",IF($K$16="Use global average",D$276,IF($K$16="Use regional average",INDEX(D$280:D$296,MATCH($B27,$B$280:$B$296,0)),IF($K$16="Leave blank","",IF($K$16="Fill with zeros", 0,IF($K$16="Use global median",D$277,"Fill out I16"))))), D27))) -> 9788.6356 | H27: =IF(H$2="","", IF(E27="",IF($K$16="Use global average",E$276,IF($K$16="Use regional average",INDEX(E$280:E$296,MATCH($B27,$B$280:$B$296,0)),IF($K$16="Leave blank","",IF($K$16="Fill with zeros", 0,IF($K$16="Use global median",E$277,"Fill out I16"))))), E27)) | I27: =IF(I$2="","", IF(F27="",IF($K$16="Use global average",F$276,IF($K$16="Use regional average",INDEX(F$280:F$296,MATCH($B27,$B$280:$B$296,0)),IF($K$16="Leave blank","",IF($K$16="Fill with zeros", 0,IF($K$16="Use global median",F$277,"Fill out I16"))))), F27)) | L27: =IF(M27="","",IF(COUNTIF(Countries!$B$1:$H$271,M27)>0,"",IF(COUNTIF(Countries!$M$1:$S$271,M27)>0,"Not a country","ERROR – NOT LISTED. Add alt spelling to ''Countries'' tab"))) | M27: Botswana | N27: 4.842955 | O27: =N27*365*1.28 -> 2262.6286 | P27: 0.5686291 | Q27: 0.2362 | R27: =IFERROR(O27/(P27*(1-Q27)),"") -> 5209.6018
A28: =Countries!B27 -> Bulgaria | B28: =Countries!I27 -> Europe | C28: =IFERROR(IFERROR(IFERROR(IFERROR(IFERROR(IFERROR(IFERROR(MATCH(Countries!$B27,$M$3:$M$1003,0),MATCH(Countries!$C27,$M$3:$M$1003,0)),MATCH(Countries!$D27,$M$3:$M$1003,0)),MATCH(Countries!$E27,$M$3:$M$1003,0)),MATCH(Countries!$F27,$M$3:$M$1003,0)),MATCH(Countries!$G27,$M$3:$M$1003,0)),MATCH(Countries!$H27,$M$3:$M$1003,0)),"X") -> 28 | D28: =IF(G$2="","",IF($C28="X","",INDEX($N$3:$CC$1003,$C28,MATCH(G$2,$N$2:$CC$2,0)))) -> 19984.069 | E28: =IF(H$2="","",IF($C28="X","",INDEX($N$3:$CC$1003,$C28,MATCH(H$2,$N$2:$CC$2,0)))) | F28: =IF(I$2="","",IF($C28="X","",INDEX($N$3:$CC$1003,$C28,MATCH(I$2,$N$2:$CC$2,0)))) | G28: =IF(A28="","",IF(G$2="","", IF(D28="",IF($K$16="Use global average",D$276,IF($K$16="Use regional average",INDEX(D$280:D$296,MATCH($B28,$B$280:$B$296,0)),IF($K$16="Leave blank","",IF($K$16="Fill with zeros", 0,IF($K$16="Use global median",D$277,"Fill out I16"))))), D28))) -> 19984.069 | H28: =IF(H$2="","", IF(E28="",IF($K$16="Use global average",E$276,IF($K$16="Use regional average",INDEX(E$280:E$296,MATCH($B28,$B$280:$B$296,0)),IF($K$16="Leave blank","",IF($K$16="Fill with zeros", 0,IF($K$16="Use global median",E$277,"Fill out I16"))))), E28)) | I28: =IF(I$2="","", IF(F28="",IF($K$16="Use global average",F$276,IF($K$16="Use regional average",INDEX(F$280:F$296,MATCH($B28,$B$280:$B$296,0)),IF($K$16="Leave blank","",IF($K$16="Fill with zeros", 0,IF($K$16="Use global median",F$277,"Fill out I16"))))), F28)) | L28: =IF(M28="","",IF(COUNTIF(Countries!$B$1:$H$271,M28)>0,"",IF(COUNTIF(Countries!$M$1:$S$271,M28)>0,"Not a country","ERROR – NOT LISTED. Add alt spelling to ''Countries'' tab"))) | M28: Brazil | N28: 12.991237 | O28: =N28*365*1.28 -> 6069.5059 | P28: 0.4402432 | Q28: 0.0923 | R28: =IFERROR(O28/(P28*(1-Q28)),"") -> 15188.621
A29: =Countries!B28 -> Burkina Faso | B29: =Countries!I28 -> Sub-Saharan Africa | C29: =IFERROR(IFERROR(IFERROR(IFERROR(IFERROR(IFERROR(IFERROR(MATCH(Countries!$B28,$M$3:$M$1003,0),MATCH(Countries!$C28,$M$3:$M$1003,0)),MATCH(Countries!$D28,$M$3:$M$1003,0)),MATCH(Countries!$E28,$M$3:$M$1003,0)),MATCH(Countries!$F28,$M$3:$M$1003,0)),MATCH(Countries!$G28,$M$3:$M$1003,0)),MATCH(Countries!$H28,$M$3:$M$1003,0)),"X") -> 29 | D29: =IF(G$2="","",IF($C29="X","",INDEX($N$3:$CC$1003,$C29,MATCH(G$2,$N$2:$CC$2,0)))) -> 1875.3984 | E29: =IF(H$2="","",IF($C29="X","",INDEX($N$3:$CC$1003,$C29,MATCH(H$2,$N$2:$CC$2,0)))) | F29: =IF(I$2="","",IF($C29="X","",INDEX($N$3:$CC$1003,$C29,MATCH(I$2,$N$2:$CC$2,0)))) | G29: =IF(A29="","",IF(G$2="","", IF(D29="",IF($K$16="Use global average",D$276,IF($K$16="Use regional average",INDEX(D$280:D$296,MATCH($B29,$B$280:$B$296,0)),IF($K$16="Leave blank","",IF($K$16="Fill with zeros", 0,IF($K$16="Use global median",D$277,"Fill out I16"))))), D29))) -> 1875.3984 | H29: =IF(H$2="","", IF(E29="",IF($K$16="Use global average",E$276,IF($K$16="Use regional average",INDEX(E$280:E$296,MATCH($B29,$B$280:$B$296,0)),IF($K$16="Leave blank","",IF($K$16="Fill with zeros", 0,IF($K$16="Use global median",E$277,"Fill out I16"))))), E29)) | I29: =IF(I$2="","", IF(F29="",IF($K$16="Use global average",F$276,IF($K$16="Use regional average",INDEX(F$280:F$296,MATCH($B29,$B$280:$B$296,0)),IF($K$16="Leave blank","",IF($K$16="Fill with zeros", 0,IF($K$16="Use global median",F$277,"Fill out I16"))))), F29)) | L29: =IF(M29="","",IF(COUNTIF(Countries!$B$1:$H$271,M29)>0,"",IF(COUNTIF(Countries!$M$1:$S$271,M29)>0,"Not a country","ERROR – NOT LISTED. Add alt spelling to ''Countries'' tab"))) | M29: Brunei | N29: NA | O29: =N29*365*1.28 -> #VALUE! | P29: 0.3799826 | Q29: 0.04452 | R29: =IFERROR(O29/(P29*(1-Q29)),"")
A30: =Countries!B29 -> Burundi | B30: =Countries!I29 -> Sub-Saharan Africa | C30: =IFERROR(IFERROR(IFERROR(IFERROR(IFERROR(IFERROR(IFERROR(MATCH(Countries!$B29,$M$3:$M$1003,0),MATCH(Countries!$C29,$M$3:$M$1003,0)),MATCH(Countries!$D29,$M$3:$M$1003,0)),MATCH(Countries!$E29,$M$3:$M$1003,0)),MATCH(Countries!$F29,$M$3:$M$1003,0)),MATCH(Countries!$G29,$M$3:$M$1003,0)),MATCH(Countries!$H29,$M$3:$M$1003,0)),"X") -> 30 | D30: =IF(G$2="","",IF($C30="X","",INDEX($N$3:$CC$1003,$C30,MATCH(G$2,$N$2:$CC$2,0)))) -> 921.86838 | E30: =IF(H$2="","",IF($C30="X","",INDEX($N$3:$CC$1003,$C30,MATCH(H$2,$N$2:$CC$2,0)))) | F30: =IF(I$2="","",IF($C30="X","",INDEX($N$3:$CC$1003,$C30,MATCH(I$2,$N$2:$CC$2,0)))) | G30: =IF(A30="","",IF(G$2="","", IF(D30="",IF($K$16="Use global average",D$276,IF($K$16="Use regional average",INDEX(D$280:D$296,MATCH($B30,$B$280:$B$296,0)),IF($K$16="Leave blank","",IF($K$16="Fill with zeros", 0,IF($K$16="Use global median",D$277,"Fill out I16"))))), D30))) -> 921.86838 | H30: =IF(H$2="","", IF(E30="",IF($K$16="Use global average",E$276,IF($K$16="Use regional average",INDEX(E$280:E$296,MATCH($B30,$B$280:$B$296,0)),IF($K$16="Leave blank","",IF($K$16="Fill with zeros", 0,IF($K$16="Use global median",E$277,"Fill out I16"))))), E30)) | I30: =IF(I$2="","", IF(F30="",IF($K$16="Use global average",F$276,IF($K$16="Use regional average",INDEX(F$280:F$296,MATCH($B30,$B$280:$B$296,0)),IF($K$16="Leave blank","",IF($K$16="Fill with zeros", 0,IF($K$16="Use global median",F$277,"Fill out I16"))))), F30)) | L30: =IF(M30="","",IF(COUNTIF(Countries!$B$1:$H$271,M30)>0,"",IF(COUNTIF(Countries!$M$1:$S$271,M30)>0,"Not a country","ERROR – NOT LISTED. Add alt spelling to ''Countries'' tab"))) | M30: Bulgaria | N30: 23.402508 | O30: =N30*365*1.28 -> 10933.652 | P30: 0.5715224 | Q30: 0.0427 | R30: =IFERROR(O30/(P30*(1-Q30)),"") -> 19984.069
A31: =Countries!B30 -> Cambodia | B31: =Countries!I30 -> Southeast Asia | C31: =IFERROR(IFERROR(IFERROR(IFERROR(IFERROR(IFERROR(IFERROR(MATCH(Countries!$B30,$M$3:$M$1003,0),MATCH(Countries!$C30,$M$3:$M$1003,0)),MATCH(Countries!$D30,$M$3:$M$1003,0)),MATCH(Countries!$E30,$M$3:$M$1003,0)),MATCH(Countries!$F30,$M$3:$M$1003,0)),MATCH(Countries!$G30,$M$3:$M$1003,0)),MATCH(Countries!$H30,$M$3:$M$1003,0)),"X") -> 31 | D31: =IF(G$2="","",IF($C31="X","",INDEX($N$3:$CC$1003,$C31,MATCH(G$2,$N$2:$CC$2,0)))) | E31: =IF(H$2="","",IF($C31="X","",INDEX($N$3:$CC$1003,$C31,MATCH(H$2,$N$2:$CC$2,0)))) | F31: =IF(I$2="","",IF($C31="X","",INDEX($N$3:$CC$1003,$C31,MATCH(I$2,$N$2:$CC$2,0)))) | G31: =IF(A31="","",IF(G$2="","", IF(D31="",IF($K$16="Use global average",D$276,IF($K$16="Use regional average",INDEX(D$280:D$296,MATCH($B31,$B$280:$B$296,0)),IF($K$16="Leave blank","",IF($K$16="Fill with zeros", 0,IF($K$16="Use global median",D$277,"Fill out I16"))))), D31))) -> 9788.6356 | H31: =IF(H$2="","", IF(E31="",IF($K$16="Use global average",E$276,IF($K$16="Use regional average",INDEX(E$280:E$296,MATCH($B31,$B$280:$B$296,0)),IF($K$16="Leave blank","",IF($K$16="Fill with zeros", 0,IF($K$16="Use global median",E$277,"Fill out I16"))))), E31)) | I31: =IF(I$2="","", IF(F31="",IF($K$16="Use global average",F$276,IF($K$16="Use regional average",INDEX(F$280:F$296,MATCH($B31,$B$280:$B$296,0)),IF($K$16="Leave blank","",IF($K$16="Fill with zeros", 0,IF($K$16="Use global median",F$277,"Fill out I16"))))), F31)) | L31: =IF(M31="","",IF(COUNTIF(Countries!$B$1:$H$271,M31)>0,"",IF(COUNTIF(Countries!$M$1:$S$271,M31)>0,"Not a country","ERROR – NOT LISTED. Add alt spelling to ''Countries'' tab"))) | M31: Burkina Faso | N31: 3.1207023 | O31: =N31*365*1.28 -> 1457.9921 | P31: 0.8189083 | Q31: 0.05065 | R31: =IFERROR(O31/(P31*(1-Q31)),"") -> 1875.3984
A32: =Countries!B31 -> Cameroon | B32: =Countries!I31 -> Sub-Saharan Africa | C32: =IFERROR(IFERROR(IFERROR(IFERROR(IFERROR(IFERROR(IFERROR(MATCH(Countries!$B31,$M$3:$M$1003,0),MATCH(Countries!$C31,$M$3:$M$1003,0)),MATCH(Countries!$D31,$M$3:$M$1003,0)),MATCH(Countries!$E31,$M$3:$M$1003,0)),MATCH(Countries!$F31,$M$3:$M$1003,0)),MATCH(Countries!$G31,$M$3:$M$1003,0)),MATCH(Countries!$H31,$M$3:$M$1003,0)),"X") -> 32 | D32: =IF(G$2="","",IF($C32="X","",INDEX($N$3:$CC$1003,$C32,MATCH(G$2,$N$2:$CC$2,0)))) -> 2363.5434 | E32: =IF(H$2="","",IF($C32="X","",INDEX($N$3:$CC$1003,$C32,MATCH(H$2,$N$2:$CC$2,0)))) | F32: =IF(I$2="","",IF($C32="X","",INDEX($N$3:$CC$1003,$C32,MATCH(I$2,$N$2:$CC$2,0)))) | G32: =IF(A32="","",IF(G$2="","", IF(D32="",IF($K$16="Use global average",D$276,IF($K$16="Use regional average",INDEX(D$280:D$296,MATCH($B32,$B$280:$B$296,0)),IF($K$16="Leave blank","",IF($K$16="Fill with zeros", 0,IF($K$16="Use global median",D$277,"Fill out I16"))))), D32))) -> 2363.5434 | H32: =IF(H$2="","", IF(E32="",IF($K$16="Use global average",E$276,IF($K$16="Use regional average",INDEX(E$280:E$296,MATCH($B32,$B$280:$B$296,0)),IF($K$16="Leave blank","",IF($K$16="Fill with zeros", 0,IF($K$16="Use global median",E$277,"Fill out I16"))))), E32)) | I32: =IF(I$2="","", IF(F32="",IF($K$16="Use global average",F$276,IF($K$16="Use regional average",INDEX(F$280:F$296,MATCH($B32,$B$280:$B$296,0)),IF($K$16="Leave blank","",IF($K$16="Fill with zeros", 0,IF($K$16="Use global median",F$277,"Fill out I16"))))), F32)) | L32: =IF(M32="","",IF(COUNTIF(Countries!$B$1:$H$271,M32)>0,"",IF(COUNTIF(Countries!$M$1:$S$271,M32)>0,"Not a country","ERROR – NOT LISTED. Add alt spelling to ''Countries'' tab"))) | M32: Burundi | N32: 1.795875 | O32: =N32*365*1.28 -> 839.0328 | P32: 0.9184651 | Q32: 0.00906 | R32: =IFERROR(O32/(P32*(1-Q32)),"") -> 921.86838
A33: =Countries!B32 -> Canada | B33: =Countries!I32 -> North America | C33: =IFERROR(IFERROR(IFERROR(IFERROR(IFERROR(IFERROR(IFERROR(MATCH(Countries!$B32,$M$3:$M$1003,0),MATCH(Countries!$C32,$M$3:$M$1003,0)),MATCH(Countries!$D32,$M$3:$M$1003,0)),MATCH(Countries!$E32,$M$3:$M$1003,0)),MATCH(Countries!$F32,$M$3:$M$1003,0)),MATCH(Countries!$G32,$M$3:$M$1003,0)),MATCH(Countries!$H32,$M$3:$M$1003,0)),"X") -> 33 | D33: =IF(G$2="","",IF($C33="X","",INDEX($N$3:$CC$1003,$C33,MATCH(G$2,$N$2:$CC$2,0)))) -> 52398.103 | E33: =IF(H$2="","",IF($C33="X","",INDEX($N$3:$CC$1003,$C33,MATCH(H$2,$N$2:$CC$2,0)))) | F33: =IF(I$2="","",IF($C33="X","",INDEX($N$3:$CC$1003,$C33,MATCH(I$2,$N$2:$CC$2,0)))) | G33: =IF(A33="","",IF(G$2="","", IF(D33="",IF($K$16="Use global average",D$276,IF($K$16="Use regional average",INDEX(D$280:D$296,MATCH($B33,$B$280:$B$296,0)),IF($K$16="Leave blank","",IF($K$16="Fill with zeros", 0,IF($K$16="Use global median",D$277,"Fill out I16"))))), D33))) -> 52398.103 | H33: =IF(H$2="","", IF(E33="",IF($K$16="Use global average",E$276,IF($K$16="Use regional average",INDEX(E$280:E$296,MATCH($B33,$B$280:$B$296,0)),IF($K$16="Leave blank","",IF($K$16="Fill with zeros", 0,IF($K$16="Use global median",E$277,"Fill out I16"))))), E33)) | I33: =IF(I$2="","", IF(F33="",IF($K$16="Use global average",F$276,IF($K$16="Use regional average",INDEX(F$280:F$296,MATCH($B33,$B$280:$B$296,0)),IF($K$16="Leave blank","",IF($K$16="Fill with zeros", 0,IF($K$16="Use global median",F$277,"Fill out I16"))))), F33)) | L33: =IF(M33="","",IF(COUNTIF(Countries!$B$1:$H$271,M33)>0,"",IF(COUNTIF(Countries!$M$1:$S$271,M33)>0,"Not a country","ERROR – NOT LISTED. Add alt spelling to ''Countries'' tab"))) | M33: Cambodia | N33: NA | O33: =N33*365*1.28 -> #VALUE! | P33: 0.56424873 | Q33: 0.00226 | R33: =IFERROR(O33/(P33*(1-Q33)),"")
A34: =Countries!B33 -> Cape Verde | B34: =Countries!I33 -> Sub-Saharan Africa | C34: =IFERROR(IFERROR(IFERROR(IFERROR(IFERROR(IFERROR(IFERROR(MATCH(Countries!$B33,$M$3:$M$1003,0),MATCH(Countries!$C33,$M$3:$M$1003,0)),MATCH(Countries!$D33,$M$3:$M$1003,0)),MATCH(Countries!$E33,$M$3:$M$1003,0)),MATCH(Countries!$F33,$M$3:$M$1003,0)),MATCH(Countries!$G33,$M$3:$M$1003,0)),MATCH(Countries!$H33,$M$3:$M$1003,0)),"X") -> 34 | D34: =IF(G$2="","",IF($C34="X","",INDEX($N$3:$CC$1003,$C34,MATCH(G$2,$N$2:$CC$2,0)))) -> 7304.7543 | E34: =IF(H$2="","",IF($C34="X","",INDEX($N$3:$CC$1003,$C34,MATCH(H$2,$N$2:$CC$2,0)))) | F34: =IF(I$2="","",IF($C34="X","",INDEX($N$3:$CC$1003,$C34,MATCH(I$2,$N$2:$CC$2,0)))) | G34: =IF(A34="","",IF(G$2="","", IF(D34="",IF($K$16="Use global average",D$276,IF($K$16="Use regional average",INDEX(D$280:D$296,MATCH($B34,$B$280:$B$296,0)),IF($K$16="Leave blank","",IF($K$16="Fill with zeros", 0,IF($K$16="Use global median",D$277,"Fill out I16"))))), D34))) -> 7304.7543 | H34: =IF(H$2="","", IF(E34="",IF($K$16="Use global average",E$276,IF($K$16="Use regional average",INDEX(E$280:E$296,MATCH($B34,$B$280:$B$296,0)),IF($K$16="Leave blank","",IF($K$16="Fill with zeros", 0,IF($K$16="Use global median",E$277,"Fill out I16"))))), E34)) | I34: =IF(I$2="","", IF(F34="",IF($K$16="Use global average",F$276,IF($K$16="Use regional average",INDEX(F$280:F$296,MATCH($B34,$B$280:$B$296,0)),IF($K$16="Leave blank","",IF($K$16="Fill with zeros", 0,IF($K$16="Use global median",F$277,"Fill out I16"))))), F34)) | L34: =IF(M34="","",IF(COUNTIF(Countries!$B$1:$H$271,M34)>0,"",IF(COUNTIF(Countries!$M$1:$S$271,M34)>0,"Not a country","ERROR – NOT LISTED. Add alt spelling to ''Countries'' tab"))) | M34: Cameroon | N34: 3.9085712 | O34: =N34*365*1.28 -> 1826.0845 | P34: 0.802948 | Q34: 0.03779 | R34: =IFERROR(O34/(P34*(1-Q34)),"") -> 2363.5434
A35: =Countries!B34 -> Central African Republic | B35: =Countries!I34 -> Sub-Saharan Africa | C35: =IFERROR(IFERROR(IFERROR(IFERROR(IFERROR(IFERROR(IFERROR(MATCH(Countries!$B34,$M$3:$M$1003,0),MATCH(Countries!$C34,$M$3:$M$1003,0)),MATCH(Countries!$D34,$M$3:$M$1003,0)),MATCH(Countries!$E34,$M$3:$M$1003,0)),MATCH(Countries!$F34,$M$3:$M$1003,0)),MATCH(Countries!$G34,$M$3:$M$1003,0)),MATCH(Countries!$H34,$M$3:$M$1003,0)),"X") -> 35 | D35: =IF(G$2="","",IF($C35="X","",INDEX($N$3:$CC$1003,$C35,MATCH(G$2,$N$2:$CC$2,0)))) -> 742.99675 | E35: =IF(H$2="","",IF($C35="X","",INDEX($N$3:$CC$1003,$C35,MATCH(H$2,$N$2:$CC$2,0)))) | F35: =IF(I$2="","",IF($C35="X","",INDEX($N$3:$CC$1003,$C35,MATCH(I$2,$N$2:$CC$2,0)))) | G35: =IF(A35="","",IF(G$2="","", IF(D35="",IF($K$16="Use global average",D$276,IF($K$16="Use regional average",INDEX(D$280:D$296,MATCH($B35,$B$280:$B$296,0)),IF($K$16="Leave blank","",IF($K$16="Fill with zeros", 0,IF($K$16="Use global median",D$277,"Fill out I16"))))), D35))) -> 742.99675 | H35: =IF(H$2="","", IF(E35="",IF($K$16="Use global average",E$276,IF($K$16="Use regional average",INDEX(E$280:E$296,MATCH($B35,$B$280:$B$296,0)),IF($K$16="Leave blank","",IF($K$16="Fill with zeros", 0,IF($K$16="Use global median",E$277,"Fill out I16"))))), E35)) | I35: =IF(I$2="","", IF(F35="",IF($K$16="Use global average",F$276,IF($K$16="Use regional average",INDEX(F$280:F$296,MATCH($B35,$B$280:$B$296,0)),IF($K$16="Leave blank","",IF($K$16="Fill with zeros", 0,IF($K$16="Use global median",F$277,"Fill out I16"))))), F35)) | L35: =IF(M35="","",IF(COUNTIF(Countries!$B$1:$H$271,M35)>0,"",IF(COUNTIF(Countries!$M$1:$S$271,M35)>0,"Not a country","ERROR – NOT LISTED. Add alt spelling to ''Countries'' tab"))) | M35: Canada | N35: 56.303295 | O35: =N35*365*1.28 -> 26304.899 | P35: 0.5300043 | Q35: 0.0528 | R35: =IFERROR(O35/(P35*(1-Q35)),"") -> 52398.103
A36: =Countries!B35 -> Chad | B36: =Countries!I35 -> Sub-Saharan Africa | C36: =IFERROR(IFERROR(IFERROR(IFERROR(IFERROR(IFERROR(IFERROR(MATCH(Countries!$B35,$M$3:$M$1003,0),MATCH(Countries!$C35,$M$3:$M$1003,0)),MATCH(Countries!$D35,$M$3:$M$1003,0)),MATCH(Countries!$E35,$M$3:$M$1003,0)),MATCH(Countries!$F35,$M$3:$M$1003,0)),MATCH(Countries!$G35,$M$3:$M$1003,0)),MATCH(Countries!$H35,$M$3:$M$1003,0)),"X") -> 36 | D36: =IF(G$2="","",IF($C36="X","",INDEX($N$3:$CC$1003,$C36,MATCH(G$2,$N$2:$CC$2,0)))) -> 1539.0383 | E36: =IF(H$2="","",IF($C36="X","",INDEX($N$3:$CC$1003,$C36,MATCH(H$2,$N$2:$CC$2,0)))) | F36: =IF(I$2="","",IF($C36="X","",INDEX($N$3:$CC$1003,$C36,MATCH(I$2,$N$2:$CC$2,0)))) | G36: =IF(A36="","",IF(G$2="","", IF(D36="",IF($K$16="Use global average",D$276,IF($K$16="Use regional average",INDEX(D$280:D$296,MATCH($B36,$B$280:$B$296,0)),IF($K$16="Leave blank","",IF($K$16="Fill with zeros", 0,IF($K$16="Use global median",D$277,"Fill out I16"))))), D36))) -> 1539.0383 | H36: =IF(H$2="","", IF(E36="",IF($K$16="Use global average",E$276,IF($K$16="Use regional average",INDEX(E$280:E$296,MATCH($B36,$B$280:$B$296,0)),IF($K$16="Leave blank","",IF($K$16="Fill with zeros", 0,IF($K$16="Use global median",E$277,"Fill out I16"))))), E36)) | I36: =IF(I$2="","", IF(F36="",IF($K$16="Use global average",F$276,IF($K$16="Use regional average",INDEX(F$280:F$296,MATCH($B36,$B$280:$B$296,0)),IF($K$16="Leave blank","",IF($K$16="Fill with zeros", 0,IF($K$16="Use global median",F$277,"Fill out I16"))))), F36)) | L36: =IF(M36="","",IF(COUNTIF(Countries!$B$1:$H$271,M36)>0,"",IF(COUNTIF(Countries!$M$1:$S$271,M36)>0,"Not a country","ERROR – NOT LISTED. Add alt spelling to ''Countries'' tab"))) | M36: Cape Verde | N36: 6.7278094 | O36: =N36*365*1.28 -> 3143.2326 | P36: 0.49143394 | Q36: 0.1244 | R36: =IFERROR(O36/(P36*(1-Q36)),"") -> 7304.7543
A37: =Countries!B36 -> Chile | B37: =Countries!I36 -> Latin America | C37: =IFERROR(IFERROR(IFERROR(IFERROR(IFERROR(IFERROR(IFERROR(MATCH(Countries!$B36,$M$3:$M$1003,0),MATCH(Countries!$C36,$M$3:$M$1003,0)),MATCH(Countries!$D36,$M$3:$M$1003,0)),MATCH(Countries!$E36,$M$3:$M$1003,0)),MATCH(Countries!$F36,$M$3:$M$1003,0)),MATCH(Countries!$G36,$M$3:$M$1003,0)),MATCH(Countries!$H36,$M$3:$M$1003,0)),"X") -> 37 | D37: =IF(G$2="","",IF($C37="X","",INDEX($N$3:$CC$1003,$C37,MATCH(G$2,$N$2:$CC$2,0)))) -> 22587.333 | E37: =IF(H$2="","",IF($C37="X","",INDEX($N$3:$CC$1003,$C37,MATCH(H$2,$N$2:$CC$2,0)))) | F37: =IF(I$2="","",IF($C37="X","",INDEX($N$3:$CC$1003,$C37,MATCH(I$2,$N$2:$CC$2,0)))) | G37: =IF(A37="","",IF(G$2="","", IF(D37="",IF($K$16="Use global average",D$276,IF($K$16="Use regional average",INDEX(D$280:D$296,MATCH($B37,$B$280:$B$296,0)),IF($K$16="Leave blank","",IF($K$16="Fill with zeros", 0,IF($K$16="Use global median",D$277,"Fill out I16"))))), D37))) -> 22587.333 | H37: =IF(H$2="","", IF(E37="",IF($K$16="Use global average",E$276,IF($K$16="Use regional average",INDEX(E$280:E$296,MATCH($B37,$B$280:$B$296,0)),IF($K$16="Leave blank","",IF($K$16="Fill with zeros", 0,IF($K$16="Use global median",E$277,"Fill out I16"))))), E37)) | I37: =IF(I$2="","", IF(F37="",IF($K$16="Use global average",F$276,IF($K$16="Use regional average",INDEX(F$280:F$296,MATCH($B37,$B$280:$B$296,0)),IF($K$16="Leave blank","",IF($K$16="Fill with zeros", 0,IF($K$16="Use global median",F$277,"Fill out I16"))))), F37)) | L37: =IF(M37="","",IF(COUNTIF(Countries!$B$1:$H$271,M37)>0,"",IF(COUNTIF(Countries!$M$1:$S$271,M37)>0,"Not a country","ERROR – NOT LISTED. Add alt spelling to ''Countries'' tab"))) | M37: Central African Republic | N37: 1.5665926 | O37: =N37*365*1.28 -> 731.91206 | P37: 1.0517741 | Q37: 0.06341 | R37: =IFERROR(O37/(P37*(1-Q37)),"") -> 742.99675
A38: =Countries!B37 -> China | B38: =Countries!I37 -> East Asia | C38: =IFERROR(IFERROR(IFERROR(IFERROR(IFERROR(IFERROR(IFERROR(MATCH(Countries!$B37,$M$3:$M$1003,0),MATCH(Countries!$C37,$M$3:$M$1003,0)),MATCH(Countries!$D37,$M$3:$M$1003,0)),MATCH(Countries!$E37,$M$3:$M$1003,0)),MATCH(Countries!$F37,$M$3:$M$1003,0)),MATCH(Countries!$G37,$M$3:$M$1003,0)),MATCH(Countries!$H37,$M$3:$M$1003,0)),"X") -> 38 | D38: =IF(G$2="","",IF($C38="X","",INDEX($N$3:$CC$1003,$C38,MATCH(G$2,$N$2:$CC$2,0)))) -> 11426.329 | E38: =IF(H$2="","",IF($C38="X","",INDEX($N$3:$CC$1003,$C38,MATCH(H$2,$N$2:$CC$2,0)))) | F38: =IF(I$2="","",IF($C38="X","",INDEX($N$3:$CC$1003,$C38,MATCH(I$2,$N$2:$CC$2,0)))) | G38: =IF(A38="","",IF(G$2="","", IF(D38="",IF($K$16="Use global average",D$276,IF($K$16="Use regional average",INDEX(D$280:D$296,MATCH($B38,$B$280:$B$296,0)),IF($K$16="Leave blank","",IF($K$16="Fill with zeros", 0,IF($K$16="Use global median",D$277,"Fill out I16"))))), D38))) -> 11426.329 | H38: =IF(H$2="","", IF(E38="",IF($K$16="Use global average",E$276,IF($K$16="Use regional average",INDEX(E$280:E$296,MATCH($B38,$B$280:$B$296,0)),IF($K$16="Leave blank","",IF($K$16="Fill with zeros", 0,IF($K$16="Use global median",E$277,"Fill out I16"))))), E38)) | I38: =IF(I$2="","", IF(F38="",IF($K$16="Use global average",F$276,IF($K$16="Use regional average",INDEX(F$280:F$296,MATCH($B38,$B$280:$B$296,0)),IF($K$16="Leave blank","",IF($K$16="Fill with zeros", 0,IF($K$16="Use global median",F$277,"Fill out I16"))))), F38)) | L38: =IF(M38="","",IF(COUNTIF(Countries!$B$1:$H$271,M38)>0,"",IF(COUNTIF(Countries!$M$1:$S$271,M38)>0,"Not a country","ERROR – NOT LISTED. Add alt spelling to ''Countries'' tab"))) | M38: Chad | N38: 3.106669 | O38: =N38*365*1.28 -> 1451.4358 | P38: 0.95356895 | Q38: 0.011 | R38: =IFERROR(O38/(P38*(1-Q38)),"") -> 1539.0383
A39: =Countries!B38 -> Colombia | B39: =Countries!I38 -> Latin America | C39: =IFERROR(IFERROR(IFERROR(IFERROR(IFERROR(IFERROR(IFERROR(MATCH(Countries!$B38,$M$3:$M$1003,0),MATCH(Countries!$C38,$M$3:$M$1003,0)),MATCH(Countries!$D38,$M$3:$M$1003,0)),MATCH(Countries!$E38,$M$3:$M$1003,0)),MATCH(Countries!$F38,$M$3:$M$1003,0)),MATCH(Countries!$G38,$M$3:$M$1003,0)),MATCH(Countries!$H38,$M$3:$M$1003,0)),"X") -> 39 | D39: =IF(G$2="","",IF($C39="X","",INDEX($N$3:$CC$1003,$C39,MATCH(G$2,$N$2:$CC$2,0)))) -> 11818.448 | E39: =IF(H$2="","",IF($C39="X","",INDEX($N$3:$CC$1003,$C39,MATCH(H$2,$N$2:$CC$2,0)))) | F39: =IF(I$2="","",IF($C39="X","",INDEX($N$3:$CC$1003,$C39,MATCH(I$2,$N$2:$CC$2,0)))) | G39: =IF(A39="","",IF(G$2="","", IF(D39="",IF($K$16="Use global average",D$276,IF($K$16="Use regional average",INDEX(D$280:D$296,MATCH($B39,$B$280:$B$296,0)),IF($K$16="Leave blank","",IF($K$16="Fill with zeros", 0,IF($K$16="Use global median",D$277,"Fill out I16"))))), D39))) -> 11818.448 | H39: =IF(H$2="","", IF(E39="",IF($K$16="Use global average",E$276,IF($K$16="Use regional average",INDEX(E$280:E$296,MATCH($B39,$B$280:$B$296,0)),IF($K$16="Leave blank","",IF($K$16="Fill with zeros", 0,IF($K$16="Use global median",E$277,"Fill out I16"))))), E39)) | I39: =IF(I$2="","", IF(F39="",IF($K$16="Use global average",F$276,IF($K$16="Use regional average",INDEX(F$280:F$296,MATCH($B39,$B$280:$B$296,0)),IF($K$16="Leave blank","",IF($K$16="Fill with zeros", 0,IF($K$16="Use global median",F$277,"Fill out I16"))))), F39)) | L39: =IF(M39="","",IF(COUNTIF(Countries!$B$1:$H$271,M39)>0,"",IF(COUNTIF(Countries!$M$1:$S$271,M39)>0,"Not a country","ERROR – NOT LISTED. Add alt spelling to ''Countries'' tab"))) | M39: Chile | N39: 19.984573 | O39: =N39*365*1.28 -> 9336.7925 | P39: 0.45053307 | Q39: 0.0825 | R39: =IFERROR(O39/(P39*(1-Q39)),"") -> 22587.333
A40: =Countries!B39 -> Comoros | B40: =Countries!I39 -> Sub-Saharan Africa | C40: =IFERROR(IFERROR(IFERROR(IFERROR(IFERROR(IFERROR(IFERROR(MATCH(Countries!$B39,$M$3:$M$1003,0),MATCH(Countries!$C39,$M$3:$M$1003,0)),MATCH(Countries!$D39,$M$3:$M$1003,0)),MATCH(Countries!$E39,$M$3:$M$1003,0)),MATCH(Countries!$F39,$M$3:$M$1003,0)),MATCH(Countries!$G39,$M$3:$M$1003,0)),MATCH(Countries!$H39,$M$3:$M$1003,0)),"X") -> 40 | D40: =IF(G$2="","",IF($C40="X","",INDEX($N$3:$CC$1003,$C40,MATCH(G$2,$N$2:$CC$2,0)))) -> 3020.023 | E40: =IF(H$2="","",IF($C40="X","",INDEX($N$3:$CC$1003,$C40,MATCH(H$2,$N$2:$CC$2,0)))) | F40: =IF(I$2="","",IF($C40="X","",INDEX($N$3:$CC$1003,$C40,MATCH(I$2,$N$2:$CC$2,0)))) | G40: =IF(A40="","",IF(G$2="","", IF(D40="",IF($K$16="Use global average",D$276,IF($K$16="Use regional average",INDEX(D$280:D$296,MATCH($B40,$B$280:$B$296,0)),IF($K$16="Leave blank","",IF($K$16="Fill with zeros", 0,IF($K$16="Use global median",D$277,"Fill out I16"))))), D40))) -> 3020.023 | H40: =IF(H$2="","", IF(E40="",IF($K$16="Use global average",E$276,IF($K$16="Use regional average",INDEX(E$280:E$296,MATCH($B40,$B$280:$B$296,0)),IF($K$16="Leave blank","",IF($K$16="Fill with zeros", 0,IF($K$16="Use global median",E$277,"Fill out I16"))))), E40)) | I40: =IF(I$2="","", IF(F40="",IF($K$16="Use global average",F$276,IF($K$16="Use regional average",INDEX(F$280:F$296,MATCH($B40,$B$280:$B$296,0)),IF($K$16="Leave blank","",IF($K$16="Fill with zeros", 0,IF($K$16="Use global median",F$277,"Fill out I16"))))), F40)) | L40: =IF(M40="","",IF(COUNTIF(Countries!$B$1:$H$271,M40)>0,"",IF(COUNTIF(Countries!$M$1:$S$271,M40)>0,"Not a country","ERROR – NOT LISTED. Add alt spelling to ''Countries'' tab"))) | M40: China | N40: 10.393845 | O40: =N40*365*1.28 -> 4856.0044 | P40: 0.44725716 | Q40: 0.0498 | R40: =IFERROR(O40/(P40*(1-Q40)),"") -> 11426.329
A41: =Countries!B40 -> Congo | B41: =Countries!I40 -> Sub-Saharan Africa | C41: =IFERROR(IFERROR(IFERROR(IFERROR(IFERROR(IFERROR(IFERROR(MATCH(Countries!$B40,$M$3:$M$1003,0),MATCH(Countries!$C40,$M$3:$M$1003,0)),MATCH(Countries!$D40,$M$3:$M$1003,0)),MATCH(Countries!$E40,$M$3:$M$1003,0)),MATCH(Countries!$F40,$M$3:$M$1003,0)),MATCH(Countries!$G40,$M$3:$M$1003,0)),MATCH(Countries!$H40,$M$3:$M$1003,0)),"X") -> 41 | D41: =IF(G$2="","",IF($C41="X","",INDEX($N$3:$CC$1003,$C41,MATCH(G$2,$N$2:$CC$2,0)))) -> 2246.8536 | E41: =IF(H$2="","",IF($C41="X","",INDEX($N$3:$CC$1003,$C41,MATCH(H$2,$N$2:$CC$2,0)))) | F41: =IF(I$2="","",IF($C41="X","",INDEX($N$3:$CC$1003,$C41,MATCH(I$2,$N$2:$CC$2,0)))) | G41: =IF(A41="","",IF(G$2="","", IF(D41="",IF($K$16="Use global average",D$276,IF($K$16="Use regional average",INDEX(D$280:D$296,MATCH($B41,$B$280:$B$296,0)),IF($K$16="Leave blank","",IF($K$16="Fill with zeros", 0,IF($K$16="Use global median",D$277,"Fill out I16"))))), D41))) -> 2246.8536 | H41: =IF(H$2="","", IF(E41="",IF($K$16="Use global average",E$276,IF($K$16="Use regional average",INDEX(E$280:E$296,MATCH($B41,$B$280:$B$296,0)),IF($K$16="Leave blank","",IF($K$16="Fill with zeros", 0,IF($K$16="Use global median",E$277,"Fill out I16"))))), E41)) | I41: =IF(I$2="","", IF(F41="",IF($K$16="Use global average",F$276,IF($K$16="Use regional average",INDEX(F$280:F$296,MATCH($B41,$B$280:$B$296,0)),IF($K$16="Leave blank","",IF($K$16="Fill with zeros", 0,IF($K$16="Use global median",F$277,"Fill out I16"))))), F41)) | L41: =IF(M41="","",IF(COUNTIF(Countries!$B$1:$H$271,M41)>0,"",IF(COUNTIF(Countries!$M$1:$S$271,M41)>0,"Not a country","ERROR – NOT LISTED. Add alt spelling to ''Countries'' tab"))) | M41: Colombia | N41: 9.6840725 | O41: =N41*365*1.28 -> 4524.3987 | P41: 0.42797665 | Q41: 0.1055 | R41: =IFERROR(O41/(P41*(1-Q41)),"") -> 11818.448
A42: =Countries!B41 -> Cook Islands | B42: =Countries!I41 -> Oceania | C42: =IFERROR(IFERROR(IFERROR(IFERROR(IFERROR(IFERROR(IFERROR(MATCH(Countries!$B41,$M$3:$M$1003,0),MATCH(Countries!$C41,$M$3:$M$1003,0)),MATCH(Countries!$D41,$M$3:$M$1003,0)),MATCH(Countries!$E41,$M$3:$M$1003,0)),MATCH(Countries!$F41,$M$3:$M$1003,0)),MATCH(Countries!$G41,$M$3:$M$1003,0)),MATCH(Countries!$H41,$M$3:$M$1003,0)),"X") -> 42 | D42: =IF(G$2="","",IF($C42="X","",INDEX($N$3:$CC$1003,$C42,MATCH(G$2,$N$2:$CC$2,0)))) | E42: =IF(H$2="","",IF($C42="X","",INDEX($N$3:$CC$1003,$C42,MATCH(H$2,$N$2:$CC$2,0)))) | F42: =IF(I$2="","",IF($C42="X","",INDEX($N$3:$CC$1003,$C42,MATCH(I$2,$N$2:$CC$2,0)))) | G42: =IF(A42="","",IF(G$2="","", IF(D42="",IF($K$16="Use global average",D$276,IF($K$16="Use regional average",INDEX(D$280:D$296,MATCH($B42,$B$280:$B$296,0)),IF($K$16="Leave blank","",IF($K$16="Fill with zeros", 0,IF($K$16="Use global median",D$277,"Fill out I16"))))), D42))) -> 4193.5801 | H42: =IF(H$2="","", IF(E42="",IF($K$16="Use global average",E$276,IF($K$16="Use regional average",INDEX(E$280:E$296,MATCH($B42,$B$280:$B$296,0)),IF($K$16="Leave blank","",IF($K$16="Fill with zeros", 0,IF($K$16="Use global median",E$277,"Fill out I16"))))), E42)) | I42: =IF(I$2="","", IF(F42="",IF($K$16="Use global average",F$276,IF($K$16="Use regional average",INDEX(F$280:F$296,MATCH($B42,$B$280:$B$296,0)),IF($K$16="Leave blank","",IF($K$16="Fill with zeros", 0,IF($K$16="Use global median",F$277,"Fill out I16"))))), F42)) | L42: =IF(M42="","",IF(COUNTIF(Countries!$B$1:$H$271,M42)>0,"",IF(COUNTIF(Countries!$M$1:$S$271,M42)>0,"Not a country","ERROR – NOT LISTED. Add alt spelling to ''Countries'' tab"))) | M42: Comoros | N42: 4.389313 | O42: =N42*365*1.28 -> 2050.687 | P42: 0.7204183 | Q42: 0.05745 | R42: =IFERROR(O42/(P42*(1-Q42)),"") -> 3020.023
A43: =Countries!B42 -> Costa Rica | B43: =Countries!I42 -> Latin America | C43: =IFERROR(IFERROR(IFERROR(IFERROR(IFERROR(IFERROR(IFERROR(MATCH(Countries!$B42,$M$3:$M$1003,0),MATCH(Countries!$C42,$M$3:$M$1003,0)),MATCH(Countries!$D42,$M$3:$M$1003,0)),MATCH(Countries!$E42,$M$3:$M$1003,0)),MATCH(Countries!$F42,$M$3:$M$1003,0)),MATCH(Countries!$G42,$M$3:$M$1003,0)),MATCH(Countries!$H42,$M$3:$M$1003,0)),"X") -> 43 | D43: =IF(G$2="","",IF($C43="X","",INDEX($N$3:$CC$1003,$C43,MATCH(G$2,$N$2:$CC$2,0)))) -> 18562.651 | E43: =IF(H$2="","",IF($C43="X","",INDEX($N$3:$CC$1003,$C43,MATCH(H$2,$N$2:$CC$2,0)))) | F43: =IF(I$2="","",IF($C43="X","",INDEX($N$3:$CC$1003,$C43,MATCH(I$2,$N$2:$CC$2,0)))) | G43: =IF(A43="","",IF(G$2="","", IF(D43="",IF($K$16="Use global average",D$276,IF($K$16="Use regional average",INDEX(D$280:D$296,MATCH($B43,$B$280:$B$296,0)),IF($K$16="Leave blank","",IF($K$16="Fill with zeros", 0,IF($K$16="Use global median",D$277,"Fill out I16"))))), D43))) -> 18562.651 | H43: =IF(H$2="","", IF(E43="",IF($K$16="Use global average",E$276,IF($K$16="Use regional average",INDEX(E$280:E$296,MATCH($B43,$B$280:$B$296,0)),IF($K$16="Leave blank","",IF($K$16="Fill with zeros", 0,IF($K$16="Use global median",E$277,"Fill out I16"))))), E43)) | I43: =IF(I$2="","", IF(F43="",IF($K$16="Use global average",F$276,IF($K$16="Use regional average",INDEX(F$280:F$296,MATCH($B43,$B$280:$B$296,0)),IF($K$16="Leave blank","",IF($K$16="Fill with zeros", 0,IF($K$16="Use global median",F$277,"Fill out I16"))))), F43)) | L43: =IF(M43="","",IF(COUNTIF(Countries!$B$1:$H$271,M43)>0,"",IF(COUNTIF(Countries!$M$1:$S$271,M43)>0,"Not a country","ERROR – NOT LISTED. Add alt spelling to ''Countries'' tab"))) | M43: Congo | N43: 2.9803798 | O43: =N43*365*1.28 -> 1392.4334 | P43: 0.779304 | Q43: 0.20477 | R43: =IFERROR(O43/(P43*(1-Q43)),"") -> 2246.8536
A44: =Countries!B43 -> Côte d'Ivoire | B44: =Countries!I43 -> Sub-Saharan Africa | C44: =IFERROR(IFERROR(IFERROR(IFERROR(IFERROR(IFERROR(IFERROR(MATCH(Countries!$B43,$M$3:$M$1003,0),MATCH(Countries!$C43,$M$3:$M$1003,0)),MATCH(Countries!$D43,$M$3:$M$1003,0)),MATCH(Countries!$E43,$M$3:$M$1003,0)),MATCH(Countries!$F43,$M$3:$M$1003,0)),MATCH(Countries!$G43,$M$3:$M$1003,0)),MATCH(Countries!$H43,$M$3:$M$1003,0)),"X") -> 44 | D44: =IF(G$2="","",IF($C44="X","",INDEX($N$3:$CC$1003,$C44,MATCH(G$2,$N$2:$CC$2,0)))) -> 2661.2195 | E44: =IF(H$2="","",IF($C44="X","",INDEX($N$3:$CC$1003,$C44,MATCH(H$2,$N$2:$CC$2,0)))) | F44: =IF(I$2="","",IF($C44="X","",INDEX($N$3:$CC$1003,$C44,MATCH(I$2,$N$2:$CC$2,0)))) | G44: =IF(A44="","",IF(G$2="","", IF(D44="",IF($K$16="Use global average",D$276,IF($K$16="Use regional average",INDEX(D$280:D$296,MATCH($B44,$B$280:$B$296,0)),IF($K$16="Leave blank","",IF($K$16="Fill with zeros", 0,IF($K$16="Use global median",D$277,"Fill out I16"))))), D44))) -> 2661.2195 | H44: =IF(H$2="","", IF(E44="",IF($K$16="Use global average",E$276,IF($K$16="Use regional average",INDEX(E$280:E$296,MATCH($B44,$B$280:$B$296,0)),IF($K$16="Leave blank","",IF($K$16="Fill with zeros", 0,IF($K$16="Use global median",E$277,"Fill out I16"))))), E44)) | I44: =IF(I$2="","", IF(F44="",IF($K$16="Use global average",F$276,IF($K$16="Use regional average",INDEX(F$280:F$296,MATCH($B44,$B$280:$B$296,0)),IF($K$16="Leave blank","",IF($K$16="Fill with zeros", 0,IF($K$16="Use global median",F$277,"Fill out I16"))))), F44)) | L44: =IF(M44="","",IF(COUNTIF(Countries!$B$1:$H$271,M44)>0,"",IF(COUNTIF(Countries!$M$1:$S$271,M44)>0,"Not a country","ERROR – NOT LISTED. Add alt spelling to ''Countries'' tab"))) | M44: Cook Islands | N44: NA | O44: =N44*365*1.28 -> #VALUE! | P44: 0.6057497 | Q44: #VALUE! | R44: =IFERROR(O44/(P44*(1-Q44)),"")
A45: =Countries!B44 -> Croatia | B45: =Countries!I44 -> Europe | C45: =IFERROR(IFERROR(IFERROR(IFERROR(IFERROR(IFERROR(IFERROR(MATCH(Countries!$B44,$M$3:$M$1003,0),MATCH(Countries!$C44,$M$3:$M$1003,0)),MATCH(Countries!$D44,$M$3:$M$1003,0)),MATCH(Countries!$E44,$M$3:$M$1003,0)),MATCH(Countries!$F44,$M$3:$M$1003,0)),MATCH(Countries!$G44,$M$3:$M$1003,0)),MATCH(Countries!$H44,$M$3:$M$1003,0)),"X") -> 45 | D45: =IF(G$2="","",IF($C45="X","",INDEX($N$3:$CC$1003,$C45,MATCH(G$2,$N$2:$CC$2,0)))) -> 24645.275 | E45: =IF(H$2="","",IF($C45="X","",INDEX($N$3:$CC$1003,$C45,MATCH(H$2,$N$2:$CC$2,0)))) | F45: =IF(I$2="","",IF($C45="X","",INDEX($N$3:$CC$1003,$C45,MATCH(I$2,$N$2:$CC$2,0)))) | G45: =IF(A45="","",IF(G$2="","", IF(D45="",IF($K$16="Use global average",D$276,IF($K$16="Use regional average",INDEX(D$280:D$296,MATCH($B45,$B$280:$B$296,0)),IF($K$16="Leave blank","",IF($K$16="Fill with zeros", 0,IF($K$16="Use global median",D$277,"Fill out I16"))))), D45))) -> 24645.275 | H45: =IF(H$2="","", IF(E45="",IF($K$16="Use global average",E$276,IF($K$16="Use regional average",INDEX(E$280:E$296,MATCH($B45,$B$280:$B$296,0)),IF($K$16="Leave blank","",IF($K$16="Fill with zeros", 0,IF($K$16="Use global median",E$277,"Fill out I16"))))), E45)) | I45: =IF(I$2="","", IF(F45="",IF($K$16="Use global average",F$276,IF($K$16="Use regional average",INDEX(F$280:F$296,MATCH($B45,$B$280:$B$296,0)),IF($K$16="Leave blank","",IF($K$16="Fill with zeros", 0,IF($K$16="Use global median",F$277,"Fill out I16"))))), F45)) | L45: =IF(M45="","",IF(COUNTIF(Countries!$B$1:$H$271,M45)>0,"",IF(COUNTIF(Countries!$M$1:$S$271,M45)>0,"Not a country","ERROR – NOT LISTED. Add alt spelling to ''Countries'' tab"))) | M45: Costa Rica | N45: 15.86023 | O45: =N45*365*1.28 -> 7409.8995 | P45: 0.450139 | Q45: 0.1132 | R45: =IFERROR(O45/(P45*(1-Q45)),"") -> 18562.651
A46: =Countries!B45 -> Cuba | B46: =Countries!I45 -> Caribbean | C46: =IFERROR(IFERROR(IFERROR(IFERROR(IFERROR(IFERROR(IFERROR(MATCH(Countries!$B45,$M$3:$M$1003,0),MATCH(Countries!$C45,$M$3:$M$1003,0)),MATCH(Countries!$D45,$M$3:$M$1003,0)),MATCH(Countries!$E45,$M$3:$M$1003,0)),MATCH(Countries!$F45,$M$3:$M$1003,0)),MATCH(Countries!$G45,$M$3:$M$1003,0)),MATCH(Countries!$H45,$M$3:$M$1003,0)),"X") -> 46 | D46: =IF(G$2="","",IF($C46="X","",INDEX($N$3:$CC$1003,$C46,MATCH(G$2,$N$2:$CC$2,0)))) | E46: =IF(H$2="","",IF($C46="X","",INDEX($N$3:$CC$1003,$C46,MATCH(H$2,$N$2:$CC$2,0)))) | F46: =IF(I$2="","",IF($C46="X","",INDEX($N$3:$CC$1003,$C46,MATCH(I$2,$N$2:$CC$2,0)))) | G46: =IF(A46="","",IF(G$2="","", IF(D46="",IF($K$16="Use global average",D$276,IF($K$16="Use regional average",INDEX(D$280:D$296,MATCH($B46,$B$280:$B$296,0)),IF($K$16="Leave blank","",IF($K$16="Fill with zeros", 0,IF($K$16="Use global median",D$277,"Fill out I16"))))), D46))) -> 12713.18 | H46: =IF(H$2="","", IF(E46="",IF($K$16="Use global average",E$276,IF($K$16="Use regional average",INDEX(E$280:E$296,MATCH($B46,$B$280:$B$296,0)),IF($K$16="Leave blank","",IF($K$16="Fill with zeros", 0,IF($K$16="Use global median",E$277,"Fill out I16"))))), E46)) | I46: =IF(I$2="","", IF(F46="",IF($K$16="Use global average",F$276,IF($K$16="Use regional average",INDEX(F$280:F$296,MATCH($B46,$B$280:$B$296,0)),IF($K$16="Leave blank","",IF($K$16="Fill with zeros", 0,IF($K$16="Use global median",F$277,"Fill out I16"))))), F46)) | L46: =IF(M46="","",IF(COUNTIF(Countries!$B$1:$H$271,M46)>0,"",IF(COUNTIF(Countries!$M$1:$S$271,M46)>0,"Not a country","ERROR – NOT LISTED. Add alt spelling to ''Countries'' tab"))) | M46: Cote d'Ivoire | N46: 4.336595 | O46: =N46*365*1.28 -> 2026.0572 | P46: 0.7807597 | Q46: 0.02489 | R46: =IFERROR(O46/(P46*(1-Q46)),"") -> 2661.2195
A47: =Countries!B46 -> Cyprus | B47: =Countries!I46 -> Europe | C47: =IFERROR(IFERROR(IFERROR(IFERROR(IFERROR(IFERROR(IFERROR(MATCH(Countries!$B46,$M$3:$M$1003,0),MATCH(Countries!$C46,$M$3:$M$1003,0)),MATCH(Countries!$D46,$M$3:$M$1003,0)),MATCH(Countries!$E46,$M$3:$M$1003,0)),MATCH(Countries!$F46,$M$3:$M$1003,0)),MATCH(Countries!$G46,$M$3:$M$1003,0)),MATCH(Countries!$H46,$M$3:$M$1003,0)),"X") -> 48 | D47: =IF(G$2="","",IF($C47="X","",INDEX($N$3:$CC$1003,$C47,MATCH(G$2,$N$2:$CC$2,0)))) -> 52479.13 | E47: =IF(H$2="","",IF($C47="X","",INDEX($N$3:$CC$1003,$C47,MATCH(H$2,$N$2:$CC$2,0)))) | F47: =IF(I$2="","",IF($C47="X","",INDEX($N$3:$CC$1003,$C47,MATCH(I$2,$N$2:$CC$2,0)))) | G47: =IF(A47="","",IF(G$2="","", IF(D47="",IF($K$16="Use global average",D$276,IF($K$16="Use regional average",INDEX(D$280:D$296,MATCH($B47,$B$280:$B$296,0)),IF($K$16="Leave blank","",IF($K$16="Fill with zeros", 0,IF($K$16="Use global median",D$277,"Fill out I16"))))), D47))) -> 52479.13 | H47: =IF(H$2="","", IF(E47="",IF($K$16="Use global average",E$276,IF($K$16="Use regional average",INDEX(E$280:E$296,MATCH($B47,$B$280:$B$296,0)),IF($K$16="Leave blank","",IF($K$16="Fill with zeros", 0,IF($K$16="Use global median",E$277,"Fill out I16"))))), E47)) | I47: =IF(I$2="","", IF(F47="",IF($K$16="Use global average",F$276,IF($K$16="Use regional average",INDEX(F$280:F$296,MATCH($B47,$B$280:$B$296,0)),IF($K$16="Leave blank","",IF($K$16="Fill with zeros", 0,IF($K$16="Use global median",F$277,"Fill out I16"))))), F47)) | L47: =IF(M47="","",IF(COUNTIF(Countries!$B$1:$H$271,M47)>0,"",IF(COUNTIF(Countries!$M$1:$S$271,M47)>0,"Not a country","ERROR – NOT LISTED. Add alt spelling to ''Countries'' tab"))) | M47: Croatia | N47: 28.754229 | O47: =N47*365*1.28 -> 13433.976 | P47: 0.5858699 | Q47: 0.0696 | R47: =IFERROR(O47/(P47*(1-Q47)),"") -> 24645.275
A48: =Countries!B47 -> Czechia | B48: =Countries!I47 -> Europe | C48: =IFERROR(IFERROR(IFERROR(IFERROR(IFERROR(IFERROR(IFERROR(MATCH(Countries!$B47,$M$3:$M$1003,0),MATCH(Countries!$C47,$M$3:$M$1003,0)),MATCH(Countries!$D47,$M$3:$M$1003,0)),MATCH(Countries!$E47,$M$3:$M$1003,0)),MATCH(Countries!$F47,$M$3:$M$1003,0)),MATCH(Countries!$G47,$M$3:$M$1003,0)),MATCH(Countries!$H47,$M$3:$M$1003,0)),"X") -> 49 | D48: =IF(G$2="","",IF($C48="X","",INDEX($N$3:$CC$1003,$C48,MATCH(G$2,$N$2:$CC$2,0)))) -> 30930.228 | E48: =IF(H$2="","",IF($C48="X","",INDEX($N$3:$CC$1003,$C48,MATCH(H$2,$N$2:$CC$2,0)))) | F48: =IF(I$2="","",IF($C48="X","",INDEX($N$3:$CC$1003,$C48,MATCH(I$2,$N$2:$CC$2,0)))) | G48: =IF(A48="","",IF(G$2="","", IF(D48="",IF($K$16="Use global average",D$276,IF($K$16="Use regional average",INDEX(D$280:D$296,MATCH($B48,$B$280:$B$296,0)),IF($K$16="Leave blank","",IF($K$16="Fill with zeros", 0,IF($K$16="Use global median",D$277,"Fill out I16"))))), D48))) -> 30930.228 | H48: =IF(H$2="","", IF(E48="",IF($K$16="Use global average",E$276,IF($K$16="Use regional average",INDEX(E$280:E$296,MATCH($B48,$B$280:$B$296,0)),IF($K$16="Leave blank","",IF($K$16="Fill with zeros", 0,IF($K$16="Use global median",E$277,"Fill out I16"))))), E48)) | I48: =IF(I$2="","", IF(F48="",IF($K$16="Use global average",F$276,IF($K$16="Use regional average",INDEX(F$280:F$296,MATCH($B48,$B$280:$B$296,0)),IF($K$16="Leave blank","",IF($K$16="Fill with zeros", 0,IF($K$16="Use global median",F$277,"Fill out I16"))))), F48)) | L48: =IF(M48="","",IF(COUNTIF(Countries!$B$1:$H$271,M48)>0,"",IF(COUNTIF(Countries!$M$1:$S$271,M48)>0,"Not a country","ERROR – NOT LISTED. Add alt spelling to ''Countries'' tab"))) | M48: Cuba | N48: NA | O48: =N48*365*1.28 -> #VALUE! | P48: 0.46398045 | Q48: 0.01254 | R48: =IFERROR(O48/(P48*(1-Q48)),"")
A49: =Countries!B48 -> Denmark | B49: =Countries!I48 -> Europe | C49: =IFERROR(IFERROR(IFERROR(IFERROR(IFERROR(IFERROR(IFERROR(MATCH(Countries!$B48,$M$3:$M$1003,0),MATCH(Countries!$C48,$M$3:$M$1003,0)),MATCH(Countries!$D48,$M$3:$M$1003,0)),MATCH(Countries!$E48,$M$3:$M$1003,0)),MATCH(Countries!$F48,$M$3:$M$1003,0)),MATCH(Countries!$G48,$M$3:$M$1003,0)),MATCH(Countries!$H48,$M$3:$M$1003,0)),"X") -> 51 | D49: =IF(G$2="","",IF($C49="X","",INDEX($N$3:$CC$1003,$C49,MATCH(G$2,$N$2:$CC$2,0)))) -> 48649.706 | E49: =IF(H$2="","",IF($C49="X","",INDEX($N$3:$CC$1003,$C49,MATCH(H$2,$N$2:$CC$2,0)))) | F49: =IF(I$2="","",IF($C49="X","",INDEX($N$3:$CC$1003,$C49,MATCH(I$2,$N$2:$CC$2,0)))) | G49: =IF(A49="","",IF(G$2="","", IF(D49="",IF($K$16="Use global average",D$276,IF($K$16="Use regional average",INDEX(D$280:D$296,MATCH($B49,$B$280:$B$296,0)),IF($K$16="Leave blank","",IF($K$16="Fill with zeros", 0,IF($K$16="Use global median",D$277,"Fill out I16"))))), D49))) -> 48649.706 | H49: =IF(H$2="","", IF(E49="",IF($K$16="Use global average",E$276,IF($K$16="Use regional average",INDEX(E$280:E$296,MATCH($B49,$B$280:$B$296,0)),IF($K$16="Leave blank","",IF($K$16="Fill with zeros", 0,IF($K$16="Use global median",E$277,"Fill out I16"))))), E49)) | I49: =IF(I$2="","", IF(F49="",IF($K$16="Use global average",F$276,IF($K$16="Use regional average",INDEX(F$280:F$296,MATCH($B49,$B$280:$B$296,0)),IF($K$16="Leave blank","",IF($K$16="Fill with zeros", 0,IF($K$16="Use global median",F$277,"Fill out I16"))))), F49)) | L49: =IF(M49="","",IF(COUNTIF(Countries!$B$1:$H$271,M49)>0,"",IF(COUNTIF(Countries!$M$1:$S$271,M49)>0,"Not a country","ERROR – NOT LISTED. Add alt spelling to ''Countries'' tab"))) -> Not a country | M49: Curacao | N49: NA | O49: =N49*365*1.28 -> #VALUE! | P49: 0.46034683 | Q49: #VALUE! | R49: =IFERROR(O49/(P49*(1-Q49)),"")
A50: =Countries!B49 -> Djibouti | B50: =Countries!I49 -> Sub-Saharan Africa | C50: =IFERROR(IFERROR(IFERROR(IFERROR(IFERROR(IFERROR(IFERROR(MATCH(Countries!$B49,$M$3:$M$1003,0),MATCH(Countries!$C49,$M$3:$M$1003,0)),MATCH(Countries!$D49,$M$3:$M$1003,0)),MATCH(Countries!$E49,$M$3:$M$1003,0)),MATCH(Countries!$F49,$M$3:$M$1003,0)),MATCH(Countries!$G49,$M$3:$M$1003,0)),MATCH(Countries!$H49,$M$3:$M$1003,0)),"X") -> 52 | D50: =IF(G$2="","",IF($C50="X","",INDEX($N$3:$CC$1003,$C50,MATCH(G$2,$N$2:$CC$2,0)))) -> 4982.762 | E50: =IF(H$2="","",IF($C50="X","",INDEX($N$3:$CC$1003,$C50,MATCH(H$2,$N$2:$CC$2,0)))) | F50: =IF(I$2="","",IF($C50="X","",INDEX($N$3:$CC$1003,$C50,MATCH(I$2,$N$2:$CC$2,0)))) | G50: =IF(A50="","",IF(G$2="","", IF(D50="",IF($K$16="Use global average",D$276,IF($K$16="Use regional average",INDEX(D$280:D$296,MATCH($B50,$B$280:$B$296,0)),IF($K$16="Leave blank","",IF($K$16="Fill with zeros", 0,IF($K$16="Use global median",D$277,"Fill out I16"))))), D50))) -> 4982.762 | H50: =IF(H$2="","", IF(E50="",IF($K$16="Use global average",E$276,IF($K$16="Use regional average",INDEX(E$280:E$296,MATCH($B50,$B$280:$B$296,0)),IF($K$16="Leave blank","",IF($K$16="Fill with zeros", 0,IF($K$16="Use global median",E$277,"Fill out I16"))))), E50)) | I50: =IF(I$2="","", IF(F50="",IF($K$16="Use global average",F$276,IF($K$16="Use regional average",INDEX(F$280:F$296,MATCH($B50,$B$280:$B$296,0)),IF($K$16="Leave blank","",IF($K$16="Fill with zeros", 0,IF($K$16="Use global median",F$277,"Fill out I16"))))), F50)) | L50: =IF(M50="","",IF(COUNTIF(Countries!$B$1:$H$271,M50)>0,"",IF(COUNTIF(Countries!$M$1:$S$271,M50)>0,"Not a country","ERROR – NOT LISTED. Add alt spelling to ''Countries'' tab"))) | M50: Cyprus | N50: 45.669167 | O50: =N50*365*1.28 -> 21336.635 | P50: 0.4361443 | Q50: 0.0678 | R50: =IFERROR(O50/(P50*(1-Q50)),"") -> 52479.13
A51: =Countries!B50 -> Dominica | B51: =Countries!I50 -> Caribbean | C51: =IFERROR(IFERROR(IFERROR(IFERROR(IFERROR(IFERROR(IFERROR(MATCH(Countries!$B50,$M$3:$M$1003,0),MATCH(Countries!$C50,$M$3:$M$1003,0)),MATCH(Countries!$D50,$M$3:$M$1003,0)),MATCH(Countries!$E50,$M$3:$M$1003,0)),MATCH(Countries!$F50,$M$3:$M$1003,0)),MATCH(Countries!$G50,$M$3:$M$1003,0)),MATCH(Countries!$H50,$M$3:$M$1003,0)),"X") -> 53 | D51: =IF(G$2="","",IF($C51="X","",INDEX($N$3:$CC$1003,$C51,MATCH(G$2,$N$2:$CC$2,0)))) | E51: =IF(H$2="","",IF($C51="X","",INDEX($N$3:$CC$1003,$C51,MATCH(H$2,$N$2:$CC$2,0)))) | F51: =IF(I$2="","",IF($C51="X","",INDEX($N$3:$CC$1003,$C51,MATCH(I$2,$N$2:$CC$2,0)))) | G51: =IF(A51="","",IF(G$2="","", IF(D51="",IF($K$16="Use global average",D$276,IF($K$16="Use regional average",INDEX(D$280:D$296,MATCH($B51,$B$280:$B$296,0)),IF($K$16="Leave blank","",IF($K$16="Fill with zeros", 0,IF($K$16="Use global median",D$277,"Fill out I16"))))), D51))) -> 12713.18 | H51: =IF(H$2="","", IF(E51="",IF($K$16="Use global average",E$276,IF($K$16="Use regional average",INDEX(E$280:E$296,MATCH($B51,$B$280:$B$296,0)),IF($K$16="Leave blank","",IF($K$16="Fill with zeros", 0,IF($K$16="Use global median",E$277,"Fill out I16"))))), E51)) | I51: =IF(I$2="","", IF(F51="",IF($K$16="Use global average",F$276,IF($K$16="Use regional average",INDEX(F$280:F$296,MATCH($B51,$B$280:$B$296,0)),IF($K$16="Leave blank","",IF($K$16="Fill with zeros", 0,IF($K$16="Use global median",F$277,"Fill out I16"))))), F51)) | L51: =IF(M51="","",IF(COUNTIF(Countries!$B$1:$H$271,M51)>0,"",IF(COUNTIF(Countries!$M$1:$S$271,M51)>0,"Not a country","ERROR – NOT LISTED. Add alt spelling to ''Countries'' tab"))) | M51: Czechia | N51: 36.751797 | O51: =N51*365*1.28 -> 17170.44 | P51: 0.56773838 | Q51: 0.0222 | R51: =IFERROR(O51/(P51*(1-Q51)),"") -> 30930.228
A52: =Countries!B51 -> Dominican Republic | B52: =Countries!I51 -> Caribbean | C52: =IFERROR(IFERROR(IFERROR(IFERROR(IFERROR(IFERROR(IFERROR(MATCH(Countries!$B51,$M$3:$M$1003,0),MATCH(Countries!$C51,$M$3:$M$1003,0)),MATCH(Countries!$D51,$M$3:$M$1003,0)),MATCH(Countries!$E51,$M$3:$M$1003,0)),MATCH(Countries!$F51,$M$3:$M$1003,0)),MATCH(Countries!$G51,$M$3:$M$1003,0)),MATCH(Countries!$H51,$M$3:$M$1003,0)),"X") -> 54 | D52: =IF(G$2="","",IF($C52="X","",INDEX($N$3:$CC$1003,$C52,MATCH(G$2,$N$2:$CC$2,0)))) -> 10647.239 | E52: =IF(H$2="","",IF($C52="X","",INDEX($N$3:$CC$1003,$C52,MATCH(H$2,$N$2:$CC$2,0)))) | F52: =IF(I$2="","",IF($C52="X","",INDEX($N$3:$CC$1003,$C52,MATCH(I$2,$N$2:$CC$2,0)))) | G52: =IF(A52="","",IF(G$2="","", IF(D52="",IF($K$16="Use global average",D$276,IF($K$16="Use regional average",INDEX(D$280:D$296,MATCH($B52,$B$280:$B$296,0)),IF($K$16="Leave blank","",IF($K$16="Fill with zeros", 0,IF($K$16="Use global median",D$277,"Fill out I16"))))), D52))) -> 10647.239 | H52: =IF(H$2="","", IF(E52="",IF($K$16="Use global average",E$276,IF($K$16="Use regional average",INDEX(E$280:E$296,MATCH($B52,$B$280:$B$296,0)),IF($K$16="Leave blank","",IF($K$16="Fill with zeros", 0,IF($K$16="Use global median",E$277,"Fill out I16"))))), E52)) | I52: =IF(I$2="","", IF(F52="",IF($K$16="Use global average",F$276,IF($K$16="Use regional average",INDEX(F$280:F$296,MATCH($B52,$B$280:$B$296,0)),IF($K$16="Leave blank","",IF($K$16="Fill with zeros", 0,IF($K$16="Use global median",F$277,"Fill out I16"))))), F52)) | L52: =IF(M52="","",IF(COUNTIF(Countries!$B$1:$H$271,M52)>0,"",IF(COUNTIF(Countries!$M$1:$S$271,M52)>0,"Not a country","ERROR – NOT LISTED. Add alt spelling to ''Countries'' tab"))) | M52: Democratic Republic of Congo | N52: 1.1797127 | O52: =N52*365*1.28 -> 551.16177 | P52: 0.9668238 | Q52: 0.04685 | R52: =IFERROR(O52/(P52*(1-Q52)),"") -> 598.09546
A53: =Countries!B52 -> DR Congo | B53: =Countries!I52 -> Sub-Saharan Africa | C53: =IFERROR(IFERROR(IFERROR(IFERROR(IFERROR(IFERROR(IFERROR(MATCH(Countries!$B52,$M$3:$M$1003,0),MATCH(Countries!$C52,$M$3:$M$1003,0)),MATCH(Countries!$D52,$M$3:$M$1003,0)),MATCH(Countries!$E52,$M$3:$M$1003,0)),MATCH(Countries!$F52,$M$3:$M$1003,0)),MATCH(Countries!$G52,$M$3:$M$1003,0)),MATCH(Countries!$H52,$M$3:$M$1003,0)),"X") -> 50 | D53: =IF(G$2="","",IF($C53="X","",INDEX($N$3:$CC$1003,$C53,MATCH(G$2,$N$2:$CC$2,0)))) -> 598.09546 | E53: =IF(H$2="","",IF($C53="X","",INDEX($N$3:$CC$1003,$C53,MATCH(H$2,$N$2:$CC$2,0)))) | F53: =IF(I$2="","",IF($C53="X","",INDEX($N$3:$CC$1003,$C53,MATCH(I$2,$N$2:$CC$2,0)))) | G53: =IF(A53="","",IF(G$2="","", IF(D53="",IF($K$16="Use global average",D$276,IF($K$16="Use regional average",INDEX(D$280:D$296,MATCH($B53,$B$280:$B$296,0)),IF($K$16="Leave blank","",IF($K$16="Fill with zeros", 0,IF($K$16="Use global median",D$277,"Fill out I16"))))), D53))) -> 598.09546 | H53: =IF(H$2="","", IF(E53="",IF($K$16="Use global average",E$276,IF($K$16="Use regional average",INDEX(E$280:E$296,MATCH($B53,$B$280:$B$296,0)),IF($K$16="Leave blank","",IF($K$16="Fill with zeros", 0,IF($K$16="Use global median",E$277,"Fill out I16"))))), E53)) | I53: =IF(I$2="","", IF(F53="",IF($K$16="Use global average",F$276,IF($K$16="Use regional average",INDEX(F$280:F$296,MATCH($B53,$B$280:$B$296,0)),IF($K$16="Leave blank","",IF($K$16="Fill with zeros", 0,IF($K$16="Use global median",F$277,"Fill out I16"))))), F53)) | L53: =IF(M53="","",IF(COUNTIF(Countries!$B$1:$H$271,M53)>0,"",IF(COUNTIF(Countries!$M$1:$S$271,M53)>0,"Not a country","ERROR – NOT LISTED. Add alt spelling to ''Countries'' tab"))) | M53: Denmark | N53: 57.08956 | O53: =N53*365*1.28 -> 26672.242 | P53: 0.57366417 | Q53: 0.0443 | R53: =IFERROR(O53/(P53*(1-Q53)),"") -> 48649.706
A54: =Countries!B53 -> Ecuador | B54: =Countries!I53 -> Latin America | C54: =IFERROR(IFERROR(IFERROR(IFERROR(IFERROR(IFERROR(IFERROR(MATCH(Countries!$B53,$M$3:$M$1003,0),MATCH(Countries!$C53,$M$3:$M$1003,0)),MATCH(Countries!$D53,$M$3:$M$1003,0)),MATCH(Countries!$E53,$M$3:$M$1003,0)),MATCH(Countries!$F53,$M$3:$M$1003,0)),MATCH(Countries!$G53,$M$3:$M$1003,0)),MATCH(Countries!$H53,$M$3:$M$1003,0)),"X") -> 56 | D54: =IF(G$2="","",IF($C54="X","",INDEX($N$3:$CC$1003,$C54,MATCH(G$2,$N$2:$CC$2,0)))) -> 10457.203 | E54: =IF(H$2="","",IF($C54="X","",INDEX($N$3:$CC$1003,$C54,MATCH(H$2,$N$2:$CC$2,0)))) | F54: =IF(I$2="","",IF($C54="X","",INDEX($N$3:$CC$1003,$C54,MATCH(I$2,$N$2:$CC$2,0)))) | G54: =IF(A54="","",IF(G$2="","", IF(D54="",IF($K$16="Use global average",D$276,IF($K$16="Use regional average",INDEX(D$280:D$296,MATCH($B54,$B$280:$B$296,0)),IF($K$16="Leave blank","",IF($K$16="Fill with zeros", 0,IF($K$16="Use global median",D$277,"Fill out I16"))))), D54))) -> 10457.203 | H54: =IF(H$2="","", IF(E54="",IF($K$16="Use global average",E$276,IF($K$16="Use regional average",INDEX(E$280:E$296,MATCH($B54,$B$280:$B$296,0)),IF($K$16="Leave blank","",IF($K$16="Fill with zeros", 0,IF($K$16="Use global median",E$277,"Fill out I16"))))), E54)) | I54: =IF(I$2="","", IF(F54="",IF($K$16="Use global average",F$276,IF($K$16="Use regional average",INDEX(F$280:F$296,MATCH($B54,$B$280:$B$296,0)),IF($K$16="Leave blank","",IF($K$16="Fill with zeros", 0,IF($K$16="Use global median",F$277,"Fill out I16"))))), F54)) | L54: =IF(M54="","",IF(COUNTIF(Countries!$B$1:$H$271,M54)>0,"",IF(COUNTIF(Countries!$M$1:$S$271,M54)>0,"Not a country","ERROR – NOT LISTED. Add alt spelling to ''Countries'' tab"))) | M54: Djibouti | N54: 4.0851326 | O54: =N54*365*1.28 -> 1908.574 | P54: 0.52231617 | Q54: 0.26666 | R54: =IFERROR(O54/(P54*(1-Q54)),"") -> 4982.762
A55: =Countries!B54 -> Egypt | B55: =Countries!I54 -> North Africa | C55: =IFERROR(IFERROR(IFERROR(IFERROR(IFERROR(IFERROR(IFERROR(MATCH(Countries!$B54,$M$3:$M$1003,0),MATCH(Countries!$C54,$M$3:$M$1003,0)),MATCH(Countries!$D54,$M$3:$M$1003,0)),MATCH(Countries!$E54,$M$3:$M$1003,0)),MATCH(Countries!$F54,$M$3:$M$1003,0)),MATCH(Countries!$G54,$M$3:$M$1003,0)),MATCH(Countries!$H54,$M$3:$M$1003,0)),"X") -> 57 | D55: =IF(G$2="","",IF($C55="X","",INDEX($N$3:$CC$1003,$C55,MATCH(G$2,$N$2:$CC$2,0)))) -> 4529.4948 | E55: =IF(H$2="","",IF($C55="X","",INDEX($N$3:$CC$1003,$C55,MATCH(H$2,$N$2:$CC$2,0)))) | F55: =IF(I$2="","",IF($C55="X","",INDEX($N$3:$CC$1003,$C55,MATCH(I$2,$N$2:$CC$2,0)))) | G55: =IF(A55="","",IF(G$2="","", IF(D55="",IF($K$16="Use global average",D$276,IF($K$16="Use regional average",INDEX(D$280:D$296,MATCH($B55,$B$280:$B$296,0)),IF($K$16="Leave blank","",IF($K$16="Fill with zeros", 0,IF($K$16="Use global median",D$277,"Fill out I16"))))), D55))) -> 4529.4948 | H55: =IF(H$2="","", IF(E55="",IF($K$16="Use global average",E$276,IF($K$16="Use regional average",INDEX(E$280:E$296,MATCH($B55,$B$280:$B$296,0)),IF($K$16="Leave blank","",IF($K$16="Fill with zeros", 0,IF($K$16="Use global median",E$277,"Fill out I16"))))), E55)) | I55: =IF(I$2="","", IF(F55="",IF($K$16="Use global average",F$276,IF($K$16="Use regional average",INDEX(F$280:F$296,MATCH($B55,$B$280:$B$296,0)),IF($K$16="Leave blank","",IF($K$16="Fill with zeros", 0,IF($K$16="Use global median",F$277,"Fill out I16"))))), F55)) | L55: =IF(M55="","",IF(COUNTIF(Countries!$B$1:$H$271,M55)>0,"",IF(COUNTIF(Countries!$M$1:$S$271,M55)>0,"Not a country","ERROR – NOT LISTED. Add alt spelling to ''Countries'' tab"))) | M55: Dominica | N55: NA | O55: =N55*365*1.28 -> #VALUE! | P55: 0.4463746 | Q55: #VALUE! | R55: =IFERROR(O55/(P55*(1-Q55)),"")
A56: =Countries!B55 -> El Salvador | B56: =Countries!I55 -> Latin America | C56: =IFERROR(IFERROR(IFERROR(IFERROR(IFERROR(IFERROR(IFERROR(MATCH(Countries!$B55,$M$3:$M$1003,0),MATCH(Countries!$C55,$M$3:$M$1003,0)),MATCH(Countries!$D55,$M$3:$M$1003,0)),MATCH(Countries!$E55,$M$3:$M$1003,0)),MATCH(Countries!$F55,$M$3:$M$1003,0)),MATCH(Countries!$G55,$M$3:$M$1003,0)),MATCH(Countries!$H55,$M$3:$M$1003,0)),"X") -> 58 | D56: =IF(G$2="","",IF($C56="X","",INDEX($N$3:$CC$1003,$C56,MATCH(G$2,$N$2:$CC$2,0)))) -> 10031.114 | E56: =IF(H$2="","",IF($C56="X","",INDEX($N$3:$CC$1003,$C56,MATCH(H$2,$N$2:$CC$2,0)))) | F56: =IF(I$2="","",IF($C56="X","",INDEX($N$3:$CC$1003,$C56,MATCH(I$2,$N$2:$CC$2,0)))) | G56: =IF(A56="","",IF(G$2="","", IF(D56="",IF($K$16="Use global average",D$276,IF($K$16="Use regional average",INDEX(D$280:D$296,MATCH($B56,$B$280:$B$296,0)),IF($K$16="Leave blank","",IF($K$16="Fill with zeros", 0,IF($K$16="Use global median",D$277,"Fill out I16"))))), D56))) -> 10031.114 | H56: =IF(H$2="","", IF(E56="",IF($K$16="Use global average",E$276,IF($K$16="Use regional average",INDEX(E$280:E$296,MATCH($B56,$B$280:$B$296,0)),IF($K$16="Leave blank","",IF($K$16="Fill with zeros", 0,IF($K$16="Use global median",E$277,"Fill out I16"))))), E56)) | I56: =IF(I$2="","", IF(F56="",IF($K$16="Use global average",F$276,IF($K$16="Use regional average",INDEX(F$280:F$296,MATCH($B56,$B$280:$B$296,0)),IF($K$16="Leave blank","",IF($K$16="Fill with zeros", 0,IF($K$16="Use global median",F$277,"Fill out I16"))))), F56)) | L56: =IF(M56="","",IF(COUNTIF(Countries!$B$1:$H$271,M56)>0,"",IF(COUNTIF(Countries!$M$1:$S$271,M56)>0,"Not a country","ERROR – NOT LISTED. Add alt spelling to ''Countries'' tab"))) | M56: Dominican Republic | N56: 11.336495 | O56: =N56*365*1.28 -> 5296.4105 | P56: 0.52641857 | Q56: 0.05504 | R56: =IFERROR(O56/(P56*(1-Q56)),"") -> 10647.239
A57: =Countries!B56 -> Equatorial Guinea | B57: =Countries!I56 -> Sub-Saharan Africa | C57: =IFERROR(IFERROR(IFERROR(IFERROR(IFERROR(IFERROR(IFERROR(MATCH(Countries!$B56,$M$3:$M$1003,0),MATCH(Countries!$C56,$M$3:$M$1003,0)),MATCH(Countries!$D56,$M$3:$M$1003,0)),MATCH(Countries!$E56,$M$3:$M$1003,0)),MATCH(Countries!$F56,$M$3:$M$1003,0)),MATCH(Countries!$G56,$M$3:$M$1003,0)),MATCH(Countries!$H56,$M$3:$M$1003,0)),"X") -> 59 | D57: =IF(G$2="","",IF($C57="X","",INDEX($N$3:$CC$1003,$C57,MATCH(G$2,$N$2:$CC$2,0)))) | E57: =IF(H$2="","",IF($C57="X","",INDEX($N$3:$CC$1003,$C57,MATCH(H$2,$N$2:$CC$2,0)))) | F57: =IF(I$2="","",IF($C57="X","",INDEX($N$3:$CC$1003,$C57,MATCH(I$2,$N$2:$CC$2,0)))) | G57: =IF(A57="","",IF(G$2="","", IF(D57="",IF($K$16="Use global average",D$276,IF($K$16="Use regional average",INDEX(D$280:D$296,MATCH($B57,$B$280:$B$296,0)),IF($K$16="Leave blank","",IF($K$16="Fill with zeros", 0,IF($K$16="Use global median",D$277,"Fill out I16"))))), D57))) -> 2791.4697 | H57: =IF(H$2="","", IF(E57="",IF($K$16="Use global average",E$276,IF($K$16="Use regional average",INDEX(E$280:E$296,MATCH($B57,$B$280:$B$296,0)),IF($K$16="Leave blank","",IF($K$16="Fill with zeros", 0,IF($K$16="Use global median",E$277,"Fill out I16"))))), E57)) | I57: =IF(I$2="","", IF(F57="",IF($K$16="Use global average",F$276,IF($K$16="Use regional average",INDEX(F$280:F$296,MATCH($B57,$B$280:$B$296,0)),IF($K$16="Leave blank","",IF($K$16="Fill with zeros", 0,IF($K$16="Use global median",F$277,"Fill out I16"))))), F57)) | L57: =IF(M57="","",IF(COUNTIF(Countries!$B$1:$H$271,M57)>0,"",IF(COUNTIF(Countries!$M$1:$S$271,M57)>0,"Not a country","ERROR – NOT LISTED. Add alt spelling to ''Countries'' tab"))) | M57: East Timor | N57: 2.8969195 | O57: =N57*365*1.28 -> 1353.4408 | P57: 0.6546412 | Q57: 0.01786 | R57: =IFERROR(O57/(P57*(1-Q57)),"") -> 2105.0505
A58: =Countries!B57 -> Eritrea | B58: =Countries!I57 -> Sub-Saharan Africa | C58: =IFERROR(IFERROR(IFERROR(IFERROR(IFERROR(IFERROR(IFERROR(MATCH(Countries!$B57,$M$3:$M$1003,0),MATCH(Countries!$C57,$M$3:$M$1003,0)),MATCH(Countries!$D57,$M$3:$M$1003,0)),MATCH(Countries!$E57,$M$3:$M$1003,0)),MATCH(Countries!$F57,$M$3:$M$1003,0)),MATCH(Countries!$G57,$M$3:$M$1003,0)),MATCH(Countries!$H57,$M$3:$M$1003,0)),"X") -> 60 | D58: =IF(G$2="","",IF($C58="X","",INDEX($N$3:$CC$1003,$C58,MATCH(G$2,$N$2:$CC$2,0)))) | E58: =IF(H$2="","",IF($C58="X","",INDEX($N$3:$CC$1003,$C58,MATCH(H$2,$N$2:$CC$2,0)))) | F58: =IF(I$2="","",IF($C58="X","",INDEX($N$3:$CC$1003,$C58,MATCH(I$2,$N$2:$CC$2,0)))) | G58: =IF(A58="","",IF(G$2="","", IF(D58="",IF($K$16="Use global average",D$276,IF($K$16="Use regional average",INDEX(D$280:D$296,MATCH($B58,$B$280:$B$296,0)),IF($K$16="Leave blank","",IF($K$16="Fill with zeros", 0,IF($K$16="Use global median",D$277,"Fill out I16"))))), D58))) -> 2791.4697 | H58: =IF(H$2="","", IF(E58="",IF($K$16="Use global average",E$276,IF($K$16="Use regional average",INDEX(E$280:E$296,MATCH($B58,$B$280:$B$296,0)),IF($K$16="Leave blank","",IF($K$16="Fill with zeros", 0,IF($K$16="Use global median",E$277,"Fill out I16"))))), E58)) | I58: =IF(I$2="","", IF(F58="",IF($K$16="Use global average",F$276,IF($K$16="Use regional average",INDEX(F$280:F$296,MATCH($B58,$B$280:$B$296,0)),IF($K$16="Leave blank","",IF($K$16="Fill with zeros", 0,IF($K$16="Use global median",F$277,"Fill out I16"))))), F58)) | L58: =IF(M58="","",IF(COUNTIF(Countries!$B$1:$H$271,M58)>0,"",IF(COUNTIF(Countries!$M$1:$S$271,M58)>0,"Not a country","ERROR – NOT LISTED. Add alt spelling to ''Countries'' tab"))) | M58: Ecuador | N58: 10.655273 | O58: =N58*365*1.28 -> 4978.1433 | P58: 0.494648 | Q58: 0.0376 | R58: =IFERROR(O58/(P58*(1-Q58)),"") -> 10457.203
A59: =Countries!B58 -> Estonia | B59: =Countries!I58 -> Europe | C59: =IFERROR(IFERROR(IFERROR(IFERROR(IFERROR(IFERROR(IFERROR(MATCH(Countries!$B58,$M$3:$M$1003,0),MATCH(Countries!$C58,$M$3:$M$1003,0)),MATCH(Countries!$D58,$M$3:$M$1003,0)),MATCH(Countries!$E58,$M$3:$M$1003,0)),MATCH(Countries!$F58,$M$3:$M$1003,0)),MATCH(Countries!$G58,$M$3:$M$1003,0)),MATCH(Countries!$H58,$M$3:$M$1003,0)),"X") -> 61 | D59: =IF(G$2="","",IF($C59="X","",INDEX($N$3:$CC$1003,$C59,MATCH(G$2,$N$2:$CC$2,0)))) -> 33931.192 | E59: =IF(H$2="","",IF($C59="X","",INDEX($N$3:$CC$1003,$C59,MATCH(H$2,$N$2:$CC$2,0)))) | F59: =IF(I$2="","",IF($C59="X","",INDEX($N$3:$CC$1003,$C59,MATCH(I$2,$N$2:$CC$2,0)))) | G59: =IF(A59="","",IF(G$2="","", IF(D59="",IF($K$16="Use global average",D$276,IF($K$16="Use regional average",INDEX(D$280:D$296,MATCH($B59,$B$280:$B$296,0)),IF($K$16="Leave blank","",IF($K$16="Fill with zeros", 0,IF($K$16="Use global median",D$277,"Fill out I16"))))), D59))) -> 33931.192 | H59: =IF(H$2="","", IF(E59="",IF($K$16="Use global average",E$276,IF($K$16="Use regional average",INDEX(E$280:E$296,MATCH($B59,$B$280:$B$296,0)),IF($K$16="Leave blank","",IF($K$16="Fill with zeros", 0,IF($K$16="Use global median",E$277,"Fill out I16"))))), E59)) | I59: =IF(I$2="","", IF(F59="",IF($K$16="Use global average",F$276,IF($K$16="Use regional average",INDEX(F$280:F$296,MATCH($B59,$B$280:$B$296,0)),IF($K$16="Leave blank","",IF($K$16="Fill with zeros", 0,IF($K$16="Use global median",F$277,"Fill out I16"))))), F59)) | L59: =IF(M59="","",IF(COUNTIF(Countries!$B$1:$H$271,M59)>0,"",IF(COUNTIF(Countries!$M$1:$S$271,M59)>0,"Not a country","ERROR – NOT LISTED. Add alt spelling to ''Countries'' tab"))) | M59: Egypt | N59: 5.422779 | O59: =N59*365*1.28 -> 2533.5223 | P59: 0.59756508 | Q59: 0.06397 | R59: =IFERROR(O59/(P59*(1-Q59)),"") -> 4529.4948
A60: =Countries!B59 -> Eswatini | B60: =Countries!I59 -> Sub-Saharan Africa | C60: =IFERROR(IFERROR(IFERROR(IFERROR(IFERROR(IFERROR(IFERROR(MATCH(Countries!$B59,$M$3:$M$1003,0),MATCH(Countries!$C59,$M$3:$M$1003,0)),MATCH(Countries!$D59,$M$3:$M$1003,0)),MATCH(Countries!$E59,$M$3:$M$1003,0)),MATCH(Countries!$F59,$M$3:$M$1003,0)),MATCH(Countries!$G59,$M$3:$M$1003,0)),MATCH(Countries!$H59,$M$3:$M$1003,0)),"X") -> 62 | D60: =IF(G$2="","",IF($C60="X","",INDEX($N$3:$CC$1003,$C60,MATCH(G$2,$N$2:$CC$2,0)))) -> 2933.4888 | E60: =IF(H$2="","",IF($C60="X","",INDEX($N$3:$CC$1003,$C60,MATCH(H$2,$N$2:$CC$2,0)))) | F60: =IF(I$2="","",IF($C60="X","",INDEX($N$3:$CC$1003,$C60,MATCH(I$2,$N$2:$CC$2,0)))) | G60: =IF(A60="","",IF(G$2="","", IF(D60="",IF($K$16="Use global average",D$276,IF($K$16="Use regional average",INDEX(D$280:D$296,MATCH($B60,$B$280:$B$296,0)),IF($K$16="Leave blank","",IF($K$16="Fill with zeros", 0,IF($K$16="Use global median",D$277,"Fill out I16"))))), D60))) -> 2933.4888 | H60: =IF(H$2="","", IF(E60="",IF($K$16="Use global average",E$276,IF($K$16="Use regional average",INDEX(E$280:E$296,MATCH($B60,$B$280:$B$296,0)),IF($K$16="Leave blank","",IF($K$16="Fill with zeros", 0,IF($K$16="Use global median",E$277,"Fill out I16"))))), E60)) | I60: =IF(I$2="","", IF(F60="",IF($K$16="Use global average",F$276,IF($K$16="Use regional average",INDEX(F$280:F$296,MATCH($B60,$B$280:$B$296,0)),IF($K$16="Leave blank","",IF($K$16="Fill with zeros", 0,IF($K$16="Use global median",F$277,"Fill out I16"))))), F60)) | L60: =IF(M60="","",IF(COUNTIF(Countries!$B$1:$H$271,M60)>0,"",IF(COUNTIF(Countries!$M$1:$S$271,M60)>0,"Not a country","ERROR – NOT LISTED. Add alt spelling to ''Countries'' tab"))) | M60: El Salvador | N60: 10.355628 | O60: =N60*365*1.28 -> 4838.1494 | P60: 0.4972312 | Q60: 0.03 | R60: =IFERROR(O60/(P60*(1-Q60)),"") -> 10031.114
A61: =Countries!B60 -> Ethiopia | B61: =Countries!I60 -> Sub-Saharan Africa | C61: =IFERROR(IFERROR(IFERROR(IFERROR(IFERROR(IFERROR(IFERROR(MATCH(Countries!$B60,$M$3:$M$1003,0),MATCH(Countries!$C60,$M$3:$M$1003,0)),MATCH(Countries!$D60,$M$3:$M$1003,0)),MATCH(Countries!$E60,$M$3:$M$1003,0)),MATCH(Countries!$F60,$M$3:$M$1003,0)),MATCH(Countries!$G60,$M$3:$M$1003,0)),MATCH(Countries!$H60,$M$3:$M$1003,0)),"X") -> 63 | D61: =IF(G$2="","",IF($C61="X","",INDEX($N$3:$CC$1003,$C61,MATCH(G$2,$N$2:$CC$2,0)))) -> 2000.8108 | E61: =IF(H$2="","",IF($C61="X","",INDEX($N$3:$CC$1003,$C61,MATCH(H$2,$N$2:$CC$2,0)))) | F61: =IF(I$2="","",IF($C61="X","",INDEX($N$3:$CC$1003,$C61,MATCH(I$2,$N$2:$CC$2,0)))) | G61: =IF(A61="","",IF(G$2="","", IF(D61="",IF($K$16="Use global average",D$276,IF($K$16="Use regional average",INDEX(D$280:D$296,MATCH($B61,$B$280:$B$296,0)),IF($K$16="Leave blank","",IF($K$16="Fill with zeros", 0,IF($K$16="Use global median",D$277,"Fill out I16"))))), D61))) -> 2000.8108 | H61: =IF(H$2="","", IF(E61="",IF($K$16="Use global average",E$276,IF($K$16="Use regional average",INDEX(E$280:E$296,MATCH($B61,$B$280:$B$296,0)),IF($K$16="Leave blank","",IF($K$16="Fill with zeros", 0,IF($K$16="Use global median",E$277,"Fill out I16"))))), E61)) | I61: =IF(I$2="","", IF(F61="",IF($K$16="Use global average",F$276,IF($K$16="Use regional average",INDEX(F$280:F$296,MATCH($B61,$B$280:$B$296,0)),IF($K$16="Leave blank","",IF($K$16="Fill with zeros", 0,IF($K$16="Use global median",F$277,"Fill out I16"))))), F61)) | L61: =IF(M61="","",IF(COUNTIF(Countries!$B$1:$H$271,M61)>0,"",IF(COUNTIF(Countries!$M$1:$S$271,M61)>0,"Not a country","ERROR – NOT LISTED. Add alt spelling to ''Countries'' tab"))) | M61: Equatorial Guinea | N61: NA | O61: =N61*365*1.28 -> #VALUE! | P61: 0.6980037 | Q61: 0.08584 | R61: =IFERROR(O61/(P61*(1-Q61)),"")
A62: =Countries!B61 -> Fiji | B62: =Countries!I61 -> Oceania | C62: =IFERROR(IFERROR(IFERROR(IFERROR(IFERROR(IFERROR(IFERROR(MATCH(Countries!$B61,$M$3:$M$1003,0),MATCH(Countries!$C61,$M$3:$M$1003,0)),MATCH(Countries!$D61,$M$3:$M$1003,0)),MATCH(Countries!$E61,$M$3:$M$1003,0)),MATCH(Countries!$F61,$M$3:$M$1003,0)),MATCH(Countries!$G61,$M$3:$M$1003,0)),MATCH(Countries!$H61,$M$3:$M$1003,0)),"X") -> 64 | D62: =IF(G$2="","",IF($C62="X","",INDEX($N$3:$CC$1003,$C62,MATCH(G$2,$N$2:$CC$2,0)))) -> 6390.018 | E62: =IF(H$2="","",IF($C62="X","",INDEX($N$3:$CC$1003,$C62,MATCH(H$2,$N$2:$CC$2,0)))) | F62: =IF(I$2="","",IF($C62="X","",INDEX($N$3:$CC$1003,$C62,MATCH(I$2,$N$2:$CC$2,0)))) | G62: =IF(A62="","",IF(G$2="","", IF(D62="",IF($K$16="Use global average",D$276,IF($K$16="Use regional average",INDEX(D$280:D$296,MATCH($B62,$B$280:$B$296,0)),IF($K$16="Leave blank","",IF($K$16="Fill with zeros", 0,IF($K$16="Use global median",D$277,"Fill out I16"))))), D62))) -> 6390.018 | H62: =IF(H$2="","", IF(E62="",IF($K$16="Use global average",E$276,IF($K$16="Use regional average",INDEX(E$280:E$296,MATCH($B62,$B$280:$B$296,0)),IF($K$16="Leave blank","",IF($K$16="Fill with zeros", 0,IF($K$16="Use global median",E$277,"Fill out I16"))))), E62)) | I62: =IF(I$2="","", IF(F62="",IF($K$16="Use global average",F$276,IF($K$16="Use regional average",INDEX(F$280:F$296,MATCH($B62,$B$280:$B$296,0)),IF($K$16="Leave blank","",IF($K$16="Fill with zeros", 0,IF($K$16="Use global median",F$277,"Fill out I16"))))), F62)) | L62: =IF(M62="","",IF(COUNTIF(Countries!$B$1:$H$271,M62)>0,"",IF(COUNTIF(Countries!$M$1:$S$271,M62)>0,"Not a country","ERROR – NOT LISTED. Add alt spelling to ''Countries'' tab"))) | M62: Eritrea | N62: NA | O62: =N62*365*1.28 -> #VALUE! | P62: 0.7491229 | Q62: 0.05974 | R62: =IFERROR(O62/(P62*(1-Q62)),"")
A63: =Countries!B62 -> Finland | B63: =Countries!I62 -> Europe | C63: =IFERROR(IFERROR(IFERROR(IFERROR(IFERROR(IFERROR(IFERROR(MATCH(Countries!$B62,$M$3:$M$1003,0),MATCH(Countries!$C62,$M$3:$M$1003,0)),MATCH(Countries!$D62,$M$3:$M$1003,0)),MATCH(Countries!$E62,$M$3:$M$1003,0)),MATCH(Countries!$F62,$M$3:$M$1003,0)),MATCH(Countries!$G62,$M$3:$M$1003,0)),MATCH(Countries!$H62,$M$3:$M$1003,0)),"X") -> 65 | D63: =IF(G$2="","",IF($C63="X","",INDEX($N$3:$CC$1003,$C63,MATCH(G$2,$N$2:$CC$2,0)))) -> 41473.727 | E63: =IF(H$2="","",IF($C63="X","",INDEX($N$3:$CC$1003,$C63,MATCH(H$2,$N$2:$CC$2,0)))) | F63: =IF(I$2="","",IF($C63="X","",INDEX($N$3:$CC$1003,$C63,MATCH(I$2,$N$2:$CC$2,0)))) | G63: =IF(A63="","",IF(G$2="","", IF(D63="",IF($K$16="Use global average",D$276,IF($K$16="Use regional average",INDEX(D$280:D$296,MATCH($B63,$B$280:$B$296,0)),IF($K$16="Leave blank","",IF($K$16="Fill with zeros", 0,IF($K$16="Use global median",D$277,"Fill out I16"))))), D63))) -> 41473.727 | H63: =IF(H$2="","", IF(E63="",IF($K$16="Use global average",E$276,IF($K$16="Use regional average",INDEX(E$280:E$296,MATCH($B63,$B$280:$B$296,0)),IF($K$16="Leave blank","",IF($K$16="Fill with zeros", 0,IF($K$16="Use global median",E$277,"Fill out I16"))))), E63)) | I63: =IF(I$2="","", IF(F63="",IF($K$16="Use global average",F$276,IF($K$16="Use regional average",INDEX(F$280:F$296,MATCH($B63,$B$280:$B$296,0)),IF($K$16="Leave blank","",IF($K$16="Fill with zeros", 0,IF($K$16="Use global median",F$277,"Fill out I16"))))), F63)) | L63: =IF(M63="","",IF(COUNTIF(Countries!$B$1:$H$271,M63)>0,"",IF(COUNTIF(Countries!$M$1:$S$271,M63)>0,"Not a country","ERROR – NOT LISTED. Add alt spelling to ''Countries'' tab"))) | M63: Estonia | N63: 40.0546 | O63: =N63*365*1.28 -> 18713.509 | P63: 0.58404476 | Q63: 0.0557 | R63: =IFERROR(O63/(P63*(1-Q63)),"") -> 33931.192
A64: =Countries!B63 -> France | B64: =Countries!I63 -> Europe | C64: =IFERROR(IFERROR(IFERROR(IFERROR(IFERROR(IFERROR(IFERROR(MATCH(Countries!$B63,$M$3:$M$1003,0),MATCH(Countries!$C63,$M$3:$M$1003,0)),MATCH(Countries!$D63,$M$3:$M$1003,0)),MATCH(Countries!$E63,$M$3:$M$1003,0)),MATCH(Countries!$F63,$M$3:$M$1003,0)),MATCH(Countries!$G63,$M$3:$M$1003,0)),MATCH(Countries!$H63,$M$3:$M$1003,0)),"X") -> 66 | D64: =IF(G$2="","",IF($C64="X","",INDEX($N$3:$CC$1003,$C64,MATCH(G$2,$N$2:$CC$2,0)))) -> 40069.463 | E64: =IF(H$2="","",IF($C64="X","",INDEX($N$3:$CC$1003,$C64,MATCH(H$2,$N$2:$CC$2,0)))) | F64: =IF(I$2="","",IF($C64="X","",INDEX($N$3:$CC$1003,$C64,MATCH(I$2,$N$2:$CC$2,0)))) | G64: =IF(A64="","",IF(G$2="","", IF(D64="",IF($K$16="Use global average",D$276,IF($K$16="Use regional average",INDEX(D$280:D$296,MATCH($B64,$B$280:$B$296,0)),IF($K$16="Leave blank","",IF($K$16="Fill with zeros", 0,IF($K$16="Use global median",D$277,"Fill out I16"))))), D64))) -> 40069.463 | H64: =IF(H$2="","", IF(E64="",IF($K$16="Use global average",E$276,IF($K$16="Use regional average",INDEX(E$280:E$296,MATCH($B64,$B$280:$B$296,0)),IF($K$16="Leave blank","",IF($K$16="Fill with zeros", 0,IF($K$16="Use global median",E$277,"Fill out I16"))))), E64)) | I64: =IF(I$2="","", IF(F64="",IF($K$16="Use global average",F$276,IF($K$16="Use regional average",INDEX(F$280:F$296,MATCH($B64,$B$280:$B$296,0)),IF($K$16="Leave blank","",IF($K$16="Fill with zeros", 0,IF($K$16="Use global median",F$277,"Fill out I16"))))), F64)) | L64: =IF(M64="","",IF(COUNTIF(Countries!$B$1:$H$271,M64)>0,"",IF(COUNTIF(Countries!$M$1:$S$271,M64)>0,"Not a country","ERROR – NOT LISTED. Add alt spelling to ''Countries'' tab"))) | M64: Eswatini | N64: 2.9537303 | O64: =N64*365*1.28 -> 1379.9828 | P64: 0.60812046 | Q64: 0.22643 | R64: =IFERROR(O64/(P64*(1-Q64)),"") -> 2933.4888
A65: =Countries!B64 -> Gabon | B65: =Countries!I64 -> Sub-Saharan Africa | C65: =IFERROR(IFERROR(IFERROR(IFERROR(IFERROR(IFERROR(IFERROR(MATCH(Countries!$B64,$M$3:$M$1003,0),MATCH(Countries!$C64,$M$3:$M$1003,0)),MATCH(Countries!$D64,$M$3:$M$1003,0)),MATCH(Countries!$E64,$M$3:$M$1003,0)),MATCH(Countries!$F64,$M$3:$M$1003,0)),MATCH(Countries!$G64,$M$3:$M$1003,0)),MATCH(Countries!$H64,$M$3:$M$1003,0)),"X") -> 67 | D65: =IF(G$2="","",IF($C65="X","",INDEX($N$3:$CC$1003,$C65,MATCH(G$2,$N$2:$CC$2,0)))) -> 8292.94 | E65: =IF(H$2="","",IF($C65="X","",INDEX($N$3:$CC$1003,$C65,MATCH(H$2,$N$2:$CC$2,0)))) | F65: =IF(I$2="","",IF($C65="X","",INDEX($N$3:$CC$1003,$C65,MATCH(I$2,$N$2:$CC$2,0)))) | G65: =IF(A65="","",IF(G$2="","", IF(D65="",IF($K$16="Use global average",D$276,IF($K$16="Use regional average",INDEX(D$280:D$296,MATCH($B65,$B$280:$B$296,0)),IF($K$16="Leave blank","",IF($K$16="Fill with zeros", 0,IF($K$16="Use global median",D$277,"Fill out I16"))))), D65))) -> 8292.94 | H65: =IF(H$2="","", IF(E65="",IF($K$16="Use global average",E$276,IF($K$16="Use regional average",INDEX(E$280:E$296,MATCH($B65,$B$280:$B$296,0)),IF($K$16="Leave blank","",IF($K$16="Fill with zeros", 0,IF($K$16="Use global median",E$277,"Fill out I16"))))), E65)) | I65: =IF(I$2="","", IF(F65="",IF($K$16="Use global average",F$276,IF($K$16="Use regional average",INDEX(F$280:F$296,MATCH($B65,$B$280:$B$296,0)),IF($K$16="Leave blank","",IF($K$16="Fill with zeros", 0,IF($K$16="Use global median",F$277,"Fill out I16"))))), F65)) | L65: =IF(M65="","",IF(COUNTIF(Countries!$B$1:$H$271,M65)>0,"",IF(COUNTIF(Countries!$M$1:$S$271,M65)>0,"Not a country","ERROR – NOT LISTED. Add alt spelling to ''Countries'' tab"))) | M65: Ethiopia | N65: 3.0618846 | O65: =N65*365*1.28 -> 1430.5125 | P65: 0.7402458 | Q65: 0.03415 | R65: =IFERROR(O65/(P65*(1-Q65)),"") -> 2000.8108
A66: =Countries!B65 -> Gambia | B66: =Countries!I65 -> Sub-Saharan Africa | C66: =IFERROR(IFERROR(IFERROR(IFERROR(IFERROR(IFERROR(IFERROR(MATCH(Countries!$B65,$M$3:$M$1003,0),MATCH(Countries!$C65,$M$3:$M$1003,0)),MATCH(Countries!$D65,$M$3:$M$1003,0)),MATCH(Countries!$E65,$M$3:$M$1003,0)),MATCH(Countries!$F65,$M$3:$M$1003,0)),MATCH(Countries!$G65,$M$3:$M$1003,0)),MATCH(Countries!$H65,$M$3:$M$1003,0)),"X") -> 68 | D66: =IF(G$2="","",IF($C66="X","",INDEX($N$3:$CC$1003,$C66,MATCH(G$2,$N$2:$CC$2,0)))) -> 2400.6524 | E66: =IF(H$2="","",IF($C66="X","",INDEX($N$3:$CC$1003,$C66,MATCH(H$2,$N$2:$CC$2,0)))) | F66: =IF(I$2="","",IF($C66="X","",INDEX($N$3:$CC$1003,$C66,MATCH(I$2,$N$2:$CC$2,0)))) | G66: =IF(A66="","",IF(G$2="","", IF(D66="",IF($K$16="Use global average",D$276,IF($K$16="Use regional average",INDEX(D$280:D$296,MATCH($B66,$B$280:$B$296,0)),IF($K$16="Leave blank","",IF($K$16="Fill with zeros", 0,IF($K$16="Use global median",D$277,"Fill out I16"))))), D66))) -> 2400.6524 | H66: =IF(H$2="","", IF(E66="",IF($K$16="Use global average",E$276,IF($K$16="Use regional average",INDEX(E$280:E$296,MATCH($B66,$B$280:$B$296,0)),IF($K$16="Leave blank","",IF($K$16="Fill with zeros", 0,IF($K$16="Use global median",E$277,"Fill out I16"))))), E66)) | I66: =IF(I$2="","", IF(F66="",IF($K$16="Use global average",F$276,IF($K$16="Use regional average",INDEX(F$280:F$296,MATCH($B66,$B$280:$B$296,0)),IF($K$16="Leave blank","",IF($K$16="Fill with zeros", 0,IF($K$16="Use global median",F$277,"Fill out I16"))))), F66)) | L66: =IF(M66="","",IF(COUNTIF(Countries!$B$1:$H$271,M66)>0,"",IF(COUNTIF(Countries!$M$1:$S$271,M66)>0,"Not a country","ERROR – NOT LISTED. Add alt spelling to ''Countries'' tab"))) | M66: Fiji | N66: 6.643387 | O66: =N66*365*1.28 -> 3103.7904 | P66: 0.5089428 | Q66: 0.04562 | R66: =IFERROR(O66/(P66*(1-Q66)),"") -> 6390.018
A67: =Countries!B66 -> Georgia | B67: =Countries!I66 -> Europe | C67: =IFERROR(IFERROR(IFERROR(IFERROR(IFERROR(IFERROR(IFERROR(MATCH(Countries!$B66,$M$3:$M$1003,0),MATCH(Countries!$C66,$M$3:$M$1003,0)),MATCH(Countries!$D66,$M$3:$M$1003,0)),MATCH(Countries!$E66,$M$3:$M$1003,0)),MATCH(Countries!$F66,$M$3:$M$1003,0)),MATCH(Countries!$G66,$M$3:$M$1003,0)),MATCH(Countries!$H66,$M$3:$M$1003,0)),"X") -> 69 | D67: =IF(G$2="","",IF($C67="X","",INDEX($N$3:$CC$1003,$C67,MATCH(G$2,$N$2:$CC$2,0)))) -> 5875.0578 | E67: =IF(H$2="","",IF($C67="X","",INDEX($N$3:$CC$1003,$C67,MATCH(H$2,$N$2:$CC$2,0)))) | F67: =IF(I$2="","",IF($C67="X","",INDEX($N$3:$CC$1003,$C67,MATCH(I$2,$N$2:$CC$2,0)))) | G67: =IF(A67="","",IF(G$2="","", IF(D67="",IF($K$16="Use global average",D$276,IF($K$16="Use regional average",INDEX(D$280:D$296,MATCH($B67,$B$280:$B$296,0)),IF($K$16="Leave blank","",IF($K$16="Fill with zeros", 0,IF($K$16="Use global median",D$277,"Fill out I16"))))), D67))) -> 5875.0578 | H67: =IF(H$2="","", IF(E67="",IF($K$16="Use global average",E$276,IF($K$16="Use regional average",INDEX(E$280:E$296,MATCH($B67,$B$280:$B$296,0)),IF($K$16="Leave blank","",IF($K$16="Fill with zeros", 0,IF($K$16="Use global median",E$277,"Fill out I16"))))), E67)) | I67: =IF(I$2="","", IF(F67="",IF($K$16="Use global average",F$276,IF($K$16="Use regional average",INDEX(F$280:F$296,MATCH($B67,$B$280:$B$296,0)),IF($K$16="Leave blank","",IF($K$16="Fill with zeros", 0,IF($K$16="Use global median",F$277,"Fill out I16"))))), F67)) | L67: =IF(M67="","",IF(COUNTIF(Countries!$B$1:$H$271,M67)>0,"",IF(COUNTIF(Countries!$M$1:$S$271,M67)>0,"Not a country","ERROR – NOT LISTED. Add alt spelling to ''Countries'' tab"))) | M67: Finland | N67: 51.83912 | O67: =N67*365*1.28 -> 24219.237 | P67: 0.62603535 | Q67: 0.0672 | R67: =IFERROR(O67/(P67*(1-Q67)),"") -> 41473.727
A68: =Countries!B67 -> Germany | B68: =Countries!I67 -> Europe | C68: =IFERROR(IFERROR(IFERROR(IFERROR(IFERROR(IFERROR(IFERROR(MATCH(Countries!$B67,$M$3:$M$1003,0),MATCH(Countries!$C67,$M$3:$M$1003,0)),MATCH(Countries!$D67,$M$3:$M$1003,0)),MATCH(Countries!$E67,$M$3:$M$1003,0)),MATCH(Countries!$F67,$M$3:$M$1003,0)),MATCH(Countries!$G67,$M$3:$M$1003,0)),MATCH(Countries!$H67,$M$3:$M$1003,0)),"X") -> 70 | D68: =IF(G$2="","",IF($C68="X","",INDEX($N$3:$CC$1003,$C68,MATCH(G$2,$N$2:$CC$2,0)))) -> 46342.344 | E68: =IF(H$2="","",IF($C68="X","",INDEX($N$3:$CC$1003,$C68,MATCH(H$2,$N$2:$CC$2,0)))) | F68: =IF(I$2="","",IF($C68="X","",INDEX($N$3:$CC$1003,$C68,MATCH(I$2,$N$2:$CC$2,0)))) | G68: =IF(A68="","",IF(G$2="","", IF(D68="",IF($K$16="Use global average",D$276,IF($K$16="Use regional average",INDEX(D$280:D$296,MATCH($B68,$B$280:$B$296,0)),IF($K$16="Leave blank","",IF($K$16="Fill with zeros", 0,IF($K$16="Use global median",D$277,"Fill out I16"))))), D68))) -> 46342.344 | H68: =IF(H$2="","", IF(E68="",IF($K$16="Use global average",E$276,IF($K$16="Use regional average",INDEX(E$280:E$296,MATCH($B68,$B$280:$B$296,0)),IF($K$16="Leave blank","",IF($K$16="Fill with zeros", 0,IF($K$16="Use global median",E$277,"Fill out I16"))))), E68)) | I68: =IF(I$2="","", IF(F68="",IF($K$16="Use global average",F$276,IF($K$16="Use regional average",INDEX(F$280:F$296,MATCH($B68,$B$280:$B$296,0)),IF($K$16="Leave blank","",IF($K$16="Fill with zeros", 0,IF($K$16="Use global median",F$277,"Fill out I16"))))), F68)) | L68: =IF(M68="","",IF(COUNTIF(Countries!$B$1:$H$271,M68)>0,"",IF(COUNTIF(Countries!$M$1:$S$271,M68)>0,"Not a country","ERROR – NOT LISTED. Add alt spelling to ''Countries'' tab"))) | M68: France | N68: 49.779552 | O68: =N68*365*1.28 -> 23257.007 | P68: 0.62619186 | Q68: 0.0731 | R68: =IFERROR(O68/(P68*(1-Q68)),"") -> 40069.463
A69: =Countries!B68 -> Ghana | B69: =Countries!I68 -> Sub-Saharan Africa | C69: =IFERROR(IFERROR(IFERROR(IFERROR(IFERROR(IFERROR(IFERROR(MATCH(Countries!$B68,$M$3:$M$1003,0),MATCH(Countries!$C68,$M$3:$M$1003,0)),MATCH(Countries!$D68,$M$3:$M$1003,0)),MATCH(Countries!$E68,$M$3:$M$1003,0)),MATCH(Countries!$F68,$M$3:$M$1003,0)),MATCH(Countries!$G68,$M$3:$M$1003,0)),MATCH(Countries!$H68,$M$3:$M$1003,0)),"X") -> 71 | D69: =IF(G$2="","",IF($C69="X","",INDEX($N$3:$CC$1003,$C69,MATCH(G$2,$N$2:$CC$2,0)))) -> 2736.5771 | E69: =IF(H$2="","",IF($C69="X","",INDEX($N$3:$CC$1003,$C69,MATCH(H$2,$N$2:$CC$2,0)))) | F69: =IF(I$2="","",IF($C69="X","",INDEX($N$3:$CC$1003,$C69,MATCH(I$2,$N$2:$CC$2,0)))) | G69: =IF(A69="","",IF(G$2="","", IF(D69="",IF($K$16="Use global average",D$276,IF($K$16="Use regional average",INDEX(D$280:D$296,MATCH($B69,$B$280:$B$296,0)),IF($K$16="Leave blank","",IF($K$16="Fill with zeros", 0,IF($K$16="Use global median",D$277,"Fill out I16"))))), D69))) -> 2736.5771 | H69: =IF(H$2="","", IF(E69="",IF($K$16="Use global average",E$276,IF($K$16="Use regional average",INDEX(E$280:E$296,MATCH($B69,$B$280:$B$296,0)),IF($K$16="Leave blank","",IF($K$16="Fill with zeros", 0,IF($K$16="Use global median",E$277,"Fill out I16"))))), E69)) | I69: =IF(I$2="","", IF(F69="",IF($K$16="Use global average",F$276,IF($K$16="Use regional average",INDEX(F$280:F$296,MATCH($B69,$B$280:$B$296,0)),IF($K$16="Leave blank","",IF($K$16="Fill with zeros", 0,IF($K$16="Use global median",F$277,"Fill out I16"))))), F69)) | L69: =IF(M69="","",IF(COUNTIF(Countries!$B$1:$H$271,M69)>0,"",IF(COUNTIF(Countries!$M$1:$S$271,M69)>0,"Not a country","ERROR – NOT LISTED. Add alt spelling to ''Countries'' tab"))) | M69: Gabon | N69: 9.673192 | O69: =N69*365*1.28 -> 4519.3153 | P69: 0.68643326 | Q69: 0.2061 | R69: =IFERROR(O69/(P69*(1-Q69)),"") -> 8292.94
A70: =Countries!B69 -> Greece | B70: =Countries!I69 -> Europe | C70: =IFERROR(IFERROR(IFERROR(IFERROR(IFERROR(IFERROR(IFERROR(MATCH(Countries!$B69,$M$3:$M$1003,0),MATCH(Countries!$C69,$M$3:$M$1003,0)),MATCH(Countries!$D69,$M$3:$M$1003,0)),MATCH(Countries!$E69,$M$3:$M$1003,0)),MATCH(Countries!$F69,$M$3:$M$1003,0)),MATCH(Countries!$G69,$M$3:$M$1003,0)),MATCH(Countries!$H69,$M$3:$M$1003,0)),"X") -> 72 | D70: =IF(G$2="","",IF($C70="X","",INDEX($N$3:$CC$1003,$C70,MATCH(G$2,$N$2:$CC$2,0)))) -> 23959.568 | E70: =IF(H$2="","",IF($C70="X","",INDEX($N$3:$CC$1003,$C70,MATCH(H$2,$N$2:$CC$2,0)))) | F70: =IF(I$2="","",IF($C70="X","",INDEX($N$3:$CC$1003,$C70,MATCH(I$2,$N$2:$CC$2,0)))) | G70: =IF(A70="","",IF(G$2="","", IF(D70="",IF($K$16="Use global average",D$276,IF($K$16="Use regional average",INDEX(D$280:D$296,MATCH($B70,$B$280:$B$296,0)),IF($K$16="Leave blank","",IF($K$16="Fill with zeros", 0,IF($K$16="Use global median",D$277,"Fill out I16"))))), D70))) -> 23959.568 | H70: =IF(H$2="","", IF(E70="",IF($K$16="Use global average",E$276,IF($K$16="Use regional average",INDEX(E$280:E$296,MATCH($B70,$B$280:$B$296,0)),IF($K$16="Leave blank","",IF($K$16="Fill with zeros", 0,IF($K$16="Use global median",E$277,"Fill out I16"))))), E70)) | I70: =IF(I$2="","", IF(F70="",IF($K$16="Use global average",F$276,IF($K$16="Use regional average",INDEX(F$280:F$296,MATCH($B70,$B$280:$B$296,0)),IF($K$16="Leave blank","",IF($K$16="Fill with zeros", 0,IF($K$16="Use global median",F$277,"Fill out I16"))))), F70)) | L70: =IF(M70="","",IF(COUNTIF(Countries!$B$1:$H$271,M70)>0,"",IF(COUNTIF(Countries!$M$1:$S$271,M70)>0,"Not a country","ERROR – NOT LISTED. Add alt spelling to ''Countries'' tab"))) | M70: Gambia | N70: 3.8196523 | O70: =N70*365*1.28 -> 1784.5416 | P70: 0.7764735 | Q70: 0.04265 | R70: =IFERROR(O70/(P70*(1-Q70)),"") -> 2400.6524
A71: =Countries!B70 -> Grenada | B71: =Countries!I70 -> Caribbean | C71: =IFERROR(IFERROR(IFERROR(IFERROR(IFERROR(IFERROR(IFERROR(MATCH(Countries!$B70,$M$3:$M$1003,0),MATCH(Countries!$C70,$M$3:$M$1003,0)),MATCH(Countries!$D70,$M$3:$M$1003,0)),MATCH(Countries!$E70,$M$3:$M$1003,0)),MATCH(Countries!$F70,$M$3:$M$1003,0)),MATCH(Countries!$G70,$M$3:$M$1003,0)),MATCH(Countries!$H70,$M$3:$M$1003,0)),"X") -> 73 | D71: =IF(G$2="","",IF($C71="X","",INDEX($N$3:$CC$1003,$C71,MATCH(G$2,$N$2:$CC$2,0)))) | E71: =IF(H$2="","",IF($C71="X","",INDEX($N$3:$CC$1003,$C71,MATCH(H$2,$N$2:$CC$2,0)))) | F71: =IF(I$2="","",IF($C71="X","",INDEX($N$3:$CC$1003,$C71,MATCH(I$2,$N$2:$CC$2,0)))) | G71: =IF(A71="","",IF(G$2="","", IF(D71="",IF($K$16="Use global average",D$276,IF($K$16="Use regional average",INDEX(D$280:D$296,MATCH($B71,$B$280:$B$296,0)),IF($K$16="Leave blank","",IF($K$16="Fill with zeros", 0,IF($K$16="Use global median",D$277,"Fill out I16"))))), D71))) -> 12713.18 | H71: =IF(H$2="","", IF(E71="",IF($K$16="Use global average",E$276,IF($K$16="Use regional average",INDEX(E$280:E$296,MATCH($B71,$B$280:$B$296,0)),IF($K$16="Leave blank","",IF($K$16="Fill with zeros", 0,IF($K$16="Use global median",E$277,"Fill out I16"))))), E71)) | I71: =IF(I$2="","", IF(F71="",IF($K$16="Use global average",F$276,IF($K$16="Use regional average",INDEX(F$280:F$296,MATCH($B71,$B$280:$B$296,0)),IF($K$16="Leave blank","",IF($K$16="Fill with zeros", 0,IF($K$16="Use global median",F$277,"Fill out I16"))))), F71)) | L71: =IF(M71="","",IF(COUNTIF(Countries!$B$1:$H$271,M71)>0,"",IF(COUNTIF(Countries!$M$1:$S$271,M71)>0,"Not a country","ERROR – NOT LISTED. Add alt spelling to ''Countries'' tab"))) | M71: Georgia | N71: 6.3433757 | O71: =N71*365*1.28 -> 2963.6251 | P71: 0.57117188 | Q71: 0.11683 | R71: =IFERROR(O71/(P71*(1-Q71)),"") -> 5875.0578
A72: =Countries!B71 -> Guatemala | B72: =Countries!I71 -> Latin America | C72: =IFERROR(IFERROR(IFERROR(IFERROR(IFERROR(IFERROR(IFERROR(MATCH(Countries!$B71,$M$3:$M$1003,0),MATCH(Countries!$C71,$M$3:$M$1003,0)),MATCH(Countries!$D71,$M$3:$M$1003,0)),MATCH(Countries!$E71,$M$3:$M$1003,0)),MATCH(Countries!$F71,$M$3:$M$1003,0)),MATCH(Countries!$G71,$M$3:$M$1003,0)),MATCH(Countries!$H71,$M$3:$M$1003,0)),"X") -> 74 | D72: =IF(G$2="","",IF($C72="X","",INDEX($N$3:$CC$1003,$C72,MATCH(G$2,$N$2:$CC$2,0)))) -> 5090.143 | E72: =IF(H$2="","",IF($C72="X","",INDEX($N$3:$CC$1003,$C72,MATCH(H$2,$N$2:$CC$2,0)))) | F72: =IF(I$2="","",IF($C72="X","",INDEX($N$3:$CC$1003,$C72,MATCH(I$2,$N$2:$CC$2,0)))) | G72: =IF(A72="","",IF(G$2="","", IF(D72="",IF($K$16="Use global average",D$276,IF($K$16="Use regional average",INDEX(D$280:D$296,MATCH($B72,$B$280:$B$296,0)),IF($K$16="Leave blank","",IF($K$16="Fill with zeros", 0,IF($K$16="Use global median",D$277,"Fill out I16"))))), D72))) -> 5090.143 | H72: =IF(H$2="","", IF(E72="",IF($K$16="Use global average",E$276,IF($K$16="Use regional average",INDEX(E$280:E$296,MATCH($B72,$B$280:$B$296,0)),IF($K$16="Leave blank","",IF($K$16="Fill with zeros", 0,IF($K$16="Use global median",E$277,"Fill out I16"))))), E72)) | I72: =IF(I$2="","", IF(F72="",IF($K$16="Use global average",F$276,IF($K$16="Use regional average",INDEX(F$280:F$296,MATCH($B72,$B$280:$B$296,0)),IF($K$16="Leave blank","",IF($K$16="Fill with zeros", 0,IF($K$16="Use global median",F$277,"Fill out I16"))))), F72)) | L72: =IF(M72="","",IF(COUNTIF(Countries!$B$1:$H$271,M72)>0,"",IF(COUNTIF(Countries!$M$1:$S$271,M72)>0,"Not a country","ERROR – NOT LISTED. Add alt spelling to ''Countries'' tab"))) | M72: Germany | N72: 55.684296 | O72: =N72*365*1.28 -> 26015.703 | P72: 0.57957962 | Q72: 0.0314 | R72: =IFERROR(O72/(P72*(1-Q72)),"") -> 46342.344
A73: =Countries!B72 -> Guinea | B73: =Countries!I72 -> Sub-Saharan Africa | C73: =IFERROR(IFERROR(IFERROR(IFERROR(IFERROR(IFERROR(IFERROR(MATCH(Countries!$B72,$M$3:$M$1003,0),MATCH(Countries!$C72,$M$3:$M$1003,0)),MATCH(Countries!$D72,$M$3:$M$1003,0)),MATCH(Countries!$E72,$M$3:$M$1003,0)),MATCH(Countries!$F72,$M$3:$M$1003,0)),MATCH(Countries!$G72,$M$3:$M$1003,0)),MATCH(Countries!$H72,$M$3:$M$1003,0)),"X") -> 75 | D73: =IF(G$2="","",IF($C73="X","",INDEX($N$3:$CC$1003,$C73,MATCH(G$2,$N$2:$CC$2,0)))) -> 2328.665 | E73: =IF(H$2="","",IF($C73="X","",INDEX($N$3:$CC$1003,$C73,MATCH(H$2,$N$2:$CC$2,0)))) | F73: =IF(I$2="","",IF($C73="X","",INDEX($N$3:$CC$1003,$C73,MATCH(I$2,$N$2:$CC$2,0)))) | G73: =IF(A73="","",IF(G$2="","", IF(D73="",IF($K$16="Use global average",D$276,IF($K$16="Use regional average",INDEX(D$280:D$296,MATCH($B73,$B$280:$B$296,0)),IF($K$16="Leave blank","",IF($K$16="Fill with zeros", 0,IF($K$16="Use global median",D$277,"Fill out I16"))))), D73))) -> 2328.665 | H73: =IF(H$2="","", IF(E73="",IF($K$16="Use global average",E$276,IF($K$16="Use regional average",INDEX(E$280:E$296,MATCH($B73,$B$280:$B$296,0)),IF($K$16="Leave blank","",IF($K$16="Fill with zeros", 0,IF($K$16="Use global median",E$277,"Fill out I16"))))), E73)) | I73: =IF(I$2="","", IF(F73="",IF($K$16="Use global average",F$276,IF($K$16="Use regional average",INDEX(F$280:F$296,MATCH($B73,$B$280:$B$296,0)),IF($K$16="Leave blank","",IF($K$16="Fill with zeros", 0,IF($K$16="Use global median",F$277,"Fill out I16"))))), F73)) | L73: =IF(M73="","",IF(COUNTIF(Countries!$B$1:$H$271,M73)>0,"",IF(COUNTIF(Countries!$M$1:$S$271,M73)>0,"Not a country","ERROR – NOT LISTED. Add alt spelling to ''Countries'' tab"))) | M73: Ghana | N73: 3.7379272 | O73: =N73*365*1.28 -> 1746.3596 | P73: 0.6614236 | Q73: 0.03518 | R73: =IFERROR(O73/(P73*(1-Q73)),"") -> 2736.5771
A74: =Countries!B73 -> Guinea-Bissau | B74: =Countries!I73 -> Sub-Saharan Africa | C74: =IFERROR(IFERROR(IFERROR(IFERROR(IFERROR(IFERROR(IFERROR(MATCH(Countries!$B73,$M$3:$M$1003,0),MATCH(Countries!$C73,$M$3:$M$1003,0)),MATCH(Countries!$D73,$M$3:$M$1003,0)),MATCH(Countries!$E73,$M$3:$M$1003,0)),MATCH(Countries!$F73,$M$3:$M$1003,0)),MATCH(Countries!$G73,$M$3:$M$1003,0)),MATCH(Countries!$H73,$M$3:$M$1003,0)),"X") -> 76 | D74: =IF(G$2="","",IF($C74="X","",INDEX($N$3:$CC$1003,$C74,MATCH(G$2,$N$2:$CC$2,0)))) -> 2042.5864 | E74: =IF(H$2="","",IF($C74="X","",INDEX($N$3:$CC$1003,$C74,MATCH(H$2,$N$2:$CC$2,0)))) | F74: =IF(I$2="","",IF($C74="X","",INDEX($N$3:$CC$1003,$C74,MATCH(I$2,$N$2:$CC$2,0)))) | G74: =IF(A74="","",IF(G$2="","", IF(D74="",IF($K$16="Use global average",D$276,IF($K$16="Use regional average",INDEX(D$280:D$296,MATCH($B74,$B$280:$B$296,0)),IF($K$16="Leave blank","",IF($K$16="Fill with zeros", 0,IF($K$16="Use global median",D$277,"Fill out I16"))))), D74))) -> 2042.5864 | H74: =IF(H$2="","", IF(E74="",IF($K$16="Use global average",E$276,IF($K$16="Use regional average",INDEX(E$280:E$296,MATCH($B74,$B$280:$B$296,0)),IF($K$16="Leave blank","",IF($K$16="Fill with zeros", 0,IF($K$16="Use global median",E$277,"Fill out I16"))))), E74)) | I74: =IF(I$2="","", IF(F74="",IF($K$16="Use global average",F$276,IF($K$16="Use regional average",INDEX(F$280:F$296,MATCH($B74,$B$280:$B$296,0)),IF($K$16="Leave blank","",IF($K$16="Fill with zeros", 0,IF($K$16="Use global median",F$277,"Fill out I16"))))), F74)) | L74: =IF(M74="","",IF(COUNTIF(Countries!$B$1:$H$271,M74)>0,"",IF(COUNTIF(Countries!$M$1:$S$271,M74)>0,"Not a country","ERROR – NOT LISTED. Add alt spelling to ''Countries'' tab"))) | M74: Greece | N74: 26.430964 | O74: =N74*365*1.28 -> 12348.546 | P74: 0.58854748 | Q74: 0.1243 | R74: =IFERROR(O74/(P74*(1-Q74)),"") -> 23959.568
A75: =Countries!B74 -> Guyana | B75: =Countries!I74 -> Latin America | C75: =IFERROR(IFERROR(IFERROR(IFERROR(IFERROR(IFERROR(IFERROR(MATCH(Countries!$B74,$M$3:$M$1003,0),MATCH(Countries!$C74,$M$3:$M$1003,0)),MATCH(Countries!$D74,$M$3:$M$1003,0)),MATCH(Countries!$E74,$M$3:$M$1003,0)),MATCH(Countries!$F74,$M$3:$M$1003,0)),MATCH(Countries!$G74,$M$3:$M$1003,0)),MATCH(Countries!$H74,$M$3:$M$1003,0)),"X") -> 77 | D75: =IF(G$2="","",IF($C75="X","",INDEX($N$3:$CC$1003,$C75,MATCH(G$2,$N$2:$CC$2,0)))) -> 5772.8018 | E75: =IF(H$2="","",IF($C75="X","",INDEX($N$3:$CC$1003,$C75,MATCH(H$2,$N$2:$CC$2,0)))) | F75: =IF(I$2="","",IF($C75="X","",INDEX($N$3:$CC$1003,$C75,MATCH(I$2,$N$2:$CC$2,0)))) | G75: =IF(A75="","",IF(G$2="","", IF(D75="",IF($K$16="Use global average",D$276,IF($K$16="Use regional average",INDEX(D$280:D$296,MATCH($B75,$B$280:$B$296,0)),IF($K$16="Leave blank","",IF($K$16="Fill with zeros", 0,IF($K$16="Use global median",D$277,"Fill out I16"))))), D75))) -> 5772.8018 | H75: =IF(H$2="","", IF(E75="",IF($K$16="Use global average",E$276,IF($K$16="Use regional average",INDEX(E$280:E$296,MATCH($B75,$B$280:$B$296,0)),IF($K$16="Leave blank","",IF($K$16="Fill with zeros", 0,IF($K$16="Use global median",E$277,"Fill out I16"))))), E75)) | I75: =IF(I$2="","", IF(F75="",IF($K$16="Use global average",F$276,IF($K$16="Use regional average",INDEX(F$280:F$296,MATCH($B75,$B$280:$B$296,0)),IF($K$16="Leave blank","",IF($K$16="Fill with zeros", 0,IF($K$16="Use global median",F$277,"Fill out I16"))))), F75)) | L75: =IF(M75="","",IF(COUNTIF(Countries!$B$1:$H$271,M75)>0,"",IF(COUNTIF(Countries!$M$1:$S$271,M75)>0,"Not a country","ERROR – NOT LISTED. Add alt spelling to ''Countries'' tab"))) | M75: Grenada | N75: 14.055036 | O75: =N75*365*1.28 -> 6566.5128 | P75: 0.4642951 | Q75: #VALUE! | R75: =IFERROR(O75/(P75*(1-Q75)),"")
A76: =Countries!B75 -> Haiti | B76: =Countries!I75 -> Caribbean | C76: =IFERROR(IFERROR(IFERROR(IFERROR(IFERROR(IFERROR(IFERROR(MATCH(Countries!$B75,$M$3:$M$1003,0),MATCH(Countries!$C75,$M$3:$M$1003,0)),MATCH(Countries!$D75,$M$3:$M$1003,0)),MATCH(Countries!$E75,$M$3:$M$1003,0)),MATCH(Countries!$F75,$M$3:$M$1003,0)),MATCH(Countries!$G75,$M$3:$M$1003,0)),MATCH(Countries!$H75,$M$3:$M$1003,0)),"X") -> 78 | D76: =IF(G$2="","",IF($C76="X","",INDEX($N$3:$CC$1003,$C76,MATCH(G$2,$N$2:$CC$2,0)))) -> 1648.1585 | E76: =IF(H$2="","",IF($C76="X","",INDEX($N$3:$CC$1003,$C76,MATCH(H$2,$N$2:$CC$2,0)))) | F76: =IF(I$2="","",IF($C76="X","",INDEX($N$3:$CC$1003,$C76,MATCH(I$2,$N$2:$CC$2,0)))) | G76: =IF(A76="","",IF(G$2="","", IF(D76="",IF($K$16="Use global average",D$276,IF($K$16="Use regional average",INDEX(D$280:D$296,MATCH($B76,$B$280:$B$296,0)),IF($K$16="Leave blank","",IF($K$16="Fill with zeros", 0,IF($K$16="Use global median",D$277,"Fill out I16"))))), D76))) -> 1648.1585 | H76: =IF(H$2="","", IF(E76="",IF($K$16="Use global average",E$276,IF($K$16="Use regional average",INDEX(E$280:E$296,MATCH($B76,$B$280:$B$296,0)),IF($K$16="Leave blank","",IF($K$16="Fill with zeros", 0,IF($K$16="Use global median",E$277,"Fill out I16"))))), E76)) | I76: =IF(I$2="","", IF(F76="",IF($K$16="Use global average",F$276,IF($K$16="Use regional average",INDEX(F$280:F$296,MATCH($B76,$B$280:$B$296,0)),IF($K$16="Leave blank","",IF($K$16="Fill with zeros", 0,IF($K$16="Use global median",F$277,"Fill out I16"))))), F76)) | L76: =IF(M76="","",IF(COUNTIF(Countries!$B$1:$H$271,M76)>0,"",IF(COUNTIF(Countries!$M$1:$S$271,M76)>0,"Not a country","ERROR – NOT LISTED. Add alt spelling to ''Countries'' tab"))) | M76: Guatemala | N76: 6.169567 | O76: =N76*365*1.28 -> 2882.4217 | P76: 0.58408993 | Q76: 0.0305 | R76: =IFERROR(O76/(P76*(1-Q76)),"") -> 5090.143
A77: =Countries!B76 -> Honduras | B77: =Countries!I76 -> Latin America | C77: =IFERROR(IFERROR(IFERROR(IFERROR(IFERROR(IFERROR(IFERROR(MATCH(Countries!$B76,$M$3:$M$1003,0),MATCH(Countries!$C76,$M$3:$M$1003,0)),MATCH(Countries!$D76,$M$3:$M$1003,0)),MATCH(Countries!$E76,$M$3:$M$1003,0)),MATCH(Countries!$F76,$M$3:$M$1003,0)),MATCH(Countries!$G76,$M$3:$M$1003,0)),MATCH(Countries!$H76,$M$3:$M$1003,0)),"X") -> 79 | D77: =IF(G$2="","",IF($C77="X","",INDEX($N$3:$CC$1003,$C77,MATCH(G$2,$N$2:$CC$2,0)))) -> 6381.8049 | E77: =IF(H$2="","",IF($C77="X","",INDEX($N$3:$CC$1003,$C77,MATCH(H$2,$N$2:$CC$2,0)))) | F77: =IF(I$2="","",IF($C77="X","",INDEX($N$3:$CC$1003,$C77,MATCH(I$2,$N$2:$CC$2,0)))) | G77: =IF(A77="","",IF(G$2="","", IF(D77="",IF($K$16="Use global average",D$276,IF($K$16="Use regional average",INDEX(D$280:D$296,MATCH($B77,$B$280:$B$296,0)),IF($K$16="Leave blank","",IF($K$16="Fill with zeros", 0,IF($K$16="Use global median",D$277,"Fill out I16"))))), D77))) -> 6381.8049 | H77: =IF(H$2="","", IF(E77="",IF($K$16="Use global average",E$276,IF($K$16="Use regional average",INDEX(E$280:E$296,MATCH($B77,$B$280:$B$296,0)),IF($K$16="Leave blank","",IF($K$16="Fill with zeros", 0,IF($K$16="Use global median",E$277,"Fill out I16"))))), E77)) | I77: =IF(I$2="","", IF(F77="",IF($K$16="Use global average",F$276,IF($K$16="Use regional average",INDEX(F$280:F$296,MATCH($B77,$B$280:$B$296,0)),IF($K$16="Leave blank","",IF($K$16="Fill with zeros", 0,IF($K$16="Use global median",F$277,"Fill out I16"))))), F77)) | L77: =IF(M77="","",IF(COUNTIF(Countries!$B$1:$H$271,M77)>0,"",IF(COUNTIF(Countries!$M$1:$S$271,M77)>0,"Not a country","ERROR – NOT LISTED. Add alt spelling to ''Countries'' tab"))) | M77: Guinea | N77: 3.8037891 | O77: =N77*365*1.28 -> 1777.1303 | P77: 0.80779274 | Q77: 0.05526 | R77: =IFERROR(O77/(P77*(1-Q77)),"") -> 2328.665
A78: =Countries!B77 -> Hungary | B78: =Countries!I77 -> Europe | C78: =IFERROR(IFERROR(IFERROR(IFERROR(IFERROR(IFERROR(IFERROR(MATCH(Countries!$B77,$M$3:$M$1003,0),MATCH(Countries!$C77,$M$3:$M$1003,0)),MATCH(Countries!$D77,$M$3:$M$1003,0)),MATCH(Countries!$E77,$M$3:$M$1003,0)),MATCH(Countries!$F77,$M$3:$M$1003,0)),MATCH(Countries!$G77,$M$3:$M$1003,0)),MATCH(Countries!$H77,$M$3:$M$1003,0)),"X") -> 80 | D78: =IF(G$2="","",IF($C78="X","",INDEX($N$3:$CC$1003,$C78,MATCH(G$2,$N$2:$CC$2,0)))) -> 25580.558 | E78: =IF(H$2="","",IF($C78="X","",INDEX($N$3:$CC$1003,$C78,MATCH(H$2,$N$2:$CC$2,0)))) | F78: =IF(I$2="","",IF($C78="X","",INDEX($N$3:$CC$1003,$C78,MATCH(I$2,$N$2:$CC$2,0)))) | G78: =IF(A78="","",IF(G$2="","", IF(D78="",IF($K$16="Use global average",D$276,IF($K$16="Use regional average",INDEX(D$280:D$296,MATCH($B78,$B$280:$B$296,0)),IF($K$16="Leave blank","",IF($K$16="Fill with zeros", 0,IF($K$16="Use global median",D$277,"Fill out I16"))))), D78))) -> 25580.558 | H78: =IF(H$2="","", IF(E78="",IF($K$16="Use global average",E$276,IF($K$16="Use regional average",INDEX(E$280:E$296,MATCH($B78,$B$280:$B$296,0)),IF($K$16="Leave blank","",IF($K$16="Fill with zeros", 0,IF($K$16="Use global median",E$277,"Fill out I16"))))), E78)) | I78: =IF(I$2="","", IF(F78="",IF($K$16="Use global average",F$276,IF($K$16="Use regional average",INDEX(F$280:F$296,MATCH($B78,$B$280:$B$296,0)),IF($K$16="Leave blank","",IF($K$16="Fill with zeros", 0,IF($K$16="Use global median",F$277,"Fill out I16"))))), F78)) | L78: =IF(M78="","",IF(COUNTIF(Countries!$B$1:$H$271,M78)>0,"",IF(COUNTIF(Countries!$M$1:$S$271,M78)>0,"Not a country","ERROR – NOT LISTED. Add alt spelling to ''Countries'' tab"))) | M78: Guinea-Bissau | N78: 3.1120498 | O78: =N78*365*1.28 -> 1453.9497 | P78: 0.7356531 | Q78: 0.0324 | R78: =IFERROR(O78/(P78*(1-Q78)),"") -> 2042.5864
A79: =Countries!B78 -> Iceland | B79: =Countries!I78 -> Europe | C79: =IFERROR(IFERROR(IFERROR(IFERROR(IFERROR(IFERROR(IFERROR(MATCH(Countries!$B78,$M$3:$M$1003,0),MATCH(Countries!$C78,$M$3:$M$1003,0)),MATCH(Countries!$D78,$M$3:$M$1003,0)),MATCH(Countries!$E78,$M$3:$M$1003,0)),MATCH(Countries!$F78,$M$3:$M$1003,0)),MATCH(Countries!$G78,$M$3:$M$1003,0)),MATCH(Countries!$H78,$M$3:$M$1003,0)),"X") -> 81 | D79: =IF(G$2="","",IF($C79="X","",INDEX($N$3:$CC$1003,$C79,MATCH(G$2,$N$2:$CC$2,0)))) -> 54739.301 | E79: =IF(H$2="","",IF($C79="X","",INDEX($N$3:$CC$1003,$C79,MATCH(H$2,$N$2:$CC$2,0)))) | F79: =IF(I$2="","",IF($C79="X","",INDEX($N$3:$CC$1003,$C79,MATCH(I$2,$N$2:$CC$2,0)))) | G79: =IF(A79="","",IF(G$2="","", IF(D79="",IF($K$16="Use global average",D$276,IF($K$16="Use regional average",INDEX(D$280:D$296,MATCH($B79,$B$280:$B$296,0)),IF($K$16="Leave blank","",IF($K$16="Fill with zeros", 0,IF($K$16="Use global median",D$277,"Fill out I16"))))), D79))) -> 54739.301 | H79: =IF(H$2="","", IF(E79="",IF($K$16="Use global average",E$276,IF($K$16="Use regional average",INDEX(E$280:E$296,MATCH($B79,$B$280:$B$296,0)),IF($K$16="Leave blank","",IF($K$16="Fill with zeros", 0,IF($K$16="Use global median",E$277,"Fill out I16"))))), E79)) | I79: =IF(I$2="","", IF(F79="",IF($K$16="Use global average",F$276,IF($K$16="Use regional average",INDEX(F$280:F$296,MATCH($B79,$B$280:$B$296,0)),IF($K$16="Leave blank","",IF($K$16="Fill with zeros", 0,IF($K$16="Use global median",F$277,"Fill out I16"))))), F79)) | L79: =IF(M79="","",IF(COUNTIF(Countries!$B$1:$H$271,M79)>0,"",IF(COUNTIF(Countries!$M$1:$S$271,M79)>0,"Not a country","ERROR – NOT LISTED. Add alt spelling to ''Countries'' tab"))) | M79: Guyana | N79: 6.042705 | O79: =N79*365*1.28 -> 2823.1518 | P79: 0.55763874 | Q79: 0.12301 | R79: =IFERROR(O79/(P79*(1-Q79)),"") -> 5772.8018
A80: =Countries!B79 -> India | B80: =Countries!I79 -> South Asia | C80: =IFERROR(IFERROR(IFERROR(IFERROR(IFERROR(IFERROR(IFERROR(MATCH(Countries!$B79,$M$3:$M$1003,0),MATCH(Countries!$C79,$M$3:$M$1003,0)),MATCH(Countries!$D79,$M$3:$M$1003,0)),MATCH(Countries!$E79,$M$3:$M$1003,0)),MATCH(Countries!$F79,$M$3:$M$1003,0)),MATCH(Countries!$G79,$M$3:$M$1003,0)),MATCH(Countries!$H79,$M$3:$M$1003,0)),"X") -> 82 | D80: =IF(G$2="","",IF($C80="X","",INDEX($N$3:$CC$1003,$C80,MATCH(G$2,$N$2:$CC$2,0)))) -> 4115.9702 | E80: =IF(H$2="","",IF($C80="X","",INDEX($N$3:$CC$1003,$C80,MATCH(H$2,$N$2:$CC$2,0)))) | F80: =IF(I$2="","",IF($C80="X","",INDEX($N$3:$CC$1003,$C80,MATCH(I$2,$N$2:$CC$2,0)))) | G80: =IF(A80="","",IF(G$2="","", IF(D80="",IF($K$16="Use global average",D$276,IF($K$16="Use regional average",INDEX(D$280:D$296,MATCH($B80,$B$280:$B$296,0)),IF($K$16="Leave blank","",IF($K$16="Fill with zeros", 0,IF($K$16="Use global median",D$277,"Fill out I16"))))), D80))) -> 4115.9702 | H80: =IF(H$2="","", IF(E80="",IF($K$16="Use global average",E$276,IF($K$16="Use regional average",INDEX(E$280:E$296,MATCH($B80,$B$280:$B$296,0)),IF($K$16="Leave blank","",IF($K$16="Fill with zeros", 0,IF($K$16="Use global median",E$277,"Fill out I16"))))), E80)) | I80: =IF(I$2="","", IF(F80="",IF($K$16="Use global average",F$276,IF($K$16="Use regional average",INDEX(F$280:F$296,MATCH($B80,$B$280:$B$296,0)),IF($K$16="Leave blank","",IF($K$16="Fill with zeros", 0,IF($K$16="Use global median",F$277,"Fill out I16"))))), F80)) | L80: =IF(M80="","",IF(COUNTIF(Countries!$B$1:$H$271,M80)>0,"",IF(COUNTIF(Countries!$M$1:$S$271,M80)>0,"Not a country","ERROR – NOT LISTED. Add alt spelling to ''Countries'' tab"))) | M80: Haiti | N80: 1.7051569 | O80: =N80*365*1.28 -> 796.6493 | P80: 0.5671609 | Q80: 0.14776 | R80: =IFERROR(O80/(P80*(1-Q80)),"") -> 1648.1585
