Workbook

Sheet Average cost-effectiveness
A1: Cage-free
B2: UAE | C2: Saudi Arabia | D2: Egypt | E2: AVG
A3: Discounted costs | B3: ='Cage-free (UAE)'!B50 -> 4567946.8 | C3: ='Cage-free (Saudi Arabia)'!B50 -> 4567946.8 | D3: ='Cage-free (Egypt)'!B51 -> 4567946.8 | E3: =AVERAGE(B3:D3) -> 4567946.8
A4: Discounted benefits | B4: ='Cage-free (UAE)'!B51 -> 28497062 | C4: ='Cage-free (Saudi Arabia)'!B51 -> 2.2099111e+08 | D4: ='Cage-free (Egypt)'!B52 -> 1.5665021e+08 | E4: =AVERAGE(B4:D4) -> 1.3537946e+08
A5: SADs averted/$ | B5: ='Cage-free (UAE)'!B52 -> 6.2384836 | C5: ='Cage-free (Saudi Arabia)'!B52 -> 48.378652 | D5: ='Cage-free (Egypt)'!B53 -> 34.293353 | E5: =AVERAGE(B5:D5) -> 29.63683
A8: Broiler welfare
B9: Costa Rica | C9: El Salvador | D9: Guatemala | E9: Honduras | F9: Nicaragua | G9: AVG
A10: Discounted costs | B10: ='Broiler welfare (Costa Rica)'!B51 -> 4567946.8 | C10: ='Broiler welfare (El Salvador)'!B51 -> 4567946.8 | D10: ='Broiler welfare (Guatemala)'!B51 -> 4567946.8 | E10: ='Broiler welfare (Honduras)'!B51 -> 4567946.8 | F10: ='Broiler welfare (Nicaragua)'!B51 -> 4567946.8 | G10: =AVERAGE(B10:F10) -> 4567946.8
A11: Discounted benefits | B11: ='Broiler welfare (Costa Rica)'!B52 -> 7595053.7 | C11: ='Broiler welfare (El Salvador)'!B52 -> 13078661 | D11: ='Broiler welfare (Guatemala)'!B52 -> 28582707 | E11: ='Broiler welfare (Honduras)'!B52 -> 16335401 | F11: ='Broiler welfare (Nicaragua)'!B52 -> 6703532.6 | G11: =AVERAGE(B11:F11) -> 14459071
A12: SADs averted/$ | B12: ='Broiler welfare (Costa Rica)'!B53 -> 1.6626844 | C12: ='Broiler welfare (El Salvador)'!B53 -> 2.8631377 | D12: ='Broiler welfare (Guatemala)'!B53 -> 6.2572328 | E12: ='Broiler welfare (Honduras)'!B53 -> 3.5760927 | F12: ='Broiler welfare (Nicaragua)'!B53 -> 1.4675155 | G12: =AVERAGE(B12:F12) -> 3.1653326
A14: Broiler welfare
B15: Ireland
A16: Discounted costs | B16: ='Broiler welfare (Ireland)'!B51 -> 4567946.8
A17: Discounted benefits | B17: ='Broiler welfare (Ireland)'!B52 -> 49710620
A18: SADs averted/$ | B18: ='Broiler welfare (Ireland)'!B53 -> 10.882487

Sheet Cage-free (UAE)
B1: UAE
A2: Inputs | B2: Expected | C2: Description | G2: Source
A3: Costs
A4: Fixed costs (Year 1) | B4: 130000 | C4: Held constant across all CEAs | G4: -
A5: Fixed costs (At scale) | B5: 280000 | C5: Held constant across all CEAs | G5: -
A6: Variable costs - Cost of running corporate campaigns | B6: =AVERAGE(534332,405436,275223,204425,301497,401996,70000,60000,20000,2000,62628,41752) -> 198274.08 | C6: Cost of corporate campaigning taken from relevant ACE recommended charities (Kafessiz Türkiye, Shrimp Welfare Project, Sinergia Animal, and THL) | G6: https://animalcharityevaluators.org/charity-review/ciftlik-hayvanlarini-koruma-dernegi/#c2 https://animalcharityevaluators.org/charity-review/shrimp-welfare-project/#c2 https://animalcharityevaluators.org/charity-review/sinergia-animal/#c2 https://animalcharityevaluators.org/charity-review/the-humane-league/#c2
A7: Charity years operating | B7: 15 | C7: 10 years for campaigning, 5 years for enforcement work. We will base this CEA off relevant cage-free data from the US. Cage-free campaigns have been ongoing in the US for about a decade now. | G7: -
A8: Number of years until shut down | B8: 3 | C8: Assume org will shut down after 3 years if no commitments have been won | G8: -
A9: Years until implementation | B9: 10 | C9: Assume we give them a ~10 year transition period (this was the case in the US where campaigns happened in late 2014 with a deadline of 2025). Conservative estimate that they will not go cage-free until deadline. | G9: -
A11: Benefits
A12: Egg production (kg, 2022) | B12: =58453.33*1000 -> 58453330 | C12: UAE produced 58,453.33 tonnes of eggs in 2022 * 1,000 for kg | G12: https://ourworldindata.org/grapher/egg-production-thousand-tonnes?tab=table
A13: Number of eggs produced per hen (kg, 2022) | B13: 12.4 | C13: Each hen in the UAE produces 12.4kg of eggs | G13: https://ourworldindata.org/grapher/egg-yield-per-bird?tab=table
A14: Number of layer hens (2022) | B14: =B12/B13 -> 4713978.2 | C14: Calculation: Egg production / number of eggs produced per hen | G14: -
A15: Annual growth of egg production | B15: =AVERAGE(-3%,12%,-13%) -> -0.013333333 | C15: 7% from USDA report - "Production is forecast to rise 7 percent in 2024 spurred by improved margins." Average of growth rates over the previous 3 years as we are trying to project growth to 2025 from 2022 numbers. 2021-2022: -3% 2020-2021: +12% 2019-2020: -13% | G15: https://ourworldindata.org/grapher/egg-production-thousand-tonnes?tab=table
A16: Capped at __ years | B16: 5 | C16: Best guess for how long growth of production will stay at 4.67% as this likely wont continue forever | G16: -
A17: Number of layer hens (2025) | B17: =B14*(1+B15)^3 -> 4527922 | C17: Calculated number of layer hens farmed in 2025 based on annual growth rates
A19: APPROACH 1
A20: % of production shifted to cage-free after 10 years of campaigning | B20: =average(39%,60%,80%) -> 0.59666667 | C20: 39%, 60% and 80% of hens in the US, Europe, and UK respectively were cage-free at the end of 2023 thanks to ~10 years of corporate campaigns. | G20: https://farmanimalwelfare.substack.com/p/a-year-of-wins-for-farmed-animals
A21: Probability of success | B21: 0.8 | C21: Best guess.
A22: Number of layer hens affected – Approach 1 | B22: =B$17*B20*B21 -> 2161328.1 | C22: Calculation
A23: Approach 1 weight | B23: 0.7 | C23: Best guess
A25: APPROACH 2
A26: Probability of success | B26: =AVERAGE(29%,30%,15%) -> 0.24666667 | C26: Best guess. Average of 29% from THL case study, 30% from Sinergia case study, and 15% for usual probability of success for corporate campaigns | G26: -
A27: Corporations targeted make up what % of total production | B27: 0.7 | C27: Best guess. This is the number we have used in previous CEAs.
A28: To account for corporations being targeted again in future years | B28: 2 | C28: Best guess.
A29: Enforcement rate of corporate campaigns | B29: =AVERAGE(48%,84%,39%,50%,89%)*(0.7/0.72) -> 0.60277778 | C29: Average of three estimates: ~48-84% expected enforcement rate for cage-free campaigns (Šimčikas, 2019), 39-50% expected enforcement rate for corporate campaigns (Sarek, 2019) and 89% actual enforcement rate of cage-free commitments with a deadline of 2023 or earlier that were actually implemented by the end of 2023 (Open Wing Alliance, 2024). This has been adjusted for slightly lower expected enforcement in UAE (0.72 WJP regulatory enforcement score on average in Europe and 0.7 in UAE). | G29: https://forum.effectivealtruism.org/posts/L5EZjjXKdNgcm253H/corporate-campaigns-affect-9-to-120-years-of-chicken-life https://forum.effectivealtruism.org/posts/SG38cPw5C7wLXAeFn/89-of-cage-free-egg-commitments-with-deadlines-of-2023-or https://forum.effectivealtruism.org/posts/JWcNfLAJCxMPZCdCu/35-independent-pieces-of-evidence-for-why-new-corporate https://worldjusticeproject.org/rule-of-law-index/country/2023/United%20Arab%20Emirates/Regulatory%20Enforcement/
A30: Number of layer hens affected – Approach 2 | B30: =B$17*B26*B28*B27*B29 -> 942528.9 | C30: Calculation
A31: Approach 2 weight | B31: 0.3 | C31: Best guess
A33: Adjustment to account for progress being harder outside of Europe and the US | B33: =Calculations!G12 -> 0.24325843 | C33: See calculations tab | G33: -
A34: Adjustment to account for progress being harder as a good cop only type actor | B34: =average(44.97%,45.8%) -> 0.45385 | C34: Analysis of number of commitments (per org) per country with just good cop actors vs good and bad cop actors - Note this uses 2023 numbers | G34: https://docs.google.com/spreadsheets/d/1-Acx-OYg8anoGT9jNYukdxowO-lPt2Biidxj1iT35Lw/edit?gid=1748706729#gid=1748706729
A36: Expected number of layer hens removed from cages after 10 years of campaigning | B36: =((B22*B23)+(B30*B31))*B33*B34*(1+B15)^B16 -> 185380.26 | C36: Calculation | G36: https://www.eurogroupforanimals.org/news/why-do-fast-growing-broiler-chicken-breeds-need-be-phased-out#:~:text=95%25%20of%20the%20broiler%20chickens,just%20five%20to%20six%20weeks.
A37: SADs averted per animal | B37: 17.486002 | C37: ~17.5 SADs averted when removing hens from battery cages and into aviaries (as hens are still in battery cages in Egypt*) * Have assumed that as there is no ban on battery cages, that hens are in these systems rather than other caged systems. | G37: https://docs.google.com/spreadsheets/d/1DssnYoZKFSE3w_-E2PLuOImLUd56JK3JNoO6JHkmTPk/edit?gid=289821833#gid=289821833 https://www.gc-animalwelfare.org/wp-content/uploads/2024/02/GCAW-Knowledge-Share-Cage-Free-Eggs-Global-Landscape-Review-Executive-Summary.pdf
A39: Discount rate (Costs) | B39: 0.04 | C39: Held constant across all CEAs | G39: -
A40: Base discount rate (Benefits) | B40: 0.014 | C40: Held constant across all CEAs | G40: -
A41: Annual chance that this would happen without our intervention | B41: 0.05 | C41: Best guess - Some chance that global commitments will affect production and some chance that OWA will start actively recruiting and find an org. | G41: -
A42: Effective discount rate (Benefits) | B42: =SUM(B40:B41) -> 0.064 | C42: Calculation: Sum of all relevant discount rates | G42: -
A44: Calculations
A45: Year | B45: 1 | C45: 2 | D45: 3 | E45: 4 | F45: 5 | G45: 6 | H45: 7 | I45: 8 | J45: 9 | K45: 10 | L45: 11 | M45: 12 | N45: 13 | O45: 14 | P45: 15 | Q45: 16 | R45: 17 | S45: 18 | T45: 19 | U45: 20 | V45: 21 | W45: 22 | X45: 23 | Y45: 24 | Z45: 25 | AA45: 26 | AB45: 27 | AC45: 28 | AD45: 29 | AE45: 30 | AF45: 31 | AG45: 32 | AH45: 33 | AI45: 34 | AJ45: 35 | AK45: 36 | AL45: 37 | AM45: 38 | AN45: 39 | AO45: 40 | AP45: 41 | AQ45: 42 | AR45: 43 | AS45: 44 | AT45: 45 | AU45: 46 | AV45: 47 | AW45: 48 | AX45: 49 | AY45: 50 | AZ45: 51 | BA45: 52 | BB45: 53 | BC45: 54 | BD45: 55 | BE45: 56 | BF45: 57 | BG45: 58 | BH45: 59 | BI45: 60 | BJ45: 61 | BK45: 62 | BL45: 63 | BM45: 64 | BN45: 65 | BO45: 66 | BP45: 67 | BQ45: 68 | BR45: 69 | BS45: 70 | BT45: 71 | BU45: 72 | BV45: 73 | BW45: 74 | BX45: 75
A46: Total Costs | B46: =B4+B6 -> 328274.08 | C46: =$B$5+$B$6 -> 478274.08 | D46: =$B$5+$B$6 -> 478274.08 | E46: =$B$5+$B$6*(($B$21*$B$23)+($B$26*$B$31)) -> 405705.77 | F46: =$B$5+$B$6*(($B$21*$B$23)+($B$26*$B$31)) -> 405705.77 | G46: =$B$5+$B$6*(($B$21*$B$23)+($B$26*$B$31)) -> 405705.77 | H46: =$B$5+$B$6*(($B$21*$B$23)+($B$26*$B$31)) -> 405705.77 | I46: =$B$5+$B$6*(($B$21*$B$23)+($B$26*$B$31)) -> 405705.77 | J46: =$B$5+$B$6*(($B$21*$B$23)+($B$26*$B$31)) -> 405705.77 | K46: =$B$5+$B$6*(($B$21*$B$23)+($B$26*$B$31)) -> 405705.77 | L46: =$B$5+$B$6*(($B$21*$B$23)+($B$26*$B$31)) -> 405705.77 | ... P46: =$B$5+$B$6*(($B$21*$B$23)+($B$26*$B$31)) -> 405705.77 | Q46: 0 | R46: 0 | S46: 0 | T46: 0 | U46: 0 | V46: 0 | W46: 0 | X46: 0 | Y46: 0 | Z46: 0 | AA46: 0 | AB46: 0 | AC46: 0 | AD46: 0 | AE46: 0 | AF46: 0 | AG46: 0 | AH46: 0 | AI46: 0 | AJ46: 0 | AK46: 0 | AL46: 0 | AM46: 0 | AN46: 0 | AO46: 0 | AP46: 0 | AQ46: 0 | AR46: 0 | AS46: 0 | AT46: 0 | AU46: 0 | AV46: 0 | AW46: 0 | AX46: 0 | AY46: 0 | AZ46: 0 | BA46: 0 | BB46: 0 | BC46: 0 | BD46: 0 | BE46: 0 | BF46: 0 | BG46: 0 | BH46: 0 | BI46: 0 | BJ46: 0 | BK46: 0 | BL46: 0 | BM46: 0 | BN46: 0 | BO46: 0 | BP46: 0 | BQ46: 0 | BR46: 0 | BS46: 0 | BT46: 0 | BU46: 0 | BV46: 0 | BW46: 0 | BX46: 0
A47: Total number of SADs averted | B47: 0 | C47: 0 | D47: 0 | E47: 0 | F47: 0 | G47: 0 | H47: 0 | I47: 0 | J47: 0 | K47: =$B$36*$B$37 -> 3241559.6 | L47: =$B$36*$B$37 -> 3241559.6 | M47: =$B$36*$B$37 -> 3241559.6 | N47: =$B$36*$B$37 -> 3241559.6 | O47: =$B$36*$B$37 -> 3241559.6 | P47: =$B$36*$B$37 -> 3241559.6 | Q47: =$B$36*$B$37 -> 3241559.6 | R47: =$B$36*$B$37 -> 3241559.6 | ... BX47: =$B$36*$B$37 -> 3241559.6
A49: Results
A50: Discounted costs | B50: {=NPV(B39,46:46)} -> 4567946.8
A51: Discounted benefits | B51: {=NPV(B42,47:47)} -> 28497062
A52: SADs averted/$ | B52: =B51/B50 -> 6.2384836

Sheet Cage-free (Saudi Arabia)
B1: Saudi Arabia
A2: Inputs | B2: Expected | C2: Description | G2: Source
A3: Costs
A4: Fixed costs (Year 1) | B4: 130000 | C4: Held constant across all CEAs | G4: -
A5: Fixed costs (At scale) | B5: 280000 | C5: Held constant across all CEAs | G5: -
A6: Variable costs - Cost of running corporate campaigns | B6: =AVERAGE(534332,405436,275223,204425,301497,401996,70000,60000,20000,2000,62628,41752) -> 198274.08 | C6: Cost of corporate campaigning taken from relevant ACE recommended charities (Kafessiz Türkiye, Shrimp Welfare Project, Sinergia Animal, and THL) | G6: https://animalcharityevaluators.org/charity-review/ciftlik-hayvanlarini-koruma-dernegi/#c2 https://animalcharityevaluators.org/charity-review/shrimp-welfare-project/#c2 https://animalcharityevaluators.org/charity-review/sinergia-animal/#c2 https://animalcharityevaluators.org/charity-review/the-humane-league/#c2
A7: Charity years operating | B7: 15 | C7: 10 years for campaigning, 5 years for enforcement work. We will base this CEA off relevant cage-free data from the US. Cage-free campaigns have been ongoing in the US for about a decade now. | G7: -
A8: Number of years until shut down | B8: 3 | C8: Assume org will shut down after 3 years if no commitments have been won | G8: -
A9: Years until implementation | B9: 10 | C9: Assume we give them a ~10 year transition period (this was the case in the US where campaigns happened in late 2014 with a deadline of 2025). Conservative estimate that they will not go cage-free until deadline. | G9: -
A11: Benefits
A12: Egg production (kg, 2022) | B12: =375000*1000 -> 375000000 | C12: Saudi Arabia produced 375,000 tonnes of eggs in 2022 * 1,000 for kg | G12: https://ourworldindata.org/grapher/egg-production-thousand-tonnes?tab=table
A13: Number of eggs produced per hen (kg, 2022) | B13: 11.12 | C13: Each hen in Saudi Arabia produces 11.12kg of eggs | G13: https://ourworldindata.org/grapher/egg-yield-per-bird?tab=table
A14: Number of layer hens (2022) | B14: =B12/B13 -> 33723022 | C14: Calculation: Egg production / number of eggs produced per hen | G14: -
A15: Annual growth of egg production | B15: =AVERAGE(4%,3%,-8%) -> -0.0033333333 | C15: Average of growth rates over the previous 3 years as we are trying to project growth to 2025 from 2022 numbers. 2021-2022: 4% 2020-2021: 3% 2019-2020: -8% | G15: https://ourworldindata.org/grapher/egg-production-thousand-tonnes?tab=table
A16: Capped at __ years | B16: 5 | C16: Best guess for how long growth of production will stay at 4.67% as this likely wont continue forever | G16: -
A17: Number of layer hens (2025) | B17: =B14*(1+B15)^3 -> 33386914 | C17: Calculated number of layer hens farmed in 2025 based on annual growth rates
A19: APPROACH 1
A20: % of production shifted to cage-free after 10 years of campaigning | B20: =average(39%,60%,80%) -> 0.59666667 | C20: 39%, 60% and 80% of hens in the US, Europe, and UK respectively were cage-free at the end of 2023 thanks to ~10 years of corporate campaigns. | G20: https://farmanimalwelfare.substack.com/p/a-year-of-wins-for-farmed-animals
A21: Probability of success | B21: 0.8 | C21: Best guess.
A22: Number of layer hens affected – Approach 1 | B22: =B$17*B20*B21 -> 15936687 | C22: Calculation | N22: =B21*(1-B33)*(1-B34) -> 0.33063553
A23: Approach 1 weight | B23: 0.7 | C23: Best guess
A25: APPROACH 2
A26: Probability of success | B26: =AVERAGE(29%,30%,15%) -> 0.24666667 | C26: Best guess. Average of 29% from THL case study, 30% from Sinergia case study, and 15% for usual probability of success for corporate campaigns | G26: -
A27: Corporations targeted make up what % of total production | B27: 0.7 | C27: Best guess. This is the number we have used in previous CEAs.
A28: To account for corporations being targeted again in future years | B28: 2 | C28: Best guess.
A29: Enforcement rate of corporate campaigns | B29: =AVERAGE(48%,84%,39%,50%,89%)*(0.7/0.72) -> 0.60277778 | C29: Average of three estimates: ~48-84% expected enforcement rate for cage-free campaigns (Šimčikas, 2019), 39-50% expected enforcement rate for corporate campaigns (Sarek, 2019) and 89% actual enforcement rate of cage-free commitments with a deadline of 2023 or earlier that were actually implemented by the end of 2023 (Open Wing Alliance, 2024). This has been adjusted for slightly lower expected enforcement in UAE (0.72 WJP regulatory enforcement score on average in Europe and 0.7 in UAE). Had to use UAE numbers as WJP doesn't have data on Saudi Arabia. | G29: https://forum.effectivealtruism.org/posts/L5EZjjXKdNgcm253H/corporate-campaigns-affect-9-to-120-years-of-chicken-life https://forum.effectivealtruism.org/posts/SG38cPw5C7wLXAeFn/89-of-cage-free-egg-commitments-with-deadlines-of-2023-or https://forum.effectivealtruism.org/posts/JWcNfLAJCxMPZCdCu/35-independent-pieces-of-evidence-for-why-new-corporate https://worldjusticeproject.org/rule-of-law-index/country/2023/United%20Arab%20Emirates/Regulatory%20Enforcement/
A30: Number of layer hens affected – Approach 2 | B30: =B$17*B26*B28*B27*B29 -> 6949795.3 | C30: Calculation
A31: Approach 2 weight | B31: 0.3 | C31: Best guess
A33: Adjustment to account for progress being harder outside of Europe and the US | B33: =Calculations!G12 -> 0.24325843 | C33: See calculations tab | G33: -
A34: Adjustment to account for progress being harder as a good cop only type actor | B34: =average(44.97%,45.8%) -> 0.45385 | C34: Analysis of number of commitments (per org) per country with just good cop actors vs good and bad cop actors - Note this uses 2023 numbers | G34: https://docs.google.com/spreadsheets/d/1-Acx-OYg8anoGT9jNYukdxowO-lPt2Biidxj1iT35Lw/edit?gid=1748706729#gid=1748706729
A36: Expected number of layer hens removed from cages after 10 years of campaigning | B36: =((B22*B23)+(B30*B31))*B33*B34*(1+B15)^B16 -> 1437600.5 | C36: Calculation | G36: https://www.eurogroupforanimals.org/news/why-do-fast-growing-broiler-chicken-breeds-need-be-phased-out#:~:text=95%25%20of%20the%20broiler%20chickens,just%20five%20to%20six%20weeks.
A37: SADs averted per animal | B37: 17.486002 | C37: ~17.5 SADs averted when removing hens from battery cages and into aviaries (as hens are still in battery cages in Egypt*) * Have assumed that as there is no ban on battery cages, that hens are in these systems rather than other caged systems. | G37: https://docs.google.com/spreadsheets/d/1DssnYoZKFSE3w_-E2PLuOImLUd56JK3JNoO6JHkmTPk/edit?gid=289821833#gid=289821833 https://www.gc-animalwelfare.org/wp-content/uploads/2024/02/GCAW-Knowledge-Share-Cage-Free-Eggs-Global-Landscape-Review-Executive-Summary.pdf
A39: Discount rate (Costs) | B39: 0.04 | C39: Held constant across all CEAs | G39: -
A40: Base discount rate (Benefits) | B40: 0.014 | C40: Held constant across all CEAs | G40: -
A41: Annual chance that this would happen without our intervention | B41: 0.05 | C41: Best guess - Some chance that global commitments will affect production and some chance that OWA will start actively recruiting and find an org. | G41: -
A42: Effective discount rate (Benefits) | B42: =SUM(B40:B41) -> 0.064 | C42: Calculation: Sum of all relevant discount rates | G42: -
A44: Calculations
A45: Year | B45: 1 | C45: 2 | D45: 3 | E45: 4 | F45: 5 | G45: 6 | H45: 7 | I45: 8 | J45: 9 | K45: 10 | L45: 11 | M45: 12 | N45: 13 | O45: 14 | P45: 15 | Q45: 16 | R45: 17 | S45: 18 | T45: 19 | U45: 20 | V45: 21 | W45: 22 | X45: 23 | Y45: 24 | Z45: 25 | AA45: 26 | AB45: 27 | AC45: 28 | AD45: 29 | AE45: 30 | AF45: 31 | AG45: 32 | AH45: 33 | AI45: 34 | AJ45: 35 | AK45: 36 | AL45: 37 | AM45: 38 | AN45: 39 | AO45: 40 | AP45: 41 | AQ45: 42 | AR45: 43 | AS45: 44 | AT45: 45 | AU45: 46 | AV45: 47 | AW45: 48 | AX45: 49 | AY45: 50 | AZ45: 51 | BA45: 52 | BB45: 53 | BC45: 54 | BD45: 55 | BE45: 56 | BF45: 57 | BG45: 58 | BH45: 59 | BI45: 60 | BJ45: 61 | BK45: 62 | BL45: 63 | BM45: 64 | BN45: 65 | BO45: 66 | BP45: 67 | BQ45: 68 | BR45: 69 | BS45: 70 | BT45: 71 | BU45: 72 | BV45: 73 | BW45: 74 | BX45: 75
A46: Total Costs | B46: =B4+B6 -> 328274.08 | C46: =$B$5+$B$6 -> 478274.08 | D46: =$B$5+$B$6 -> 478274.08 | E46: =$B$5+$B$6*(($B$21*$B$23)+($B$26*$B$31)) -> 405705.77 | F46: =$B$5+$B$6*(($B$21*$B$23)+($B$26*$B$31)) -> 405705.77 | G46: =$B$5+$B$6*(($B$21*$B$23)+($B$26*$B$31)) -> 405705.77 | H46: =$B$5+$B$6*(($B$21*$B$23)+($B$26*$B$31)) -> 405705.77 | I46: =$B$5+$B$6*(($B$21*$B$23)+($B$26*$B$31)) -> 405705.77 | J46: =$B$5+$B$6*(($B$21*$B$23)+($B$26*$B$31)) -> 405705.77 | K46: =$B$5+$B$6*(($B$21*$B$23)+($B$26*$B$31)) -> 405705.77 | L46: =$B$5+$B$6*(($B$21*$B$23)+($B$26*$B$31)) -> 405705.77 | ... P46: =$B$5+$B$6*(($B$21*$B$23)+($B$26*$B$31)) -> 405705.77 | Q46: 0 | R46: 0 | S46: 0 | T46: 0 | U46: 0 | V46: 0 | W46: 0 | X46: 0 | Y46: 0 | Z46: 0 | AA46: 0 | AB46: 0 | AC46: 0 | AD46: 0 | AE46: 0 | AF46: 0 | AG46: 0 | AH46: 0 | AI46: 0 | AJ46: 0 | AK46: 0 | AL46: 0 | AM46: 0 | AN46: 0 | AO46: 0 | AP46: 0 | AQ46: 0 | AR46: 0 | AS46: 0 | AT46: 0 | AU46: 0 | AV46: 0 | AW46: 0 | AX46: 0 | AY46: 0 | AZ46: 0 | BA46: 0 | BB46: 0 | BC46: 0 | BD46: 0 | BE46: 0 | BF46: 0 | BG46: 0 | BH46: 0 | BI46: 0 | BJ46: 0 | BK46: 0 | BL46: 0 | BM46: 0 | BN46: 0 | BO46: 0 | BP46: 0 | BQ46: 0 | BR46: 0 | BS46: 0 | BT46: 0 | BU46: 0 | BV46: 0 | BW46: 0 | BX46: 0
A47: Total number of SADs averted | B47: 0 | C47: 0 | D47: 0 | E47: 0 | F47: 0 | G47: 0 | H47: 0 | I47: 0 | J47: 0 | K47: =$B$36*$B$37 -> 25137885 | L47: =$B$36*$B$37 -> 25137885 | M47: =$B$36*$B$37 -> 25137885 | N47: =$B$36*$B$37 -> 25137885 | O47: =$B$36*$B$37 -> 25137885 | P47: =$B$36*$B$37 -> 25137885 | Q47: =$B$36*$B$37 -> 25137885 | R47: =$B$36*$B$37 -> 25137885 | ... BX47: =$B$36*$B$37 -> 25137885
A49: Results
A50: Discounted costs | B50: {=NPV(B39,46:46)} -> 4567946.8
A51: Discounted benefits | B51: {=NPV(B42,47:47)} -> 2.2099111e+08
A52: SADs averted/$ | B52: =B51/B50 -> 48.378652

Sheet Cage-free (Egypt)
B1: Egypt
A2: Inputs | B2: Expected | C2: Description | G2: Source
A3: Costs
A4: Fixed costs (Year 1) | B4: 130000 | C4: Held constant across all CEAs | G4: -
A5: Fixed costs (At scale) | B5: 280000 | C5: Held constant across all CEAs | G5: -
A6: Variable costs - Cost of running corporate campaigns | B6: =AVERAGE(534332,405436,275223,204425,301497,401996,70000,60000,20000,2000,62628,41752) -> 198274.08 | C6: Cost of corporate campaigning taken from relevant ACE recommended charities (Kafessiz Türkiye, Shrimp Welfare Project, Sinergia Animal, and THL) | G6: https://animalcharityevaluators.org/charity-review/ciftlik-hayvanlarini-koruma-dernegi/#c2 https://animalcharityevaluators.org/charity-review/shrimp-welfare-project/#c2 https://animalcharityevaluators.org/charity-review/sinergia-animal/#c2 https://animalcharityevaluators.org/charity-review/the-humane-league/#c2
A7: Charity years operating | B7: 15 | C7: 10 years for campaigning, 5 years for enforcement work. We will base this CEA off relevant cage-free data from the US. Cage-free campaigns have been ongoing in the US for about a decade now. | G7: -
A8: Number of years until shut down | B8: 3 | C8: Assume org will shut down after 3 years if no commitments have been won | G8: -
A9: Years until implementation | B9: 10 | C9: Assume we give them a ~10 year transition period (this was the case in the US where campaigns happened in late 2014 with a deadline of 2025). Conservative estimate that they will not go cage-free until deadline. | G9: -
A11: Benefits
A12: Egg production (kg, 2022) | B12: =614154*1000 -> 614154000 | C12: Egypt produced 614,154 tonnes of eggs in 2022 * 1,000 for kg | G12: https://ourworldindata.org/grapher/egg-production-thousand-tonnes?tab=table
A13: Number of eggs produced per hen (kg, 2022) | B13: 17.55 | C13: Each hen in Egypt produces 17.55kg of eggs | G13: https://ourworldindata.org/grapher/egg-yield-per-bird?tab=table
A14: Number of layer hens (2022) | B14: =B12/B13 -> 34994530 | C14: Calculation: Egg production / number of eggs produced per hen | G14: -
A15: Annual growth of egg production | B15: =AVERAGE(-6%,9%,11%) -> 0.046666667 | C15: Average of growth rates over the previous 3 years as we are trying to project growth to 2025 from 2022 numbers. 2021-2022: -6% 2020-2021: 9% 2019-2020: 11% | G15: https://ourworldindata.org/grapher/egg-production-thousand-tonnes?tab=table
A16: Capped at __ years | B16: 5 | C16: Best guess for how long growth of production will stay at 4.67% as this likely wont continue forever | G16: -
A17: Number of layer hens (2025) | B17: =B14*(1+B15)^3 -> 40125952 | C17: Calculated number of layer hens farmed in 2025 based on annual growth rates
A19: APPROACH 1
A20: % of production shifted to cage-free after 10 years of campaigning | B20: =average(39%,60%,80%) -> 0.59666667 | C20: 39%, 60% and 80% of hens in the US, Europe, and UK respectively were cage-free at the end of 2023 thanks to ~10 years of corporate campaigns. | G20: https://farmanimalwelfare.substack.com/p/a-year-of-wins-for-farmed-animals
A21: Probability of success | B21: 0.8 | C21: Best guess.
A22: Number of layer hens affected – Approach 1 | B22: =B$17*B20*B21 -> 19153454 | C22: Calculation
A23: Approach 1 weight | B23: 0.7 | C23: Best guess
A25: APPROACH 2
A26: Probability of success | B26: =AVERAGE(29%,30%,15%) -> 0.24666667 | C26: Best guess. Average of 29% from THL case study, 30% from Sinergia case study, and 15% for usual probability of success for corporate campaigns | G26: -
A27: Corporations targeted make up what % of total production | B27: 0.7 | C27: Best guess. This is the number we have used in previous CEAs.
A28: To account for corporations being targeted again in future years | B28: 2 | C28: Best guess.
A29: Enforcement rate of corporate campaigns | B29: =AVERAGE(48%,84%,39%,50%,89%)*(0.36/0.72) -> 0.31 | C29: Average of three estimates: ~48-84% expected enforcement rate for cage-free campaigns (Šimčikas, 2019), 39-50% expected enforcement rate for corporate campaigns (Sarek, 2019) and 89% actual enforcement rate of cage-free commitments with a deadline of 2023 or earlier that were actually implemented by the end of 2023 (Open Wing Alliance, 2024). This has been adjusted for slightly lower expected enforcement in UAE (0.72 WJP regulatory enforcement score on average in Europe and 0.36 in Egypt). | G29: https://forum.effectivealtruism.org/posts/L5EZjjXKdNgcm253H/corporate-campaigns-affect-9-to-120-years-of-chicken-life https://forum.effectivealtruism.org/posts/SG38cPw5C7wLXAeFn/89-of-cage-free-egg-commitments-with-deadlines-of-2023-or https://forum.effectivealtruism.org/posts/JWcNfLAJCxMPZCdCu/35-independent-pieces-of-evidence-for-why-new-corporate https://worldjusticeproject.org/rule-of-law-index/country/2023/United%20Arab%20Emirates/Regulatory%20Enforcement/
A30: Number of layer hens affected – Approach 2 | B30: =B$17*B26*B28*B27*B29 -> 4295616.9 | C30: Calculation
A31: Approach 2 weight | B31: 0.3 | C31: Best guess
A33: Adjustment to account for some hens already been in cage-free systems | B33: 0.5 | C33: 50% of eggs are already produced in cage free systems in Egpyt | G33: https://www.gc-animalwelfare.org/wp-content/uploads/2024/02/GCAW-Knowledge-Share-Cage-Free-Eggs-Global-Landscape-Review-Executive-Summary.pdf
A34: Adjustment to account for progress being harder outside of Europe and the US | B34: =Calculations!G12 -> 0.24325843 | C34: See calculations tab | G34: -
A35: Adjustment to account for progress being harder as a good cop only type actor | B35: =average(44.97%,45.8%) -> 0.45385 | C35: Analysis of number of commitments (per org) per country with just good cop actors vs good and bad cop actors - Note this uses 2023 numbers | G35: https://docs.google.com/spreadsheets/d/1-Acx-OYg8anoGT9jNYukdxowO-lPt2Biidxj1iT35Lw/edit?gid=1748706729#gid=1748706729
A37: Expected number of layer hens removed from cages after 10 years of campaigning | B37: =((B22*B23)+(B30*B31))*B33*B34*B35*(1+B15)^B16 -> 1019047.4 | C37: Calculation | G37: https://www.eurogroupforanimals.org/news/why-do-fast-growing-broiler-chicken-breeds-need-be-phased-out#:~:text=95%25%20of%20the%20broiler%20chickens,just%20five%20to%20six%20weeks.
A38: SADs averted per animal | B38: 17.486002 | C38: ~17.5 SADs averted when removing hens from battery cages and into aviaries (as hens are still in battery cages in Egypt*) * Have assumed that as there is no ban on battery cages, that hens are in these systems rather than other caged systems. | G38: https://docs.google.com/spreadsheets/d/1DssnYoZKFSE3w_-E2PLuOImLUd56JK3JNoO6JHkmTPk/edit?gid=289821833#gid=289821833 https://www.gc-animalwelfare.org/wp-content/uploads/2024/02/GCAW-Knowledge-Share-Cage-Free-Eggs-Global-Landscape-Review-Executive-Summary.pdf
A40: Discount rate (Costs) | B40: 0.04 | C40: Held constant across all CEAs | G40: -
A41: Base discount rate (Benefits) | B41: 0.014 | C41: Held constant across all CEAs | G41: -
A42: Annual chance that this would happen without our intervention | B42: 0.05 | C42: Best guess - Some chance that global commitments will affect production and some chance that OWA will start actively recruiting and find an org. | G42: -
A43: Effective discount rate (Benefits) | B43: =SUM(B41:B42) -> 0.064 | C43: Calculation: Sum of all relevant discount rates | G43: -
A45: Calculations
A46: Year | B46: 1 | C46: 2 | D46: 3 | E46: 4 | F46: 5 | G46: 6 | H46: 7 | I46: 8 | J46: 9 | K46: 10 | L46: 11 | M46: 12 | N46: 13 | O46: 14 | P46: 15 | Q46: 16 | R46: 17 | S46: 18 | T46: 19 | U46: 20 | V46: 21 | W46: 22 | X46: 23 | Y46: 24 | Z46: 25 | AA46: 26 | AB46: 27 | AC46: 28 | AD46: 29 | AE46: 30 | AF46: 31 | AG46: 32 | AH46: 33 | AI46: 34 | AJ46: 35 | AK46: 36 | AL46: 37 | AM46: 38 | AN46: 39 | AO46: 40 | AP46: 41 | AQ46: 42 | AR46: 43 | AS46: 44 | AT46: 45 | AU46: 46 | AV46: 47 | AW46: 48 | AX46: 49 | AY46: 50 | AZ46: 51 | BA46: 52 | BB46: 53 | BC46: 54 | BD46: 55 | BE46: 56 | BF46: 57 | BG46: 58 | BH46: 59 | BI46: 60 | BJ46: 61 | BK46: 62 | BL46: 63 | BM46: 64 | BN46: 65 | BO46: 66 | BP46: 67 | BQ46: 68 | BR46: 69 | BS46: 70 | BT46: 71 | BU46: 72 | BV46: 73 | BW46: 74 | BX46: 75
A47: Total Costs | B47: =B4+B6 -> 328274.08 | C47: =$B$5+$B$6 -> 478274.08 | D47: =$B$5+$B$6 -> 478274.08 | E47: =$B$5+$B$6*(($B$21*$B$23)+($B$26*$B$31)) -> 405705.77 | F47: =$B$5+$B$6*(($B$21*$B$23)+($B$26*$B$31)) -> 405705.77 | G47: =$B$5+$B$6*(($B$21*$B$23)+($B$26*$B$31)) -> 405705.77 | H47: =$B$5+$B$6*(($B$21*$B$23)+($B$26*$B$31)) -> 405705.77 | I47: =$B$5+$B$6*(($B$21*$B$23)+($B$26*$B$31)) -> 405705.77 | J47: =$B$5+$B$6*(($B$21*$B$23)+($B$26*$B$31)) -> 405705.77 | K47: =$B$5+$B$6*(($B$21*$B$23)+($B$26*$B$31)) -> 405705.77 | L47: =$B$5+$B$6*(($B$21*$B$23)+($B$26*$B$31)) -> 405705.77 | ... P47: =$B$5+$B$6*(($B$21*$B$23)+($B$26*$B$31)) -> 405705.77 | Q47: 0 | R47: 0 | S47: 0 | T47: 0 | U47: 0 | V47: 0 | W47: 0 | X47: 0 | Y47: 0 | Z47: 0 | AA47: 0 | AB47: 0 | AC47: 0 | AD47: 0 | AE47: 0 | AF47: 0 | AG47: 0 | AH47: 0 | AI47: 0 | AJ47: 0 | AK47: 0 | AL47: 0 | AM47: 0 | AN47: 0 | AO47: 0 | AP47: 0 | AQ47: 0 | AR47: 0 | AS47: 0 | AT47: 0 | AU47: 0 | AV47: 0 | AW47: 0 | AX47: 0 | AY47: 0 | AZ47: 0 | BA47: 0 | BB47: 0 | BC47: 0 | BD47: 0 | BE47: 0 | BF47: 0 | BG47: 0 | BH47: 0 | BI47: 0 | BJ47: 0 | BK47: 0 | BL47: 0 | BM47: 0 | BN47: 0 | BO47: 0 | BP47: 0 | BQ47: 0 | BR47: 0 | BS47: 0 | BT47: 0 | BU47: 0 | BV47: 0 | BW47: 0 | BX47: 0
A48: Total number of SADs averted | B48: 0 | C48: 0 | D48: 0 | E48: 0 | F48: 0 | G48: 0 | H48: 0 | I48: 0 | J48: 0 | K48: =$B$37*$B$38 -> 17819065 | L48: =$B$37*$B$38 -> 17819065 | M48: =$B$37*$B$38 -> 17819065 | N48: =$B$37*$B$38 -> 17819065 | O48: =$B$37*$B$38 -> 17819065 | P48: =$B$37*$B$38 -> 17819065 | Q48: =$B$37*$B$38 -> 17819065 | R48: =$B$37*$B$38 -> 17819065 | ... BX48: =$B$37*$B$38 -> 17819065
A50: Results
A51: Discounted costs | B51: {=NPV(B40,47:47)} -> 4567946.8
A52: Discounted benefits | B52: {=NPV(B43,48:48)} -> 1.5665021e+08
A53: SADs averted/$ | B53: =B52/B51 -> 34.293353

Sheet Broiler welfare (Costa Rica)
B1: Costa Rica
A2: Inputs | B2: Expected | C2: Description | G2: Source
A3: Costs
A4: Fixed costs (Year 1) | B4: 130000 | C4: Held constant across all CEAs | G4: -
A5: Fixed costs (At scale) | B5: 280000 | C5: Held constant across all CEAs | G5: -
A6: Variable costs - Cost of running corporate campaigns | B6: =AVERAGE(534332,405436,275223,204425,301497,401996,70000,60000,20000,2000,62628,41752) -> 198274.08 | C6: Cost of corporate campaigning taken from relevant ACE recommended charities (Kafessiz Türkiye, Shrimp Welfare Project, Sinergia Animal, and THL) | G6: https://animalcharityevaluators.org/charity-review/ciftlik-hayvanlarini-koruma-dernegi/#c2 https://animalcharityevaluators.org/charity-review/shrimp-welfare-project/#c2 https://animalcharityevaluators.org/charity-review/sinergia-animal/#c2 https://animalcharityevaluators.org/charity-review/the-humane-league/#c2
A7: Charity years operating | B7: 15 | C7: 10 years for campaigning, 5 years for enforcement work. We will base this CEA off relevant cage-free data from the US. Cage-free campaigns have been ongoing in the US for about a decade now. | G7: -
A8: Number of years until shut down | B8: 3 | C8: Assume org will shut down after 3 years if no commitments have been won | G8: -
A9: Years until implementation | B9: 10 | C9: Assume we give them a ~10 year transition period (this was the case in the US where campaigns happened in late 2014 with a deadline of 2025). Conservative estimate that they will not go cage-free until deadline. | G9: -
A11: Benefits
A12: Chicken meat production (kg, 2022) | B12: =152238*1000 -> 152238000 | C12: Costa Rica produced 152,238 tonnes of chicken meat in 2022 * 1,000 for kg | G12: https://ourworldindata.org/grapher/chicken-meat-production?tab=table
A13: Meat yield per bird (kg, 2022) | B13: 1.89 | C13: Each chicken in Costa Rica produces 1.89kg of meat | G13: https://ourworldindata.org/grapher/chicken-meat-yields-per-animal
A14: Number of broiler chickens (2022) | B14: =B12/B13 -> 80549206 | C14: Calculation: Chicken meat production / meat yield per bird | G14: -
A15: Annual growth of chicken production | B15: =AVERAGE(3%,8%,-5%) -> 0.02 | C15: Average of growth rates over the previous 3 years as we are trying to project growth to 2025 from 2022 numbers. 2021-2022: 3% 2020-2021: 8% 2019-2020: -5% | G15: https://ourworldindata.org/grapher/chicken-meat-production?tab=table
A16: Capped at __ years | B16: 5 | C16: Best guess for how long growth of production will stay at 4.67% as this likely wont continue forever | G16: -
A17: Number of broilers (2025) | B17: =B14*(1+B15)^3 -> 85479462 | C17: Calculated number of layer hens farmed in 2025 based on annual growth rates
A19: APPROACH 1
A20: % of production shifted after 10 years of campaigning | B20: =average(39%,60%,80%) -> 0.59666667 | C20: 39%, 60% and 80% of hens in the US, Europe, and UK respectively were cage-free at the end of 2023 thanks to ~10 years of corporate campaigns. | G20: https://farmanimalwelfare.substack.com/p/a-year-of-wins-for-farmed-animals
A21: Probability of success | B21: 0.8 | C21: Best guess.
A22: Number of broilers affected – Approach 1 | B22: =B$17*B20*B21 -> 40802197 | C22: Calculation
A23: Approach 1 weight | B23: 0.7 | C23: Best guess
A25: APPROACH 2
A26: Probability of success | B26: =AVERAGE(29%,30%,15%) -> 0.24666667 | C26: Best guess. Average of 29% from THL case study, 30% from Sinergia case study, and 15% for usual probability of success for corporate campaigns | G26: -
A27: Corporations targeted make up what % of total production | B27: 0.7 | C27: Best guess. This is the number we have used in previous CEAs.
A28: To account for corporations being targeted again in future years | B28: 2 | C28: Best guess.
A29: Enforcement rate of corporate campaigns | B29: =AVERAGE(48%,84%,39%,50%,89%)*(0.68/0.72) -> 0.58555556 | C29: Average of three estimates: ~48-84% expected enforcement rate for cage-free campaigns (Šimčikas, 2019), 39-50% expected enforcement rate for corporate campaigns (Sarek, 2019) and 89% actual enforcement rate of cage-free commitments with a deadline of 2023 or earlier that were actually implemented by the end of 2023 (Open Wing Alliance, 2024). This has been adjusted for slightly lower expected enforcement in UAE (0.72 WJP regulatory enforcement score on average in Europe and 0.68 in Costa Rica). | G29: https://forum.effectivealtruism.org/posts/L5EZjjXKdNgcm253H/corporate-campaigns-affect-9-to-120-years-of-chicken-life https://forum.effectivealtruism.org/posts/SG38cPw5C7wLXAeFn/89-of-cage-free-egg-commitments-with-deadlines-of-2023-or https://forum.effectivealtruism.org/posts/JWcNfLAJCxMPZCdCu/35-independent-pieces-of-evidence-for-why-new-corporate https://worldjusticeproject.org/rule-of-law-index/country/2023/United%20Arab%20Emirates/Regulatory%20Enforcement/
A30: Number of broilers affected – Approach 2 | B30: =B$17*B26*B28*B27*B29 -> 17284960 | C30: Calculation
A31: Approach 2 weight | B31: 0.3 | C31: Best guess
A33: Adjustment to account for progress being harder outside of Europe and the US | B33: =Calculations!G12 -> 0.24325843 | C33: See calculations tab | G33: -
A34: Adjustment to account for progress being slower with BCC | B34: =24%/64% -> 0.375 | C34: Best guess based on expected enforcement rate of cage-free campaigns is 64% and expected enforcement rate of BCC is 24%
A35: Adjustment to account for progress being harder as a good cop only type actor | B35: =average(44.97%,45.8%) -> 0.45385 | C35: Analysis of number of commitments (per org) per country with just good cop actors vs good and bad cop actors - Note this uses 2023 numbers | G35: https://docs.google.com/spreadsheets/d/1-Acx-OYg8anoGT9jNYukdxowO-lPt2Biidxj1iT35Lw/edit?gid=1748706729#gid=1748706729
A37: Expected number of broilers affected after 10 years of campaigning | B37: =((B22*B23)+(B30*B31))*B33*B34*B35*(1+B15)^B16 -> 1542580.6 | C37: Calculation | G37: https://www.eurogroupforanimals.org/news/why-do-fast-growing-broiler-chicken-breeds-need-be-phased-out#:~:text=95%25%20of%20the%20broiler%20chickens,just%20five%20to%20six%20weeks.
A38: SADs averted per animal | B38: 0.94730467 | C38: SADs averted per animal by moving from fast growing to slow growing breeds (accounts for sentience, welfare range, and moral weights of different intensities of pain) | G38: https://docs.google.com/spreadsheets/d/1DssnYoZKFSE3w_-E2PLuOImLUd56JK3JNoO6JHkmTPk/edit?gid=289821833#gid=289821833
A40: Discount rate (Costs) | B40: 0.04 | C40: Held constant across all CEAs | G40: -
A41: Base discount rate (Benefits) | B41: 0.014 | C41: Held constant across all CEAs | G41: -
A42: Annual chance that this would happen without our intervention | B42: 0.075 | C42: Best guess - Some chance that global commitments will affect production and some chance that OWA will start actively recruiting and find an org. More chance that someone else will do this in Central America than in the Middle East given the presence of orgs in Latin America and North America. | G42: -
A43: Effective discount rate (Benefits) | B43: =SUM(B41:B42) -> 0.089 | C43: Calculation: Sum of all relevant discount rates | G43: -
A45: Calculations
A46: Year | B46: 1 | C46: 2 | D46: 3 | E46: 4 | F46: 5 | G46: 6 | H46: 7 | I46: 8 | J46: 9 | K46: 10 | L46: 11 | M46: 12 | N46: 13 | O46: 14 | P46: 15 | Q46: 16 | R46: 17 | S46: 18 | T46: 19 | U46: 20 | V46: 21 | W46: 22 | X46: 23 | Y46: 24 | Z46: 25 | AA46: 26 | AB46: 27 | AC46: 28 | AD46: 29 | AE46: 30 | AF46: 31 | AG46: 32 | AH46: 33 | AI46: 34 | AJ46: 35 | AK46: 36 | AL46: 37 | AM46: 38 | AN46: 39 | AO46: 40 | AP46: 41 | AQ46: 42 | AR46: 43 | AS46: 44 | AT46: 45 | AU46: 46 | AV46: 47 | AW46: 48 | AX46: 49 | AY46: 50 | AZ46: 51 | BA46: 52 | BB46: 53 | BC46: 54 | BD46: 55 | BE46: 56 | BF46: 57 | BG46: 58 | BH46: 59 | BI46: 60 | BJ46: 61 | BK46: 62 | BL46: 63 | BM46: 64 | BN46: 65 | BO46: 66 | BP46: 67 | BQ46: 68 | BR46: 69 | BS46: 70 | BT46: 71 | BU46: 72 | BV46: 73 | BW46: 74 | BX46: 75
A47: Total Costs | B47: =B4+B6 -> 328274.08 | C47: =$B$5+$B$6 -> 478274.08 | D47: =$B$5+$B$6 -> 478274.08 | E47: =$B$5+$B$6*(($B$21*$B$23)+($B$26*$B$31)) -> 405705.77 | F47: =$B$5+$B$6*(($B$21*$B$23)+($B$26*$B$31)) -> 405705.77 | G47: =$B$5+$B$6*(($B$21*$B$23)+($B$26*$B$31)) -> 405705.77 | H47: =$B$5+$B$6*(($B$21*$B$23)+($B$26*$B$31)) -> 405705.77 | I47: =$B$5+$B$6*(($B$21*$B$23)+($B$26*$B$31)) -> 405705.77 | J47: =$B$5+$B$6*(($B$21*$B$23)+($B$26*$B$31)) -> 405705.77 | K47: =$B$5+$B$6*(($B$21*$B$23)+($B$26*$B$31)) -> 405705.77 | L47: =$B$5+$B$6*(($B$21*$B$23)+($B$26*$B$31)) -> 405705.77 | ... P47: =$B$5+$B$6*(($B$21*$B$23)+($B$26*$B$31)) -> 405705.77 | Q47: 0 | R47: 0 | S47: 0 | T47: 0 | U47: 0 | V47: 0 | W47: 0 | X47: 0 | Y47: 0 | Z47: 0 | AA47: 0 | AB47: 0 | AC47: 0 | AD47: 0 | AE47: 0 | AF47: 0 | AG47: 0 | AH47: 0 | AI47: 0 | AJ47: 0 | AK47: 0 | AL47: 0 | AM47: 0 | AN47: 0 | AO47: 0 | AP47: 0 | AQ47: 0 | AR47: 0 | AS47: 0 | AT47: 0 | AU47: 0 | AV47: 0 | AW47: 0 | AX47: 0 | AY47: 0 | AZ47: 0 | BA47: 0 | BB47: 0 | BC47: 0 | BD47: 0 | BE47: 0 | BF47: 0 | BG47: 0 | BH47: 0 | BI47: 0 | BJ47: 0 | BK47: 0 | BL47: 0 | BM47: 0 | BN47: 0 | BO47: 0 | BP47: 0 | BQ47: 0 | BR47: 0 | BS47: 0 | BT47: 0 | BU47: 0 | BV47: 0 | BW47: 0 | BX47: 0
A48: Total number of SADs averted | B48: 0 | C48: 0 | D48: 0 | E48: 0 | F48: 0 | G48: 0 | H48: 0 | I48: 0 | J48: 0 | K48: =$B$37*$B$38 -> 1461293.8 | L48: =$B$37*$B$38 -> 1461293.8 | M48: =$B$37*$B$38 -> 1461293.8 | N48: =$B$37*$B$38 -> 1461293.8 | O48: =$B$37*$B$38 -> 1461293.8 | P48: =$B$37*$B$38 -> 1461293.8 | Q48: =$B$37*$B$38 -> 1461293.8 | R48: =$B$37*$B$38 -> 1461293.8 | ... BX48: =$B$37*$B$38 -> 1461293.8
A50: Results
A51: Discounted costs | B51: {=NPV(B40,47:47)} -> 4567946.8
A52: Discounted benefits | B52: {=NPV(B43,48:48)} -> 7595053.7
A53: SADs averted/$ | B53: =B52/B51 -> 1.6626844

Sheet Broiler welfare (El Salvador)
B1: El Salvador
A2: Inputs | B2: Expected | C2: Description | G2: Source
A3: Costs
A4: Fixed costs (Year 1) | B4: 130000 | C4: Held constant across all CEAs | G4: -
A5: Fixed costs (At scale) | B5: 280000 | C5: Held constant across all CEAs | G5: -
A6: Variable costs - Cost of running corporate campaigns | B6: =AVERAGE(534332,405436,275223,204425,301497,401996,70000,60000,20000,2000,62628,41752) -> 198274.08 | C6: Cost of corporate campaigning taken from relevant ACE recommended charities (Kafessiz Türkiye, Shrimp Welfare Project, Sinergia Animal, and THL) | G6: https://animalcharityevaluators.org/charity-review/ciftlik-hayvanlarini-koruma-dernegi/#c2 https://animalcharityevaluators.org/charity-review/shrimp-welfare-project/#c2 https://animalcharityevaluators.org/charity-review/sinergia-animal/#c2 https://animalcharityevaluators.org/charity-review/the-humane-league/#c2
A7: Charity years operating | B7: 15 | C7: 10 years for campaigning, 5 years for enforcement work. We will base this CEA off relevant cage-free data from the US. Cage-free campaigns have been ongoing in the US for about a decade now. | G7: -
A8: Number of years until shut down | B8: 3 | C8: Assume org will shut down after 3 years if no commitments have been won | G8: -
A9: Years until implementation | B9: 10 | C9: Assume we give them a ~10 year transition period (this was the case in the US where campaigns happened in late 2014 with a deadline of 2025). Conservative estimate that they will not go cage-free until deadline. | G9: -
A11: Benefits
A12: Chicken meat production (kg, 2022) | B12: =161680*1000 -> 161680000 | C12: El Salvador produced 161,680 tonnes of chicken meat in 2022 * 1,000 for kg | G12: https://ourworldindata.org/grapher/chicken-meat-production?tab=table
A13: Meat yield per bird (kg, 2022) | B13: 1.3 | C13: Each chicken in El Salvador produces 1.3kg of meat | G13: https://ourworldindata.org/grapher/chicken-meat-yields-per-animal
A14: Number of broiler chickens (2022) | B14: =B12/B13 -> 1.2436923e+08 | C14: Calculation: Chicken meat production / meat yield per bird | G14: -
A15: Annual growth of chicken production | B15: =AVERAGE(4%,18%,-10%) -> 0.04 | C15: Average of growth rates over the previous 3 years as we are trying to project growth to 2025 from 2022 numbers. 2021-2022: 4% 2020-2021: 18% 2019-2020: -10% | G15: https://ourworldindata.org/grapher/chicken-meat-production?tab=table
A16: Capped at __ years | B16: 5 | C16: Best guess for how long growth of production will stay at 4.67% as this likely wont continue forever | G16: -
A17: Number of broilers (2025) | B17: =B14*(1+B15)^3 -> 1.3989847e+08 | C17: Calculated number of layer hens farmed in 2025 based on annual growth rates
A19: APPROACH 1
A20: % of production shifted after 10 years of campaigning | B20: =average(39%,60%,80%) -> 0.59666667 | C20: 39%, 60% and 80% of hens in the US, Europe, and UK respectively were cage-free at the end of 2023 thanks to ~10 years of corporate campaigns. | G20: https://farmanimalwelfare.substack.com/p/a-year-of-wins-for-farmed-animals
A21: Probability of success | B21: 0.8 | C21: Best guess.
A22: Number of broilers affected – Approach 1 | B22: =B$17*B20*B21 -> 66778203 | C22: Calculation
A23: Approach 1 weight | B23: 0.7 | C23: Best guess
A25: APPROACH 2
A26: Probability of success | B26: =AVERAGE(29%,30%,15%) -> 0.24666667 | C26: Best guess. Average of 29% from THL case study, 30% from Sinergia case study, and 15% for usual probability of success for corporate campaigns | G26: -
A27: Corporations targeted make up what % of total production | B27: 0.7 | C27: Best guess. This is the number we have used in previous CEAs.
A28: To account for corporations being targeted again in future years | B28: 2 | C28: Best guess.
A29: Enforcement rate of corporate campaigns | B29: =AVERAGE(48%,84%,39%,50%,89%)*(0.48/0.72) -> 0.41333333 | C29: Average of three estimates: ~48-84% expected enforcement rate for cage-free campaigns (Šimčikas, 2019), 39-50% expected enforcement rate for corporate campaigns (Sarek, 2019) and 89% actual enforcement rate of cage-free commitments with a deadline of 2023 or earlier that were actually implemented by the end of 2023 (Open Wing Alliance, 2024). This has been adjusted for slightly lower expected enforcement in UAE (0.72 WJP regulatory enforcement score on average in Europe and 0.48 in El Salvador). | G29: https://forum.effectivealtruism.org/posts/L5EZjjXKdNgcm253H/corporate-campaigns-affect-9-to-120-years-of-chicken-life https://forum.effectivealtruism.org/posts/SG38cPw5C7wLXAeFn/89-of-cage-free-egg-commitments-with-deadlines-of-2023-or https://forum.effectivealtruism.org/posts/JWcNfLAJCxMPZCdCu/35-independent-pieces-of-evidence-for-why-new-corporate https://worldjusticeproject.org/rule-of-law-index/country/2023/United%20Arab%20Emirates/Regulatory%20Enforcement/
A30: Number of broilers affected – Approach 2 | B30: =B$17*B26*B28*B27*B29 -> 19968797 | C30: Calculation
A31: Approach 2 weight | B31: 0.3 | C31: Best guess
A33: Adjustment to account for progress being harder outside of Europe and the US | B33: =Calculations!G12 -> 0.24325843 | C33: See calculations tab | G33: -
A34: Adjustment to account for progress being slower with BCC | B34: =24%/64% -> 0.375 | C34: Best guess based on expected enforcement rate of cage-free campaigns is 64% and expected enforcement rate of BCC is 24%
A35: Adjustment to account for progress being harder as a good cop only type actor | B35: =average(44.97%,45.8%) -> 0.45385 | C35: Analysis of number of commitments (per org) per country with just good cop actors vs good and bad cop actors - Note this uses 2023 numbers | G35: https://docs.google.com/spreadsheets/d/1-Acx-OYg8anoGT9jNYukdxowO-lPt2Biidxj1iT35Lw/edit?gid=1748706729#gid=1748706729
A37: Expected number of broilers affected after 10 years of campaigning | B37: =((B22*B23)+(B30*B31))*B33*B34*B35*(1+B15)^B16 -> 2656319.4 | C37: Calculation | G37: https://www.eurogroupforanimals.org/news/why-do-fast-growing-broiler-chicken-breeds-need-be-phased-out#:~:text=95%25%20of%20the%20broiler%20chickens,just%20five%20to%20six%20weeks.
A38: SADs averted per animal | B38: 0.94730467 | C38: SADs averted per animal by moving from fast growing to slow growing breeds (accounts for sentience, welfare range, and moral weights of different intensities of pain) | G38: https://docs.google.com/spreadsheets/d/1DssnYoZKFSE3w_-E2PLuOImLUd56JK3JNoO6JHkmTPk/edit?gid=289821833#gid=289821833
A40: Discount rate (Costs) | B40: 0.04 | C40: Held constant across all CEAs | G40: -
A41: Base discount rate (Benefits) | B41: 0.014 | C41: Held constant across all CEAs | G41: -
A42: Annual chance that this would happen without our intervention | B42: 0.075 | C42: Best guess - Some chance that global commitments will affect production and some chance that OWA will start actively recruiting and find an org. More chance that someone else will do this in Central America than in the Middle East given the presence of orgs in Latin America and North America. | G42: -
A43: Effective discount rate (Benefits) | B43: =SUM(B41:B42) -> 0.089 | C43: Calculation: Sum of all relevant discount rates | G43: -
A45: Calculations
A46: Year | B46: 1 | C46: 2 | D46: 3 | E46: 4 | F46: 5 | G46: 6 | H46: 7 | I46: 8 | J46: 9 | K46: 10 | L46: 11 | M46: 12 | N46: 13 | O46: 14 | P46: 15 | Q46: 16 | R46: 17 | S46: 18 | T46: 19 | U46: 20 | V46: 21 | W46: 22 | X46: 23 | Y46: 24 | Z46: 25 | AA46: 26 | AB46: 27 | AC46: 28 | AD46: 29 | AE46: 30 | AF46: 31 | AG46: 32 | AH46: 33 | AI46: 34 | AJ46: 35 | AK46: 36 | AL46: 37 | AM46: 38 | AN46: 39 | AO46: 40 | AP46: 41 | AQ46: 42 | AR46: 43 | AS46: 44 | AT46: 45 | AU46: 46 | AV46: 47 | AW46: 48 | AX46: 49 | AY46: 50 | AZ46: 51 | BA46: 52 | BB46: 53 | BC46: 54 | BD46: 55 | BE46: 56 | BF46: 57 | BG46: 58 | BH46: 59 | BI46: 60 | BJ46: 61 | BK46: 62 | BL46: 63 | BM46: 64 | BN46: 65 | BO46: 66 | BP46: 67 | BQ46: 68 | BR46: 69 | BS46: 70 | BT46: 71 | BU46: 72 | BV46: 73 | BW46: 74 | BX46: 75
A47: Total Costs | B47: =B4+B6 -> 328274.08 | C47: =$B$5+$B$6 -> 478274.08 | D47: =$B$5+$B$6 -> 478274.08 | E47: =$B$5+$B$6*(($B$21*$B$23)+($B$26*$B$31)) -> 405705.77 | F47: =$B$5+$B$6*(($B$21*$B$23)+($B$26*$B$31)) -> 405705.77 | G47: =$B$5+$B$6*(($B$21*$B$23)+($B$26*$B$31)) -> 405705.77 | H47: =$B$5+$B$6*(($B$21*$B$23)+($B$26*$B$31)) -> 405705.77 | I47: =$B$5+$B$6*(($B$21*$B$23)+($B$26*$B$31)) -> 405705.77 | J47: =$B$5+$B$6*(($B$21*$B$23)+($B$26*$B$31)) -> 405705.77 | K47: =$B$5+$B$6*(($B$21*$B$23)+($B$26*$B$31)) -> 405705.77 | L47: =$B$5+$B$6*(($B$21*$B$23)+($B$26*$B$31)) -> 405705.77 | ... P47: =$B$5+$B$6*(($B$21*$B$23)+($B$26*$B$31)) -> 405705.77 | Q47: 0 | R47: 0 | S47: 0 | T47: 0 | U47: 0 | V47: 0 | W47: 0 | X47: 0 | Y47: 0 | Z47: 0 | AA47: 0 | AB47: 0 | AC47: 0 | AD47: 0 | AE47: 0 | AF47: 0 | AG47: 0 | AH47: 0 | AI47: 0 | AJ47: 0 | AK47: 0 | AL47: 0 | AM47: 0 | AN47: 0 | AO47: 0 | AP47: 0 | AQ47: 0 | AR47: 0 | AS47: 0 | AT47: 0 | AU47: 0 | AV47: 0 | AW47: 0 | AX47: 0 | AY47: 0 | AZ47: 0 | BA47: 0 | BB47: 0 | BC47: 0 | BD47: 0 | BE47: 0 | BF47: 0 | BG47: 0 | BH47: 0 | BI47: 0 | BJ47: 0 | BK47: 0 | BL47: 0 | BM47: 0 | BN47: 0 | BO47: 0 | BP47: 0 | BQ47: 0 | BR47: 0 | BS47: 0 | BT47: 0 | BU47: 0 | BV47: 0 | BW47: 0 | BX47: 0
A48: Total number of SADs averted | B48: 0 | C48: 0 | D48: 0 | E48: 0 | F48: 0 | G48: 0 | H48: 0 | I48: 0 | J48: 0 | K48: =$B$37*$B$38 -> 2516343.7 | L48: =$B$37*$B$38 -> 2516343.7 | M48: =$B$37*$B$38 -> 2516343.7 | N48: =$B$37*$B$38 -> 2516343.7 | O48: =$B$37*$B$38 -> 2516343.7 | P48: =$B$37*$B$38 -> 2516343.7 | Q48: =$B$37*$B$38 -> 2516343.7 | R48: =$B$37*$B$38 -> 2516343.7 | ... BX48: =$B$37*$B$38 -> 2516343.7
A50: Results
A51: Discounted costs | B51: {=NPV(B40,47:47)} -> 4567946.8
A52: Discounted benefits | B52: {=NPV(B43,48:48)} -> 13078661
A53: SADs averted/$ | B53: =B52/B51 -> 2.8631377

Sheet Broiler welfare (Guatemala)
B1: Guatemala
A2: Inputs | B2: Expected | C2: Description | G2: Source
A3: Costs
A4: Fixed costs (Year 1) | B4: 130000 | C4: Held constant across all CEAs | G4: -
A5: Fixed costs (At scale) | B5: 280000 | C5: Held constant across all CEAs | G5: -
A6: Variable costs - Cost of running corporate campaigns | B6: =AVERAGE(534332,405436,275223,204425,301497,401996,70000,60000,20000,2000,62628,41752) -> 198274.08 | C6: Cost of corporate campaigning taken from relevant ACE recommended charities (Kafessiz Türkiye, Shrimp Welfare Project, Sinergia Animal, and THL) | G6: https://animalcharityevaluators.org/charity-review/ciftlik-hayvanlarini-koruma-dernegi/#c2 https://animalcharityevaluators.org/charity-review/shrimp-welfare-project/#c2 https://animalcharityevaluators.org/charity-review/sinergia-animal/#c2 https://animalcharityevaluators.org/charity-review/the-humane-league/#c2
A7: Charity years operating | B7: 15 | C7: 10 years for campaigning, 5 years for enforcement work. We will base this CEA off relevant cage-free data from the US. Cage-free campaigns have been ongoing in the US for about a decade now. | G7: -
A8: Number of years until shut down | B8: 3 | C8: Assume org will shut down after 3 years if no commitments have been won | G8: -
A9: Years until implementation | B9: 10 | C9: Assume we give them a ~10 year transition period (this was the case in the US where campaigns happened in late 2014 with a deadline of 2025). Conservative estimate that they will not go cage-free until deadline. | G9: -
A11: Benefits
A12: Chicken meat production (kg, 2022) | B12: =385380*1000 -> 385380000 | C12: Guatemala produced 385,380 tonnes of chicken meat in 2022 * 1,000 for kg | G12: https://ourworldindata.org/grapher/chicken-meat-production?tab=table
A13: Meat yield per bird (kg, 2022) | B13: 1.62 | C13: Each chicken in Guatemala produces 1.62kg of meat | G13: https://ourworldindata.org/grapher/chicken-meat-yields-per-animal
A14: Number of broiler chickens (2022) | B14: =B12/B13 -> 2.3788889e+08 | C14: Calculation: Chicken meat production / meat yield per bird | G14: -
A15: Annual growth of chicken production | B15: =AVERAGE(13%,-20%,25%) -> 0.06 | C15: Average of growth rates over the previous 3 years as we are trying to project growth to 2025 from 2022 numbers. 2021-2022: 13% 2020-2021: -20% 2019-2020: 25% | G15: https://ourworldindata.org/grapher/chicken-meat-production?tab=table
A16: Capped at __ years | B16: 5 | C16: Best guess for how long growth of production will stay at 4.67% as this likely wont continue forever | G16: -
A17: Number of broilers (2025) | B17: =B14*(1+B15)^3 -> 2.8332947e+08 | C17: Calculated number of layer hens farmed in 2025 based on annual growth rates
A19: APPROACH 1
A20: % of production shifted after 10 years of campaigning | B20: =average(39%,60%,80%) -> 0.59666667 | C20: 39%, 60% and 80% of hens in the US, Europe, and UK respectively were cage-free at the end of 2023 thanks to ~10 years of corporate campaigns. | G20: https://farmanimalwelfare.substack.com/p/a-year-of-wins-for-farmed-animals
A21: Probability of success | B21: 0.8 | C21: Best guess.
A22: Number of broilers affected – Approach 1 | B22: =B$17*B20*B21 -> 1.352426e+08 | C22: Calculation
A23: Approach 1 weight | B23: 0.7 | C23: Best guess
A25: APPROACH 2
A26: Probability of success | B26: =AVERAGE(29%,30%,15%) -> 0.24666667 | C26: Best guess. Average of 29% from THL case study, 30% from Sinergia case study, and 15% for usual probability of success for corporate campaigns | G26: -
A27: Corporations targeted make up what % of total production | B27: 0.7 | C27: Best guess. This is the number we have used in previous CEAs.
A28: To account for corporations being targeted again in future years | B28: 2 | C28: Best guess.
A29: Enforcement rate of corporate campaigns | B29: =AVERAGE(48%,84%,39%,50%,89%)*(0.4/0.72) -> 0.34444444 | C29: Average of three estimates: ~48-84% expected enforcement rate for cage-free campaigns (Šimčikas, 2019), 39-50% expected enforcement rate for corporate campaigns (Sarek, 2019) and 89% actual enforcement rate of cage-free commitments with a deadline of 2023 or earlier that were actually implemented by the end of 2023 (Open Wing Alliance, 2024). This has been adjusted for slightly lower expected enforcement in UAE (0.72 WJP regulatory enforcement score on average in Europe and 0.4 in Guatemala). | G29: https://forum.effectivealtruism.org/posts/L5EZjjXKdNgcm253H/corporate-campaigns-affect-9-to-120-years-of-chicken-life https://forum.effectivealtruism.org/posts/SG38cPw5C7wLXAeFn/89-of-cage-free-egg-commitments-with-deadlines-of-2023-or https://forum.effectivealtruism.org/posts/JWcNfLAJCxMPZCdCu/35-independent-pieces-of-evidence-for-why-new-corporate https://worldjusticeproject.org/rule-of-law-index/country/2023/United%20Arab%20Emirates/Regulatory%20Enforcement/
A30: Number of broilers affected – Approach 2 | B30: =B$17*B26*B28*B27*B29 -> 33701516 | C30: Calculation
A31: Approach 2 weight | B31: 0.3 | C31: Best guess
A33: Adjustment to account for progress being harder outside of Europe and the US | B33: =Calculations!G12 -> 0.24325843 | C33: See calculations tab | G33: -
A34: Adjustment to account for progress being slower with BCC | B34: =24%/64% -> 0.375 | C34: Best guess based on expected enforcement rate of cage-free campaigns is 64% and expected enforcement rate of BCC is 24%
A35: Adjustment to account for progress being harder as a good cop only type actor | B35: =average(44.97%,45.8%) -> 0.45385 | C35: Analysis of number of commitments (per org) per country with just good cop actors vs good and bad cop actors - Note this uses 2023 numbers | G35: https://docs.google.com/spreadsheets/d/1-Acx-OYg8anoGT9jNYukdxowO-lPt2Biidxj1iT35Lw/edit?gid=1748706729#gid=1748706729
A37: Expected number of broilers affected after 10 years of campaigning | B37: =((B22*B23)+(B30*B31))*B33*B34*B35*(1+B15)^B16 -> 5805242.5 | C37: Calculation | G37: https://www.eurogroupforanimals.org/news/why-do-fast-growing-broiler-chicken-breeds-need-be-phased-out#:~:text=95%25%20of%20the%20broiler%20chickens,just%20five%20to%20six%20weeks.
A38: SADs averted per animal | B38: 0.94730467 | C38: SADs averted per animal by moving from fast growing to slow growing breeds (accounts for sentience, welfare range, and moral weights of different intensities of pain) | G38: https://docs.google.com/spreadsheets/d/1DssnYoZKFSE3w_-E2PLuOImLUd56JK3JNoO6JHkmTPk/edit?gid=289821833#gid=289821833
A40: Discount rate (Costs) | B40: 0.04 | C40: Held constant across all CEAs | G40: -
A41: Base discount rate (Benefits) | B41: 0.014 | C41: Held constant across all CEAs | G41: -
A42: Annual chance that this would happen without our intervention | B42: 0.075 | C42: Best guess - Some chance that global commitments will affect production and some chance that OWA will start actively recruiting and find an org. More chance that someone else will do this in Central America than in the Middle East given the presence of orgs in Latin America and North America. | G42: -
A43: Effective discount rate (Benefits) | B43: =SUM(B41:B42) -> 0.089 | C43: Calculation: Sum of all relevant discount rates | G43: -
A45: Calculations
A46: Year | B46: 1 | C46: 2 | D46: 3 | E46: 4 | F46: 5 | G46: 6 | H46: 7 | I46: 8 | J46: 9 | K46: 10 | L46: 11 | M46: 12 | N46: 13 | O46: 14 | P46: 15 | Q46: 16 | R46: 17 | S46: 18 | T46: 19 | U46: 20 | V46: 21 | W46: 22 | X46: 23 | Y46: 24 | Z46: 25 | AA46: 26 | AB46: 27 | AC46: 28 | AD46: 29 | AE46: 30 | AF46: 31 | AG46: 32 | AH46: 33 | AI46: 34 | AJ46: 35 | AK46: 36 | AL46: 37 | AM46: 38 | AN46: 39 | AO46: 40 | AP46: 41 | AQ46: 42 | AR46: 43 | AS46: 44 | AT46: 45 | AU46: 46 | AV46: 47 | AW46: 48 | AX46: 49 | AY46: 50 | AZ46: 51 | BA46: 52 | BB46: 53 | BC46: 54 | BD46: 55 | BE46: 56 | BF46: 57 | BG46: 58 | BH46: 59 | BI46: 60 | BJ46: 61 | BK46: 62 | BL46: 63 | BM46: 64 | BN46: 65 | BO46: 66 | BP46: 67 | BQ46: 68 | BR46: 69 | BS46: 70 | BT46: 71 | BU46: 72 | BV46: 73 | BW46: 74 | BX46: 75
A47: Total Costs | B47: =B4+B6 -> 328274.08 | C47: =$B$5+$B$6 -> 478274.08 | D47: =$B$5+$B$6 -> 478274.08 | E47: =$B$5+$B$6*(($B$21*$B$23)+($B$26*$B$31)) -> 405705.77 | F47: =$B$5+$B$6*(($B$21*$B$23)+($B$26*$B$31)) -> 405705.77 | G47: =$B$5+$B$6*(($B$21*$B$23)+($B$26*$B$31)) -> 405705.77 | H47: =$B$5+$B$6*(($B$21*$B$23)+($B$26*$B$31)) -> 405705.77 | I47: =$B$5+$B$6*(($B$21*$B$23)+($B$26*$B$31)) -> 405705.77 | J47: =$B$5+$B$6*(($B$21*$B$23)+($B$26*$B$31)) -> 405705.77 | K47: =$B$5+$B$6*(($B$21*$B$23)+($B$26*$B$31)) -> 405705.77 | L47: =$B$5+$B$6*(($B$21*$B$23)+($B$26*$B$31)) -> 405705.77 | ... P47: =$B$5+$B$6*(($B$21*$B$23)+($B$26*$B$31)) -> 405705.77 | Q47: 0 | R47: 0 | S47: 0 | T47: 0 | U47: 0 | V47: 0 | W47: 0 | X47: 0 | Y47: 0 | Z47: 0 | AA47: 0 | AB47: 0 | AC47: 0 | AD47: 0 | AE47: 0 | AF47: 0 | AG47: 0 | AH47: 0 | AI47: 0 | AJ47: 0 | AK47: 0 | AL47: 0 | AM47: 0 | AN47: 0 | AO47: 0 | AP47: 0 | AQ47: 0 | AR47: 0 | AS47: 0 | AT47: 0 | AU47: 0 | AV47: 0 | AW47: 0 | AX47: 0 | AY47: 0 | AZ47: 0 | BA47: 0 | BB47: 0 | BC47: 0 | BD47: 0 | BE47: 0 | BF47: 0 | BG47: 0 | BH47: 0 | BI47: 0 | BJ47: 0 | BK47: 0 | BL47: 0 | BM47: 0 | BN47: 0 | BO47: 0 | BP47: 0 | BQ47: 0 | BR47: 0 | BS47: 0 | BT47: 0 | BU47: 0 | BV47: 0 | BW47: 0 | BX47: 0
A48: Total number of SADs averted | B48: 0 | C48: 0 | D48: 0 | E48: 0 | F48: 0 | G48: 0 | H48: 0 | I48: 0 | J48: 0 | K48: =$B$37*$B$38 -> 5499333.3 | L48: =$B$37*$B$38 -> 5499333.3 | M48: =$B$37*$B$38 -> 5499333.3 | N48: =$B$37*$B$38 -> 5499333.3 | O48: =$B$37*$B$38 -> 5499333.3 | P48: =$B$37*$B$38 -> 5499333.3 | Q48: =$B$37*$B$38 -> 5499333.3 | R48: =$B$37*$B$38 -> 5499333.3 | ... BX48: =$B$37*$B$38 -> 5499333.3
A50: Results
A51: Discounted costs | B51: {=NPV(B40,47:47)} -> 4567946.8
A52: Discounted benefits | B52: {=NPV(B43,48:48)} -> 28582707
A53: SADs averted/$ | B53: =B52/B51 -> 6.2572328

Sheet Broiler welfare (Honduras)
B1: Honduras
A2: Inputs | B2: Expected | C2: Description | G2: Source
A3: Costs
A4: Fixed costs (Year 1) | B4: 130000 | C4: Held constant across all CEAs | G4: -
A5: Fixed costs (At scale) | B5: 280000 | C5: Held constant across all CEAs | G5: -
A6: Variable costs - Cost of running corporate campaigns | B6: =AVERAGE(534332,405436,275223,204425,301497,401996,70000,60000,20000,2000,62628,41752) -> 198274.08 | C6: Cost of corporate campaigning taken from relevant ACE recommended charities (Kafessiz Türkiye, Shrimp Welfare Project, Sinergia Animal, and THL) | G6: https://animalcharityevaluators.org/charity-review/ciftlik-hayvanlarini-koruma-dernegi/#c2 https://animalcharityevaluators.org/charity-review/shrimp-welfare-project/#c2 https://animalcharityevaluators.org/charity-review/sinergia-animal/#c2 https://animalcharityevaluators.org/charity-review/the-humane-league/#c2
A7: Charity years operating | B7: 15 | C7: 10 years for campaigning, 5 years for enforcement work. We will base this CEA off relevant cage-free data from the US. Cage-free campaigns have been ongoing in the US for about a decade now. | G7: -
A8: Number of years until shut down | B8: 3 | C8: Assume org will shut down after 3 years if no commitments have been won | G8: -
A9: Years until implementation | B9: 10 | C9: Assume we give them a ~10 year transition period (this was the case in the US where campaigns happened in late 2014 with a deadline of 2025). Conservative estimate that they will not go cage-free until deadline. | G9: -
A11: Benefits
A12: Chicken meat production (kg, 2022) | B12: =257903*1000 -> 257903000 | C12: Honduras produced 257,903 tonnes of chicken meat in 2022 * 1,000 for kg | G12: https://ourworldindata.org/grapher/chicken-meat-production?tab=table
A13: Meat yield per bird (kg, 2022) | B13: 2.04 | C13: Each chicken in Honduras produces 2.04kg of meat | G13: https://ourworldindata.org/grapher/chicken-meat-yields-per-animal
A14: Number of broiler chickens (2022) | B14: =B12/B13 -> 1.2642304e+08 | C14: Calculation: Chicken meat production / meat yield per bird | G14: -
A15: Annual growth of chicken production | B15: =AVERAGE(6%,23%,-8%) -> 0.07 | C15: Average of growth rates over the previous 3 years as we are trying to project growth to 2025 from 2022 numbers. 2021-2022: 6% 2020-2021: 23% 2019-2020: -8% | G15: https://ourworldindata.org/grapher/chicken-meat-production?tab=table
A16: Capped at __ years | B16: 5 | C16: Best guess for how long growth of production will stay at 4.67% as this likely wont continue forever | G16: -
A17: Number of broilers (2025) | B17: =B14*(1+B15)^3 -> 1.5487366e+08 | C17: Calculated number of layer hens farmed in 2025 based on annual growth rates
A19: APPROACH 1
A20: % of production shifted after 10 years of campaigning | B20: =average(39%,60%,80%) -> 0.59666667 | C20: 39%, 60% and 80% of hens in the US, Europe, and UK respectively were cage-free at the end of 2023 thanks to ~10 years of corporate campaigns. | G20: https://farmanimalwelfare.substack.com/p/a-year-of-wins-for-farmed-animals
A21: Probability of success | B21: 0.8 | C21: Best guess.
A22: Number of broilers affected – Approach 1 | B22: =B$17*B20*B21 -> 73926360 | C22: Calculation
A23: Approach 1 weight | B23: 0.7 | C23: Best guess
A25: APPROACH 2
A26: Probability of success | B26: =AVERAGE(29%,30%,15%) -> 0.24666667 | C26: Best guess. Average of 29% from THL case study, 30% from Sinergia case study, and 15% for usual probability of success for corporate campaigns | G26: -
A27: Corporations targeted make up what % of total production | B27: 0.7 | C27: Best guess. This is the number we have used in previous CEAs.
A28: To account for corporations being targeted again in future years | B28: 2 | C28: Best guess.
A29: Enforcement rate of corporate campaigns | B29: =AVERAGE(48%,84%,39%,50%,89%)*(0.39/0.72) -> 0.33583333 | C29: Average of three estimates: ~48-84% expected enforcement rate for cage-free campaigns (Šimčikas, 2019), 39-50% expected enforcement rate for corporate campaigns (Sarek, 2019) and 89% actual enforcement rate of cage-free commitments with a deadline of 2023 or earlier that were actually implemented by the end of 2023 (Open Wing Alliance, 2024). This has been adjusted for slightly lower expected enforcement in UAE (0.72 WJP regulatory enforcement score on average in Europe and 0.39 in Honduras). | G29: https://forum.effectivealtruism.org/posts/L5EZjjXKdNgcm253H/corporate-campaigns-affect-9-to-120-years-of-chicken-life https://forum.effectivealtruism.org/posts/SG38cPw5C7wLXAeFn/89-of-cage-free-egg-commitments-with-deadlines-of-2023-or https://forum.effectivealtruism.org/posts/JWcNfLAJCxMPZCdCu/35-independent-pieces-of-evidence-for-why-new-corporate https://worldjusticeproject.org/rule-of-law-index/country/2023/United%20Arab%20Emirates/Regulatory%20Enforcement/
A30: Number of broilers affected – Approach 2 | B30: =B$17*B26*B28*B27*B29 -> 17961387 | C30: Calculation
A31: Approach 2 weight | B31: 0.3 | C31: Best guess
A33: Adjustment to account for progress being harder outside of Europe and the US | B33: =Calculations!G12 -> 0.24325843 | C33: See calculations tab | G33: -
A34: Adjustment to account for progress being slower with BCC | B34: =24%/64% -> 0.375 | C34: Best guess based on expected enforcement rate of cage-free campaigns is 64% and expected enforcement rate of BCC is 24%
A35: Adjustment to account for progress being harder as a good cop only type actor | B35: =average(44.97%,45.8%) -> 0.45385 | C35: Analysis of number of commitments (per org) per country with just good cop actors vs good and bad cop actors - Note this uses 2023 numbers | G35: https://docs.google.com/spreadsheets/d/1-Acx-OYg8anoGT9jNYukdxowO-lPt2Biidxj1iT35Lw/edit?gid=1748706729#gid=1748706729
A37: Expected number of broilers affected after 10 years of campaigning | B37: =((B22*B23)+(B30*B31))*B33*B34*B35*(1+B15)^B16 -> 3317774.2 | C37: Calculation | G37: https://www.eurogroupforanimals.org/news/why-do-fast-growing-broiler-chicken-breeds-need-be-phased-out#:~:text=95%25%20of%20the%20broiler%20chickens,just%20five%20to%20six%20weeks.
A38: SADs averted per animal | B38: 0.94730467 | C38: SADs averted per animal by moving from fast growing to slow growing breeds (accounts for sentience, welfare range, and moral weights of different intensities of pain) | G38: https://docs.google.com/spreadsheets/d/1DssnYoZKFSE3w_-E2PLuOImLUd56JK3JNoO6JHkmTPk/edit?gid=289821833#gid=289821833
A40: Discount rate (Costs) | B40: 0.04 | C40: Held constant across all CEAs | G40: -
A41: Base discount rate (Benefits) | B41: 0.014 | C41: Held constant across all CEAs | G41: -
A42: Annual chance that this would happen without our intervention | B42: 0.075 | C42: Best guess - Some chance that global commitments will affect production and some chance that OWA will start actively recruiting and find an org. More chance that someone else will do this in Central America than in the Middle East given the presence of orgs in Latin America and North America. | G42: -
A43: Effective discount rate (Benefits) | B43: =SUM(B41:B42) -> 0.089 | C43: Calculation: Sum of all relevant discount rates | G43: -
A45: Calculations
A46: Year | B46: 1 | C46: 2 | D46: 3 | E46: 4 | F46: 5 | G46: 6 | H46: 7 | I46: 8 | J46: 9 | K46: 10 | L46: 11 | M46: 12 | N46: 13 | O46: 14 | P46: 15 | Q46: 16 | R46: 17 | S46: 18 | T46: 19 | U46: 20 | V46: 21 | W46: 22 | X46: 23 | Y46: 24 | Z46: 25 | AA46: 26 | AB46: 27 | AC46: 28 | AD46: 29 | AE46: 30 | AF46: 31 | AG46: 32 | AH46: 33 | AI46: 34 | AJ46: 35 | AK46: 36 | AL46: 37 | AM46: 38 | AN46: 39 | AO46: 40 | AP46: 41 | AQ46: 42 | AR46: 43 | AS46: 44 | AT46: 45 | AU46: 46 | AV46: 47 | AW46: 48 | AX46: 49 | AY46: 50 | AZ46: 51 | BA46: 52 | BB46: 53 | BC46: 54 | BD46: 55 | BE46: 56 | BF46: 57 | BG46: 58 | BH46: 59 | BI46: 60 | BJ46: 61 | BK46: 62 | BL46: 63 | BM46: 64 | BN46: 65 | BO46: 66 | BP46: 67 | BQ46: 68 | BR46: 69 | BS46: 70 | BT46: 71 | BU46: 72 | BV46: 73 | BW46: 74 | BX46: 75
A47: Total Costs | B47: =B4+B6 -> 328274.08 | C47: =$B$5+$B$6 -> 478274.08 | D47: =$B$5+$B$6 -> 478274.08 | E47: =$B$5+$B$6*(($B$21*$B$23)+($B$26*$B$31)) -> 405705.77 | F47: =$B$5+$B$6*(($B$21*$B$23)+($B$26*$B$31)) -> 405705.77 | G47: =$B$5+$B$6*(($B$21*$B$23)+($B$26*$B$31)) -> 405705.77 | H47: =$B$5+$B$6*(($B$21*$B$23)+($B$26*$B$31)) -> 405705.77 | I47: =$B$5+$B$6*(($B$21*$B$23)+($B$26*$B$31)) -> 405705.77 | J47: =$B$5+$B$6*(($B$21*$B$23)+($B$26*$B$31)) -> 405705.77 | K47: =$B$5+$B$6*(($B$21*$B$23)+($B$26*$B$31)) -> 405705.77 | L47: =$B$5+$B$6*(($B$21*$B$23)+($B$26*$B$31)) -> 405705.77 | ... P47: =$B$5+$B$6*(($B$21*$B$23)+($B$26*$B$31)) -> 405705.77 | Q47: 0 | R47: 0 | S47: 0 | T47: 0 | U47: 0 | V47: 0 | W47: 0 | X47: 0 | Y47: 0 | Z47: 0 | AA47: 0 | AB47: 0 | AC47: 0 | AD47: 0 | AE47: 0 | AF47: 0 | AG47: 0 | AH47: 0 | AI47: 0 | AJ47: 0 | AK47: 0 | AL47: 0 | AM47: 0 | AN47: 0 | AO47: 0 | AP47: 0 | AQ47: 0 | AR47: 0 | AS47: 0 | AT47: 0 | AU47: 0 | AV47: 0 | AW47: 0 | AX47: 0 | AY47: 0 | AZ47: 0 | BA47: 0 | BB47: 0 | BC47: 0 | BD47: 0 | BE47: 0 | BF47: 0 | BG47: 0 | BH47: 0 | BI47: 0 | BJ47: 0 | BK47: 0 | BL47: 0 | BM47: 0 | BN47: 0 | BO47: 0 | BP47: 0 | BQ47: 0 | BR47: 0 | BS47: 0 | BT47: 0 | BU47: 0 | BV47: 0 | BW47: 0 | BX47: 0
A48: Total number of SADs averted | B48: 0 | C48: 0 | D48: 0 | E48: 0 | F48: 0 | G48: 0 | H48: 0 | I48: 0 | J48: 0 | K48: =$B$37*$B$38 -> 3142943 | L48: =$B$37*$B$38 -> 3142943 | M48: =$B$37*$B$38 -> 3142943 | N48: =$B$37*$B$38 -> 3142943 | O48: =$B$37*$B$38 -> 3142943 | P48: =$B$37*$B$38 -> 3142943 | Q48: =$B$37*$B$38 -> 3142943 | R48: =$B$37*$B$38 -> 3142943 | ... BX48: =$B$37*$B$38 -> 3142943
A50: Results
A51: Discounted costs | B51: {=NPV(B40,47:47)} -> 4567946.8
A52: Discounted benefits | B52: {=NPV(B43,48:48)} -> 16335401
A53: SADs averted/$ | B53: =B52/B51 -> 3.5760927

Sheet Broiler welfare (Nicaragua)
B1: Nicaragua
A2: Inputs | B2: Expected | C2: Description | G2: Source
A3: Costs
A4: Fixed costs (Year 1) | B4: 130000 | C4: Held constant across all CEAs | G4: -
A5: Fixed costs (At scale) | B5: 280000 | C5: Held constant across all CEAs | G5: -
A6: Variable costs - Cost of running corporate campaigns | B6: =AVERAGE(534332,405436,275223,204425,301497,401996,70000,60000,20000,2000,62628,41752) -> 198274.08 | C6: Cost of corporate campaigning taken from relevant ACE recommended charities (Kafessiz Türkiye, Shrimp Welfare Project, Sinergia Animal, and THL) | G6: https://animalcharityevaluators.org/charity-review/ciftlik-hayvanlarini-koruma-dernegi/#c2 https://animalcharityevaluators.org/charity-review/shrimp-welfare-project/#c2 https://animalcharityevaluators.org/charity-review/sinergia-animal/#c2 https://animalcharityevaluators.org/charity-review/the-humane-league/#c2
A7: Charity years operating | B7: 15 | C7: 10 years for campaigning, 5 years for enforcement work. We will base this CEA off relevant cage-free data from the US. Cage-free campaigns have been ongoing in the US for about a decade now. | G7: -
A8: Number of years until shut down | B8: 3 | C8: Assume org will shut down after 3 years if no commitments have been won | G8: -
A9: Years until implementation | B9: 10 | C9: Assume we give them a ~10 year transition period (this was the case in the US where campaigns happened in late 2014 with a deadline of 2025). Conservative estimate that they will not go cage-free until deadline. | G9: -
A11: Benefits
A12: Chicken meat production (kg, 2022) | B12: =154154*1000 -> 154154000 | C12: Nicaragua produced 154,154 tonnes of chicken meat in 2022 * 1,000 for kg | G12: https://ourworldindata.org/grapher/chicken-meat-production?tab=table
A13: Meat yield per bird (kg, 2022) | B13: 2.29 | C13: Each chicken in Nicaragua produces 2.29kg of meat | G13: https://ourworldindata.org/grapher/chicken-meat-yields-per-animal
A14: Number of broiler chickens (2022) | B14: =B12/B13 -> 67316157 | C14: Calculation: Chicken meat production / meat yield per bird | G14: -
A15: Annual growth of chicken production | B15: =AVERAGE(8%,2%,1%) -> 0.036666667 | C15: Average of growth rates over the previous 3 years as we are trying to project growth to 2025 from 2022 numbers. 2021-2022: 8% 2020-2021: 2% 2019-2020: 1% | G15: https://ourworldindata.org/grapher/chicken-meat-production?tab=table
A16: Capped at __ years | B16: 5 | C16: Best guess for how long growth of production will stay at 4.67% as this likely wont continue forever | G16: -
A17: Number of broilers (2025) | B17: =B14*(1+B15)^3 -> 74995761 | C17: Calculated number of layer hens farmed in 2025 based on annual growth rates
A19: APPROACH 1
A20: % of production shifted after 10 years of campaigning | B20: =average(39%,60%,80%) -> 0.59666667 | C20: 39%, 60% and 80% of hens in the US, Europe, and UK respectively were cage-free at the end of 2023 thanks to ~10 years of corporate campaigns. | G20: https://farmanimalwelfare.substack.com/p/a-year-of-wins-for-farmed-animals
A21: Probability of success | B21: 0.8 | C21: Best guess.
A22: Number of broilers affected – Approach 1 | B22: =B$17*B20*B21 -> 35797977 | C22: Calculation
A23: Approach 1 weight | B23: 0.7 | C23: Best guess
A25: APPROACH 2
A26: Probability of success | B26: =AVERAGE(29%,30%,15%) -> 0.24666667 | C26: Best guess. Average of 29% from THL case study, 30% from Sinergia case study, and 15% for usual probability of success for corporate campaigns | G26: -
A27: Corporations targeted make up what % of total production | B27: 0.7 | C27: Best guess. This is the number we have used in previous CEAs.
A28: To account for corporations being targeted again in future years | B28: 2 | C28: Best guess.
A29: Enforcement rate of corporate campaigns | B29: =AVERAGE(48%,84%,39%,50%,89%)*(0.36/0.72) -> 0.31 | C29: Average of three estimates: ~48-84% expected enforcement rate for cage-free campaigns (Šimčikas, 2019), 39-50% expected enforcement rate for corporate campaigns (Sarek, 2019) and 89% actual enforcement rate of cage-free commitments with a deadline of 2023 or earlier that were actually implemented by the end of 2023 (Open Wing Alliance, 2024). This has been adjusted for slightly lower expected enforcement in Nicaragua (0.72 WJP regulatory enforcement score on average in Europe and 0.36 in Nicaragua). | G29: https://forum.effectivealtruism.org/posts/L5EZjjXKdNgcm253H/corporate-campaigns-affect-9-to-120-years-of-chicken-life https://forum.effectivealtruism.org/posts/SG38cPw5C7wLXAeFn/89-of-cage-free-egg-commitments-with-deadlines-of-2023-or https://forum.effectivealtruism.org/posts/JWcNfLAJCxMPZCdCu/35-independent-pieces-of-evidence-for-why-new-corporate https://worldjusticeproject.org/rule-of-law-index/country/2023/United%20Arab%20Emirates/Regulatory%20Enforcement/
A30: Number of broilers affected – Approach 2 | B30: =B$17*B26*B28*B27*B29 -> 8028546.2 | C30: Calculation
A31: Approach 2 weight | B31: 0.3 | C31: Best guess
A33: Adjustment to account for progress being harder outside of Europe and the US | B33: =Calculations!G12 -> 0.24325843 | C33: See calculations tab | G33: -
A34: Adjustment to account for progress being slower with BCC | B34: =24%/64% -> 0.375 | C34: Best guess based on expected enforcement rate of cage-free campaigns is 64% and expected enforcement rate of BCC is 24%
A35: Adjustment to account for progress being harder as a good cop only type actor | B35: =average(44.97%,45.8%) -> 0.45385 | C35: Analysis of number of commitments (per org) per country with just good cop actors vs good and bad cop actors - Note this uses 2023 numbers | G35: https://docs.google.com/spreadsheets/d/1-Acx-OYg8anoGT9jNYukdxowO-lPt2Biidxj1iT35Lw/edit?gid=1748706729#gid=1748706729
A37: Expected number of broilers affected after 10 years of campaigning | B37: =((B22*B23)+(B30*B31))*B33*B34*B35*(1+B15)^B16 -> 1361509.7 | C37: Calculation | G37: https://www.eurogroupforanimals.org/news/why-do-fast-growing-broiler-chicken-breeds-need-be-phased-out#:~:text=95%25%20of%20the%20broiler%20chickens,just%20five%20to%20six%20weeks.
A38: SADs averted per animal | B38: 0.94730467 | C38: SADs averted per animal by moving from fast growing to slow growing breeds (accounts for sentience, welfare range, and moral weights of different intensities of pain) | G38: https://docs.google.com/spreadsheets/d/1DssnYoZKFSE3w_-E2PLuOImLUd56JK3JNoO6JHkmTPk/edit?gid=289821833#gid=289821833
A40: Discount rate (Costs) | B40: 0.04 | C40: Held constant across all CEAs | G40: -
A41: Base discount rate (Benefits) | B41: 0.014 | C41: Held constant across all CEAs | G41: -
A42: Annual chance that this would happen without our intervention | B42: 0.075 | C42: Best guess - Some chance that global commitments will affect production and some chance that OWA will start actively recruiting and find an org. More chance that someone else will do this in Central America than in the Middle East given the presence of orgs in Latin America and North America. | G42: -
A43: Effective discount rate (Benefits) | B43: =SUM(B41:B42) -> 0.089 | C43: Calculation: Sum of all relevant discount rates | G43: -
A45: Calculations
A46: Year | B46: 1 | C46: 2 | D46: 3 | E46: 4 | F46: 5 | G46: 6 | H46: 7 | I46: 8 | J46: 9 | K46: 10 | L46: 11 | M46: 12 | N46: 13 | O46: 14 | P46: 15 | Q46: 16 | R46: 17 | S46: 18 | T46: 19 | U46: 20 | V46: 21 | W46: 22 | X46: 23 | Y46: 24 | Z46: 25 | AA46: 26 | AB46: 27 | AC46: 28 | AD46: 29 | AE46: 30 | AF46: 31 | AG46: 32 | AH46: 33 | AI46: 34 | AJ46: 35 | AK46: 36 | AL46: 37 | AM46: 38 | AN46: 39 | AO46: 40 | AP46: 41 | AQ46: 42 | AR46: 43 | AS46: 44 | AT46: 45 | AU46: 46 | AV46: 47 | AW46: 48 | AX46: 49 | AY46: 50 | AZ46: 51 | BA46: 52 | BB46: 53 | BC46: 54 | BD46: 55 | BE46: 56 | BF46: 57 | BG46: 58 | BH46: 59 | BI46: 60 | BJ46: 61 | BK46: 62 | BL46: 63 | BM46: 64 | BN46: 65 | BO46: 66 | BP46: 67 | BQ46: 68 | BR46: 69 | BS46: 70 | BT46: 71 | BU46: 72 | BV46: 73 | BW46: 74 | BX46: 75
A47: Total Costs | B47: =B4+B6 -> 328274.08 | C47: =$B$5+$B$6 -> 478274.08 | D47: =$B$5+$B$6 -> 478274.08 | E47: =$B$5+$B$6*(($B$21*$B$23)+($B$26*$B$31)) -> 405705.77 | F47: =$B$5+$B$6*(($B$21*$B$23)+($B$26*$B$31)) -> 405705.77 | G47: =$B$5+$B$6*(($B$21*$B$23)+($B$26*$B$31)) -> 405705.77 | H47: =$B$5+$B$6*(($B$21*$B$23)+($B$26*$B$31)) -> 405705.77 | I47: =$B$5+$B$6*(($B$21*$B$23)+($B$26*$B$31)) -> 405705.77 | J47: =$B$5+$B$6*(($B$21*$B$23)+($B$26*$B$31)) -> 405705.77 | K47: =$B$5+$B$6*(($B$21*$B$23)+($B$26*$B$31)) -> 405705.77 | L47: =$B$5+$B$6*(($B$21*$B$23)+($B$26*$B$31)) -> 405705.77 | ... P47: =$B$5+$B$6*(($B$21*$B$23)+($B$26*$B$31)) -> 405705.77 | Q47: 0 | R47: 0 | S47: 0 | T47: 0 | U47: 0 | V47: 0 | W47: 0 | X47: 0 | Y47: 0 | Z47: 0 | AA47: 0 | AB47: 0 | AC47: 0 | AD47: 0 | AE47: 0 | AF47: 0 | AG47: 0 | AH47: 0 | AI47: 0 | AJ47: 0 | AK47: 0 | AL47: 0 | AM47: 0 | AN47: 0 | AO47: 0 | AP47: 0 | AQ47: 0 | AR47: 0 | AS47: 0 | AT47: 0 | AU47: 0 | AV47: 0 | AW47: 0 | AX47: 0 | AY47: 0 | AZ47: 0 | BA47: 0 | BB47: 0 | BC47: 0 | BD47: 0 | BE47: 0 | BF47: 0 | BG47: 0 | BH47: 0 | BI47: 0 | BJ47: 0 | BK47: 0 | BL47: 0 | BM47: 0 | BN47: 0 | BO47: 0 | BP47: 0 | BQ47: 0 | BR47: 0 | BS47: 0 | BT47: 0 | BU47: 0 | BV47: 0 | BW47: 0 | BX47: 0
A48: Total number of SADs averted | B48: 0 | C48: 0 | D48: 0 | E48: 0 | F48: 0 | G48: 0 | H48: 0 | I48: 0 | J48: 0 | K48: =$B$37*$B$38 -> 1289764.5 | L48: =$B$37*$B$38 -> 1289764.5 | M48: =$B$37*$B$38 -> 1289764.5 | N48: =$B$37*$B$38 -> 1289764.5 | O48: =$B$37*$B$38 -> 1289764.5 | P48: =$B$37*$B$38 -> 1289764.5 | Q48: =$B$37*$B$38 -> 1289764.5 | R48: =$B$37*$B$38 -> 1289764.5 | ... BX48: =$B$37*$B$38 -> 1289764.5
A50: Results
A51: Discounted costs | B51: {=NPV(B40,47:47)} -> 4567946.8
A52: Discounted benefits | B52: {=NPV(B43,48:48)} -> 6703532.6
A53: SADs averted/$ | B53: =B52/B51 -> 1.4675155

Sheet Broiler welfare (Ireland)
B1: Ireland
A2: Inputs | B2: Expected | C2: Description | G2: Source
A3: Costs
A4: Fixed costs (Year 1) | B4: 130000 | C4: Held constant across all CEAs | G4: -
A5: Fixed costs (At scale) | B5: 280000 | C5: Held constant across all CEAs | G5: -
A6: Variable costs - Cost of running corporate campaigns | B6: =AVERAGE(534332,405436,275223,204425,301497,401996,70000,60000,20000,2000,62628,41752) -> 198274.08 | C6: Cost of corporate campaigning taken from relevant ACE recommended charities (Kafessiz Türkiye, Shrimp Welfare Project, Sinergia Animal, and THL) | G6: https://animalcharityevaluators.org/charity-review/ciftlik-hayvanlarini-koruma-dernegi/#c2 https://animalcharityevaluators.org/charity-review/shrimp-welfare-project/#c2 https://animalcharityevaluators.org/charity-review/sinergia-animal/#c2 https://animalcharityevaluators.org/charity-review/the-humane-league/#c2
A7: Charity years operating | B7: 15 | C7: 10 years for campaigning, 5 years for enforcement work. We will base this CEA off relevant cage-free data from the US. Cage-free campaigns have been ongoing in the US for about a decade now. | G7: -
A8: Number of years until shut down | B8: 3 | C8: Assume org will shut down after 3 years if no commitments have been won | G8: -
A9: Years until implementation | B9: 10 | C9: Assume we give them a ~10 year transition period (this was the case in the US where campaigns happened in late 2014 with a deadline of 2025). Conservative estimate that they will not go cage-free until deadline. | G9: -
A11: Benefits
A12: Chicken meat production (kg, 2022) | B12: =144730*1000 -> 144730000 | C12: Ireland produced 144,730 tonnes of chicken meat in 2022 * 1,000 for kg | G12: https://ourworldindata.org/grapher/chicken-meat-production?tab=table
A13: Meat yield per bird (kg, 2022) | B13: 1.48 | C13: Each chicken in Ireland produces 1.48kg of meat | G13: https://ourworldindata.org/grapher/chicken-meat-yields-per-animal
A14: Number of broiler chickens (2022) | B14: =B12/B13 -> 97790541 | C14: Calculation: Chicken meat production / meat yield per bird | G14: -
A15: Annual growth of chicken production | B15: =AVERAGE(-2%,-3%,8%) -> 0.01 | C15: Average of growth rates over the previous 3 years as we are trying to project growth to 2025 from 2022 numbers. 2021-2022: -2% 2020-2021: -3% 2019-2020: 8% | G15: https://ourworldindata.org/grapher/chicken-meat-production?tab=table
A16: Capped at __ years | B16: 5 | C16: Best guess for how long growth of production will stay at 4.67% as this likely wont continue forever | G16: -
A17: Number of broilers (2025) | B17: =B14*(1+B15)^3 -> 1.0075369e+08 | C17: Calculated number of layer hens farmed in 2025 based on annual growth rates
A19: APPROACH 1
A20: % of production shifted after 10 years of campaigning | B20: =average(39%,60%,80%) -> 0.59666667 | C20: 39%, 60% and 80% of hens in the US, Europe, and UK respectively were cage-free at the end of 2023 thanks to ~10 years of corporate campaigns. | G20: https://farmanimalwelfare.substack.com/p/a-year-of-wins-for-farmed-animals
A21: Probability of success | B21: 0.8 | C21: Best guess.
A22: Number of broilers affected – Approach 1 | B22: =B$17*B20*B21 -> 48093096 | C22: Calculation
A23: Approach 1 weight | B23: 0.7 | C23: Best guess
A25: APPROACH 2
A26: Probability of success | B26: =AVERAGE(29%,30%,15%) -> 0.24666667 | C26: Best guess. Average of 29% from THL case study, 30% from Sinergia case study, and 15% for usual probability of success for corporate campaigns | G26: -
A27: Corporations targeted make up what % of total production | B27: 0.7 | C27: Best guess. This is the number we have used in previous CEAs.
A28: To account for corporations being targeted again in future years | B28: 2 | C28: Best guess.
A29: Enforcement rate of corporate campaigns | B29: =AVERAGE(48%,84%,39%,50%,89%) -> 0.62 | C29: Average of three estimates: ~48-84% expected enforcement rate for cage-free campaigns (Šimčikas, 2019), 39-50% expected enforcement rate for corporate campaigns (Sarek, 2019) and 89% actual enforcement rate of cage-free commitments with a deadline of 2023 or earlier that were actually implemented by the end of 2023 (Open Wing Alliance, 2024). This does not need to be adjusted as Ireland is also in Europe. | G29: https://forum.effectivealtruism.org/posts/L5EZjjXKdNgcm253H/corporate-campaigns-affect-9-to-120-years-of-chicken-life https://forum.effectivealtruism.org/posts/SG38cPw5C7wLXAeFn/89-of-cage-free-egg-commitments-with-deadlines-of-2023-or https://forum.effectivealtruism.org/posts/JWcNfLAJCxMPZCdCu/35-independent-pieces-of-evidence-for-why-new-corporate https://worldjusticeproject.org/rule-of-law-index/country/2023/United%20Arab%20Emirates/Regulatory%20Enforcement/
A30: Number of broilers affected – Approach 2 | B30: =B$17*B26*B28*B27*B29 -> 21572037 | C30: Calculation
A31: Approach 2 weight | B31: 0.3 | C31: Best guess
A33: Adjustment to account for progress being harder outside of Europe and the US | B33: 1 | C33: Set to 100% - Not needed in this instance as Ireland is in Europe. | G33: -
A34: Adjustment to account for progress being slower with BCC | B34: =24%/64% -> 0.375 | C34: Best guess based on expected enforcement rate of cage-free campaigns is 64% and expected enforcement rate of BCC is 24%
A35: Adjustment to account for progress being harder as a good cop only type actor | B35: 1 | C35: Set to 100% - Not needed in this instance as we suggest taking the bad cop approach in Ireland | G35: -
A37: Expected number of broilers affected after 10 years of campaigning | B37: =((B22*B23)+(B30*B31))*B33*B34*B35*(1+B15)^B16 -> 15819059 | C37: Calculation | G37: https://www.eurogroupforanimals.org/news/why-do-fast-growing-broiler-chicken-breeds-need-be-phased-out#:~:text=95%25%20of%20the%20broiler%20chickens,just%20five%20to%20six%20weeks.
A38: SADs averted per animal | B38: 0.94730467 | C38: SADs averted per animal by moving from fast growing to slow growing breeds (accounts for sentience, welfare range, and moral weights of different intensities of pain) | G38: https://docs.google.com/spreadsheets/d/1DssnYoZKFSE3w_-E2PLuOImLUd56JK3JNoO6JHkmTPk/edit?gid=289821833#gid=289821833
A40: Discount rate (Costs) | B40: 0.04 | C40: Held constant across all CEAs | G40: -
A41: Base discount rate (Benefits) | B41: 0.014 | C41: Held constant across all CEAs | G41: -
A42: Annual chance that this would happen without our intervention | B42: 0.1 | C42: Best guess - Some chance that global commitments will affect production and some chance that OWA will start actively recruiting and find an org. Mostly likely that this would happen in Ireland without our work than in Central America and the Middle East. | G42: -
A43: Effective discount rate (Benefits) | B43: =SUM(B41:B42) -> 0.114 | C43: Calculation: Sum of all relevant discount rates | G43: -
A45: Calculations
A46: Year | B46: 1 | C46: 2 | D46: 3 | E46: 4 | F46: 5 | G46: 6 | H46: 7 | I46: 8 | J46: 9 | K46: 10 | L46: 11 | M46: 12 | N46: 13 | O46: 14 | P46: 15 | Q46: 16 | R46: 17 | S46: 18 | T46: 19 | U46: 20 | V46: 21 | W46: 22 | X46: 23 | Y46: 24 | Z46: 25 | AA46: 26 | AB46: 27 | AC46: 28 | AD46: 29 | AE46: 30 | AF46: 31 | AG46: 32 | AH46: 33 | AI46: 34 | AJ46: 35 | AK46: 36 | AL46: 37 | AM46: 38 | AN46: 39 | AO46: 40 | AP46: 41 | AQ46: 42 | AR46: 43 | AS46: 44 | AT46: 45 | AU46: 46 | AV46: 47 | AW46: 48 | AX46: 49 | AY46: 50 | AZ46: 51 | BA46: 52 | BB46: 53 | BC46: 54 | BD46: 55 | BE46: 56 | BF46: 57 | BG46: 58 | BH46: 59 | BI46: 60 | BJ46: 61 | BK46: 62 | BL46: 63 | BM46: 64 | BN46: 65 | BO46: 66 | BP46: 67 | BQ46: 68 | BR46: 69 | BS46: 70 | BT46: 71 | BU46: 72 | BV46: 73 | BW46: 74 | BX46: 75
A47: Total Costs | B47: =B4+B6 -> 328274.08 | C47: =$B$5+$B$6 -> 478274.08 | D47: =$B$5+$B$6 -> 478274.08 | E47: =$B$5+$B$6*(($B$21*$B$23)+($B$26*$B$31)) -> 405705.77 | F47: =$B$5+$B$6*(($B$21*$B$23)+($B$26*$B$31)) -> 405705.77 | G47: =$B$5+$B$6*(($B$21*$B$23)+($B$26*$B$31)) -> 405705.77 | H47: =$B$5+$B$6*(($B$21*$B$23)+($B$26*$B$31)) -> 405705.77 | I47: =$B$5+$B$6*(($B$21*$B$23)+($B$26*$B$31)) -> 405705.77 | J47: =$B$5+$B$6*(($B$21*$B$23)+($B$26*$B$31)) -> 405705.77 | K47: =$B$5+$B$6*(($B$21*$B$23)+($B$26*$B$31)) -> 405705.77 | L47: =$B$5+$B$6*(($B$21*$B$23)+($B$26*$B$31)) -> 405705.77 | ... P47: =$B$5+$B$6*(($B$21*$B$23)+($B$26*$B$31)) -> 405705.77 | Q47: 0 | R47: 0 | S47: 0 | T47: 0 | U47: 0 | V47: 0 | W47: 0 | X47: 0 | Y47: 0 | Z47: 0 | AA47: 0 | AB47: 0 | AC47: 0 | AD47: 0 | AE47: 0 | AF47: 0 | AG47: 0 | AH47: 0 | AI47: 0 | AJ47: 0 | AK47: 0 | AL47: 0 | AM47: 0 | AN47: 0 | AO47: 0 | AP47: 0 | AQ47: 0 | AR47: 0 | AS47: 0 | AT47: 0 | AU47: 0 | AV47: 0 | AW47: 0 | AX47: 0 | AY47: 0 | AZ47: 0 | BA47: 0 | BB47: 0 | BC47: 0 | BD47: 0 | BE47: 0 | BF47: 0 | BG47: 0 | BH47: 0 | BI47: 0 | BJ47: 0 | BK47: 0 | BL47: 0 | BM47: 0 | BN47: 0 | BO47: 0 | BP47: 0 | BQ47: 0 | BR47: 0 | BS47: 0 | BT47: 0 | BU47: 0 | BV47: 0 | BW47: 0 | BX47: 0
A48: Total number of SADs averted | B48: 0 | C48: 0 | D48: 0 | E48: 0 | F48: 0 | G48: 0 | H48: 0 | I48: 0 | J48: 0 | K48: =$B$37*$B$38 -> 14985468 | L48: =$B$37*$B$38 -> 14985468 | M48: =$B$37*$B$38 -> 14985468 | N48: =$B$37*$B$38 -> 14985468 | O48: =$B$37*$B$38 -> 14985468 | P48: =$B$37*$B$38 -> 14985468 | Q48: =$B$37*$B$38 -> 14985468 | R48: =$B$37*$B$38 -> 14985468 | ... BX48: =$B$37*$B$38 -> 14985468
A50: Results
A51: Discounted costs | B51: {=NPV(B40,47:47)} -> 4567946.8
A52: Discounted benefits | B52: {=NPV(B43,48:48)} -> 49710620
A53: SADs averted/$ | B53: =B52/B51 -> 10.882487

Sheet Calculations
A1: Calculations
A2: Discount rate to account for progress being harder in Middle East
A3: We use progress in Latin America vs the US as a proxy here. Sinergia Animal started campaigning in 2017 in Argentina, Brazil, Chile, and Colombia. This is 7 years ago. We look at the number of corporate campaigns secured in these regions compared to the number secured in the US over the same period (campaigns started in late 2014, so we will consider the 2014-2021 period in the US)
A4: Geography | B4: Year | C4: Number of cage-free commitments (ChickenWatch)
A5: USA | B5: 2014 | C5: 5
A6: USA | B6: 2015 | C6: 64 | E6: Country | F6: Total number of commitments | G6: Ratio USA:Country
A7: USA | B7: 2016 | C7: 224 | E7: USA | F7: =C13 -> 445 | G7: =F7/$F$7 -> 1
A8: USA | B8: 2017 | C8: 64 | E8: Argentina | F8: =C22 -> 68 | G8: =F8/$F$7 -> 0.15280899
A9: USA | B9: 2018 | C9: 36 | E9: Brazil | F9: =C31 -> 202 | G9: =F9/$F$7 -> 0.45393258
A10: USA | B10: 2019 | C10: 15 | E10: Chile | F10: =C40 -> 86 | G10: =F10/$F$7 -> 0.19325843
A11: USA | B11: 2020 | C11: 19 | E11: Colombia | F11: =C49 -> 77 | G11: =F11/$F$7 -> 0.17303371
A12: USA | B12: 2021 | C12: 18 | F12: AVG | G12: =AVERAGE(G8:G11) -> 0.24325843
B13: TOTAL | C13: =SUM(C5:C12) -> 445
A14: Argentina | B14: 2017 | C14: 13
A15: Argentina | B15: 2018 | C15: 10
A16: Argentina | B16: 2019 | C16: 10
A17: Argentina | B17: 2020 | C17: 9
A18: Argentina | B18: 2021 | C18: 7
A19: Argentina | B19: 2022 | C19: 6
A20: Argentina | B20: 2023 | C20: 6
A21: Argentina | B21: 2024 | C21: 7
B22: TOTAL | C22: =SUM(C14:C21) -> 68
A23: Brazil | B23: 2017 | C23: 48
A24: Brazil | B24: 2018 | C24: 49
A25: Brazil | B25: 2019 | C25: 29
A26: Brazil | B26: 2020 | C26: 20
A27: Brazil | B27: 2021 | C27: 25
A28: Brazil | B28: 2022 | C28: 16
A29: Brazil | B29: 2023 | C29: 12
A30: Brazil | B30: 2024 | C30: 3
B31: TOTAL | C31: =SUM(C23:C30) -> 202
A32: Chile | B32: 2017 | C32: 14
A33: Chile | B33: 2018 | C33: 10
A34: Chile | B34: 2019 | C34: 16
A35: Chile | B35: 2020 | C35: 6
A36: Chile | B36: 2021 | C36: 13
A37: Chile | B37: 2022 | C37: 14
A38: Chile | B38: 2023 | C38: 10
A39: Chile | B39: 2024 | C39: 3
B40: TOTAL | C40: =SUM(C32:C39) -> 86
A41: Colombia | B41: 2017 | C41: 14
A42: Colombia | B42: 2018 | C42: 17
A43: Colombia | B43: 2019 | C43: 5
A44: Colombia | B44: 2020 | C44: 8
A45: Colombia | B45: 2021 | C45: 12
A46: Colombia | B46: 2022 | C46: 8
A47: Colombia | B47: 2023 | C47: 10
A48: Colombia | B48: 2024 | C48: 3
B49: TOTAL | C49: =SUM(C41:C48) -> 77
