Workbook

Sheet Summary
B1: Rwanda | C1: Average country in SSA | D1: AVG | E1: Notes / explanation
A2: Costs | B2: ='CEA (Rwanda)'!B116 -> 23155995 | C2: ='CEA (SSA)'!B116 -> 33688568 | D2: =AVERAGE(B2:C2) -> 28422282
A3: Benefits | B3: ='CEA (Rwanda)'!B117 -> 5.8327157e+08 | C3: ='CEA (SSA)'!B117 -> 1920423914 | D3: =AVERAGE(B3:C3) -> 1251847741 | E3: Benefits higher in SSA average case as average salary is higher than in Rwanda so an intervention that sees a % increase in salaries is more beneficial
A4: BCR | B4: ='CEA (Rwanda)'!B118 -> 25.188793 | C4: ='CEA (SSA)'!B118 -> 57.005211 | D4: =AVERAGE(B4:C4) -> 41.097002 | E4: Benefits rise more than costs for SSA average case as some costs fixed regardless of country, so a higher BCR in SSA average case
A5: $/DALY equivalent | B5: ='CEA (Rwanda)'!B125 -> 52.367299 | C5: ='CEA (SSA)'!B125 -> 46.306786 | D5: =AVERAGE(B5:C5) -> 49.337043 | E5: Difference not as extreme as BCR as the total increase in income means less to a wealthier cohort

Sheet CEA (Rwanda)
A1: 4
A2: Inputs | B2: Expected | C2: Description
A3: Costs
A4: Testing/pilot costs
A5: Duration of testing/pilot period (in years) | B5: 1 | F5: Suggested areas for improvement if more time:
A6: Fixed charity costs | B6: 125000 | C6: Best guess | F6: • Review costs, Try to get better numbers for "costs of lesson plans". For example does it make sense that at scale costs are 70% fixed costs; "Cost of lesson plans per child" could be modelled per classroom rather than per child; and "Cost of lesson plans per teacher" could look at how much training actually costs
F7: • Review the "Delay (years before any effect on growth in economy)" on "method 2".
A8: At scale costs
A9: Years delay to design program and lesson plans | B9: 1 | C9: Best guess
A10: Years to reach scale | B10: 8 | C10: Best guess
A11: Staff costs | B11: 225000 | C11: Costs roughly based on 4 staff members plus additional buffer. These costs will increase each year during scale up ie. Staff costs will be $225,000 in year 2, $550,000 in year 3, and so on until scale is reached in year 9.
A12: Cost of lesson plans per child | B12: 0.16 | C12: https://www.sciencedirect.com/science/article/pii/S0305750X18300287
A13: Cost of lesson plans per teacher | B13: 25 | C13: Assume some training and delivery costs (best guess)
A14: Years until benefit starts | B14: =AVERAGE(Calculations!$A$136:$A$138) -> 6.6666667 | C14: See calculations tab
A15: Charity years operating | B15: 30 | C15: Best guess, note this has very little effect on the results
A16: Number of years to model impact for | B16: =roundup(AVERAGE(Calculations!A128:A132),0) -> 30 | C16: See calculations tab
A17: Number of years each child needs to receive intervention to receive full benefit | B17: 8 | C17: Duration of compulsory education in SSA (World Bank)
A19: Reach
A20: Total number of primary schools in Rwanda | B20: 2961 | C20: https://www.mineduc.gov.rw/basic-education
A21: Total number of primary school aged children in school in Rwanda | B21: 2512465 | C21: Basic Education
A22: Number of children per school | B22: =B21/B20 -> 848.51908 | C22: Calculation: Total number of children / total number of schools
A23: Student-teacher ratio | B23: 58.34 | C23: Each teacher teaches 58.34 students (https://ourworldindata.org/grapher/pupil-teacher-ratio-for-primary-education-by-country?tab=table)
A24: Number of teachers per school | B24: =B22/B23 -> 14.544379 | C24: Calculation: Number of children per school / student-teacher ratio
A25: % of schools reached in pilot | B25: 0.01 | C25: Assume we work with 1% of schools during pilot (Bridge International did this in their pilot in Kenya)
A26: % of schools reached at scale | B26: 0.5 | C26: Assume we can work with 50% of schools at scale (best guess). Note: This is currently decoupled from fixed staff costs. If you decrease this, you'll presumably need to decrease staff costs too | H26: Might be lower
A27: Number of schools worked with during pilot | B27: =B20*B25 -> 29.61 | C27: Calculation: Number of schools * % of schools worked with
A28: Number of schools worked with in year 2 | B28: =$B$27+(($B$35-$B$27)/$B$10) -> 210.97125
A29: Number of schools worked with in year 3 | B29: =B28+(($B$35-$B$27)/$B$10) -> 392.3325
A30: Number of schools worked with in year 4 | B30: =B29+(($B$35-$B$27)/$B$10) -> 573.69375
A31: Number of schools worked with in year 5 | B31: =B30+(($B$35-$B$27)/$B$10) -> 755.055
A32: Number of schools worked with in year 6 | B32: =B31+(($B$35-$B$27)/$B$10) -> 936.41625
A33: Number of schools worked with in year 7 | B33: =B32+(($B$35-$B$27)/$B$10) -> 1117.7775
A34: Number of schools worked with in year 8 | B34: =B33+(($B$35-$B$27)/$B$10) -> 1299.1388
A35: Number of schools worked with at scale | B35: =B20*B26 -> 1480.5 | C35: Calculation: Number of schools * % of schools worked with
A36: Number of children reached during pilot | B36: =B27*B22 -> 25124.65 | C36: Calculation: Number of children per school * number of schools worked with during pilot
A37: Number of children worked with in year 2 | B37: =B36+(($B$44-$B$36)/$B$10) -> 179013.13
A38: Number of children worked with in year 3 | B38: =B37+(($B$44-$B$36)/$B$10) -> 332901.61
A39: Number of children worked with in year 4 | B39: =B38+(($B$44-$B$36)/$B$10) -> 486790.09
A40: Number of children worked with in year 5 | B40: =B39+(($B$44-$B$36)/$B$10) -> 640678.57
A41: Number of children worked with in year 6 | B41: =B40+(($B$44-$B$36)/$B$10) -> 794567.06
A42: Number of children worked with in year 7 | B42: =B41+(($B$44-$B$36)/$B$10) -> 948455.54
A43: Number of children worked with in year 8 | B43: =B42+(($B$44-$B$36)/$B$10) -> 1102344
A44: Number of children reached at scale | B44: =B22*B35 -> 1256232.5 | C44: Calculation: Number of children per school * number of schools worked with at scale
A45: Number of teachers reached during pilot | B45: =B24*B27 -> 430.65907 | C45: Calculation: Number of teachers per school * number of schools worked with during pilot
A46: Number of teachers reached at scale | B46: =B24*B35 -> 21532.953 | C46: Calculation: Number of teachers per school * number of schools worked with at scale
A47: Effect of lesson plans on test scores (SDs) | B47: =AVERAGE(0.38,0.3,0.5/6.9,0.3,0.54) -> 0.31849275 | C47: See data in Section 4.2 of final lesson plans report
A48: External validity adjustment | B48: 0.8 | C48: Best guess
A49: Effect of lesson plans on test scores (SDs) – adjusted | B49: =B47*B48 -> 0.2547942 | C49: Calculation
A51: Total spent at testing during pilot | B51: =B6+(B36*B12)+(B13*B45) -> 139786.42
A52: Total spent per year when at scale | B52: =(B11*B10)+(B12*B44)+(B13*B46) -> 2539321
A54: Probability of success following pilot | B54: 0.8 | C54: This is the probability of success that we will get government buy in following our pilot in private schools. We need this government buy in to reach scale as we plan to scale by working in government schools. Note given the pilot is only a very small part of the total costs this does not affect the end result much.
A55: Net attendance of primary schools (Children) | B55: 0.9281 | C55: Note: We have removed this factor as it seems to be accounted for in the estimates above on the number of children per school.
A56: Net attendance of primary schools (Teachers) | B56: =1-((AVERAGE(0.08*1.5/5,0.09*1.5/5))*Calculations!D124) -> 0.7545629 | C56: 8-9% teachers report absenteeism "at least once a week" (Time to Teach: Rwanda) -> Assume absent 1.5 days per week (best guess) Reported absenteeism based on findings of World Bank researchers who turned up to schools unannounced is higher than the rate self-reported by teachers (World Bank). Multiplier applied to account for this underreporting on the 8-9% number is calculated in the Calculations tab under "Teacher attendance".
A57: reduction in effect size due to imperfect usage of lesson plans | B57: 0.8 | C57: Best guess | H57: Might be lower
A58: Discount rate | B58: 0.04 | C58: Held constant across CEAs (from GiveWell)
A59: Discount rate (assuming income increase tracks growth) | B59: 0.01 | C59: We use this reduced income rate for modelling benefits in "Method 1". The income rate we use is a combination of a pure time preference factor (to account for sonner being better) a factor that accounts for future uncertainty and a factor that accounts for future growth (as benefits to richer scoieties are less valuable). But we expect that income effects will track economic growth and go up in time. As such we use a lower discount rate to account only for uncertainty (1%) and pure time preference (0%)
A61: Income effects
A62: Baseline per capita income | B62: 822.3 | C62: https://data.worldbank.org/indicator/NY.GDP.PCAP.CD?locations=RW
A63: Total population in Rwanda | B63: 13461888 | C63: https://data.worldbank.org/indicator/SP.POP.TOTL?locations=RW
A65: Moral weights
A66: GiveWell moral weight: Doubled years of income equivalent in DALYs | B66: =1/2.3 -> 0.43478261 | C66: https://docs.google.com/spreadsheets/d/1epyGHcuM9A7YjtddVpEPByBs_lxFY5fh1FQbVLlPneA/edit#gid=171561146 | D66: DALY value assigned to doubling consumption for one person for one year
A69: METHOD 1 – BASED ON INCOME EFFECTS
A70: Income increase from 1 SD increase in test scores | B70: 0.1 | C70: Using lower end estimate from most cited study on the income effects of improved test scores: 1 SD improvement in test scores leads to a 10-45% income increase (Hanushek et al., 2016)
A72: Calculations – Net present value of economic benefits
A73: Year | B73: 1 | C73: 2 | D73: 3 | E73: 4 | F73: 5 | G73: 6 | H73: 7 | I73: 8 | J73: 9 | K73: 10 | L73: 11 | M73: 12 | N73: 13 | O73: 14 | P73: 15 | Q73: 16 | R73: 17 | S73: 18 | T73: 19 | U73: 20 | V73: 21 | W73: 22 | X73: 23 | Y73: 24 | Z73: 25 | AA73: 26 | AB73: 27 | AC73: 28 | AD73: 29 | AE73: 30 | AF73: 31 | AG73: 32 | AH73: 33 | AI73: 34 | AJ73: 35 | AK73: 36 | AL73: 37 | AM73: 38
A74: Increased income per child (for a child that starts in year 1) | B74: 0 | C74: 0 | D74: 0 | E74: 0 | F74: 0 | G74: 0 | H74: 0 | I74: 0 | J74: =$B$62*($B$70)*$B$49 -> 20.951727 | K74: =$B$62*($B$70)*$B$49 -> 20.951727 | L74: =$B$62*($B$70)*$B$49 -> 20.951727 | M74: =$B$62*($B$70)*$B$49 -> 20.951727 | N74: =$B$62*($B$70)*$B$49 -> 20.951727 | O74: =$B$62*($B$70)*$B$49 -> 20.951727 | P74: =$B$62*($B$70)*$B$49 -> 20.951727 | Q74: =$B$62*($B$70)*$B$49 -> 20.951727 | ... AM74: =$B$62*($B$70)*$B$49 -> 20.951727
A75: % of annual income this represents | B75: =B74/$B62 -> 0 | C75: =C74/$B62 -> 0 | D75: =D74/$B62 -> 0 | E75: =E74/$B62 -> 0 | F75: =F74/$B62 -> 0 | G75: =G74/$B62 -> 0 | H75: =H74/$B62 -> 0 | I75: =I74/$B62 -> 0 | ... AM75: =AM74/$B62 -> 0.02547942
A77: Net present value of economic benefits per child per intervention | B77: {=NPV($B$59,$74:74)} -> 499.34221
A78: Net present value of economic benefits per child per year of intervention | B78: =B77/B17 -> 62.417777
A80: Calculations – Per capita income increase version
A81: Year | B81: 1 | C81: 2 | D81: 3 | E81: 4 | F81: 5 | G81: 6 | H81: 7 | I81: 8 | J81: 9 | K81: 10 | L81: 11 | M81: 12 | N81: 13 | O81: 14 | P81: 15 | Q81: 16 | R81: 17 | S81: 18 | T81: 19 | U81: 20 | V81: 21 | W81: 22 | X81: 23 | Y81: 24 | Z81: 25 | AA81: 26 | AB81: 27 | AC81: 28 | AD81: 29 | AE81: 30 | AF81: 31 | AG81: 32 | AH81: 33 | AI81: 34 | AJ81: 35 | AK81: 36 | AL81: 37 | AM81: 38
A82: Charity costs | B82: =B51 -> 139786.42 | C82: =($B$11+($B$12*$B28*$B$22)+($B$13*$B28*$B$24))*$B$54 -> 264282.6 | D82: =($B$11+($B$12*$B29*$B$22)+($B$13*$B29*$B$24))*$B$54 -> 336736.06 | E82: =($B$11+($B$12*$B30*$B$22)+($B$13*$B30*$B$24))*$B$54 -> 409189.52 | F82: =($B$11+($B$12*$B31*$B$22)+($B$13*$B31*$B$24))*$B$54 -> 481642.98 | G82: =($B$11+($B$12*$B32*$B$22)+($B$13*$B32*$B$24))*$B$54 -> 554096.44 | H82: =($B$11+($B$12*$B32*$B$22)+($B$13*$B32*$B$24))*$B$54 -> 554096.44 | I82: =($B$11+($B$12*$B33*$B$22)+($B$13*$B33*$B$24))*$B$54 -> 626549.9 | J82: =($B$11+($B$12*$B234*$B$22)+($B$13*$B34*$B$24))*$B$54 -> 557903.33 | K82: =$B$52*$B$54 -> 2031456.8 | L82: =$B$52*$B$54 -> 2031456.8 | M82: =$B$52*$B$54 -> 2031456.8 | N82: =$B$52*$B$54 -> 2031456.8 | O82: =$B$52*$B$54 -> 2031456.8 | P82: =$B$52*$B$54 -> 2031456.8 | Q82: =$B$52*$B$54 -> 2031456.8 | R82: =$B$52*$B$54 -> 2031456.8 | ... AE82: =$B$52*$B$54 -> 2031456.8 | AF82: 0 | AG82: 0 | AH82: 0 | AI82: 0 | AJ82: 0 | AK82: 0 | AL82: 0
A83: Number of children reach in each year | B83: 0 | C83: =($B$36*$B$54*$B$56*$B$57) -> 12133.202 | D83: =($B$37*$B$54*$B$56*$B$57) -> 86449.067 | E83: =($B$38*$B$54*$B$56*$B$57) -> 160764.93 | F83: =($B$39*$B$54*$B$56*$B$57) -> 235080.8 | G83: =($B$40*$B$54*$B$56*$B$57) -> 309396.66 | H83: =($B$41*$B$54*$B$56*$B$57) -> 383712.53 | I83: =($B$42*$B$54*$B$56*$B$57) -> 458028.39 | J83: =($B$43*$B$54*$B$56*$B$57) -> 532344.25 | K83: =($B$44*$B$54*$B$56*$B$57) -> 606660.12 | L83: =($B$44*$B$54*$B$56*$B$57) -> 606660.12 | M83: =($B$44*$B$54*$B$56*$B$57) -> 606660.12 | N83: =($B$44*$B$54*$B$56*$B$57) -> 606660.12 | O83: =($B$44*$B$54*$B$56*$B$57) -> 606660.12 | P83: =($B$44*$B$54*$B$56*$B$57) -> 606660.12 | Q83: =($B$44*$B$54*$B$56*$B$57) -> 606660.12 | R83: =($B$44*$B$54*$B$56*$B$57) -> 606660.12 | ... AL83: =($B$44*$B$54*$B$56*$B$57) -> 606660.12
A84: Economic benefit | B84: =B83*$B$78 -> 0 | C84: =C83*$B$78 -> 757327.52 | D84: =D83*$B$78 -> 5395958.6 | E84: =E83*$B$78 -> 10034590 | F84: =F83*$B$78 -> 14673221 | G84: =G83*$B$78 -> 19311852 | H84: =H83*$B$78 -> 23950483 | I84: =I83*$B$78 -> 28589114 | ... AL84: =AL83*$B$78 -> 37866376
A86: Outputs – Per capita income increase version
A87: Total discounted costs | B87: {=NPV($B$58,82:82)} -> 23155995 | D87: =B87/B44 -> 18.43289
A88: Total discounted benefit | B88: =SUM(B84:AL84) -> 1196198814
A89: Benefit-cost ratio | B89: =B88/B87 -> 51.658277
A91: METHOD 2 – BASED ON ECONOMIC GROWTH
A93: Effect size (accounting for all the factors that reduce the effect) | B93: =($B$54*$B$56*$B$57) -> 0.48292025 | C93: Calculation
A94: Total income of whole population | B94: =B63*B62 -> 11069710502 | C94: Calculation
A95: Delay (years before any effect on growth in economy) | B95: =ROUNDUP(B14/2,0) -> 4 | C95: From CEA tab but divided by 2 and rounded up as will start having an effect even before 7 years
A96: Economic growth per year assuming 100% of population affected | B96: =Calculations!D98 -> 0.0005010812 | C96: See calculations tab
A98: Calculations – Economic growth version
A99: Year | B99: 1 | C99: 2 | D99: 3 | E99: 4 | F99: 5 | G99: 6 | H99: 7 | I99: 8 | J99: 9 | K99: 10 | L99: 11 | M99: 12 | N99: 13 | O99: 14 | P99: 15 | Q99: 16 | R99: 17 | S99: 18 | T99: 19 | U99: 20 | V99: 21 | W99: 22 | X99: 23 | Y99: 24 | Z99: 25 | AA99: 26 | AB99: 27 | AC99: 28 | AD99: 29 | AE99: 30 | AF99: 31 | AG99: 32 | AH99: 33 | AI99: 34 | AJ99: 35 | AK99: 36 | AL99: 37
A100: % of schools reached | B100: 0 | C100: =$B27/$B$20 -> 0.01 | D100: =$B28/$B$20 -> 0.07125 | E100: =$B29/$B$20 -> 0.1325 | F100: =$B30/$B$20 -> 0.19375 | G100: =$B31/$B$20 -> 0.255 | H100: =$B32/$B$20 -> 0.31625 | I100: =$B33/$B$20 -> 0.3775 | J100: =$B34/$B$20 -> 0.43875 | K100: =$B35/$B$20 -> 0.5 | L100: =$B$26 -> 0.5 | M100: =$B$26 -> 0.5 | N100: =$B$26 -> 0.5 | O100: =$B$26 -> 0.5 | P100: =$B$26 -> 0.5 | Q100: =$B$26 -> 0.5 | R100: =$B$26 -> 0.5 | S100: =$B$26 -> 0.5 | ... AL100: =$B$26 -> 0.5
A101: Total income of country (ignore growth not caused by intervention) | B101: =IFERROR(A101*(1+$B96*#REF!),$B$94) -> 11069710502 | C101: =IFERROR(B101*(1+$B96*#REF!),$B$94) -> 11069710502 | D101: =IFERROR(C101*(1+$B96*#REF!),$B$94) -> 11069710502 | E101: =IFERROR(D101*(1+$B96*A100),$B$94) -> 11069710502 | F101: =IFERROR(E101*(1+$B96*$B93*B100),$B$94) -> 11069710502 | G101: =IFERROR(F101*(1+$B96*$B93*C100),$B$94) -> 11069737289 | H101: =IFERROR(G101*(1+$B96*$B93*D100),$B$94) -> 11069928145 | I101: =IFERROR(H101*(1+$B96*$B93*E100),$B$94) -> 11070283076 | J101: =IFERROR(I101*(1+$B96*$B93*F100),$B$94) -> 11070802096 | K101: =IFERROR(J101*(1+$B96*$B93*G100),$B$94) -> 11071485225 | L101: =IFERROR(K101*(1+$B96*$B93*H100),$B$94) -> 11072332492 | M101: =IFERROR(L101*(1+$B96*$B93*I100),$B$94) -> 11073343930 | ... AL101: =IFERROR(AK101*(1+$B96*$B93*AH100),$B$94) -> 11106722416
A102: Economic effect of the intervention | F102: =F101-$B94 -> 0 | G102: =G101-$B94 -> 26786.736 | H102: =H101-$B94 -> 217642.69 | I102: =I101-$B94 -> 572573.92 | J102: =J101-$B94 -> 1091593.8 | K102: =K101-$B94 -> 1774722.9 | L102: =L101-$B94 -> 2621989.2 | M102: =M101-$B94 -> 3633428 | ... AL102: =AL101-$B94 -> 37011914
A104: Outputs – Economic growth version
A105: Total discounted costs | B105: =B87 -> 23155995
A106: Total discounted benefit | B106: {=NPV($B$58,102:102)} -> 2.1551522e+08
A107: Benefit-cost ratio | B107: =B106/B105 -> 9.3071025
A109: Outputs – Combined
A110: WEIGHTINGS | B110: Vicky | C110: Sam | D110: Average | F110: ↓ Play around with weightings here
A111: Income model | B111: 0.4 | C111: 0.35 | D111: =AVERAGE(B111:C111) -> 0.375 | F111: 0.2
A112: GDP model | B112: 0.6 | C112: 0.65 | D112: =AVERAGE(B112:C112) -> 0.625 | F112: 0.8 | H112: Note: The income model has much more evidence behind it. The GDP model suggests much smaller effects. We end up weighting the GDP model more, in large part to make our overall estimate very conservative, and still show that it passes our bar compared to other charities. I expect other models would not be as conservative.
A114: Comparison: GDP model is ___% of income model | B114: =B107/B89 -> 0.18016672
A116: Total discounted costs | B116: =B87 -> 23155995 | F116: =B116 -> 23155995
A117: Weighted average economic benefits | B117: =(B88*D$111)+(B106*D$112) -> 5.8327157e+08 | F117: =(B88*F$111)+(B106*F$112) -> 4.1165194e+08
A118: Weighted average benefit-cost ratio | B118: =B117/B116 -> 25.188793 | F118: =F117/F116 -> 17.777337
...

Sheet CEA (SSA)
A1: A new charity introducing lesson plans into schools in an average country in SSA. The charity will do a pilot in its first year in private schools, then take the results of this pilot to governments and ask to pilot it and scale it up in government schools.
A2: Inputs | B2: Expected | C2: Description
A3: Costs
A4: Testing/pilot costs
A5: Duration of testing/pilot period (in years) | B5: 1 | F5: Suggested areas for improvement if more time:
A6: Fixed charity costs | B6: 125000 | C6: Best guess | F6: • Review costs, Try to get better numbers for "costs of lesson plans". For example does it make sense that at scale costs are 70% fixed costs; "Cost of lesson plans per child" could be modelled per classroom rather than per child; and "Cost of lesson plans per teacher" could look at how much training actually costs
F7: • Review the "Delay (years before any effect on growth in economy)" on "method 2".
A8: At scale costs
A9: Years delay to design program and lesson plans | B9: 1 | C9: Best guess
A10: Years to reach scale | B10: 8 | C10: Best guess
A11: Staff costs | B11: 225000 | C11: Costs roughly based on 4 staff members plus additional buffer. These costs will increase each year during scale up ie. Staff costs will be $225,000 in year 2, $550,000 in year 3, and so on until scale is reached in year 9.
A12: Cost of lesson plans per child | B12: 0.16 | C12: https://www.sciencedirect.com/science/article/pii/S0305750X18300287
A13: Cost of lesson plans per teacher | B13: 25 | C13: Assume some training and delivery costs (best guess)
A14: Years until benefit starts | B14: =AVERAGE(Calculations!$A$136:$A$138) -> 6.6666667 | C14: See calculations tab
A15: Charity years operating | B15: 30 | C15: Best guess, note this has very little effect on the results
A16: Number of years to model impact for | B16: =roundup(AVERAGE(Calculations!A128:A132),0) -> 30 | C16: See calculations tab
A17: Number of years each child needs to receive intervention to receive full benefit | B17: 8 | C17: Duration of compulsory education in SSA (World Bank)
A19: Reach
A20: Total number of schools in average country in SSA | B20: 12225
A21: Number of children out of school in SSA | B21: 265188
A22: % of children out of school in SSA | B22: 0.06
A23: Total number of primary school aged children in average country in SSA | B23: =B21/B22 -> 4419800 | C23: I couldn't find information on the total number of primary school aged children in the average country in SSA, so instead I used the number of children out of school and as we know that 6% of primary school aged children are out of school, we can calculate the total number of primary school aged children Calculation: Number of children out of school / % of children out of school
A24: Number of children per school | B24: =B23/B20 -> 361.53783 | C24: Calculation: Total number of children / total number of schools
A25: Student-teacher ratio | B25: 41.67 | C25: Each teacher teaches 41.67 students (https://ourworldindata.org/grapher/pupil-teacher-ratio-for-primary-education-by-country?tab=table)
A26: Number of teachers per school | B26: =B24/B25 -> 8.6762139 | C26: Calculation: Number of children per school / student-teacher ratio
A27: % of schools reached in pilot | B27: 0.01 | C27: Assume we work with 1% of schools during pilot (Bridge International did this in their pilot in Kenya)
A28: % of schools reached at scale | B28: 0.5 | C28: Assume we can work with 50% of schools at scale (best guess) | G28: Might be lower
A29: Number of schools worked with during pilot | B29: =B20*B27 -> 122.25 | C29: Calculation: Number of schools * % of schools worked with
A30: Number of schools worked with in year 2 | B30: =$B$29+(($B$37-$B$29)/$B$10) -> 871.03125
A31: Number of schools worked with in year 3 | B31: =B30+(($B$37-$B$29)/$B$10) -> 1619.8125
A32: Number of schools worked with in year 4 | B32: =B31+(($B$37-$B$29)/$B$10) -> 2368.5938
A33: Number of schools worked with in year 5 | B33: =B32+(($B$37-$B$29)/$B$10) -> 3117.375
A34: Number of schools worked with in year 6 | B34: =B33+(($B$37-$B$29)/$B$10) -> 3866.1562
A35: Number of schools worked with in year 7 | B35: =B34+(($B$37-$B$29)/$B$10) -> 4614.9375
A36: Number of schools worked with in year 8 | B36: =B35+(($B$37-$B$29)/$B$10) -> 5363.7188
A37: Number of schools worked with at scale | B37: =B20*B28 -> 6112.5 | C37: Calculation: Number of schools * % of schools worked with
A38: Number of children reached during pilot | B38: =B29*B24 -> 44198 | C38: Calculation: Number of children per school * number of schools worked with during pilot
A39: Number of children worked with in year 2 | B39: =B38+(($B$46-$B$38)/$B$10) -> 314910.75
A40: Number of children worked with in year 3 | B40: =B39+(($B$46-$B$38)/$B$10) -> 585623.5
A41: Number of children worked with in year 4 | B41: =B40+(($B$46-$B$38)/$B$10) -> 856336.25
A42: Number of children worked with in year 5 | B42: =B41+(($B$46-$B$38)/$B$10) -> 1127049
A43: Number of children worked with in year 6 | B43: =B42+(($B$46-$B$38)/$B$10) -> 1397761.8
A44: Number of children worked with in year 7 | B44: =B43+(($B$46-$B$38)/$B$10) -> 1668474.5
A45: Number of children worked with in year 8 | B45: =B44+(($B$46-$B$38)/$B$10) -> 1939187.2
A46: Number of children reached at scale | B46: =B24*B37 -> 2209900 | C46: Calculation: Number of children per school * number of schools worked with at scale
A47: Number of teachers reached during pilot | B47: =B26*B29 -> 1060.6671 | C47: Calculation: Number of teachers per school * number of schools worked with during pilot
A48: Number of teachers reached at scale | B48: =B26*B37 -> 53033.357 | C48: Calculation: Number of teachers per school * number of schools worked with at scale
A49: Effect of lesson plans on test scores (SDs) | B49: =AVERAGE(0.38,0.3,0.5/6.9,0.3,0.54) -> 0.31849275 | C49: See data in Section 4.2 of final lesson plans report
A50: External validity adjustment | B50: 0.8 | C50: Best guess
A51: Effect of lesson plans on test scores (SDs) – adjusted | B51: =B49*B50 -> 0.2547942 | C51: Calculation
A53: Total spent at testing during pilot | B53: =B6+(B38*B12)+(B13*B47) -> 158588.36
A54: Total spent per year when at scale | B54: =(B11*B10)+(B12*B46)+(B13*B48) -> 3479417.9
A56: Probability of success following pilot | B56: 0.8 | C56: This is the probability of success that we will get government buy in following our pilot in private schools. We need this government buy in to reach scale as we plan to scale by working in government schools. Note given the pilot is only a very small part of the total costs this does not affect the end result much.
A57: Net attendance of primary schools (Children) | B57: 0.9281 | C57: Note: We have removed this factor as it seems to be accounted for in the estimates above on the number of children per school.
A58: Net attendance of primary schools (Teachers) | B58: =1-((AVERAGE(0.155*1.5/5,0.157*1.5/5,0.147*1.5/5,0.145*1.5/5,0.422,0.56,0.29,0.336,0.379,0.217,0.53,0.467,0.525))) -> 0.69944615 | C58: 14.5-14.7% teachers report absenteeism "at least once a week" (Time to Teach: West and Central Africa). 15.5-15.7% teachers report absenteeism "at least once a week" (Time to Teach: Eastern and Southern Africa). -> Assume absent 1.5 days per week (best guess) Reported absenteeism of 21.7-56% based on findings of World Bank researchers who turned up to schools unannounced (World Bank).
A59: reduction in effect size due to imperfect usage of lesson plans | B59: 0.8 | C59: Best guess | G59: Might be lower
A60: Discount rate | B60: 0.04 | C60: Held constant across CEAs (from GiveWell)
A61: Discount rate (assuming income increase tracks growth) | B61: 0.01 | C61: We use this reduced income rate for modelling benefits in "Method 1". The income rate we use is a combination of a pure time preference factor (to account for sonner being better) a factor that accounts for future uncertainty and a factor that accounts for future growth (as benefits to richer scoieties are less valuable). But we expect that income effects will track economic growth and go up in time. As such we use a lower discount rate to account only for uncertainty (1%) and pure time preference (0%)
A63: Income effects
A64: Per capita income | B64: 1645.5 | C64: https://data.worldbank.org/indicator/NY.GDP.PCAP.CD?locations=RW
A65: Total population in average country in SSA | B65: =Calculations!B190 -> 24607557 | C65: See calculations tab
A67: Moral weights
A68: GiveWell moral weight: Doubled years of income equivalent in DALYs | B68: =1/2.3 -> 0.43478261 | C68: https://docs.google.com/spreadsheets/d/1epyGHcuM9A7YjtddVpEPByBs_lxFY5fh1FQbVLlPneA/edit#gid=171561146 | D68: Value assigned to doubling consumption for one person for one year
A71: METHOD 1 – BASED ON INCOME EFFECTS
A72: Income increase from 1 SD increase in test scores | B72: 0.1 | C72: Using lower end estimate from most cited study on the income effects of improved test scores: 1 SD improvement in test scores leads to a 10-45% income increase (Hanushek et al., 2016)
A74: Calculations – Net present value of economic benefits
A75: Year | B75: 1 | C75: 2 | D75: 3 | E75: 4 | F75: 5 | G75: 6 | H75: 7 | I75: 8 | J75: 9 | K75: 10 | L75: 11 | M75: 12 | N75: 13 | O75: 14 | P75: 15 | Q75: 16 | R75: 17 | S75: 18 | T75: 19 | U75: 20 | V75: 21 | W75: 22 | X75: 23 | Y75: 24 | Z75: 25 | AA75: 26 | AB75: 27 | AC75: 28 | AD75: 29 | AE75: 30 | AF75: 31 | AG75: 32 | AH75: 33 | AI75: 34 | AJ75: 35 | AK75: 36 | AL75: 37 | AM75: 38
A76: Increased income per child | B76: 0 | C76: 0 | D76: 0 | E76: 0 | F76: 0 | G76: 0 | H76: 0 | I76: 0 | J76: =$B$64*($B$72)*$B$51 -> 41.926386 | K76: =$B$64*($B$72)*$B$51 -> 41.926386 | L76: =$B$64*($B$72)*$B$51 -> 41.926386 | M76: =$B$64*($B$72)*$B$51 -> 41.926386 | N76: =$B$64*($B$72)*$B$51 -> 41.926386 | O76: =$B$64*($B$72)*$B$51 -> 41.926386 | P76: =$B$64*($B$72)*$B$51 -> 41.926386 | Q76: =$B$64*($B$72)*$B$51 -> 41.926386 | ... AM76: =$B$64*($B$72)*$B$51 -> 41.926386
A77: % of annual income this represents | B77: =B76/$B64 -> 0 | C77: =C76/$B64 -> 0 | D77: =D76/$B64 -> 0 | E77: =E76/$B64 -> 0 | F77: =F76/$B64 -> 0 | G77: =G76/$B64 -> 0 | H77: =H76/$B64 -> 0 | I77: =I76/$B64 -> 0 | ... AM77: =AM76/$B64 -> 0.02547942
A79: Net present value of economic benefits per child per intervention | B79: {=NPV($B$61,$76:76)} -> 999.23095
A80: Net present value of economic benefits per child per year of intervention | B80: =B79/B17 -> 124.90387
A82: Calculations – Per capita income increase version
A83: Year | B83: 1 | C83: 2 | D83: 3 | E83: 4 | F83: 5 | G83: 6 | H83: 7 | I83: 8 | J83: 9 | K83: 10 | L83: 11 | M83: 12 | N83: 13 | O83: 14 | P83: 15 | Q83: 16 | R83: 17 | S83: 18 | T83: 19 | U83: 20 | V83: 21 | W83: 22 | X83: 23 | Y83: 24 | Z83: 25 | AA83: 26 | AB83: 27 | AC83: 28 | AD83: 29 | AE83: 30 | AF83: 31 | AG83: 32 | AH83: 33 | AI83: 34 | AJ83: 35 | AK83: 36 | AL83: 37 | AM83: 38
A84: Charity costs | B84: =B53 -> 158588.36 | C84: =($B$11+($B$12*$B29*$B$24)+($B$13*$B29))*B56 -> 188102.34 | D84: =(($B$11*(D83-1))+($B$12*$B30*$B$24)+($B$13*$B3))*B56 -> 400308.58 | E84: =(($B$11*(E83-1))+($B$12*$B31*$B$24)+($B$13*$B31))*B56 -> 647356.06 | F84: =(($B$11*(F83-1))+($B$12*$B32*$B$24)+($B$13*$B32))*B56 -> 876982.92 | G84: =(($B$11*(G83-1))+($B$12*$B33*$B$24)+($B$13*$B33))*B56 -> 1106609.8 | H84: =(($B$11*(H83-1))+($B$12*$B34*$B$24)+($B$13*$B34))*B56 -> 1336236.6 | I84: =(($B$11*(I83-1))+($B$12*$B35*$B$24)+($B$13*$B35))*$B$56 -> 1565863.5 | J84: =(($B$11*(J83-1))+($B$12*$B36*$B$24)+($B$13*$B36))*$B$56 -> 1795490.3 | K84: =$B$54*$B$56 -> 2783534.3 | L84: =$B$54*$B$56 -> 2783534.3 | M84: =$B$54*$B$56 -> 2783534.3 | N84: =$B$54*$B$56 -> 2783534.3 | O84: =$B$54*$B$56 -> 2783534.3 | P84: =$B$54*$B$56 -> 2783534.3 | Q84: =$B$54*$B$56 -> 2783534.3 | R84: =$B$54*$B$56 -> 2783534.3 | ... AE84: =$B$54*$B$56 -> 2783534.3 | AF84: 0 | AG84: 0 | AH84: 0 | AI84: 0 | AJ84: 0 | AK84: 0 | AL84: 0
A85: Number of children reach in each year | B85: 0 | C85: =($B$38*$B$56*$B$58*$B$59) -> 19785.038 | D85: =($B$39*$B$56*$B$58*$B$59) -> 140968.39 | E85: =($B$40*$B$56*$B$58*$B$59) -> 262151.75 | F85: =($B$41*$B$56*$B$58*$B$59) -> 383335.1 | G85: =($B$42*$B$56*$B$58*$B$59) -> 504518.46 | H85: =($B$43*$B$56*$B$58*$B$59) -> 625701.81 | I85: =($B$44*$B$56*$B$58*$B$59) -> 746885.17 | J85: =($B$45*$B$56*$B$58*$B$59) -> 868068.52 | K85: =($B$46*$B$56*$B$58*$B$59) -> 989251.88 | L85: =($B$46*$B$56*$B$58*$B$59) -> 989251.88 | M85: =($B$46*$B$56*$B$58*$B$59) -> 989251.88 | N85: =($B$46*$B$56*$B$58*$B$59) -> 989251.88 | O85: =($B$46*$B$56*$B$58*$B$59) -> 989251.88 | P85: =($B$46*$B$56*$B$58*$B$59) -> 989251.88 | Q85: =($B$46*$B$56*$B$58*$B$59) -> 989251.88 | R85: =($B$46*$B$56*$B$58*$B$59) -> 989251.88 | ... AL85: =($B$46*$B$56*$B$58*$B$59) -> 989251.88
A86: Economic benefit | B86: =B85*$B$80 -> 0 | C86: =C85*$B$80 -> 2471227.7 | D86: =D85*$B$80 -> 17607498 | E86: =E85*$B$80 -> 32743768 | F86: =F85*$B$80 -> 47880037 | G86: =G85*$B$80 -> 63016307 | H86: =H85*$B$80 -> 78152577 | I86: =I85*$B$80 -> 93288847 | ... AL86: =AL85*$B$80 -> 1.2356139e+08
A88: Outputs – Per capita income increase version
A89: Total discounted costs | B89: {=NPV($B$60,84:84)} -> 33688568
A90: Total discounted benefit | B90: =SUM(B86:AL86) -> 3903304212
A91: Benefit-cost ratio | B91: =B90/B89 -> 115.86436
A93: METHOD 2 – BASED ON ECONOMIC GROWTH
A95: Effect size (accouning for all the factors that reduce the effect) | B95: =($B$56*$B$58*$B$59) -> 0.44764554 | C95: Calculation
A96: Total income of whole population | B96: =B65*B64 -> 40491735146 | C96: Calculation
A97: Delay (years before any effect on growth in economy) | B97: =ROUNDUP(B14/2,0) -> 4 | C97: From CEA tab but divided by 2 and rounded up as will start having an effect even before 7 years
A98: Economic growth per year assuming 100% of population affected | B98: =Calculations!D98 -> 0.0005010812 | C98: See calculations tab
A100: Calculations – Economic growth version
A101: Year | B101: 1 | C101: 2 | D101: 3 | E101: 4 | F101: 5 | G101: 6 | H101: 7 | I101: 8 | J101: 9 | K101: 10 | L101: 11 | M101: 12 | N101: 13 | O101: 14 | P101: 15 | Q101: 16 | R101: 17 | S101: 18 | T101: 19 | U101: 20 | V101: 21 | W101: 22 | X101: 23 | Y101: 24 | Z101: 25 | AA101: 26 | AB101: 27 | AC101: 28 | AD101: 29 | AE101: 30 | AF101: 31 | AG101: 32 | AH101: 33 | AI101: 34 | AJ101: 35 | AK101: 36 | AL101: 37
A102: % of schools reached | B102: 0 | C102: =$B29/$B$20 -> 0.01 | D102: =$B30/$B$20 -> 0.07125 | E102: =$B31/$B$20 -> 0.1325 | F102: =$B32/$B$20 -> 0.19375 | G102: =$B33/$B$20 -> 0.255 | H102: =$B34/$B$20 -> 0.31625 | I102: =$B35/$B$20 -> 0.3775 | J102: =$B36/$B$20 -> 0.43875 | K102: =$B37/$B$20 -> 0.5 | L102: =$B$28 -> 0.5 | M102: =$B$28 -> 0.5 | N102: =$B$28 -> 0.5 | O102: =$B$28 -> 0.5 | P102: =$B$28 -> 0.5 | Q102: =$B$28 -> 0.5 | R102: =$B$28 -> 0.5 | S102: =$B$28 -> 0.5 | ... AL102: =$B$28 -> 0.5
A103: Total income of country (ignore growth not caused by intervention) | B103: =IFERROR(A103*(1+$B98*#REF!),$B$96) -> 40491735146 | C103: =IFERROR(B103*(1+$B98*#REF!),$B$96) -> 40491735146 | D103: =IFERROR(C103*(1+$B98*#REF!),$B$96) -> 40491735146 | E103: =IFERROR(D103*(1+$B98*A102),$B$96) -> 40491735146 | F103: =IFERROR(E103*(1+$B98*$B95*B102),$B$96) -> 40491735146 | G103: =IFERROR(F103*(1+$B98*$B95*C102),$B$96) -> 40491825972 | H103: =IFERROR(G103*(1+$B98*$B95*D102),$B$96) -> 40492473107 | I103: =IFERROR(H103*(1+$B98*$B95*E102),$B$96) -> 40493676569 | J103: =IFERROR(I103*(1+$B98*$B95*F102),$B$96) -> 40495436401 | K103: =IFERROR(J103*(1+$B98*$B95*G102),$B$96) -> 40497752668 | L103: =IFERROR(K103*(1+$B98*$B95*H102),$B$96) -> 40500625458 | M103: =IFERROR(L103*(1+$B98*$B95*I102),$B$96) -> 40504054881 | ... AL103: =IFERROR(AK103*(1+$B98*$B95*AH102),$B$96) -> 40617216547
A104: Economic effect of the intervention | F104: =F103-$B96 -> 0 | G104: =G103-$B96 -> 90825.701 | H104: =H103-$B96 -> 737960.27 | I104: =I103-$B96 -> 1941422.7 | J104: =J103-$B96 -> 3701255.1 | K104: =K103-$B96 -> 6017522.1 | L104: =L103-$B96 -> 8890311.8 | M104: =M103-$B96 -> 12319735 | ... AL104: =AL103-$B96 -> 1.254814e+08
A106: Outputs – Economic growth version
A107: Total discounted costs | B107: =B89 -> 33688568
A108: Total discounted benefit | B108: {=NPV($B$60,104:104)} -> 7.3069574e+08
A109: Benefit-cost ratio | B109: =B108/B107 -> 21.689724
A111: Outputs – Combined
A112: WEIGHTINGS | B112: Vicky | C112: Sam | D112: Average
A113: Income model | B113: ='CEA (Rwanda)'!B111 -> 0.4 | C113: ='CEA (Rwanda)'!C111 -> 0.35 | D113: =AVERAGE(B113:C113) -> 0.375 | F113: Note: The income model has much more evidence behind it. The GDP model suggests much smaller effects. We end up weighting the GDP model more, in large part to make our overall estimate very conservative, and still show that it passes our bar compared to other charities. I expect other models would not be as conservative.
A114: GDP model | B114: ='CEA (Rwanda)'!B112 -> 0.6 | C114: ='CEA (Rwanda)'!C112 -> 0.65 | D114: =AVERAGE(B114:C114) -> 0.625
A116: Total discounted costs | B116: =B89 -> 33688568
A117: Weighted average economic benefits | B117: =(B90*D$113)+(B108*D$114) -> 1920423914
...

Sheet Calculations
A1: METHOD 1 – BASED ON INCOME EFFECTS
A2: Returns to education (Additional years of schooling -> Income increase)
A3: Findings | F3: Source | G3: Notes
A4: 1 | B4: additional year of schooling | C4: = | D4: 0.1 | E4: income increase | F4: Woodleigh Impact (informed by Psacharopoulos and Patrinos & World Bank)
A5: 1 | B5: additional year of schooling | C5: = | D5: 0.19047619 | E5: income increase | F5: EA Quebec (using Duflo, 2017)
A6: 1 | B6: additional year of schooling | C6: = | D6: 0.088 | E6: income increase (World average) | F6: Psacharopoulos and Patrinos, 2018
A7: 1 | B7: additional year of schooling | C7: = | D7: 0.105 | E7: income increase (in SSA) | F7: Psacharopoulos and Patrinos, 2018
A8: 1 | B8: additional year of schooling (Primary school) | C8: = | D8: 0.254 | E8: income increase | F8: Psacharopoulos and Patrinos, 2018
A9: 1 | B9: additional year of schooling | C9: = | D9: 0.097 | E9: income increase (World average) | F9: World Bank, 2014
A10: 1 | B10: additional year of schooling | C10: = | D10: 0.101 | E10: income increase (World average) | F10: World Bank, 2014
A11: 1 | B11: additional year of schooling | C11: = | D11: 0.124 | E11: income increase (in SSA) | F11: World Bank, 2014
A12: 1 | B12: additional year of schooling (Primary school) | C12: = | D12: 0.106 | E12: income increase | F12: World Bank, 2014
A13: 1 | B13: additional year of schooling (Primary school) | C13: = | D13: 0.115 | E13: income increase | F13: World Bank, 2014
A14: 1 | B14: additional year of schooling (Primary school) | C14: = | D14: 0.144 | E14: income increase (in SSA) | F14: World Bank, 2014
A15: 1 | B15: additional year of schooling | C15: = | D15: 0 | E15: income increase | F15: Filmer and Schady, 2014
C16: AVERAGE | D16: =AVERAGE(D4:D15) -> 0.11870635
A18: Returns to education (SD increase in test scores = Additional years of schooling)
A19: Findings | F19: Source | G19: Notes
A20: 1 | B20: SD increase in test scores | C20: = | D20: =AVERAGE(1.666666667,6.9) -> 4.2833333 | E20: additional years of schooling | F20: Woodleigh Impact (using Sabbates et al., 2018) | G20: 1.666666667 to 6.9 additional years of schooling
A21: 1 | B21: SD increase in test scores | C21: = | D21: =AVERAGE(8.4,10.5) -> 9.45 | E21: additional years of schooling | F21: EA Quebec (using Duflo, 2017) | G21: 8.4 to 10.5 additional years of schooling
A22: 1 | B22: SD increase in test scores | C22: = | D22: =AVERAGE(1,4.5) -> 2.75 | E22: additional years of schooling | F22: EA Quebec (using World Bank, 2014 and Hanushek et al., 2016) | G22: 1 to 4.5 additional years of schooling
C23: AVERAGE | D23: =AVERAGE(D20:D22) -> 5.4944444
A25: Returns to education (SD increase in test scores -> Income increase)
A26: Findings | F26: Source | G26: Notes
A27: 1 | B27: SD increase in test scores | C27: = | D27: =AVERAGE(0.12,0.25) -> 0.185 | E27: income increase | F27: Hanushek et al., 2013 | G27: 12% to 25%
A28: 1 | B28: SD increase in test scores | C28: = | D28: =AVERAGE(0.1,0.45) -> 0.275 | E28: income increase | F28: Hanushek et al., 2016 | G28: 10% to 45%
A29: 1 | B29: SD increase in test scores | C29: = | D29: =AVERAGE(0.01,0.25) -> 0.13 | E29: income increase | F29: Founders Pledge | G29: 1 to 25%
A30: 1 | B30: SD increase in test scores | C30: = | D30: 0.4 | E30: income increase | F30: EA Quebec (using Bettinger et al., 2014 and 2017 [Unpublished; Cited by FP and GW in their reports])
A31: 1 | B31: SD increase in test scores | C31: = | D31: =$D$20*D4 -> 0.42833333 | E31: income increase | F31: Calculation | G31: $D$19*D4
A32: 1 | B32: SD increase in test scores | C32: = | D32: =$D$20*D5 -> 0.81587302 | E32: income increase | F32: Calculation | G32: $D$19*D5
A33: 1 | B33: SD increase in test scores | C33: = | D33: =$D$20*D6 -> 0.37693333 | E33: income increase | F33: Calculation | G33: $D$19*D6
A34: 1 | B34: SD increase in test scores | C34: = | D34: =$D$20*D7 -> 0.44975 | E34: income increase | F34: Calculation | G34: $D$19*D7
A35: 1 | B35: SD increase in test scores | C35: = | D35: =$D$20*D8 -> 1.0879667 | E35: income increase | F35: Calculation | G35: $D$19*D8
A36: 1 | B36: SD increase in test scores | C36: = | D36: =$D$20*D9 -> 0.41548333 | E36: income increase | F36: Calculation | G36: $D$19*D9
A37: 1 | B37: SD increase in test scores | C37: = | D37: =$D$20*D10 -> 0.43261667 | E37: income increase | F37: Calculation | G37: $D$19*D10
A38: 1 | B38: SD increase in test scores | C38: = | D38: =$D$20*D11 -> 0.53113333 | E38: income increase | F38: Calculation | G38: $D$19*D11
A39: 1 | B39: SD increase in test scores | C39: = | D39: =$D$20*D12 -> 0.45403333 | E39: income increase | F39: Calculation | G39: $D$19*D12
A40: 1 | B40: SD increase in test scores | C40: = | D40: =$D$20*D13 -> 0.49258333 | E40: income increase | F40: Calculation | G40: $D$19*D13
A41: 1 | B41: SD increase in test scores | C41: = | D41: =$D$20*D14 -> 0.6168 | E41: income increase | F41: Calculation | G41: $D$19*D14
A42: 1 | B42: SD increase in test scores | C42: = | D42: =$D$20*D15 -> 0 | E42: income increase | F42: Calculation | G42: $D$19*D15
A43: 1 | B43: SD increase in test scores | C43: = | D43: =$D$21*D4 -> 0.945 | E43: income increase | F43: Calculation | G43: $D$20*D4
A44: 1 | B44: SD increase in test scores | C44: = | D44: =$D$21*D5 -> 1.8 | E44: income increase | F44: Calculation | G44: $D$20*D5
A45: 1 | B45: SD increase in test scores | C45: = | D45: =$D$21*D6 -> 0.8316 | E45: income increase | F45: Calculation | G45: $D$20*D6
A46: 1 | B46: SD increase in test scores | C46: = | D46: =$D$21*D7 -> 0.99225 | E46: income increase | F46: Calculation | G46: $D$20*D7
A47: 1 | B47: SD increase in test scores | C47: = | D47: =$D$21*D8 -> 2.4003 | E47: income increase | F47: Calculation | G47: $D$20*D8
A48: 1 | B48: SD increase in test scores | C48: = | D48: =$D$21*D9 -> 0.91665 | E48: income increase | F48: Calculation | G48: $D$20*D9
A49: 1 | B49: SD increase in test scores | C49: = | D49: =$D$21*D10 -> 0.95445 | E49: income increase | F49: Calculation | G49: $D$20*D10
A50: 1 | B50: SD increase in test scores | C50: = | D50: =$D$21*D11 -> 1.1718 | E50: income increase | F50: Calculation | G50: $D$20*D11
A51: 1 | B51: SD increase in test scores | C51: = | D51: =$D$21*D12 -> 1.0017 | E51: income increase | F51: Calculation | G51: $D$20*D12
A52: 1 | B52: SD increase in test scores | C52: = | D52: =$D$21*D13 -> 1.08675 | E52: income increase | F52: Calculation | G52: $D$20*D13
A53: 1 | B53: SD increase in test scores | C53: = | D53: =$D$21*D14 -> 1.3608 | E53: income increase | F53: Calculation | G53: $D$20*D14
A54: 1 | B54: SD increase in test scores | C54: = | D54: =$D$21*D15 -> 0 | E54: income increase | F54: Calculation | G54: $D$20*D15
A55: 1 | B55: SD increase in test scores | C55: = | D55: =$D$22*D4 -> 0.275 | E55: income increase | F55: Calculation | G55: $D$21*D4
A56: 1 | B56: SD increase in test scores | C56: = | D56: =$D$22*D5 -> 0.52380952 | E56: income increase | F56: Calculation | G56: $D$21*D5
A57: 1 | B57: SD increase in test scores | C57: = | D57: =$D$22*D6 -> 0.242 | E57: income increase | F57: Calculation | G57: $D$21*D6
A58: 1 | B58: SD increase in test scores | C58: = | D58: =$D$22*D7 -> 0.28875 | E58: income increase | F58: Calculation | G58: $D$21*D7
A59: 1 | B59: SD increase in test scores | C59: = | D59: =$D$22*D8 -> 0.6985 | E59: income increase | F59: Calculation | G59: $D$21*D8
A60: 1 | B60: SD increase in test scores | C60: = | D60: =$D$22*D9 -> 0.26675 | E60: income increase | F60: Calculation | G60: $D$21*D9
A61: 1 | B61: SD increase in test scores | C61: = | D61: =$D$22*D10 -> 0.27775 | E61: income increase | F61: Calculation | G61: $D$21*D10
A62: 1 | B62: SD increase in test scores | C62: = | D62: =$D$22*D11 -> 0.341 | E62: income increase | F62: Calculation | G62: $D$21*D11
A63: 1 | B63: SD increase in test scores | C63: = | D63: =$D$22*D12 -> 0.2915 | E63: income increase | F63: Calculation | G63: $D$21*D12
A64: 1 | B64: SD increase in test scores | C64: = | D64: =$D$22*D13 -> 0.31625 | E64: income increase | F64: Calculation | G64: $D$21*D13
A65: 1 | B65: SD increase in test scores | C65: = | D65: =$D$22*D14 -> 0.396 | E65: income increase | F65: Calculation | G65: $D$21*D14
A66: 1 | B66: SD increase in test scores | C66: = | D66: =$D$22*D15 -> 0 | E66: income increase | F66: Calculation | G66: $D$21*D15
C67: AVERAGE | D67: =AVERAGE(D27:D30) -> 0.2475
A68: METHOD 2 – BASED ON GDP EFFECTS
A69: Returns to education -> GDP impacts
A70: Findings | F70: Period | G70: Source | K70: Notes
A71: 0.25 | B71: SD increase in test scores | C71: = | D71: 0.062 | E71: increase in GDP over an 80-year period (in terms of the present value of future GDP) | F71: 80 | G71: The Knowledge Capital of Nations, Hanushek [Cited by FP, pg. 51]. | K71: "This approach results in an estimate that a 25-point increase in scores on PISA, a prominent international test, for the entire population (a quarter of a standard deviation) would lead to GDP being on average 6% higher over an 80-year period, or that wages for all workers would be 12% higher." AND "Separately address objections related to causality in a number of ways, to argue that the relationship between cognitive skills and growth established found above is mostly causal."
A72: 0.25 | B72: SD increase in test scores | C72: = | D72: 0.12 | E72: increase in wages over an 80-year period (in terms of the present value of future GDP) | F72: 80 | G72: The Knowledge Capital of Nations, Hanushek [Cited by FP, pg. 51]. | K72: "This approach results in an estimate that a 25-point increase in scores on PISA, a prominent international test, for the entire population (a quarter of a standard deviation) would lead to GDP being on average 6% higher over an 80-year period, or that wages for all workers would be 12% higher." AND "Separately address objections related to causality in a number of ways, to argue that the relationship between cognitive skills and growth established found above is mostly causal."
A73: 0.25 | B73: SD increase in test scores | C73: = | D73: 0.043 | E73: increase in GDP over an 80-year period (in terms of the present value of future GDP) | F73: 80 | G73: Hanushek et. al 2012
A74: 0.25 | B74: SD increase in test scores | C74: = | D74: =D75*D23/4 -> 0.0050823611 | E74: increase in GDP over 40 years | F74: 40 | G74: Calculation using above data in line below assuming no diminishing marginal return
A75: 1 | B75: additional year of schooling | C75: = | D75: 0.0037 | E75: increase in GDP over 40 years | F75: 40 | G75: Hanushek et. al 2008
A77: Effect of this intervention on test scores | D77: ='CEA (Rwanda)'!B49 -> 0.2547942 | G77: From CEA tab
A78: Assume diminishing marginal returns and decrease additional effect by: | D78: 0.5 | G78: Assumption
A80: =D$77 -> 0.2547942 | B80: SD increase in test scores | C80: = | D80: =D71+D71*D$78*(A80-A71)/A71 -> 0.062594481 | E80: increase in GDP over an 80-year period (in terms of the present value of future GDP) | F80: 80 | G80: Calculation
A81: =D$77 -> 0.2547942 | B81: SD increase in test scores | C81: = | D81: =D72+D72*D$78*(A81-A72)/A72 -> 0.12115061 | E81: increase in wages over an 80-year period (in terms of the present value of future GDP) | F81: 80 | G81: Calculation
A82: =D$77 -> 0.2547942 | B82: SD increase in test scores | C82: = | D82: =D73+D73*D$78*(A82-A73)/A73 -> 0.043412301 | E82: increase in GDP over an 80-year period (in terms of the present value of future GDP) | F82: 80 | G82: Calculation
A83: =D$77 -> 0.2547942 | B83: SD increase in test scores | C83: = | D83: =D74+D74*D$78*(A83-A74)/A74 -> 0.0051310929 | E83: increase in GDP over 40 years | F83: 40 | G83: Calculation
A86: Number of years delay before intervention has an effect: | D86: =ROUNDUP('CEA (Rwanda)'!B14/2,0) -> 4 | G86: From CEA tab but divided by 2 and rounded up as will start having an effect even before 7 years
A88: =A80 -> 0.2547942 | B88: SD increase in test scores | C88: = | D88: =(1+D80)^(1/(F71-D$86))-1 -> 0.00079918156 | E88: per year economic growth after delay | G88: Calculation
A89: =A81 -> 0.2547942 | B89: SD increase in test scores | C89: = | D89: =(1+D81)^(1/(F72-D$86))-1 -> 0.0015058101 | E89: per year economic growth after delay | G89: Calculation
A90: =A82 -> 0.2547942 | B90: SD increase in test scores | C90: = | D90: =(1+D82)^(1/(F73-D$86))-1 -> 0.00055931954 | E90: per year economic growth after delay | G90: Calculation
A91: =A83 -> 0.2547942 | B91: SD increase in test scores | C91: = | D91: =(1+D83)^(1/(F74-D$86))-1 -> 0.00014217604 | E91: per year economic growth after delay | G91: Calculation
C93: AVERAGE | D93: =AVERAGE(D88:D91) -> 0.0007516218
A95: Number of papers showing a positive effect on cross country models | D95: 8
A96: Number of papers showing a null effect on cross country models | D96: 4
C98: AVERAGE (ADJUSTED) | D98: =D93*(D95/(D95+D96)) -> 0.0005010812
A101: OLD NOTES TO BE IGNORED
A103: Findings | F103: Source | G103: Notes
A104: 0.25 | B104: SD increase in test scores | C104: = | D104: 0.062 | E104: increase in GDP over an 80-year period (in terms of the present value of future GDP) | F104: The Knowledge Capital of Nations, Hanushek [Cited by FP, pg. 51]. | I104: "This approach results in an estimate that a 25-point increase in scores on PISA, a prominent international test, for the entire population (a quarter of a standard deviation) would lead to GDP being on average 6% higher over an 80-year period, or that wages for all workers would be 12% higher." AND "Separately address objections related to causality in a number of ways, to argue that the relationship between cognitive skills and growth established found above is mostly causal."
A105: 1 | B105: SD increase in test scores | C105: = | D105: =(1+0.062)^(1/80)-1 -> 0.0007522068 | E105: increase in GDP annually | F105: Calculation | G105: I get a 0.25 increase gives | H105: =(1+0.062)^(1/80)-1 -> 0.0007522068 | K105: Over a 40 year working life this would be a total salary increase of | L105: =(-PV(-$H105,40,1)+1)/40-1 -> 0.04058395 | M105: But most of it would be towards the end of their life under this kind of formula | N105: Discounting we get | O105: =(-PV(0.04-$H105,40,1)+1)/(-PV(0.04,40,1)+1)-1 -> 0.010749049
A106: 0.25 | B106: SD increase in test scores | C106: = | D106: 0.043 | E106: increase in GDP over an 80-year period (in terms of the present value of future GDP) | F106: Hanushek et. al 2012 | H106: =(1+0.12)^(1/80)-1 -> 0.0014176124 | I106: Asume 12% after 80 years | K106: Over a 40 year working life this would be a total salary increase of | L106: =(-PV(-$H106,40,1)+1)/40-1 -> 0.054646717 | M106: But most of it would be towards the end of their life under this kind of formula | O106: =(-PV(0.04-$H106,40,1)+1)/(-PV(0.04,40,1)+1)-1 -> 0.020415885
A107: 1 | B107: SD increase in test scores | C107: = | D107: =(D106/80)*4 -> 0.00215 | E107: increase in GDP annually | F107: Calculation | G107: I get a 0.25 increase gives | H107: =(1+D106)^(1/80)-1 -> 0.0005264032 | K107: Over a 40 year working life this would be | L107: =(-PV(-H107,40,1)+1)/40-1 -> 0.035871246 | M107: But most of it would be towards the end of their life under this kind of formula | N107: Discounting we get | O107: =(-PV(0.04-$H107,40,1)+1)/(-PV(0.04,40,1)+1)-1 -> 0.0075025476
A108: 1 | B108: additional year of schooling | C108: = | D108: 0.0037 | E108: increase in GDP over 40 years | F108: Hanushek et. al 2008 | G108: I get an effect of | H108: =(1+D108)^(1/40)-1 -> 9.2333558e-05 | I108: so 0.25 increase in scores is | J108: =H108*D23/4 -> 0.0001268304 | K108: Over a 40 year working life this would be | L108: =(-PV(J108,40,1)+1)/40-1 -> 0.022404587 | M108: But most of it would be towards the end of their life under this kind of formula | N108: Discounting we get | O108: =(-PV(0.04-$H108,40,1)+1)/(-PV(0.04,40,1)+1)-1 -> 0.0013093589
A109: 1 | B109: SD increase in test scores | C109: = | D109: =D108*D20 -> 0.015848333 | E109: increase in GDP annually | F109: Calculation
A110: 1 | B110: point increase in education capital | C110: = | D110: -0.049 | E110: decrease in GDP per worker
H112: =AVERAGE(H104:H109) -> 0.000697139
A113: OTHER
A114: Teacher attendance
...
